Workbook

Sheet Defaults
B1: Values in Model | C1: Original
A2: v | B2: =1/psi -> 6.6666667 | C2: =1/psi -> 6.6666667
A3: w | B3: =1/alpha -> -1 | C3: =1/alpha -> -1
A4: y | B4: =EXP(alpha*zeta) -> 0.29229258 | C4: =EXP(alpha*zeta) -> 0.29229258
A5: Beta | B5: 180 | C5: 180
A6: Theta | B6: 0.08 | C6: 0.017
A7: Gamma | B7: 0 | C7: 0
A8: Phi | B8: 0.018 | C8: 0.018
A9: alpha | B9: -1 | C9: -1
A10: psi | B10: 0.15 | C10: 0.15
A11: zeta | B11: 1.23 | C11: 1.23
A12: kappa | B12: 90 | C12: 90

Sheet S-Toll (All-Tax)
A1: Tau | B1: OldTau | C1: Size | D1: a | E1: b | F1: ij | G1: jj | H1: BUTIJ | I1: BUTII | J1: BCCIJ | K1: BCCJJ | L1: BCk | M1: BCS | N1: BCPTJJ | O1: BCPTIJ | P1: BCPTII | Q1: BRIJ | R1: BRJJ | S1: Toll | T1: Welfare | U1: Utility | V1: Profit | W1: Revenue | X1: Cost
A2: 0 | B2: 0 | C2: 10 | D2: 0 | E2: =Size-a -> 10 | F2: =(EXP(alpha*(Tau+OldTau+zeta-2*a*psi))*((EXP(alpha*a*psi)-EXP(alpha*b*psi))^2))/((EXP(alpha*a*psi)-EXP(alpha*(2*OldTau+b*psi)))*(alpha^2)*(psi^2)) -> 10.092146 | G2: =(EXP(alpha*(zeta+(2*b-a)*psi))*(-1+EXP(alpha*(-1)*Size*psi))*(EXP(alpha*(2*(Tau+OldTau)+a*psi))-EXP(alpha*(2*(Tau+OldTau)+b*psi))))/(((EXP(alpha*a*psi)-EXP(alpha*(2*OldTau+b*psi)))^2)*(alpha^2)*(psi^2)) -> 2.8986351 | H2: =-Beta/alpha -> 180 | I2: =(-EXP(alpha*zeta)*Beta*(-1+EXP(alpha*Size*psi)-Size*alpha*psi))/((alpha^3)*(psi^2)) -> 1690.9246 | J2: =Beta*Theta -> 14.4 | K2: =Beta*Theta -> 14.4 | L2: =kappa -> 90 | M2: =Gamma*Size -> 0 | N2: =Size*Beta*Phi -> 32.4 | O2: =-(EXP(alpha*a*psi)+EXP(alpha*b*psi)*(-1+Size*psi*alpha))*(Beta*Phi)/((alpha*psi)*(EXP(alpha*a*psi)-EXP(alpha*b*psi))) -> 12.294172 | P2: =(EXP(alpha*(zeta-a*psi))*Beta*Phi*(-EXP(alpha*a*psi)*(-2+(-1)*Size*alpha*psi)+EXP(alpha*b*psi)*(-2+Size*alpha*psi)))/((alpha^3)*(psi^3)) -> 78.836376 | Q2: =Tau*Beta -> 0 | R2: =Tau*Beta -> 0 | S2: =Tau -> 0 | T2: =Profit+Utility -> 3086.6096 | U2: =ij*BUTIJ+BUTII -> 3507.5109 | V2: =Revenue-Cost -> -420.90131 | W2: =(2*ij*BRIJ)+(2)*jj*BRJJ -> 0 | X2: =BCS+jj*BCPTJJ+2*(ij*BCPTIJ)+BCPTII -> 420.90131
A3: 0 | B3: 0 | C3: 10 | D3: 0 | E3: =Size-a -> 10 | F3: =(EXP(alpha*(Tau+OldTau+zeta-2*a*psi))*((EXP(alpha*a*psi)-EXP(alpha*b*psi))^2))/((EXP(alpha*a*psi)-EXP(alpha*(2*OldTau+b*psi)))*(alpha^2)*(psi^2)) -> 10.092146 | G3: =(EXP(alpha*(zeta+(2*b-a)*psi))*(-1+EXP(alpha*(-1)*Size*psi))*(EXP(alpha*(2*(Tau+OldTau)+a*psi))-EXP(alpha*(2*(Tau+OldTau)+b*psi))))/(((EXP(alpha*a*psi)-EXP(alpha*(2*OldTau+b*psi)))^2)*(alpha^2)*(psi^2)) -> 2.8986351 | H3: =-Beta/alpha -> 180 | I3: =(-EXP(alpha*zeta)*Beta*(-1+EXP(alpha*Size*psi)-Size*alpha*psi))/((alpha^3)*(psi^2)) -> 1690.9246 | J3: =Beta*Theta -> 14.4 | K3: =Beta*Theta -> 14.4 | L3: =kappa -> 90 | M3: =Gamma*Size -> 0 | N3: =Size*Beta*Phi -> 32.4 | O3: =-(EXP(alpha*a*psi)+EXP(alpha*b*psi)*(-1+Size*psi*alpha))*(Beta*Phi)/((alpha*psi)*(EXP(alpha*a*psi)-EXP(alpha*b*psi))) -> 12.294172 | P3: =(EXP(alpha*(zeta-a*psi))*Beta*Phi*(-EXP(alpha*a*psi)*(-2+(-1)*Size*alpha*psi)+EXP(alpha*b*psi)*(-2+Size*alpha*psi)))/((alpha^3)*(psi^3)) -> 78.836376 | Q3: =Tau*Beta -> 0 | R3: =Tau*Beta -> 0 | S3: =Tau -> 0 | T3: =Profit+Utility -> 2622.4751 | U3: =ij*BUTIJ+BUTII -> 3507.5109 | V3: =Revenue-Cost -> -885.03581 | W3: =(2*ij*BRIJ)+(2)*jj*BRJJ -> 0 | X3: =2*(ij*BCCIJ)+(2*jj*BCCJJ)+BCS+jj*BCPTJJ+2*(ij*BCPTIJ)+BCPTII+BCk -> 885.03581
A4: =A2+0.1 -> 0.1 | B4: 0 | C4: 10 | D4: 0 | E4: =Size-a -> 10 | F4: =(EXP(alpha*(Tau+OldTau+zeta-2*a*psi))*((EXP(alpha*a*psi)-EXP(alpha*b*psi))^2))/((EXP(alpha*a*psi)-EXP(alpha*(2*OldTau+b*psi)))*(alpha^2)*(psi^2)) -> 9.1317515 | G4: =(EXP(alpha*(zeta+(2*b-a)*psi))*(-1+EXP(alpha*(-1)*Size*psi))*(EXP(alpha*(2*(Tau+OldTau)+a*psi))-EXP(alpha*(2*(Tau+OldTau)+b*psi))))/(((EXP(alpha*a*psi)-EXP(alpha*(2*OldTau+b*psi)))^2)*(alpha^2)*(psi^2)) -> 2.3732017 | H4: =-Beta/alpha -> 180 | I4: =(-EXP(alpha*zeta)*Beta*(-1+EXP(alpha*Size*psi)-Size*alpha*psi))/((alpha^3)*(psi^2)) -> 1690.9246 | J4: =Beta*Theta -> 14.4 | K4: =Beta*Theta -> 14.4 | L4: =kappa -> 90 | M4: =Gamma*Size -> 0 | N4: =Size*Beta*Phi -> 32.4 | O4: =-(EXP(alpha*a*psi)+EXP(alpha*b*psi)*(-1+Size*psi*alpha))*(Beta*Phi)/((alpha*psi)*(EXP(alpha*a*psi)-EXP(alpha*b*psi))) -> 12.294172 | P4: =(EXP(alpha*(zeta-a*psi))*Beta*Phi*(-EXP(alpha*a*psi)*(-2+(-1)*Size*alpha*psi)+EXP(alpha*b*psi)*(-2+Size*alpha*psi)))/((alpha^3)*(psi^3)) -> 78.836376 | Q4: =Tau*Beta -> 18 | R4: =Tau*Beta -> 18 | S4: =Tau -> 0.1 | T4: =Profit+Utility -> 2947.2128 | U4: =ij*BUTIJ+BUTII -> 3334.6399 | V4: =Revenue-Cost -> -387.42709 | W4: =(2*ij*BRIJ)+(2)*jj*BRJJ -> 414.17831 | X4: =2*(ij*BCCIJ)+(2*jj*BCCJJ)+BCS+jj*BCPTJJ+2*(ij*BCPTIJ)+BCPTII+BCk -> 801.60541
A5: =A4+0.1 -> 0.2 | B5: 0 | C5: 10 | D5: 0 | E5: =Size-a -> 10 | F5: =(EXP(alpha*(Tau+OldTau+zeta-2*a*psi))*((EXP(alpha*a*psi)-EXP(alpha*b*psi))^2))/((EXP(alpha*a*psi)-EXP(alpha*(2*OldTau+b*psi)))*(alpha^2)*(psi^2)) -> 8.2627504 | G5: =(EXP(alpha*(zeta+(2*b-a)*psi))*(-1+EXP(alpha*(-1)*Size*psi))*(EXP(alpha*(2*(Tau+OldTau)+a*psi))-EXP(alpha*(2*(Tau+OldTau)+b*psi))))/(((EXP(alpha*a*psi)-EXP(alpha*(2*OldTau+b*psi)))^2)*(alpha^2)*(psi^2)) -> 1.9430132 | H5: =-Beta/alpha -> 180 | I5: =(-EXP(alpha*zeta)*Beta*(-1+EXP(alpha*Size*psi)-Size*alpha*psi))/((alpha^3)*(psi^2)) -> 1690.9246 | J5: =Beta*Theta -> 14.4 | K5: =Beta*Theta -> 14.4 | L5: =kappa -> 90 | M5: =Gamma*Size -> 0 | N5: =Size*Beta*Phi -> 32.4 | O5: =-(EXP(alpha*a*psi)+EXP(alpha*b*psi)*(-1+Size*psi*alpha))*(Beta*Phi)/((alpha*psi)*(EXP(alpha*a*psi)-EXP(alpha*b*psi))) -> 12.294172 | P5: =(EXP(alpha*(zeta-a*psi))*Beta*Phi*(-EXP(alpha*a*psi)*(-2+(-1)*Size*alpha*psi)+EXP(alpha*b*psi)*(-2+Size*alpha*psi)))/((alpha^3)*(psi^3)) -> 78.836376 | Q5: =Tau*Beta -> 36 | R5: =Tau*Beta -> 36 | S5: =Tau -> 0.2 | T5: =Profit+Utility -> 3184.1513 | U5: =ij*BUTIJ+BUTII -> 3178.2197 | V5: =Revenue-Cost -> 5.9316365 | W5: =(2*ij*BRIJ)+(2)*jj*BRJJ -> 734.81498 | X5: =2*(ij*BCCIJ)+(2*jj*BCCJJ)+BCS+jj*BCPTJJ+2*(ij*BCPTIJ)+BCPTII+BCk -> 728.88334
A6: =A5+0.1 -> 0.3 | B6: 0 | C6: 10 | D6: 0 | E6: =Size-a -> 10 | F6: =(EXP(alpha*(Tau+OldTau+zeta-2*a*psi))*((EXP(alpha*a*psi)-EXP(alpha*b*psi))^2))/((EXP(alpha*a*psi)-EXP(alpha*(2*OldTau+b*psi)))*(alpha^2)*(psi^2)) -> 7.4764457 | G6: =(EXP(alpha*(zeta+(2*b-a)*psi))*(-1+EXP(alpha*(-1)*Size*psi))*(EXP(alpha*(2*(Tau+OldTau)+a*psi))-EXP(alpha*(2*(Tau+OldTau)+b*psi))))/(((EXP(alpha*a*psi)-EXP(alpha*(2*OldTau+b*psi)))^2)*(alpha^2)*(psi^2)) -> 1.5908047 | H6: =-Beta/alpha -> 180 | I6: =(-EXP(alpha*zeta)*Beta*(-1+EXP(alpha*Size*psi)-Size*alpha*psi))/((alpha^3)*(psi^2)) -> 1690.9246 | J6: =Beta*Theta -> 14.4 | K6: =Beta*Theta -> 14.4 | L6: =kappa -> 90 | M6: =Gamma*Size -> 0 | N6: =Size*Beta*Phi -> 32.4 | O6: =-(EXP(alpha*a*psi)+EXP(alpha*b*psi)*(-1+Size*psi*alpha))*(Beta*Phi)/((alpha*psi)*(EXP(alpha*a*psi)-EXP(alpha*b*psi))) -> 12.294172 | P6: =(EXP(alpha*(zeta-a*psi))*Beta*Phi*(-EXP(alpha*a*psi)*(-2+(-1)*Size*alpha*psi)+EXP(alpha*b*psi)*(-2+Size*alpha*psi)))/((alpha^3)*(psi^3)) -> 78.836376 | Q6: =Tau*Beta -> 54 | R6: =Tau*Beta -> 54 | S6: =Tau -> 0.3 | T6: =Profit+Utility -> 3350.5992 | U6: =ij*BUTIJ+BUTII -> 3036.6849 | V6: =Revenue-Cost -> 313.91437 | W6: =(2*ij*BRIJ)+(2)*jj*BRJJ -> 979.26304 | X6: =2*(ij*BCCIJ)+(2*jj*BCCJJ)+BCS+jj*BCPTJJ+2*(ij*BCPTIJ)+BCPTII+BCk -> 665.34868
A7: =A6+0.1 -> 0.4 | B7: 0 | C7: 10 | D7: 0 | E7: =Size-a -> 10 | F7: =(EXP(alpha*(Tau+OldTau+zeta-2*a*psi))*((EXP(alpha*a*psi)-EXP(alpha*b*psi))^2))/((EXP(alpha*a*psi)-EXP(alpha*(2*OldTau+b*psi)))*(alpha^2)*(psi^2)) -> 6.7649679 | G7: =(EXP(alpha*(zeta+(2*b-a)*psi))*(-1+EXP(alpha*(-1)*Size*psi))*(EXP(alpha*(2*(Tau+OldTau)+a*psi))-EXP(alpha*(2*(Tau+OldTau)+b*psi))))/(((EXP(alpha*a*psi)-EXP(alpha*(2*OldTau+b*psi)))^2)*(alpha^2)*(psi^2)) -> 1.3024407 | H7: =-Beta/alpha -> 180 | I7: =(-EXP(alpha*zeta)*Beta*(-1+EXP(alpha*Size*psi)-Size*alpha*psi))/((alpha^3)*(psi^2)) -> 1690.9246 | J7: =Beta*Theta -> 14.4 | K7: =Beta*Theta -> 14.4 | L7: =kappa -> 90 | M7: =Gamma*Size -> 0 | N7: =Size*Beta*Phi -> 32.4 | O7: =-(EXP(alpha*a*psi)+EXP(alpha*b*psi)*(-1+Size*psi*alpha))*(Beta*Phi)/((alpha*psi)*(EXP(alpha*a*psi)-EXP(alpha*b*psi))) -> 12.294172 | P7: =(EXP(alpha*(zeta-a*psi))*Beta*Phi*(-EXP(alpha*a*psi)*(-2+(-1)*Size*alpha*psi)+EXP(alpha*b*psi)*(-2+Size*alpha*psi)))/((alpha^3)*(psi^3)) -> 78.836376 | Q7: =Tau*Beta -> 72 | R7: =Tau*Beta -> 72 | S7: =Tau -> 0.4 | T7: =Profit+Utility -> 3460.6095 | U7: =ij*BUTIJ+BUTII -> 2908.6188 | V7: =Revenue-Cost -> 551.99066 | W7: =(2*ij*BRIJ)+(2)*jj*BRJJ -> 1161.7068 | X7: =2*(ij*BCCIJ)+(2*jj*BCCJJ)+BCS+jj*BCPTJJ+2*(ij*BCPTIJ)+BCPTII+BCk -> 609.71618
A8: =A7+0.1 -> 0.5 | B8: 0 | C8: 10 | D8: 0 | E8: =Size-a -> 10 | F8: =(EXP(alpha*(Tau+OldTau+zeta-2*a*psi))*((EXP(alpha*a*psi)-EXP(alpha*b*psi))^2))/((EXP(alpha*a*psi)-EXP(alpha*(2*OldTau+b*psi)))*(alpha^2)*(psi^2)) -> 6.1211961 | G8: =(EXP(alpha*(zeta+(2*b-a)*psi))*(-1+EXP(alpha*(-1)*Size*psi))*(EXP(alpha*(2*(Tau+OldTau)+a*psi))-EXP(alpha*(2*(Tau+OldTau)+b*psi))))/(((EXP(alpha*a*psi)-EXP(alpha*(2*OldTau+b*psi)))^2)*(alpha^2)*(psi^2)) -> 1.0663483 | H8: =-Beta/alpha -> 180 | I8: =(-EXP(alpha*zeta)*Beta*(-1+EXP(alpha*Size*psi)-Size*alpha*psi))/((alpha^3)*(psi^2)) -> 1690.9246 | J8: =Beta*Theta -> 14.4 | K8: =Beta*Theta -> 14.4 | L8: =kappa -> 90 | M8: =Gamma*Size -> 0 | N8: =Size*Beta*Phi -> 32.4 | O8: =-(EXP(alpha*a*psi)+EXP(alpha*b*psi)*(-1+Size*psi*alpha))*(Beta*Phi)/((alpha*psi)*(EXP(alpha*a*psi)-EXP(alpha*b*psi))) -> 12.294172 | P8: =(EXP(alpha*(zeta-a*psi))*Beta*Phi*(-EXP(alpha*a*psi)*(-2+(-1)*Size*alpha*psi)+EXP(alpha*b*psi)*(-2+Size*alpha*psi)))/((alpha^3)*(psi^3)) -> 78.836376 | Q8: =Tau*Beta -> 90 | R8: =Tau*Beta -> 90 | S8: =Tau -> 0.5 | T8: =Profit+Utility -> 3525.6005 | U8: =ij*BUTIJ+BUTII -> 2792.7399 | V8: =Revenue-Cost -> 732.86057 | W8: =(2*ij*BRIJ)+(2)*jj*BRJJ -> 1293.758 | X8: =2*(ij*BCCIJ)+(2*jj*BCCJJ)+BCS+jj*BCPTJJ+2*(ij*BCPTIJ)+BCPTII+BCk -> 560.89741
A9: =A8+0.1 -> 0.6 | B9: 0 | C9: 10 | D9: 0 | E9: =Size-a -> 10 | F9: =(EXP(alpha*(Tau+OldTau+zeta-2*a*psi))*((EXP(alpha*a*psi)-EXP(alpha*b*psi))^2))/((EXP(alpha*a*psi)-EXP(alpha*(2*OldTau+b*psi)))*(alpha^2)*(psi^2)) -> 5.5386872 | G9: =(EXP(alpha*(zeta+(2*b-a)*psi))*(-1+EXP(alpha*(-1)*Size*psi))*(EXP(alpha*(2*(Tau+OldTau)+a*psi))-EXP(alpha*(2*(Tau+OldTau)+b*psi))))/(((EXP(alpha*a*psi)-EXP(alpha*(2*OldTau+b*psi)))^2)*(alpha^2)*(psi^2)) -> 0.87305211 | H9: =-Beta/alpha -> 180 | I9: =(-EXP(alpha*zeta)*Beta*(-1+EXP(alpha*Size*psi)-Size*alpha*psi))/((alpha^3)*(psi^2)) -> 1690.9246 | J9: =Beta*Theta -> 14.4 | K9: =Beta*Theta -> 14.4 | L9: =kappa -> 90 | M9: =Gamma*Size -> 0 | N9: =Size*Beta*Phi -> 32.4 | O9: =-(EXP(alpha*a*psi)+EXP(alpha*b*psi)*(-1+Size*psi*alpha))*(Beta*Phi)/((alpha*psi)*(EXP(alpha*a*psi)-EXP(alpha*b*psi))) -> 12.294172 | P9: =(EXP(alpha*(zeta-a*psi))*Beta*Phi*(-EXP(alpha*a*psi)*(-2+(-1)*Size*alpha*psi)+EXP(alpha*b*psi)*(-2+Size*alpha*psi)))/((alpha^3)*(psi^3)) -> 78.836376 | Q9: =Tau*Beta -> 108 | R9: =Tau*Beta -> 108 | S9: =Tau -> 0.6 | T9: =Profit+Utility -> 3554.8555 | U9: =ij*BUTIJ+BUTII -> 2687.8883 | V9: =Revenue-Cost -> 866.9672 | W9: =(2*ij*BRIJ)+(2)*jj*BRJJ -> 1384.9357 | X9: =2*(ij*BCCIJ)+(2*jj*BCCJJ)+BCS+jj*BCPTJJ+2*(ij*BCPTIJ)+BCPTII+BCk -> 517.9685
A10: =A9+0.1 -> 0.7 | B10: 0 | C10: 10 | D10: 0 | E10: =Size-a -> 10 | F10: =(EXP(alpha*(Tau+OldTau+zeta-2*a*psi))*((EXP(alpha*a*psi)-EXP(alpha*b*psi))^2))/((EXP(alpha*a*psi)-EXP(alpha*(2*OldTau+b*psi)))*(alpha^2)*(psi^2)) -> 5.0116115 | G10: =(EXP(alpha*(zeta+(2*b-a)*psi))*(-1+EXP(alpha*(-1)*Size*psi))*(EXP(alpha*(2*(Tau+OldTau)+a*psi))-EXP(alpha*(2*(Tau+OldTau)+b*psi))))/(((EXP(alpha*a*psi)-EXP(alpha*(2*OldTau+b*psi)))^2)*(alpha^2)*(psi^2)) -> 0.71479461 | H10: =-Beta/alpha -> 180 | I10: =(-EXP(alpha*zeta)*Beta*(-1+EXP(alpha*Size*psi)-Size*alpha*psi))/((alpha^3)*(psi^2)) -> 1690.9246 | J10: =Beta*Theta -> 14.4 | K10: =Beta*Theta -> 14.4 | L10: =kappa -> 90 | M10: =Gamma*Size -> 0 | N10: =Size*Beta*Phi -> 32.4 | O10: =-(EXP(alpha*a*psi)+EXP(alpha*b*psi)*(-1+Size*psi*alpha))*(Beta*Phi)/((alpha*psi)*(EXP(alpha*a*psi)-EXP(alpha*b*psi))) -> 12.294172 | P10: =(EXP(alpha*(zeta-a*psi))*Beta*Phi*(-EXP(alpha*a*psi)*(-2+(-1)*Size*alpha*psi)+EXP(alpha*b*psi)*(-2+Size*alpha*psi)))/((alpha^3)*(psi^3)) -> 78.836376 | Q10: =Tau*Beta -> 126 | R10: =Tau*Beta -> 126 | S10: =Tau -> 0.7 | T10: =Profit+Utility -> 3555.9256 | U10: =ij*BUTIJ+BUTII -> 2593.0147 | V10: =Revenue-Cost -> 962.91089 | W10: =(2*ij*BRIJ)+(2)*jj*BRJJ -> 1443.0543 | X10: =2*(ij*BCCIJ)+(2*jj*BCCJJ)+BCS+jj*BCPTJJ+2*(ij*BCPTIJ)+BCPTII+BCk -> 480.14344
A11: =A10+0.1 -> 0.8 | B11: 0 | C11: 10 | D11: 0 | E11: =Size-a -> 10 | F11: =(EXP(alpha*(Tau+OldTau+zeta-2*a*psi))*((EXP(alpha*a*psi)-EXP(alpha*b*psi))^2))/((EXP(alpha*a*psi)-EXP(alpha*(2*OldTau+b*psi)))*(alpha^2)*(psi^2)) -> 4.5346936 | G11: =(EXP(alpha*(zeta+(2*b-a)*psi))*(-1+EXP(alpha*(-1)*Size*psi))*(EXP(alpha*(2*(Tau+OldTau)+a*psi))-EXP(alpha*(2*(Tau+OldTau)+b*psi))))/(((EXP(alpha*a*psi)-EXP(alpha*(2*OldTau+b*psi)))^2)*(alpha^2)*(psi^2)) -> 0.58522433 | H11: =-Beta/alpha -> 180 | I11: =(-EXP(alpha*zeta)*Beta*(-1+EXP(alpha*Size*psi)-Size*alpha*psi))/((alpha^3)*(psi^2)) -> 1690.9246 | J11: =Beta*Theta -> 14.4 | K11: =Beta*Theta -> 14.4 | L11: =kappa -> 90 | M11: =Gamma*Size -> 0 | N11: =Size*Beta*Phi -> 32.4 | O11: =-(EXP(alpha*a*psi)+EXP(alpha*b*psi)*(-1+Size*psi*alpha))*(Beta*Phi)/((alpha*psi)*(EXP(alpha*a*psi)-EXP(alpha*b*psi))) -> 12.294172 | P11: =(EXP(alpha*(zeta-a*psi))*Beta*Phi*(-EXP(alpha*a*psi)*(-2+(-1)*Size*alpha*psi)+EXP(alpha*b*psi)*(-2+Size*alpha*psi)))/((alpha^3)*(psi^3)) -> 78.836376 | Q11: =Tau*Beta -> 144 | R11: =Tau*Beta -> 144 | S11: =Tau -> 0.8 | T11: =Profit+Utility -> 3534.9539 | U11: =ij*BUTIJ+BUTII -> 2507.1695 | V11: =Revenue-Cost -> 1027.7845 | W11: =(2*ij*BRIJ)+(2)*jj*BRJJ -> 1474.5364 | X11: =2*(ij*BCCIJ)+(2*jj*BCCJJ)+BCS+jj*BCPTJJ+2*(ij*BCPTIJ)+BCPTII+BCk -> 446.75188
A12: =A11+0.1 -> 0.9 | B12: 0 | C12: 10 | D12: 0 | E12: =Size-a -> 10 | F12: =(EXP(alpha*(Tau+OldTau+zeta-2*a*psi))*((EXP(alpha*a*psi)-EXP(alpha*b*psi))^2))/((EXP(alpha*a*psi)-EXP(alpha*(2*OldTau+b*psi)))*(alpha^2)*(psi^2)) -> 4.1031604 | G12: =(EXP(alpha*(zeta+(2*b-a)*psi))*(-1+EXP(alpha*(-1)*Size*psi))*(EXP(alpha*(2*(Tau+OldTau)+a*psi))-EXP(alpha*(2*(Tau+OldTau)+b*psi))))/(((EXP(alpha*a*psi)-EXP(alpha*(2*OldTau+b*psi)))^2)*(alpha^2)*(psi^2)) -> 0.47914116 | H12: =-Beta/alpha -> 180 | I12: =(-EXP(alpha*zeta)*Beta*(-1+EXP(alpha*Size*psi)-Size*alpha*psi))/((alpha^3)*(psi^2)) -> 1690.9246 | J12: =Beta*Theta -> 14.4 | K12: =Beta*Theta -> 14.4 | L12: =kappa -> 90 | M12: =Gamma*Size -> 0 | N12: =Size*Beta*Phi -> 32.4 | O12: =-(EXP(alpha*a*psi)+EXP(alpha*b*psi)*(-1+Size*psi*alpha))*(Beta*Phi)/((alpha*psi)*(EXP(alpha*a*psi)-EXP(alpha*b*psi))) -> 12.294172 | P12: =(EXP(alpha*(zeta-a*psi))*Beta*Phi*(-EXP(alpha*a*psi)*(-2+(-1)*Size*alpha*psi)+EXP(alpha*b*psi)*(-2+Size*alpha*psi)))/((alpha^3)*(psi^3)) -> 78.836376 | Q12: =Tau*Beta -> 162 | R12: =Tau*Beta -> 162 | S12: =Tau -> 0.9 | T12: =Profit+Utility -> 3496.9385 | U12: =ij*BUTIJ+BUTII -> 2429.4935 | V12: =Revenue-Cost -> 1067.445 | W12: =(2*ij*BRIJ)+(2)*jj*BRJJ -> 1484.6657 | X12: =2*(ij*BCCIJ)+(2*jj*BCCJJ)+BCS+jj*BCPTJJ+2*(ij*BCPTIJ)+BCPTII+BCk -> 417.22075
A13: =A12+0.1 -> 1 | B13: 0 | C13: 10 | D13: 0 | E13: =Size-a -> 10 | F13: =(EXP(alpha*(Tau+OldTau+zeta-2*a*psi))*((EXP(alpha*a*psi)-EXP(alpha*b*psi))^2))/((EXP(alpha*a*psi)-EXP(alpha*(2*OldTau+b*psi)))*(alpha^2)*(psi^2)) -> 3.7126931 | G13: =(EXP(alpha*(zeta+(2*b-a)*psi))*(-1+EXP(alpha*(-1)*Size*psi))*(EXP(alpha*(2*(Tau+OldTau)+a*psi))-EXP(alpha*(2*(Tau+OldTau)+b*psi))))/(((EXP(alpha*a*psi)-EXP(alpha*(2*OldTau+b*psi)))^2)*(alpha^2)*(psi^2)) -> 0.3922876 | H13: =-Beta/alpha -> 180 | I13: =(-EXP(alpha*zeta)*Beta*(-1+EXP(alpha*Size*psi)-Size*alpha*psi))/((alpha^3)*(psi^2)) -> 1690.9246 | J13: =Beta*Theta -> 14.4 | K13: =Beta*Theta -> 14.4 | L13: =kappa -> 90 | M13: =Gamma*Size -> 0 | N13: =Size*Beta*Phi -> 32.4 | O13: =-(EXP(alpha*a*psi)+EXP(alpha*b*psi)*(-1+Size*psi*alpha))*(Beta*Phi)/((alpha*psi)*(EXP(alpha*a*psi)-EXP(alpha*b*psi))) -> 12.294172 | P13: =(EXP(alpha*(zeta-a*psi))*Beta*Phi*(-EXP(alpha*a*psi)*(-2+(-1)*Size*alpha*psi)+EXP(alpha*b*psi)*(-2+Size*alpha*psi)))/((alpha^3)*(psi^3)) -> 78.836376 | Q13: =Tau*Beta -> 180 | R13: =Tau*Beta -> 180 | S13: =Tau -> 1 | T13: =Profit+Utility -> 3445.9435 | U13: =ij*BUTIJ+BUTII -> 2359.2094 | V13: =Revenue-Cost -> 1086.7341 | W13: =(2*ij*BRIJ)+(2)*jj*BRJJ -> 1477.793 | X13: =2*(ij*BCCIJ)+(2*jj*BCCJJ)+BCS+jj*BCPTJJ+2*(ij*BCPTIJ)+BCPTII+BCk -> 391.05891
A14: =A13+0.1 -> 1.1 | B14: 0 | C14: 10 | D14: 0 | E14: =Size-a -> 10 | F14: =(EXP(alpha*(Tau+OldTau+zeta-2*a*psi))*((EXP(alpha*a*psi)-EXP(alpha*b*psi))^2))/((EXP(alpha*a*psi)-EXP(alpha*(2*OldTau+b*psi)))*(alpha^2)*(psi^2)) -> 3.3593836 | G14: =(EXP(alpha*(zeta+(2*b-a)*psi))*(-1+EXP(alpha*(-1)*Size*psi))*(EXP(alpha*(2*(Tau+OldTau)+a*psi))-EXP(alpha*(2*(Tau+OldTau)+b*psi))))/(((EXP(alpha*a*psi)-EXP(alpha*(2*OldTau+b*psi)))^2)*(alpha^2)*(psi^2)) -> 0.32117792 | H14: =-Beta/alpha -> 180 | I14: =(-EXP(alpha*zeta)*Beta*(-1+EXP(alpha*Size*psi)-Size*alpha*psi))/((alpha^3)*(psi^2)) -> 1690.9246 | J14: =Beta*Theta -> 14.4 | K14: =Beta*Theta -> 14.4 | L14: =kappa -> 90 | M14: =Gamma*Size -> 0 | N14: =Size*Beta*Phi -> 32.4 | O14: =-(EXP(alpha*a*psi)+EXP(alpha*b*psi)*(-1+Size*psi*alpha))*(Beta*Phi)/((alpha*psi)*(EXP(alpha*a*psi)-EXP(alpha*b*psi))) -> 12.294172 | P14: =(EXP(alpha*(zeta-a*psi))*Beta*Phi*(-EXP(alpha*a*psi)*(-2+(-1)*Size*alpha*psi)+EXP(alpha*b*psi)*(-2+Size*alpha*psi)))/((alpha^3)*(psi^3)) -> 78.836376 | Q14: =Tau*Beta -> 198 | R14: =Tau*Beta -> 198 | S14: =Tau -> 1.1 | T14: =Profit+Utility -> 3385.2717 | U14: =ij*BUTIJ+BUTII -> 2295.6137 | V14: =Revenue-Cost -> 1089.658 | W14: =(2*ij*BRIJ)+(2)*jj*BRJJ -> 1457.5024 | X14: =2*(ij*BCCIJ)+(2*jj*BCCJJ)+BCS+jj*BCPTJJ+2*(ij*BCPTIJ)+BCPTII+BCk -> 367.84439
A15: =A14+0.1 -> 1.2 | B15: 0 | C15: 10 | D15: 0 | E15: =Size-a -> 10 | F15: =(EXP(alpha*(Tau+OldTau+zeta-2*a*psi))*((EXP(alpha*a*psi)-EXP(alpha*b*psi))^2))/((EXP(alpha*a*psi)-EXP(alpha*(2*OldTau+b*psi)))*(alpha^2)*(psi^2)) -> 3.039696 | G15: =(EXP(alpha*(zeta+(2*b-a)*psi))*(-1+EXP(alpha*(-1)*Size*psi))*(EXP(alpha*(2*(Tau+OldTau)+a*psi))-EXP(alpha*(2*(Tau+OldTau)+b*psi))))/(((EXP(alpha*a*psi)-EXP(alpha*(2*OldTau+b*psi)))^2)*(alpha^2)*(psi^2)) -> 0.26295824 | H15: =-Beta/alpha -> 180 | I15: =(-EXP(alpha*zeta)*Beta*(-1+EXP(alpha*Size*psi)-Size*alpha*psi))/((alpha^3)*(psi^2)) -> 1690.9246 | J15: =Beta*Theta -> 14.4 | K15: =Beta*Theta -> 14.4 | L15: =kappa -> 90 | M15: =Gamma*Size -> 0 | N15: =Size*Beta*Phi -> 32.4 | O15: =-(EXP(alpha*a*psi)+EXP(alpha*b*psi)*(-1+Size*psi*alpha))*(Beta*Phi)/((alpha*psi)*(EXP(alpha*a*psi)-EXP(alpha*b*psi))) -> 12.294172 | P15: =(EXP(alpha*(zeta-a*psi))*Beta*Phi*(-EXP(alpha*a*psi)*(-2+(-1)*Size*alpha*psi)+EXP(alpha*b*psi)*(-2+Size*alpha*psi)))/((alpha^3)*(psi^3)) -> 78.836376 | Q15: =Tau*Beta -> 216 | R15: =Tau*Beta -> 216 | S15: =Tau -> 1.2 | T15: =Profit+Utility -> 3317.6028 | U15: =ij*BUTIJ+BUTII -> 2238.0699 | V15: =Revenue-Cost -> 1079.5329 | W15: =(2*ij*BRIJ)+(2)*jj*BRJJ -> 1426.7466 | X15: =2*(ij*BCCIJ)+(2*jj*BCCJJ)+BCS+jj*BCPTJJ+2*(ij*BCPTIJ)+BCPTII+BCk -> 347.21376
A16: =A15+0.1 -> 1.3 | B16: 0 | C16: 10 | D16: 0 | E16: =Size-a -> 10 | F16: =(EXP(alpha*(Tau+OldTau+zeta-2*a*psi))*((EXP(alpha*a*psi)-EXP(alpha*b*psi))^2))/((EXP(alpha*a*psi)-EXP(alpha*(2*OldTau+b*psi)))*(alpha^2)*(psi^2)) -> 2.7504307 | G16: =(EXP(alpha*(zeta+(2*b-a)*psi))*(-1+EXP(alpha*(-1)*Size*psi))*(EXP(alpha*(2*(Tau+OldTau)+a*psi))-EXP(alpha*(2*(Tau+OldTau)+b*psi))))/(((EXP(alpha*a*psi)-EXP(alpha*(2*OldTau+b*psi)))^2)*(alpha^2)*(psi^2)) -> 0.215292 | H16: =-Beta/alpha -> 180 | I16: =(-EXP(alpha*zeta)*Beta*(-1+EXP(alpha*Size*psi)-Size*alpha*psi))/((alpha^3)*(psi^2)) -> 1690.9246 | J16: =Beta*Theta -> 14.4 | K16: =Beta*Theta -> 14.4 | L16: =kappa -> 90 | M16: =Gamma*Size -> 0 | N16: =Size*Beta*Phi -> 32.4 | O16: =-(EXP(alpha*a*psi)+EXP(alpha*b*psi)*(-1+Size*psi*alpha))*(Beta*Phi)/((alpha*psi)*(EXP(alpha*a*psi)-EXP(alpha*b*psi))) -> 12.294172 | P16: =(EXP(alpha*(zeta-a*psi))*Beta*Phi*(-EXP(alpha*a*psi)*(-2+(-1)*Size*alpha*psi)+EXP(alpha*b*psi)*(-2+Size*alpha*psi)))/((alpha^3)*(psi^3)) -> 78.836376 | Q16: =Tau*Beta -> 234 | R16: =Tau*Beta -> 234 | S16: =Tau -> 1.3 | T16: =Profit+Utility -> 3245.1072 | U16: =ij*BUTIJ+BUTII -> 2186.0022 | V16: =Revenue-Cost -> 1059.105 | W16: =(2*ij*BRIJ)+(2)*jj*BRJJ -> 1387.9582 | X16: =2*(ij*BCCIJ)+(2*jj*BCCJJ)+BCS+jj*BCPTJJ+2*(ij*BCPTIJ)+BCPTII+BCk -> 328.85319
... A51: =A50+0.1 -> 4.8 | B51: 0 | C51: 10 | D51: 0 | E51: =Size-a -> 10 | F51: =(EXP(alpha*(Tau+OldTau+zeta-2*a*psi))*((EXP(alpha*a*psi)-EXP(alpha*b*psi))^2))/((EXP(alpha*a*psi)-EXP(alpha*(2*OldTau+b*psi)))*(alpha^2)*(psi^2)) -> 0.08305581 | G51: =(EXP(alpha*(zeta+(2*b-a)*psi))*(-1+EXP(alpha*(-1)*Size*psi))*(EXP(alpha*(2*(Tau+OldTau)+a*psi))-EXP(alpha*(2*(Tau+OldTau)+b*psi))))/(((EXP(alpha*a*psi)-EXP(alpha*(2*OldTau+b*psi)))^2)*(alpha^2)*(psi^2)) -> 0.00019632089 | H51: =-Beta/alpha -> 180 | I51: =(-EXP(alpha*zeta)*Beta*(-1+EXP(alpha*Size*psi)-Size*alpha*psi))/((alpha^3)*(psi^2)) -> 1690.9246 | J51: =Beta*Theta -> 14.4 | K51: =Beta*Theta -> 14.4 | L51: =kappa -> 90 | M51: =Gamma*Size -> 0 | N51: =Size*Beta*Phi -> 32.4 | O51: =-(EXP(alpha*a*psi)+EXP(alpha*b*psi)*(-1+Size*psi*alpha))*(Beta*Phi)/((alpha*psi)*(EXP(alpha*a*psi)-EXP(alpha*b*psi))) -> 12.294172 | P51: =(EXP(alpha*(zeta-a*psi))*Beta*Phi*(-EXP(alpha*a*psi)*(-2+(-1)*Size*alpha*psi)+EXP(alpha*b*psi)*(-2+Size*alpha*psi)))/((alpha^3)*(psi^3)) -> 78.836376 | Q51: =Tau*Beta -> 864 | R51: =Tau*Beta -> 864 | S51: =Tau -> 4.8 | T51: =Profit+Utility -> 1676.4518 | U51: =ij*BUTIJ+BUTII -> 1705.8747 | V51: =Revenue-Cost -> -29.422921 | W51: =(2*ij*BRIJ)+(2)*jj*BRJJ -> 143.85968 | X51: =2*(ij*BCCIJ)+(2*jj*BCCJJ)+BCS+jj*BCPTJJ+2*(ij*BCPTIJ)+BCPTII+BCk -> 173.2826

Sheet S-Toll(All-Toll)
A1: Tau | B1: OldTau | C1: Size | D1: a | E1: b | F1: ij | G1: jj | H1: BUTIJ | I1: BUTII | J1: BCCIJ | K1: BCCJJ | L1: BCk | M1: BCS | N1: BCPTJJ | O1: BCPTIJ | P1: BCPTII | Q1: BRIJ | R1: BRJJ | S1: Toll | T1: Welfare | U1: Utility | V1: Profit | W1: Revenue | X1: Cost
A2: 0 | B2: 0.6 | C2: 10 | D2: 0 | E2: =Size-a -> 10 | F2: =(EXP(alpha*(Tau+OldTau+zeta-2*a*psi))*((EXP(alpha*a*psi)-EXP(alpha*b*psi))^2))/((EXP(alpha*a*psi)-EXP(alpha*(2*OldTau+b*psi)))*(alpha^2)*(psi^2)) -> 4.6128479 | G2: =(EXP(alpha*(zeta+(2*b-a)*psi))*(-1+EXP(alpha*(-1)*Size*psi))*(EXP(alpha*(2*(Tau+OldTau)+a*psi))-EXP(alpha*(2*(Tau+OldTau)+b*psi))))/(((EXP(alpha*a*psi)-EXP(alpha*(2*OldTau+b*psi)))^2)*(alpha^2)*(psi^2)) -> 0.60557055 | H2: =-Beta/alpha -> 180 | I2: =(-EXP(alpha*zeta)*Beta*(-1+EXP(alpha*Size*psi)-Size*alpha*psi))/((alpha^3)*(psi^2)) -> 1690.9246 | J2: =Beta*Theta -> 14.4 | K2: =Beta*Theta -> 14.4 | L2: =kappa -> 90 | M2: =Gamma*Size -> 0 | N2: =Size*Beta*Phi -> 32.4 | O2: =-(EXP(alpha*a*psi)+EXP(alpha*b*psi)*(-1+Size*psi*alpha))*(Beta*Phi)/((alpha*psi)*(EXP(alpha*a*psi)-EXP(alpha*b*psi))) -> 12.294172 | P2: =(EXP(alpha*(zeta-a*psi))*Beta*Phi*(-EXP(alpha*a*psi)*(-2+(-1)*Size*alpha*psi)+EXP(alpha*b*psi)*(-2+Size*alpha*psi)))/((alpha^3)*(psi^3)) -> 78.836376 | Q2: =Tau*Beta -> 0 | R2: =Tau*Beta -> 0 | S2: =Tau -> 0 | T2: =Profit+Utility -> 2309.3581 | U2: =ij*BUTIJ+BUTII -> 2521.2372 | V2: =Revenue-Cost -> -211.87915 | W2: =(2*ij*BRIJ)+(2)*jj*BRJJ -> 0 | X2: =BCS+jj*BCPTJJ+2*(ij*BCPTIJ)+BCPTII -> 211.87915
A3: 0 | B3: 0.6 | C3: 10 | D3: 0 | E3: =Size-a -> 10 | F3: =(EXP(alpha*(Tau+OldTau+zeta-2*a*psi))*((EXP(alpha*a*psi)-EXP(alpha*b*psi))^2))/((EXP(alpha*a*psi)-EXP(alpha*(2*OldTau+b*psi)))*(alpha^2)*(psi^2)) -> 4.6128479 | G3: =(EXP(alpha*(zeta+(2*b-a)*psi))*(-1+EXP(alpha*(-1)*Size*psi))*(EXP(alpha*(2*(Tau+OldTau)+a*psi))-EXP(alpha*(2*(Tau+OldTau)+b*psi))))/(((EXP(alpha*a*psi)-EXP(alpha*(2*OldTau+b*psi)))^2)*(alpha^2)*(psi^2)) -> 0.60557055 | H3: =-Beta/alpha -> 180 | I3: =(-EXP(alpha*zeta)*Beta*(-1+EXP(alpha*Size*psi)-Size*alpha*psi))/((alpha^3)*(psi^2)) -> 1690.9246 | J3: =Beta*Theta -> 14.4 | K3: =Beta*Theta -> 14.4 | L3: =kappa -> 90 | M3: =Gamma*Size -> 0 | N3: =Size*Beta*Phi -> 32.4 | O3: =-(EXP(alpha*a*psi)+EXP(alpha*b*psi)*(-1+Size*psi*alpha))*(Beta*Phi)/((alpha*psi)*(EXP(alpha*a*psi)-EXP(alpha*b*psi))) -> 12.294172 | P3: =(EXP(alpha*(zeta-a*psi))*Beta*Phi*(-EXP(alpha*a*psi)*(-2+(-1)*Size*alpha*psi)+EXP(alpha*b*psi)*(-2+Size*alpha*psi)))/((alpha^3)*(psi^3)) -> 78.836376 | Q3: =Tau*Beta -> 0 | R3: =Tau*Beta -> 0 | S3: =Tau -> 0 | T3: =Profit+Utility -> 2069.0676 | U3: =ij*BUTIJ+BUTII -> 2521.2372 | V3: =Revenue-Cost -> -452.1696 | W3: =(2*ij*BRIJ)+(2)*jj*BRJJ -> 0 | X3: =2*(ij*BCCIJ)+(2*jj*BCCJJ)+BCS+jj*BCPTJJ+2*(ij*BCPTIJ)+BCPTII+BCk -> 452.1696
A4: =A2+0.1 -> 0.1 | B4: 0.6 | C4: 10 | D4: 0 | E4: =Size-a -> 10 | F4: =(EXP(alpha*(Tau+OldTau+zeta-2*a*psi))*((EXP(alpha*a*psi)-EXP(alpha*b*psi))^2))/((EXP(alpha*a*psi)-EXP(alpha*(2*OldTau+b*psi)))*(alpha^2)*(psi^2)) -> 4.1738774 | G4: =(EXP(alpha*(zeta+(2*b-a)*psi))*(-1+EXP(alpha*(-1)*Size*psi))*(EXP(alpha*(2*(Tau+OldTau)+a*psi))-EXP(alpha*(2*(Tau+OldTau)+b*psi))))/(((EXP(alpha*a*psi)-EXP(alpha*(2*OldTau+b*psi)))^2)*(alpha^2)*(psi^2)) -> 0.49579924 | H4: =-Beta/alpha -> 180 | I4: =(-EXP(alpha*zeta)*Beta*(-1+EXP(alpha*Size*psi)-Size*alpha*psi))/((alpha^3)*(psi^2)) -> 1690.9246 | J4: =Beta*Theta -> 14.4 | K4: =Beta*Theta -> 14.4 | L4: =kappa -> 90 | M4: =Gamma*Size -> 0 | N4: =Size*Beta*Phi -> 32.4 | O4: =-(EXP(alpha*a*psi)+EXP(alpha*b*psi)*(-1+Size*psi*alpha))*(Beta*Phi)/((alpha*psi)*(EXP(alpha*a*psi)-EXP(alpha*b*psi))) -> 12.294172 | P4: =(EXP(alpha*(zeta-a*psi))*Beta*Phi*(-EXP(alpha*a*psi)*(-2+(-1)*Size*alpha*psi)+EXP(alpha*b*psi)*(-2+Size*alpha*psi)))/((alpha^3)*(psi^3)) -> 78.836376 | Q4: =Tau*Beta -> 18 | R4: =Tau*Beta -> 18 | S4: =Tau -> 0.1 | T4: =Profit+Utility -> 2188.3152 | U4: =ij*BUTIJ+BUTII -> 2442.2226 | V4: =Revenue-Cost -> -253.90733 | W4: =(2*ij*BRIJ)+(2)*jj*BRJJ -> 168.10836 | X4: =2*(ij*BCCIJ)+(2*jj*BCCJJ)+BCS+jj*BCPTJJ+2*(ij*BCPTIJ)+BCPTII+BCk -> 422.01569
A5: =A4+0.1 -> 0.2 | B5: 0.6 | C5: 10 | D5: 0 | E5: =Size-a -> 10 | F5: =(EXP(alpha*(Tau+OldTau+zeta-2*a*psi))*((EXP(alpha*a*psi)-EXP(alpha*b*psi))^2))/((EXP(alpha*a*psi)-EXP(alpha*(2*OldTau+b*psi)))*(alpha^2)*(psi^2)) -> 3.7766804 | G5: =(EXP(alpha*(zeta+(2*b-a)*psi))*(-1+EXP(alpha*(-1)*Size*psi))*(EXP(alpha*(2*(Tau+OldTau)+a*psi))-EXP(alpha*(2*(Tau+OldTau)+b*psi))))/(((EXP(alpha*a*psi)-EXP(alpha*(2*OldTau+b*psi)))^2)*(alpha^2)*(psi^2)) -> 0.40592608 | H5: =-Beta/alpha -> 180 | I5: =(-EXP(alpha*zeta)*Beta*(-1+EXP(alpha*Size*psi)-Size*alpha*psi))/((alpha^3)*(psi^2)) -> 1690.9246 | J5: =Beta*Theta -> 14.4 | K5: =Beta*Theta -> 14.4 | L5: =kappa -> 90 | M5: =Gamma*Size -> 0 | N5: =Size*Beta*Phi -> 32.4 | O5: =-(EXP(alpha*a*psi)+EXP(alpha*b*psi)*(-1+Size*psi*alpha))*(Beta*Phi)/((alpha*psi)*(EXP(alpha*a*psi)-EXP(alpha*b*psi))) -> 12.294172 | P5: =(EXP(alpha*(zeta-a*psi))*Beta*Phi*(-EXP(alpha*a*psi)*(-2+(-1)*Size*alpha*psi)+EXP(alpha*b*psi)*(-2+Size*alpha*psi)))/((alpha^3)*(psi^3)) -> 78.836376 | Q5: =Tau*Beta -> 36 | R5: =Tau*Beta -> 36 | S5: =Tau -> 0.2 | T5: =Profit+Utility -> 2276.565 | U5: =ij*BUTIJ+BUTII -> 2370.7271 | V5: =Revenue-Cost -> -94.162097 | W5: =(2*ij*BRIJ)+(2)*jj*BRJJ -> 301.14767 | X5: =2*(ij*BCCIJ)+(2*jj*BCCJJ)+BCS+jj*BCPTJJ+2*(ij*BCPTIJ)+BCPTII+BCk -> 395.30976
A6: =A5+0.1 -> 0.3 | B6: 0.6 | C6: 10 | D6: 0 | E6: =Size-a -> 10 | F6: =(EXP(alpha*(Tau+OldTau+zeta-2*a*psi))*((EXP(alpha*a*psi)-EXP(alpha*b*psi))^2))/((EXP(alpha*a*psi)-EXP(alpha*(2*OldTau+b*psi)))*(alpha^2)*(psi^2)) -> 3.4172818 | G6: =(EXP(alpha*(zeta+(2*b-a)*psi))*(-1+EXP(alpha*(-1)*Size*psi))*(EXP(alpha*(2*(Tau+OldTau)+a*psi))-EXP(alpha*(2*(Tau+OldTau)+b*psi))))/(((EXP(alpha*a*psi)-EXP(alpha*(2*OldTau+b*psi)))^2)*(alpha^2)*(psi^2)) -> 0.33234417 | H6: =-Beta/alpha -> 180 | I6: =(-EXP(alpha*zeta)*Beta*(-1+EXP(alpha*Size*psi)-Size*alpha*psi))/((alpha^3)*(psi^2)) -> 1690.9246 | J6: =Beta*Theta -> 14.4 | K6: =Beta*Theta -> 14.4 | L6: =kappa -> 90 | M6: =Gamma*Size -> 0 | N6: =Size*Beta*Phi -> 32.4 | O6: =-(EXP(alpha*a*psi)+EXP(alpha*b*psi)*(-1+Size*psi*alpha))*(Beta*Phi)/((alpha*psi)*(EXP(alpha*a*psi)-EXP(alpha*b*psi))) -> 12.294172 | P6: =(EXP(alpha*(zeta-a*psi))*Beta*Phi*(-EXP(alpha*a*psi)*(-2+(-1)*Size*alpha*psi)+EXP(alpha*b*psi)*(-2+Size*alpha*psi)))/((alpha^3)*(psi^3)) -> 78.836376 | Q6: =Tau*Beta -> 54 | R6: =Tau*Beta -> 54 | S6: =Tau -> 0.3 | T6: =Profit+Utility -> 2339.3761 | U6: =ij*BUTIJ+BUTII -> 2306.0353 | V6: =Revenue-Cost -> 33.340747 | W6: =(2*ij*BRIJ)+(2)*jj*BRJJ -> 404.9596 | X6: =2*(ij*BCCIJ)+(2*jj*BCCJJ)+BCS+jj*BCPTJJ+2*(ij*BCPTIJ)+BCPTII+BCk -> 371.61885
A7: =A6+0.1 -> 0.4 | B7: 0.6 | C7: 10 | D7: 0 | E7: =Size-a -> 10 | F7: =(EXP(alpha*(Tau+OldTau+zeta-2*a*psi))*((EXP(alpha*a*psi)-EXP(alpha*b*psi))^2))/((EXP(alpha*a*psi)-EXP(alpha*(2*OldTau+b*psi)))*(alpha^2)*(psi^2)) -> 3.0920844 | G7: =(EXP(alpha*(zeta+(2*b-a)*psi))*(-1+EXP(alpha*(-1)*Size*psi))*(EXP(alpha*(2*(Tau+OldTau)+a*psi))-EXP(alpha*(2*(Tau+OldTau)+b*psi))))/(((EXP(alpha*a*psi)-EXP(alpha*(2*OldTau+b*psi)))^2)*(alpha^2)*(psi^2)) -> 0.27210039 | H7: =-Beta/alpha -> 180 | I7: =(-EXP(alpha*zeta)*Beta*(-1+EXP(alpha*Size*psi)-Size*alpha*psi))/((alpha^3)*(psi^2)) -> 1690.9246 | J7: =Beta*Theta -> 14.4 | K7: =Beta*Theta -> 14.4 | L7: =kappa -> 90 | M7: =Gamma*Size -> 0 | N7: =Size*Beta*Phi -> 32.4 | O7: =-(EXP(alpha*a*psi)+EXP(alpha*b*psi)*(-1+Size*psi*alpha))*(Beta*Phi)/((alpha*psi)*(EXP(alpha*a*psi)-EXP(alpha*b*psi))) -> 12.294172 | P7: =(EXP(alpha*(zeta-a*psi))*Beta*Phi*(-EXP(alpha*a*psi)*(-2+(-1)*Size*alpha*psi)+EXP(alpha*b*psi)*(-2+Size*alpha*psi)))/((alpha^3)*(psi^3)) -> 78.836376 | Q7: =Tau*Beta -> 72 | R7: =Tau*Beta -> 72 | S7: =Tau -> 0.4 | T7: =Profit+Utility -> 2381.3722 | U7: =ij*BUTIJ+BUTII -> 2247.4998 | V7: =Revenue-Cost -> 133.87242 | W7: =(2*ij*BRIJ)+(2)*jj*BRJJ -> 484.44261 | X7: =2*(ij*BCCIJ)+(2*jj*BCCJJ)+BCS+jj*BCPTJJ+2*(ij*BCPTIJ)+BCPTII+BCk -> 350.57018
A8: =A7+0.1 -> 0.5 | B8: 0.6 | C8: 10 | D8: 0 | E8: =Size-a -> 10 | F8: =(EXP(alpha*(Tau+OldTau+zeta-2*a*psi))*((EXP(alpha*a*psi)-EXP(alpha*b*psi))^2))/((EXP(alpha*a*psi)-EXP(alpha*(2*OldTau+b*psi)))*(alpha^2)*(psi^2)) -> 2.7978337 | G8: =(EXP(alpha*(zeta+(2*b-a)*psi))*(-1+EXP(alpha*(-1)*Size*psi))*(EXP(alpha*(2*(Tau+OldTau)+a*psi))-EXP(alpha*(2*(Tau+OldTau)+b*psi))))/(((EXP(alpha*a*psi)-EXP(alpha*(2*OldTau+b*psi)))^2)*(alpha^2)*(psi^2)) -> 0.22277696 | H8: =-Beta/alpha -> 180 | I8: =(-EXP(alpha*zeta)*Beta*(-1+EXP(alpha*Size*psi)-Size*alpha*psi))/((alpha^3)*(psi^2)) -> 1690.9246 | J8: =Beta*Theta -> 14.4 | K8: =Beta*Theta -> 14.4 | L8: =kappa -> 90 | M8: =Gamma*Size -> 0 | N8: =Size*Beta*Phi -> 32.4 | O8: =-(EXP(alpha*a*psi)+EXP(alpha*b*psi)*(-1+Size*psi*alpha))*(Beta*Phi)/((alpha*psi)*(EXP(alpha*a*psi)-EXP(alpha*b*psi))) -> 12.294172 | P8: =(EXP(alpha*(zeta-a*psi))*Beta*Phi*(-EXP(alpha*a*psi)*(-2+(-1)*Size*alpha*psi)+EXP(alpha*b*psi)*(-2+Size*alpha*psi)))/((alpha^3)*(psi^3)) -> 78.836376 | Q8: =Tau*Beta -> 90 | R8: =Tau*Beta -> 90 | S8: =Tau -> 0.5 | T8: =Profit+Utility -> 2406.4026 | U8: =ij*BUTIJ+BUTII -> 2194.5347 | V8: =Revenue-Cost -> 211.86788 | W8: =(2*ij*BRIJ)+(2)*jj*BRJJ -> 543.70991 | X8: =2*(ij*BCCIJ)+(2*jj*BCCJJ)+BCS+jj*BCPTJJ+2*(ij*BCPTIJ)+BCPTII+BCk -> 331.84203
A9: =A8+0.1 -> 0.6 | B9: 0.6 | C9: 10 | D9: 0 | E9: =Size-a -> 10 | F9: =(EXP(alpha*(Tau+OldTau+zeta-2*a*psi))*((EXP(alpha*a*psi)-EXP(alpha*b*psi))^2))/((EXP(alpha*a*psi)-EXP(alpha*(2*OldTau+b*psi)))*(alpha^2)*(psi^2)) -> 2.5315846 | G9: =(EXP(alpha*(zeta+(2*b-a)*psi))*(-1+EXP(alpha*(-1)*Size*psi))*(EXP(alpha*(2*(Tau+OldTau)+a*psi))-EXP(alpha*(2*(Tau+OldTau)+b*psi))))/(((EXP(alpha*a*psi)-EXP(alpha*(2*OldTau+b*psi)))^2)*(alpha^2)*(psi^2)) -> 0.18239435 | H9: =-Beta/alpha -> 180 | I9: =(-EXP(alpha*zeta)*Beta*(-1+EXP(alpha*Size*psi)-Size*alpha*psi))/((alpha^3)*(psi^2)) -> 1690.9246 | J9: =Beta*Theta -> 14.4 | K9: =Beta*Theta -> 14.4 | L9: =kappa -> 90 | M9: =Gamma*Size -> 0 | N9: =Size*Beta*Phi -> 32.4 | O9: =-(EXP(alpha*a*psi)+EXP(alpha*b*psi)*(-1+Size*psi*alpha))*(Beta*Phi)/((alpha*psi)*(EXP(alpha*a*psi)-EXP(alpha*b*psi))) -> 12.294172 | P9: =(EXP(alpha*(zeta-a*psi))*Beta*Phi*(-EXP(alpha*a*psi)*(-2+(-1)*Size*alpha*psi)+EXP(alpha*b*psi)*(-2+Size*alpha*psi)))/((alpha^3)*(psi^3)) -> 78.836376 | Q9: =Tau*Beta -> 108 | R9: =Tau*Beta -> 108 | S9: =Tau -> 0.6 | T9: =Profit+Utility -> 2417.6733 | U9: =ij*BUTIJ+BUTII -> 2146.6099 | V9: =Revenue-Cost -> 271.06343 | W9: =(2*ij*BRIJ)+(2)*jj*BRJJ -> 586.21945 | X9: =2*(ij*BCCIJ)+(2*jj*BCCJJ)+BCS+jj*BCPTJJ+2*(ij*BCPTIJ)+BCPTII+BCk -> 315.15602
A10: =A9+0.1 -> 0.7 | B10: 0.6 | C10: 10 | D10: 0 | E10: =Size-a -> 10 | F10: =(EXP(alpha*(Tau+OldTau+zeta-2*a*psi))*((EXP(alpha*a*psi)-EXP(alpha*b*psi))^2))/((EXP(alpha*a*psi)-EXP(alpha*(2*OldTau+b*psi)))*(alpha^2)*(psi^2)) -> 2.2906725 | G10: =(EXP(alpha*(zeta+(2*b-a)*psi))*(-1+EXP(alpha*(-1)*Size*psi))*(EXP(alpha*(2*(Tau+OldTau)+a*psi))-EXP(alpha*(2*(Tau+OldTau)+b*psi))))/(((EXP(alpha*a*psi)-EXP(alpha*(2*OldTau+b*psi)))^2)*(alpha^2)*(psi^2)) -> 0.14933186 | H10: =-Beta/alpha -> 180 | I10: =(-EXP(alpha*zeta)*Beta*(-1+EXP(alpha*Size*psi)-Size*alpha*psi))/((alpha^3)*(psi^2)) -> 1690.9246 | J10: =Beta*Theta -> 14.4 | K10: =Beta*Theta -> 14.4 | L10: =kappa -> 90 | M10: =Gamma*Size -> 0 | N10: =Size*Beta*Phi -> 32.4 | O10: =-(EXP(alpha*a*psi)+EXP(alpha*b*psi)*(-1+Size*psi*alpha))*(Beta*Phi)/((alpha*psi)*(EXP(alpha*a*psi)-EXP(alpha*b*psi))) -> 12.294172 | P10: =(EXP(alpha*(zeta-a*psi))*Beta*Phi*(-EXP(alpha*a*psi)*(-2+(-1)*Size*alpha*psi)+EXP(alpha*b*psi)*(-2+Size*alpha*psi)))/((alpha^3)*(psi^3)) -> 78.836376 | Q10: =Tau*Beta -> 126 | R10: =Tau*Beta -> 126 | S10: =Tau -> 0.7 | T10: =Profit+Utility -> 2417.8561 | U10: =ij*BUTIJ+BUTII -> 2103.2457 | V10: =Revenue-Cost -> 314.61039 | W10: =(2*ij*BRIJ)+(2)*jj*BRJJ -> 614.88109 | X10: =2*(ij*BCCIJ)+(2*jj*BCCJJ)+BCS+jj*BCPTJJ+2*(ij*BCPTIJ)+BCPTII+BCk -> 300.27069
A11: =A10+0.1 -> 0.8 | B11: 0.6 | C11: 10 | D11: 0 | E11: =Size-a -> 10 | F11: =(EXP(alpha*(Tau+OldTau+zeta-2*a*psi))*((EXP(alpha*a*psi)-EXP(alpha*b*psi))^2))/((EXP(alpha*a*psi)-EXP(alpha*(2*OldTau+b*psi)))*(alpha^2)*(psi^2)) -> 2.0726862 | G11: =(EXP(alpha*(zeta+(2*b-a)*psi))*(-1+EXP(alpha*(-1)*Size*psi))*(EXP(alpha*(2*(Tau+OldTau)+a*psi))-EXP(alpha*(2*(Tau+OldTau)+b*psi))))/(((EXP(alpha*a*psi)-EXP(alpha*(2*OldTau+b*psi)))^2)*(alpha^2)*(psi^2)) -> 0.12226259 | H11: =-Beta/alpha -> 180 | I11: =(-EXP(alpha*zeta)*Beta*(-1+EXP(alpha*Size*psi)-Size*alpha*psi))/((alpha^3)*(psi^2)) -> 1690.9246 | J11: =Beta*Theta -> 14.4 | K11: =Beta*Theta -> 14.4 | L11: =kappa -> 90 | M11: =Gamma*Size -> 0 | N11: =Size*Beta*Phi -> 32.4 | O11: =-(EXP(alpha*a*psi)+EXP(alpha*b*psi)*(-1+Size*psi*alpha))*(Beta*Phi)/((alpha*psi)*(EXP(alpha*a*psi)-EXP(alpha*b*psi))) -> 12.294172 | P11: =(EXP(alpha*(zeta-a*psi))*Beta*Phi*(-EXP(alpha*a*psi)*(-2+(-1)*Size*alpha*psi)+EXP(alpha*b*psi)*(-2+Size*alpha*psi)))/((alpha^3)*(psi^3)) -> 78.836376 | Q11: =Tau*Beta -> 144 | R11: =Tau*Beta -> 144 | S11: =Tau -> 0.8 | T11: =Profit+Utility -> 2409.1772 | U11: =ij*BUTIJ+BUTII -> 2064.0081 | V11: =Revenue-Cost -> 345.16911 | W11: =(2*ij*BRIJ)+(2)*jj*BRJJ -> 632.14524 | X11: =2*(ij*BCCIJ)+(2*jj*BCCJJ)+BCS+jj*BCPTJJ+2*(ij*BCPTIJ)+BCPTII+BCk -> 286.97613
A12: =A11+0.1 -> 0.9 | B12: 0.6 | C12: 10 | D12: 0 | E12: =Size-a -> 10 | F12: =(EXP(alpha*(Tau+OldTau+zeta-2*a*psi))*((EXP(alpha*a*psi)-EXP(alpha*b*psi))^2))/((EXP(alpha*a*psi)-EXP(alpha*(2*OldTau+b*psi)))*(alpha^2)*(psi^2)) -> 1.875444 | G12: =(EXP(alpha*(zeta+(2*b-a)*psi))*(-1+EXP(alpha*(-1)*Size*psi))*(EXP(alpha*(2*(Tau+OldTau)+a*psi))-EXP(alpha*(2*(Tau+OldTau)+b*psi))))/(((EXP(alpha*a*psi)-EXP(alpha*(2*OldTau+b*psi)))^2)*(alpha^2)*(psi^2)) -> 0.10010014 | H12: =-Beta/alpha -> 180 | I12: =(-EXP(alpha*zeta)*Beta*(-1+EXP(alpha*Size*psi)-Size*alpha*psi))/((alpha^3)*(psi^2)) -> 1690.9246 | J12: =Beta*Theta -> 14.4 | K12: =Beta*Theta -> 14.4 | L12: =kappa -> 90 | M12: =Gamma*Size -> 0 | N12: =Size*Beta*Phi -> 32.4 | O12: =-(EXP(alpha*a*psi)+EXP(alpha*b*psi)*(-1+Size*psi*alpha))*(Beta*Phi)/((alpha*psi)*(EXP(alpha*a*psi)-EXP(alpha*b*psi))) -> 12.294172 | P12: =(EXP(alpha*(zeta-a*psi))*Beta*Phi*(-EXP(alpha*a*psi)*(-2+(-1)*Size*alpha*psi)+EXP(alpha*b*psi)*(-2+Size*alpha*psi)))/((alpha^3)*(psi^3)) -> 78.836376 | Q12: =Tau*Beta -> 162 | R12: =Tau*Beta -> 162 | S12: =Tau -> 0.9 | T12: =Profit+Utility -> 2393.4915 | U12: =ij*BUTIJ+BUTII -> 2028.5045 | V12: =Revenue-Cost -> 364.98694 | W12: =(2*ij*BRIJ)+(2)*jj*BRJJ -> 640.0763 | X12: =2*(ij*BCCIJ)+(2*jj*BCCJJ)+BCS+jj*BCPTJJ+2*(ij*BCPTIJ)+BCPTII+BCk -> 275.08935
A13: =A12+0.1 -> 1 | B13: 0.6 | C13: 10 | D13: 0 | E13: =Size-a -> 10 | F13: =(EXP(alpha*(Tau+OldTau+zeta-2*a*psi))*((EXP(alpha*a*psi)-EXP(alpha*b*psi))^2))/((EXP(alpha*a*psi)-EXP(alpha*(2*OldTau+b*psi)))*(alpha^2)*(psi^2)) -> 1.6969719 | G13: =(EXP(alpha*(zeta+(2*b-a)*psi))*(-1+EXP(alpha*(-1)*Size*psi))*(EXP(alpha*(2*(Tau+OldTau)+a*psi))-EXP(alpha*(2*(Tau+OldTau)+b*psi))))/(((EXP(alpha*a*psi)-EXP(alpha*(2*OldTau+b*psi)))^2)*(alpha^2)*(psi^2)) -> 0.081955062 | H13: =-Beta/alpha -> 180 | I13: =(-EXP(alpha*zeta)*Beta*(-1+EXP(alpha*Size*psi)-Size*alpha*psi))/((alpha^3)*(psi^2)) -> 1690.9246 | J13: =Beta*Theta -> 14.4 | K13: =Beta*Theta -> 14.4 | L13: =kappa -> 90 | M13: =Gamma*Size -> 0 | N13: =Size*Beta*Phi -> 32.4 | O13: =-(EXP(alpha*a*psi)+EXP(alpha*b*psi)*(-1+Size*psi*alpha))*(Beta*Phi)/((alpha*psi)*(EXP(alpha*a*psi)-EXP(alpha*b*psi))) -> 12.294172 | P13: =(EXP(alpha*(zeta-a*psi))*Beta*Phi*(-EXP(alpha*a*psi)*(-2+(-1)*Size*alpha*psi)+EXP(alpha*b*psi)*(-2+Size*alpha*psi)))/((alpha^3)*(psi^3)) -> 78.836376 | Q13: =Tau*Beta -> 180 | R13: =Tau*Beta -> 180 | S13: =Tau -> 1 | T13: =Profit+Utility -> 2372.3427 | U13: =ij*BUTIJ+BUTII -> 1996.3796 | V13: =Revenue-Cost -> 375.96316 | W13: =(2*ij*BRIJ)+(2)*jj*BRJJ -> 640.41371 | X13: =2*(ij*BCCIJ)+(2*jj*BCCJJ)+BCS+jj*BCPTJJ+2*(ij*BCPTIJ)+BCPTII+BCk -> 264.45054
A14: =A13+0.1 -> 1.1 | B14: 0.6 | C14: 10 | D14: 0 | E14: =Size-a -> 10 | F14: =(EXP(alpha*(Tau+OldTau+zeta-2*a*psi))*((EXP(alpha*a*psi)-EXP(alpha*b*psi))^2))/((EXP(alpha*a*psi)-EXP(alpha*(2*OldTau+b*psi)))*(alpha^2)*(psi^2)) -> 1.5354837 | G14: =(EXP(alpha*(zeta+(2*b-a)*psi))*(-1+EXP(alpha*(-1)*Size*psi))*(EXP(alpha*(2*(Tau+OldTau)+a*psi))-EXP(alpha*(2*(Tau+OldTau)+b*psi))))/(((EXP(alpha*a*psi)-EXP(alpha*(2*OldTau+b*psi)))^2)*(alpha^2)*(psi^2)) -> 0.06709913 | H14: =-Beta/alpha -> 180 | I14: =(-EXP(alpha*zeta)*Beta*(-1+EXP(alpha*Size*psi)-Size*alpha*psi))/((alpha^3)*(psi^2)) -> 1690.9246 | J14: =Beta*Theta -> 14.4 | K14: =Beta*Theta -> 14.4 | L14: =kappa -> 90 | M14: =Gamma*Size -> 0 | N14: =Size*Beta*Phi -> 32.4 | O14: =-(EXP(alpha*a*psi)+EXP(alpha*b*psi)*(-1+Size*psi*alpha))*(Beta*Phi)/((alpha*psi)*(EXP(alpha*a*psi)-EXP(alpha*b*psi))) -> 12.294172 | P14: =(EXP(alpha*(zeta-a*psi))*Beta*Phi*(-EXP(alpha*a*psi)*(-2+(-1)*Size*alpha*psi)+EXP(alpha*b*psi)*(-2+Size*alpha*psi)))/((alpha^3)*(psi^3)) -> 78.836376 | Q14: =Tau*Beta -> 198 | R14: =Tau*Beta -> 198 | S14: =Tau -> 1.1 | T14: =Profit+Utility -> 2347.0147 | U14: =ij*BUTIJ+BUTII -> 1967.3117 | V14: =Revenue-Cost -> 379.70302 | W14: =(2*ij*BRIJ)+(2)*jj*BRJJ -> 634.62279 | X14: =2*(ij*BCCIJ)+(2*jj*BCCJJ)+BCS+jj*BCPTJJ+2*(ij*BCPTIJ)+BCPTII+BCk -> 254.91977
A15: =A14+0.1 -> 1.2 | B15: 0.6 | C15: 10 | D15: 0 | E15: =Size-a -> 10 | F15: =(EXP(alpha*(Tau+OldTau+zeta-2*a*psi))*((EXP(alpha*a*psi)-EXP(alpha*b*psi))^2))/((EXP(alpha*a*psi)-EXP(alpha*(2*OldTau+b*psi)))*(alpha^2)*(psi^2)) -> 1.3893631 | G15: =(EXP(alpha*(zeta+(2*b-a)*psi))*(-1+EXP(alpha*(-1)*Size*psi))*(EXP(alpha*(2*(Tau+OldTau)+a*psi))-EXP(alpha*(2*(Tau+OldTau)+b*psi))))/(((EXP(alpha*a*psi)-EXP(alpha*(2*OldTau+b*psi)))^2)*(alpha^2)*(psi^2)) -> 0.054936121 | H15: =-Beta/alpha -> 180 | I15: =(-EXP(alpha*zeta)*Beta*(-1+EXP(alpha*Size*psi)-Size*alpha*psi))/((alpha^3)*(psi^2)) -> 1690.9246 | J15: =Beta*Theta -> 14.4 | K15: =Beta*Theta -> 14.4 | L15: =kappa -> 90 | M15: =Gamma*Size -> 0 | N15: =Size*Beta*Phi -> 32.4 | O15: =-(EXP(alpha*a*psi)+EXP(alpha*b*psi)*(-1+Size*psi*alpha))*(Beta*Phi)/((alpha*psi)*(EXP(alpha*a*psi)-EXP(alpha*b*psi))) -> 12.294172 | P15: =(EXP(alpha*(zeta-a*psi))*Beta*Phi*(-EXP(alpha*a*psi)*(-2+(-1)*Size*alpha*psi)+EXP(alpha*b*psi)*(-2+Size*alpha*psi)))/((alpha^3)*(psi^3)) -> 78.836376 | Q15: =Tau*Beta -> 216 | R15: =Tau*Beta -> 216 | S15: =Tau -> 1.2 | T15: =Profit+Utility -> 2318.573 | U15: =ij*BUTIJ+BUTII -> 1941.01 | V15: =Revenue-Cost -> 377.56299 | W15: =(2*ij*BRIJ)+(2)*jj*BRJJ -> 623.93725 | X15: =2*(ij*BCCIJ)+(2*jj*BCCJJ)+BCS+jj*BCPTJJ+2*(ij*BCPTIJ)+BCPTII+BCk -> 246.37426
A16: =A15+0.1 -> 1.3 | B16: 0.6 | C16: 10 | D16: 0 | E16: =Size-a -> 10 | F16: =(EXP(alpha*(Tau+OldTau+zeta-2*a*psi))*((EXP(alpha*a*psi)-EXP(alpha*b*psi))^2))/((EXP(alpha*a*psi)-EXP(alpha*(2*OldTau+b*psi)))*(alpha^2)*(psi^2)) -> 1.2571477 | G16: =(EXP(alpha*(zeta+(2*b-a)*psi))*(-1+EXP(alpha*(-1)*Size*psi))*(EXP(alpha*(2*(Tau+OldTau)+a*psi))-EXP(alpha*(2*(Tau+OldTau)+b*psi))))/(((EXP(alpha*a*psi)-EXP(alpha*(2*OldTau+b*psi)))^2)*(alpha^2)*(psi^2)) -> 0.044977892 | H16: =-Beta/alpha -> 180 | I16: =(-EXP(alpha*zeta)*Beta*(-1+EXP(alpha*Size*psi)-Size*alpha*psi))/((alpha^3)*(psi^2)) -> 1690.9246 | J16: =Beta*Theta -> 14.4 | K16: =Beta*Theta -> 14.4 | L16: =kappa -> 90 | M16: =Gamma*Size -> 0 | N16: =Size*Beta*Phi -> 32.4 | O16: =-(EXP(alpha*a*psi)+EXP(alpha*b*psi)*(-1+Size*psi*alpha))*(Beta*Phi)/((alpha*psi)*(EXP(alpha*a*psi)-EXP(alpha*b*psi))) -> 12.294172 | P16: =(EXP(alpha*(zeta-a*psi))*Beta*Phi*(-EXP(alpha*a*psi)*(-2+(-1)*Size*alpha*psi)+EXP(alpha*b*psi)*(-2+Size*alpha*psi)))/((alpha^3)*(psi^3)) -> 78.836376 | Q16: =Tau*Beta -> 234 | R16: =Tau*Beta -> 234 | S16: =Tau -> 1.3 | T16: =Profit+Utility -> 2287.8999 | U16: =ij*BUTIJ+BUTII -> 1917.2112 | V16: =Revenue-Cost -> 370.68872 | W16: =(2*ij*BRIJ)+(2)*jj*BRJJ -> 609.39478 | X16: =2*(ij*BCCIJ)+(2*jj*BCCJJ)+BCS+jj*BCPTJJ+2*(ij*BCPTIJ)+BCPTII+BCk -> 238.70606
... A51: =A50+0.1 -> 4.8 | B51: 0.6 | C51: 10 | D51: 0 | E51: =Size-a -> 10 | F51: =(EXP(alpha*(Tau+OldTau+zeta-2*a*psi))*((EXP(alpha*a*psi)-EXP(alpha*b*psi))^2))/((EXP(alpha*a*psi)-EXP(alpha*(2*OldTau+b*psi)))*(alpha^2)*(psi^2)) -> 0.037962571 | G51: =(EXP(alpha*(zeta+(2*b-a)*psi))*(-1+EXP(alpha*(-1)*Size*psi))*(EXP(alpha*(2*(Tau+OldTau)+a*psi))-EXP(alpha*(2*(Tau+OldTau)+b*psi))))/(((EXP(alpha*a*psi)-EXP(alpha*(2*OldTau+b*psi)))^2)*(alpha^2)*(psi^2)) -> 4.1014528e-05 | H51: =-Beta/alpha -> 180 | I51: =(-EXP(alpha*zeta)*Beta*(-1+EXP(alpha*Size*psi)-Size*alpha*psi))/((alpha^3)*(psi^2)) -> 1690.9246 | J51: =Beta*Theta -> 14.4 | K51: =Beta*Theta -> 14.4 | L51: =kappa -> 90 | M51: =Gamma*Size -> 0 | N51: =Size*Beta*Phi -> 32.4 | O51: =-(EXP(alpha*a*psi)+EXP(alpha*b*psi)*(-1+Size*psi*alpha))*(Beta*Phi)/((alpha*psi)*(EXP(alpha*a*psi)-EXP(alpha*b*psi))) -> 12.294172 | P51: =(EXP(alpha*(zeta-a*psi))*Beta*Phi*(-EXP(alpha*a*psi)*(-2+(-1)*Size*alpha*psi)+EXP(alpha*b*psi)*(-2+Size*alpha*psi)))/((alpha^3)*(psi^3)) -> 78.836376 | Q51: =Tau*Beta -> 864 | R51: =Tau*Beta -> 864 | S51: =Tau -> 4.8 | T51: =Profit+Utility -> 1592.5624 | U51: =ij*BUTIJ+BUTII -> 1697.7579 | V51: =Revenue-Cost -> -105.19545 | W51: =(2*ij*BRIJ)+(2)*jj*BRJJ -> 65.670196 | X51: =2*(ij*BCCIJ)+(2*jj*BCCJJ)+BCS+jj*BCPTJJ+2*(ij*BCPTIJ)+BCPTII+BCk -> 170.86564

Sheet S-Wcompare
B1: All-Tax Environment | E1: All-Toll Environment
A2: Toll | B2: Welfare-Tax Environment | C2: Consumers' Surplus-Tax Environment | D2: Profit-Tax Environment | E2: Welfare-Toll Enviornment | F2: Consumers' Surplus-Toll Environment | G2: Profit-Toll Environment
A3: 0 | B3: ='S-Toll (All-Tax)'!T2 -> 3086.6096 | C3: ='S-Toll (All-Tax)'!U2 -> 3507.5109 | D3: ='S-Toll (All-Tax)'!V2 -> -420.90131 | E3: ='S-Toll(All-Toll)'!T2 -> 2309.3581 | F3: ='S-Toll(All-Toll)'!U2 -> 2521.2372 | G3: ='S-Toll(All-Toll)'!V2 -> -211.87915
A4: 0 | B4: ='S-Toll (All-Tax)'!T3 -> 2622.4751 | C4: ='S-Toll (All-Tax)'!U3 -> 3507.5109 | D4: ='S-Toll (All-Tax)'!V3 -> -885.03581 | E4: ='S-Toll(All-Toll)'!T3 -> 2069.0676 | F4: ='S-Toll(All-Toll)'!U3 -> 2521.2372 | G4: ='S-Toll(All-Toll)'!V3 -> -452.1696
A5: 0.1 | B5: ='S-Toll (All-Tax)'!T4 -> 2947.2128 | C5: ='S-Toll (All-Tax)'!U4 -> 3334.6399 | D5: ='S-Toll (All-Tax)'!V4 -> -387.42709 | E5: ='S-Toll(All-Toll)'!T4 -> 2188.3152 | F5: ='S-Toll(All-Toll)'!U4 -> 2442.2226 | G5: ='S-Toll(All-Toll)'!V4 -> -253.90733
A6: 0.2 | B6: ='S-Toll (All-Tax)'!T5 -> 3184.1513 | C6: ='S-Toll (All-Tax)'!U5 -> 3178.2197 | D6: ='S-Toll (All-Tax)'!V5 -> 5.9316365 | E6: ='S-Toll(All-Toll)'!T5 -> 2276.565 | F6: ='S-Toll(All-Toll)'!U5 -> 2370.7271 | G6: ='S-Toll(All-Toll)'!V5 -> -94.162097
A7: 0.3 | B7: ='S-Toll (All-Tax)'!T6 -> 3350.5992 | C7: ='S-Toll (All-Tax)'!U6 -> 3036.6849 | D7: ='S-Toll (All-Tax)'!V6 -> 313.91437 | E7: ='S-Toll(All-Toll)'!T6 -> 2339.3761 | F7: ='S-Toll(All-Toll)'!U6 -> 2306.0353 | G7: ='S-Toll(All-Toll)'!V6 -> 33.340747
A8: 0.4 | B8: ='S-Toll (All-Tax)'!T7 -> 3460.6095 | C8: ='S-Toll (All-Tax)'!U7 -> 2908.6188 | D8: ='S-Toll (All-Tax)'!V7 -> 551.99066 | E8: ='S-Toll(All-Toll)'!T7 -> 2381.3722 | F8: ='S-Toll(All-Toll)'!U7 -> 2247.4998 | G8: ='S-Toll(All-Toll)'!V7 -> 133.87242
A9: 0.5 | B9: ='S-Toll (All-Tax)'!T8 -> 3525.6005 | C9: ='S-Toll (All-Tax)'!U8 -> 2792.7399 | D9: ='S-Toll (All-Tax)'!V8 -> 732.86057 | E9: ='S-Toll(All-Toll)'!T8 -> 2406.4026 | F9: ='S-Toll(All-Toll)'!U8 -> 2194.5347 | G9: ='S-Toll(All-Toll)'!V8 -> 211.86788
A10: 0.6 | B10: ='S-Toll (All-Tax)'!T9 -> 3554.8555 | C10: ='S-Toll (All-Tax)'!U9 -> 2687.8883 | D10: ='S-Toll (All-Tax)'!V9 -> 866.9672 | E10: ='S-Toll(All-Toll)'!T9 -> 2417.6733 | F10: ='S-Toll(All-Toll)'!U9 -> 2146.6099 | G10: ='S-Toll(All-Toll)'!V9 -> 271.06343
A11: 0.7 | B11: ='S-Toll (All-Tax)'!T10 -> 3555.9256 | C11: ='S-Toll (All-Tax)'!U10 -> 2593.0147 | D11: ='S-Toll (All-Tax)'!V10 -> 962.91089 | E11: ='S-Toll(All-Toll)'!T10 -> 2417.8561 | F11: ='S-Toll(All-Toll)'!U10 -> 2103.2457 | G11: ='S-Toll(All-Toll)'!V10 -> 314.61039
A12: 0.8 | B12: ='S-Toll (All-Tax)'!T11 -> 3534.9539 | C12: ='S-Toll (All-Tax)'!U11 -> 2507.1695 | D12: ='S-Toll (All-Tax)'!V11 -> 1027.7845 | E12: ='S-Toll(All-Toll)'!T11 -> 2409.1772 | F12: ='S-Toll(All-Toll)'!U11 -> 2064.0081 | G12: ='S-Toll(All-Toll)'!V11 -> 345.16911
A13: 0.9 | B13: ='S-Toll (All-Tax)'!T12 -> 3496.9385 | C13: ='S-Toll (All-Tax)'!U12 -> 2429.4935 | D13: ='S-Toll (All-Tax)'!V12 -> 1067.445 | E13: ='S-Toll(All-Toll)'!T12 -> 2393.4915 | F13: ='S-Toll(All-Toll)'!U12 -> 2028.5045 | G13: ='S-Toll(All-Toll)'!V12 -> 364.98694
A14: 1 | B14: ='S-Toll (All-Tax)'!T13 -> 3445.9435 | C14: ='S-Toll (All-Tax)'!U13 -> 2359.2094 | D14: ='S-Toll (All-Tax)'!V13 -> 1086.7341 | E14: ='S-Toll(All-Toll)'!T13 -> 2372.3427 | F14: ='S-Toll(All-Toll)'!U13 -> 1996.3796 | G14: ='S-Toll(All-Toll)'!V13 -> 375.96316
... A52: 4.8 | B52: ='S-Toll (All-Tax)'!T51 -> 1676.4518 | C52: ='S-Toll (All-Tax)'!U51 -> 1705.8747 | D52: ='S-Toll (All-Tax)'!V51 -> -29.422921 | E52: ='S-Toll(All-Toll)'!T51 -> 1592.5624 | F52: ='S-Toll(All-Toll)'!U51 -> 1697.7579 | G52: ='S-Toll(All-Toll)'!V51 -> -105.19545

Sheet W-React-JS=10
A1: Tau | B1: OldTau | C1: Size | D1: a | E1: b | F1: ij | G1: jj | H1: BUTIJ | I1: BUTII | J1: BCCIJ | K1: BCCJJ | L1: BCk | M1: BCS | N1: BCPTJJ | O1: BCPTIJ | P1: BCPTII | Q1: BRIJ | R1: BRJJ | S1: Toll | T1: Welfare | U1: Revenue | V1: Cost | W1: Utility | X1: Profit
A2: 0.65329456 | B2: 0 | C2: 10 | D2: 0 | E2: =Size-a -> 10 | F2: =(EXP(alpha*(Tau+OldTau+zeta-2*a*psi))*((EXP(alpha*a*psi)-EXP(alpha*b*psi))^2))/((EXP(alpha*a*psi)-EXP(alpha*(2*OldTau+b*psi)))*(alpha^2)*(psi^2)) -> 5.2512332 | G2: =(EXP(alpha*(zeta+(2*b-a)*psi))*(-1+EXP(alpha*(-1)*Size*psi))*(EXP(alpha*(2*(Tau+OldTau)+a*psi))-EXP(alpha*(2*(Tau+OldTau)+b*psi))))/(((EXP(alpha*a*psi)-EXP(alpha*(2*OldTau+b*psi)))^2)*(alpha^2)*(psi^2)) -> 0.78478212 | H2: =-Beta/alpha -> 180 | I2: =(-EXP(alpha*zeta)*Beta*(-1+EXP(alpha*Size*psi)-Size*alpha*psi))/((alpha^3)*(psi^2)) -> 1690.9246 | J2: =Beta*Theta -> 14.4 | K2: =Beta*Theta -> 14.4 | L2: =kappa -> 90 | M2: =Gamma*Size -> 0 | N2: =Size*Beta*Phi -> 32.4 | O2: =-(EXP(alpha*a*psi)+EXP(alpha*b*psi)*(-1+Size*psi*alpha))*(Beta*Phi)/((alpha*psi)*(EXP(alpha*a*psi)-EXP(alpha*b*psi))) -> 12.294172 | P2: =(EXP(alpha*(zeta-a*psi))*Beta*Phi*(-EXP(alpha*a*psi)*(-2+(-1)*Size*alpha*psi)+EXP(alpha*b*psi)*(-2+Size*alpha*psi)))/((alpha^3)*(psi^3)) -> 78.836376 | Q2: =Tau*Beta -> 117.59302 | R2: =Tau*Beta -> 117.59302 | S2: =Tau -> 0.65329456 | T2: =Profit+Utility -> 3558.5135 | U2: =(2*ij*BRIJ)+(2)*jj*BRJJ -> 1419.5866 | V2: =2*(ij*BCCIJ)+(2*jj*BCCJJ)+BCS+jj*BCPTJJ+2*(ij*BCPTIJ)+BCPTII+BCk -> 497.21969 | W2: =ij*BUTIJ+BUTII -> 2636.1466 | X2: =Revenue-Cost -> 922.36687
A3: 0.65119307 | B3: 0.5 | C3: 10 | D3: 0 | E3: =Size-a -> 10 | F3: =(EXP(alpha*(Tau+OldTau+zeta-2*a*psi))*((EXP(alpha*a*psi)-EXP(alpha*b*psi))^2))/((EXP(alpha*a*psi)-EXP(alpha*(2*OldTau+b*psi)))*(alpha^2)*(psi^2)) -> 2.7012982 | G3: =(EXP(alpha*(zeta+(2*b-a)*psi))*(-1+EXP(alpha*(-1)*Size*psi))*(EXP(alpha*(2*(Tau+OldTau)+a*psi))-EXP(alpha*(2*(Tau+OldTau)+b*psi))))/(((EXP(alpha*a*psi)-EXP(alpha*(2*OldTau+b*psi)))^2)*(alpha^2)*(psi^2)) -> 0.20766894 | H3: =-Beta/alpha -> 180 | I3: =(-EXP(alpha*zeta)*Beta*(-1+EXP(alpha*Size*psi)-Size*alpha*psi))/((alpha^3)*(psi^2)) -> 1690.9246 | J3: =Beta*Theta -> 14.4 | K3: =Beta*Theta -> 14.4 | L3: =kappa -> 90 | M3: =Gamma*Size -> 0 | N3: =Size*Beta*Phi -> 32.4 | O3: =-(EXP(alpha*a*psi)+EXP(alpha*b*psi)*(-1+Size*psi*alpha))*(Beta*Phi)/((alpha*psi)*(EXP(alpha*a*psi)-EXP(alpha*b*psi))) -> 12.294172 | P3: =(EXP(alpha*(zeta-a*psi))*Beta*Phi*(-EXP(alpha*a*psi)*(-2+(-1)*Size*alpha*psi)+EXP(alpha*b*psi)*(-2+Size*alpha*psi)))/((alpha^3)*(psi^3)) -> 78.836376 | Q3: =Tau*Beta -> 117.21475 | R3: =Tau*Beta -> 117.21475 | S3: =Tau -> 0.65119307 | T3: =Profit+Utility -> 2533.3425 | U3: =(2*ij*BRIJ)+(2)*jj*BRJJ -> 681.94772 | V3: =2*(ij*BCCIJ)+(2*jj*BCCJJ)+BCS+jj*BCPTJJ+2*(ij*BCPTIJ)+BCPTII+BCk -> 325.76355 | W3: =ij*BUTIJ+BUTII -> 2177.1583 | X3: =Revenue-Cost -> 356.18417
A4: 0.6500633 | B4: 1 | C4: 10 | D4: 0 | E4: =Size-a -> 10 | F4: =(EXP(alpha*(Tau+OldTau+zeta-2*a*psi))*((EXP(alpha*a*psi)-EXP(alpha*b*psi))^2))/((EXP(alpha*a*psi)-EXP(alpha*(2*OldTau+b*psi)))*(alpha^2)*(psi^2)) -> 1.5525123 | G4: =(EXP(alpha*(zeta+(2*b-a)*psi))*(-1+EXP(alpha*(-1)*Size*psi))*(EXP(alpha*(2*(Tau+OldTau)+a*psi))-EXP(alpha*(2*(Tau+OldTau)+b*psi))))/(((EXP(alpha*a*psi)-EXP(alpha*(2*OldTau+b*psi)))^2)*(alpha^2)*(psi^2)) -> 0.068595652 | H4: =-Beta/alpha -> 180 | I4: =(-EXP(alpha*zeta)*Beta*(-1+EXP(alpha*Size*psi)-Size*alpha*psi))/((alpha^3)*(psi^2)) -> 1690.9246 | J4: =Beta*Theta -> 14.4 | K4: =Beta*Theta -> 14.4 | L4: =kappa -> 90 | M4: =Gamma*Size -> 0 | N4: =Size*Beta*Phi -> 32.4 | O4: =-(EXP(alpha*a*psi)+EXP(alpha*b*psi)*(-1+Size*psi*alpha))*(Beta*Phi)/((alpha*psi)*(EXP(alpha*a*psi)-EXP(alpha*b*psi))) -> 12.294172 | P4: =(EXP(alpha*(zeta-a*psi))*Beta*Phi*(-EXP(alpha*a*psi)*(-2+(-1)*Size*alpha*psi)+EXP(alpha*b*psi)*(-2+Size*alpha*psi)))/((alpha^3)*(psi^3)) -> 78.836376 | Q4: =Tau*Beta -> 117.01139 | R4: =Tau*Beta -> 117.01139 | S4: =Tau -> 0.6500633 | T4: =Profit+Utility -> 2093.8326 | U4: =(2*ij*BRIJ)+(2)*jj*BRJJ -> 379.37621 | V4: =2*(ij*BCCIJ)+(2*jj*BCCJJ)+BCS+jj*BCPTJJ+2*(ij*BCPTIJ)+BCPTII+BCk -> 255.92049 | W4: =ij*BUTIJ+BUTII -> 1970.3768 | X4: =Revenue-Cost -> 123.45572
A5: 0.64938564 | B5: 1.5 | C5: 10 | D5: 0 | E5: =Size-a -> 10 | F5: =(EXP(alpha*(Tau+OldTau+zeta-2*a*psi))*((EXP(alpha*a*psi)-EXP(alpha*b*psi))^2))/((EXP(alpha*a*psi)-EXP(alpha*(2*OldTau+b*psi)))*(alpha^2)*(psi^2)) -> 0.9240959 | G5: =(EXP(alpha*(zeta+(2*b-a)*psi))*(-1+EXP(alpha*(-1)*Size*psi))*(EXP(alpha*(2*(Tau+OldTau)+a*psi))-EXP(alpha*(2*(Tau+OldTau)+b*psi))))/(((EXP(alpha*a*psi)-EXP(alpha*(2*OldTau+b*psi)))^2)*(alpha^2)*(psi^2)) -> 0.024303038 | H5: =-Beta/alpha -> 180 | I5: =(-EXP(alpha*zeta)*Beta*(-1+EXP(alpha*Size*psi)-Size*alpha*psi))/((alpha^3)*(psi^2)) -> 1690.9246 | J5: =Beta*Theta -> 14.4 | K5: =Beta*Theta -> 14.4 | L5: =kappa -> 90 | M5: =Gamma*Size -> 0 | N5: =Size*Beta*Phi -> 32.4 | O5: =-(EXP(alpha*a*psi)+EXP(alpha*b*psi)*(-1+Size*psi*alpha))*(Beta*Phi)/((alpha*psi)*(EXP(alpha*a*psi)-EXP(alpha*b*psi))) -> 12.294172 | P5: =(EXP(alpha*(zeta-a*psi))*Beta*Phi*(-EXP(alpha*a*psi)*(-2+(-1)*Size*alpha*psi)+EXP(alpha*b*psi)*(-2+Size*alpha*psi)))/((alpha^3)*(psi^3)) -> 78.836376 | Q5: =Tau*Beta -> 116.88942 | R5: =Tau*Beta -> 116.88942 | S5: =Tau -> 0.64938564 | T5: =Profit+Utility -> 1859.3178 | U5: =(2*ij*BRIJ)+(2)*jj*BRJJ -> 221.71559 | V5: =2*(ij*BCCIJ)+(2*jj*BCCJJ)+BCS+jj*BCPTJJ+2*(ij*BCPTIJ)+BCPTII+BCk -> 219.65967 | W5: =ij*BUTIJ+BUTII -> 1857.2619 | X5: =Revenue-Cost -> 2.0559232
A6: 0.64896782 | B6: 2 | C6: 10 | D6: 0 | E6: =Size-a -> 10 | F6: =(EXP(alpha*(Tau+OldTau+zeta-2*a*psi))*((EXP(alpha*a*psi)-EXP(alpha*b*psi))^2))/((EXP(alpha*a*psi)-EXP(alpha*(2*OldTau+b*psi)))*(alpha^2)*(psi^2)) -> 0.55677302 | G6: =(EXP(alpha*(zeta+(2*b-a)*psi))*(-1+EXP(alpha*(-1)*Size*psi))*(EXP(alpha*(2*(Tau+OldTau)+a*psi))-EXP(alpha*(2*(Tau+OldTau)+b*psi))))/(((EXP(alpha*a*psi)-EXP(alpha*(2*OldTau+b*psi)))^2)*(alpha^2)*(psi^2)) -> 0.008822321 | H6: =-Beta/alpha -> 180 | I6: =(-EXP(alpha*zeta)*Beta*(-1+EXP(alpha*Size*psi)-Size*alpha*psi))/((alpha^3)*(psi^2)) -> 1690.9246 | J6: =Beta*Theta -> 14.4 | K6: =Beta*Theta -> 14.4 | L6: =kappa -> 90 | M6: =Gamma*Size -> 0 | N6: =Size*Beta*Phi -> 32.4 | O6: =-(EXP(alpha*a*psi)+EXP(alpha*b*psi)*(-1+Size*psi*alpha))*(Beta*Phi)/((alpha*psi)*(EXP(alpha*a*psi)-EXP(alpha*b*psi))) -> 12.294172 | P6: =(EXP(alpha*(zeta-a*psi))*Beta*Phi*(-EXP(alpha*a*psi)*(-2+(-1)*Size*alpha*psi)+EXP(alpha*b*psi)*(-2+Size*alpha*psi)))/((alpha^3)*(psi^3)) -> 78.836376 | Q6: =Tau*Beta -> 116.81421 | R6: =Tau*Beta -> 116.81421 | S6: =Tau -> 0.64896782 | T6: =Profit+Utility -> 1724.1814 | U6: =(2*ij*BRIJ)+(2)*jj*BRJJ -> 132.13914 | V6: =2*(ij*BCCIJ)+(2*jj*BCCJJ)+BCS+jj*BCPTJJ+2*(ij*BCPTIJ)+BCPTII+BCk -> 199.10149 | W6: =ij*BUTIJ+BUTII -> 1791.1438 | X6: =Revenue-Cost -> -66.962348
A7: 0.64870987 | B7: 2.5 | C7: 10 | D7: 0 | E7: =Size-a -> 10 | F7: =(EXP(alpha*(Tau+OldTau+zeta-2*a*psi))*((EXP(alpha*a*psi)-EXP(alpha*b*psi))^2))/((EXP(alpha*a*psi)-EXP(alpha*(2*OldTau+b*psi)))*(alpha^2)*(psi^2)) -> 0.3369131 | G7: =(EXP(alpha*(zeta+(2*b-a)*psi))*(-1+EXP(alpha*(-1)*Size*psi))*(EXP(alpha*(2*(Tau+OldTau)+a*psi))-EXP(alpha*(2*(Tau+OldTau)+b*psi))))/(((EXP(alpha*a*psi)-EXP(alpha*(2*OldTau+b*psi)))^2)*(alpha^2)*(psi^2)) -> 0.0032304444 | H7: =-Beta/alpha -> 180 | I7: =(-EXP(alpha*zeta)*Beta*(-1+EXP(alpha*Size*psi)-Size*alpha*psi))/((alpha^3)*(psi^2)) -> 1690.9246 | J7: =Beta*Theta -> 14.4 | K7: =Beta*Theta -> 14.4 | L7: =kappa -> 90 | M7: =Gamma*Size -> 0 | N7: =Size*Beta*Phi -> 32.4 | O7: =-(EXP(alpha*a*psi)+EXP(alpha*b*psi)*(-1+Size*psi*alpha))*(Beta*Phi)/((alpha*psi)*(EXP(alpha*a*psi)-EXP(alpha*b*psi))) -> 12.294172 | P7: =(EXP(alpha*(zeta-a*psi))*Beta*Phi*(-EXP(alpha*a*psi)*(-2+(-1)*Size*alpha*psi)+EXP(alpha*b*psi)*(-2+Size*alpha*psi)))/((alpha^3)*(psi^3)) -> 78.836376 | Q7: =Tau*Beta -> 116.76778 | R7: =Tau*Beta -> 116.76778 | S7: =Tau -> 0.64870987 | T7: =Profit+Utility -> 1643.9833 | U7: =(2*ij*BRIJ)+(2)*jj*BRJJ -> 79.435611 | V7: =2*(ij*BCCIJ)+(2*jj*BCCJJ)+BCS+jj*BCPTJJ+2*(ij*BCPTIJ)+BCPTII+BCk -> 187.02131 | W7: =ij*BUTIJ+BUTII -> 1751.569 | X7: =Revenue-Cost -> -107.5857
A8: 0.64855112 | B8: 3 | C8: 10 | D8: 0 | E8: =Size-a -> 10 | F8: =(EXP(alpha*(Tau+OldTau+zeta-2*a*psi))*((EXP(alpha*a*psi)-EXP(alpha*b*psi))^2))/((EXP(alpha*a*psi)-EXP(alpha*(2*OldTau+b*psi)))*(alpha^2)*(psi^2)) -> 0.20418623 | G8: =(EXP(alpha*(zeta+(2*b-a)*psi))*(-1+EXP(alpha*(-1)*Size*psi))*(EXP(alpha*(2*(Tau+OldTau)+a*psi))-EXP(alpha*(2*(Tau+OldTau)+b*psi))))/(((EXP(alpha*a*psi)-EXP(alpha*(2*OldTau+b*psi)))^2)*(alpha^2)*(psi^2)) -> 0.0011865318 | H8: =-Beta/alpha -> 180 | I8: =(-EXP(alpha*zeta)*Beta*(-1+EXP(alpha*Size*psi)-Size*alpha*psi))/((alpha^3)*(psi^2)) -> 1690.9246 | J8: =Beta*Theta -> 14.4 | K8: =Beta*Theta -> 14.4 | L8: =kappa -> 90 | M8: =Gamma*Size -> 0 | N8: =Size*Beta*Phi -> 32.4 | O8: =-(EXP(alpha*a*psi)+EXP(alpha*b*psi)*(-1+Size*psi*alpha))*(Beta*Phi)/((alpha*psi)*(EXP(alpha*a*psi)-EXP(alpha*b*psi))) -> 12.294172 | P8: =(EXP(alpha*(zeta-a*psi))*Beta*Phi*(-EXP(alpha*a*psi)*(-2+(-1)*Size*alpha*psi)+EXP(alpha*b*psi)*(-2+Size*alpha*psi)))/((alpha^3)*(psi^3)) -> 78.836376 | Q8: =Tau*Beta -> 116.7392 | R8: =Tau*Beta -> 116.7392 | S8: =Tau -> 0.64855112 | T8: =Profit+Utility -> 1595.8181 | U8: =(2*ij*BRIJ)+(2)*jj*BRJJ -> 47.950103 | V8: =2*(ij*BCCIJ)+(2*jj*BCCJJ)+BCS+jj*BCPTJJ+2*(ij*BCPTIJ)+BCPTII+BCk -> 179.81016 | W8: =ij*BUTIJ+BUTII -> 1727.6781 | X8: =Revenue-Cost -> -131.86005
A9: 0.64845367 | B9: 3.5 | C9: 10 | D9: 0 | E9: =Size-a -> 10 | F9: =(EXP(alpha*(Tau+OldTau+zeta-2*a*psi))*((EXP(alpha*a*psi)-EXP(alpha*b*psi))^2))/((EXP(alpha*a*psi)-EXP(alpha*(2*OldTau+b*psi)))*(alpha^2)*(psi^2)) -> 0.12381396 | G9: =(EXP(alpha*(zeta+(2*b-a)*psi))*(-1+EXP(alpha*(-1)*Size*psi))*(EXP(alpha*(2*(Tau+OldTau)+a*psi))-EXP(alpha*(2*(Tau+OldTau)+b*psi))))/(((EXP(alpha*a*psi)-EXP(alpha*(2*OldTau+b*psi)))^2)*(alpha^2)*(psi^2)) -> 0.00043628044 | H9: =-Beta/alpha -> 180 | I9: =(-EXP(alpha*zeta)*Beta*(-1+EXP(alpha*Size*psi)-Size*alpha*psi))/((alpha^3)*(psi^2)) -> 1690.9246 | J9: =Beta*Theta -> 14.4 | K9: =Beta*Theta -> 14.4 | L9: =kappa -> 90 | M9: =Gamma*Size -> 0 | N9: =Size*Beta*Phi -> 32.4 | O9: =-(EXP(alpha*a*psi)+EXP(alpha*b*psi)*(-1+Size*psi*alpha))*(Beta*Phi)/((alpha*psi)*(EXP(alpha*a*psi)-EXP(alpha*b*psi))) -> 12.294172 | P9: =(EXP(alpha*(zeta-a*psi))*Beta*Phi*(-EXP(alpha*a*psi)*(-2+(-1)*Size*alpha*psi)+EXP(alpha*b*psi)*(-2+Size*alpha*psi)))/((alpha^3)*(psi^3)) -> 78.836376 | Q9: =Tau*Beta -> 116.72166 | R9: =Tau*Beta -> 116.72166 | S9: =Tau -> 0.64845367 | T9: =Profit+Utility -> 1566.7432 | U9: =(2*ij*BRIJ)+(2)*jj*BRJJ -> 29.00539 | V9: =2*(ij*BCCIJ)+(2*jj*BCCJJ)+BCS+jj*BCPTJJ+2*(ij*BCPTIJ)+BCPTII+BCk -> 175.4733 | W9: =ij*BUTIJ+BUTII -> 1713.2111 | X9: =Revenue-Cost -> -146.46791
A10: 0.64901074 | B10: 4 | C10: 10 | D10: 0 | E10: =Size-a -> 10 | F10: =(EXP(alpha*(Tau+OldTau+zeta-2*a*psi))*((EXP(alpha*a*psi)-EXP(alpha*b*psi))^2))/((EXP(alpha*a*psi)-EXP(alpha*(2*OldTau+b*psi)))*(alpha^2)*(psi^2)) -> 0.075045488 | G10: =(EXP(alpha*(zeta+(2*b-a)*psi))*(-1+EXP(alpha*(-1)*Size*psi))*(EXP(alpha*(2*(Tau+OldTau)+a*psi))-EXP(alpha*(2*(Tau+OldTau)+b*psi))))/(((EXP(alpha*a*psi)-EXP(alpha*(2*OldTau+b*psi)))^2)*(alpha^2)*(psi^2)) -> 0.00016027864 | H10: =-Beta/alpha -> 180 | I10: =(-EXP(alpha*zeta)*Beta*(-1+EXP(alpha*Size*psi)-Size*alpha*psi))/((alpha^3)*(psi^2)) -> 1690.9246 | J10: =Beta*Theta -> 14.4 | K10: =Beta*Theta -> 14.4 | L10: =kappa -> 90 | M10: =Gamma*Size -> 0 | N10: =Size*Beta*Phi -> 32.4 | O10: =-(EXP(alpha*a*psi)+EXP(alpha*b*psi)*(-1+Size*psi*alpha))*(Beta*Phi)/((alpha*psi)*(EXP(alpha*a*psi)-EXP(alpha*b*psi))) -> 12.294172 | P10: =(EXP(alpha*(zeta-a*psi))*Beta*Phi*(-EXP(alpha*a*psi)*(-2+(-1)*Size*alpha*psi)+EXP(alpha*b*psi)*(-2+Size*alpha*psi)))/((alpha^3)*(psi^3)) -> 78.836376 | Q10: =Tau*Beta -> 116.82193 | R10: =Tau*Beta -> 116.82193 | S10: =Tau -> 0.64901074 | T10: =Profit+Utility -> 1549.1514 | U10: =(2*ij*BRIJ)+(2)*jj*BRJJ -> 17.571366 | V10: =2*(ij*BCCIJ)+(2*jj*BCCJJ)+BCS+jj*BCPTJJ+2*(ij*BCPTIJ)+BCPTII+BCk -> 172.85274 | W10: =ij*BUTIJ+BUTII -> 1704.4328 | X10: =Revenue-Cost -> -155.28137
A11: 0.64899801 | B11: 4.5 | C11: 10 | D11: 0 | E11: =Size-a -> 10 | F11: =(EXP(alpha*(Tau+OldTau+zeta-2*a*psi))*((EXP(alpha*a*psi)-EXP(alpha*b*psi))^2))/((EXP(alpha*a*psi)-EXP(alpha*(2*OldTau+b*psi)))*(alpha^2)*(psi^2)) -> 0.045515815 | G11: =(EXP(alpha*(zeta+(2*b-a)*psi))*(-1+EXP(alpha*(-1)*Size*psi))*(EXP(alpha*(2*(Tau+OldTau)+a*psi))-EXP(alpha*(2*(Tau+OldTau)+b*psi))))/(((EXP(alpha*a*psi)-EXP(alpha*(2*OldTau+b*psi)))^2)*(alpha^2)*(psi^2)) -> 5.895914e-05 | H11: =-Beta/alpha -> 180 | I11: =(-EXP(alpha*zeta)*Beta*(-1+EXP(alpha*Size*psi)-Size*alpha*psi))/((alpha^3)*(psi^2)) -> 1690.9246 | J11: =Beta*Theta -> 14.4 | K11: =Beta*Theta -> 14.4 | L11: =kappa -> 90 | M11: =Gamma*Size -> 0 | N11: =Size*Beta*Phi -> 32.4 | O11: =-(EXP(alpha*a*psi)+EXP(alpha*b*psi)*(-1+Size*psi*alpha))*(Beta*Phi)/((alpha*psi)*(EXP(alpha*a*psi)-EXP(alpha*b*psi))) -> 12.294172 | P11: =(EXP(alpha*(zeta-a*psi))*Beta*Phi*(-EXP(alpha*a*psi)*(-2+(-1)*Size*alpha*psi)+EXP(alpha*b*psi)*(-2+Size*alpha*psi)))/((alpha^3)*(psi^3)) -> 78.836376 | Q11: =Tau*Beta -> 116.81964 | R11: =Tau*Beta -> 116.81964 | S11: =Tau -> 0.64899801 | T11: =Profit+Utility -> 1538.4955 | U11: =(2*ij*BRIJ)+(2)*jj*BRJJ -> 10.648058 | V11: =2*(ij*BCCIJ)+(2*jj*BCCJJ)+BCS+jj*BCPTJJ+2*(ij*BCPTIJ)+BCPTII+BCk -> 171.27 | W11: =ij*BUTIJ+BUTII -> 1699.1175 | X11: =Revenue-Cost -> -160.62194
A12: 0.64897531 | B12: 5 | C12: 10 | D12: 0 | E12: =Size-a -> 10 | F12: =(EXP(alpha*(Tau+OldTau+zeta-2*a*psi))*((EXP(alpha*a*psi)-EXP(alpha*b*psi))^2))/((EXP(alpha*a*psi)-EXP(alpha*(2*OldTau+b*psi)))*(alpha^2)*(psi^2)) -> 0.027606884 | G12: =(EXP(alpha*(zeta+(2*b-a)*psi))*(-1+EXP(alpha*(-1)*Size*psi))*(EXP(alpha*(2*(Tau+OldTau)+a*psi))-EXP(alpha*(2*(Tau+OldTau)+b*psi))))/(((EXP(alpha*a*psi)-EXP(alpha*(2*OldTau+b*psi)))^2)*(alpha^2)*(psi^2)) -> 2.1690085e-05 | H12: =-Beta/alpha -> 180 | I12: =(-EXP(alpha*zeta)*Beta*(-1+EXP(alpha*Size*psi)-Size*alpha*psi))/((alpha^3)*(psi^2)) -> 1690.9246 | J12: =Beta*Theta -> 14.4 | K12: =Beta*Theta -> 14.4 | L12: =kappa -> 90 | M12: =Gamma*Size -> 0 | N12: =Size*Beta*Phi -> 32.4 | O12: =-(EXP(alpha*a*psi)+EXP(alpha*b*psi)*(-1+Size*psi*alpha))*(Beta*Phi)/((alpha*psi)*(EXP(alpha*a*psi)-EXP(alpha*b*psi))) -> 12.294172 | P12: =(EXP(alpha*(zeta-a*psi))*Beta*Phi*(-EXP(alpha*a*psi)*(-2+(-1)*Size*alpha*psi)+EXP(alpha*b*psi)*(-2+Size*alpha*psi)))/((alpha^3)*(psi^3)) -> 78.836376 | Q12: =Tau*Beta -> 116.81555 | R12: =Tau*Beta -> 116.81555 | S12: =Tau -> 0.64897531 | T12: =Profit+Utility -> 1532.0372 | U12: =(2*ij*BRIJ)+(2)*jj*BRJJ -> 6.4548944 | V12: =2*(ij*BCCIJ)+(2*jj*BCCJJ)+BCS+jj*BCPTJJ+2*(ij*BCPTIJ)+BCPTII+BCk -> 170.31159 | W12: =ij*BUTIJ+BUTII -> 1695.8939 | X12: =Revenue-Cost -> -163.85669

Sheet W-React-JS=1
A1: Tau | B1: OldTau | C1: Size | D1: a | E1: b | F1: ij | G1: jj | H1: BUTIJ | I1: BUTII | J1: BCCIJ | K1: BCCJJ | L1: BCk | M1: BCS | N1: BCPTJJ | O1: BCPTIJ | P1: BCPTII | Q1: BRIJ | R1: BRJJ | S1: Toll | T1: Welfare | U1: Revenue | V1: Cost | W1: Utility | X1: Profit
A2: 0.5889719 | B2: 0 | C2: 1 | D2: 0 | E2: =Size-a -> 1 | F2: =(EXP(alpha*(Tau+OldTau+zeta-2*a*psi))*((EXP(alpha*a*psi)-EXP(alpha*b*psi))^2))/((EXP(alpha*a*psi)-EXP(alpha*(2*OldTau+b*psi)))*(alpha^2)*(psi^2)) -> 1.0040938 | G2: =(EXP(alpha*(zeta+(2*b-a)*psi))*(-1+EXP(alpha*(-1)*Size*psi))*(EXP(alpha*(2*(Tau+OldTau)+a*psi))-EXP(alpha*(2*(Tau+OldTau)+b*psi))))/(((EXP(alpha*a*psi)-EXP(alpha*(2*OldTau+b*psi)))^2)*(alpha^2)*(psi^2)) -> 3.4428382 | H2: =-Beta/alpha -> 180 | I2: =(-EXP(alpha*zeta)*Beta*(-1+EXP(alpha*Size*psi)-Size*alpha*psi))/((alpha^3)*(psi^2)) -> 25.038896 | J2: =Beta*Theta -> 14.4 | K2: =Beta*Theta -> 14.4 | L2: =kappa -> 90 | M2: =Gamma*Size -> 0 | N2: =Size*Beta*Phi -> 3.24 | O2: =-(EXP(alpha*a*psi)+EXP(alpha*b*psi)*(-1+Size*psi*alpha))*(Beta*Phi)/((alpha*psi)*(EXP(alpha*a*psi)-EXP(alpha*b*psi))) -> 1.5795152 | P2: =(EXP(alpha*(zeta-a*psi))*Beta*Phi*(-EXP(alpha*a*psi)*(-2+(-1)*Size*alpha*psi)+EXP(alpha*b*psi)*(-2+Size*alpha*psi)))/((alpha^3)*(psi^3)) -> 0.14651555 | Q2: =Tau*Beta -> 106.01494 | R2: =Tau*Beta -> 106.01494 | S2: =Tau -> 0.5889719 | T2: =Profit+Utility -> 916.11332 | U2: =(2*ij*BRIJ)+(2)*jj*BRJJ -> 942.88245 | V2: =2*(ij*BCCIJ)+(2*jj*BCCJJ)+BCS+jj*BCPTJJ+2*(ij*BCPTIJ)+BCPTII+BCk -> 232.54491 | W2: =ij*BUTIJ+BUTII -> 205.77577 | X2: =Revenue-Cost -> 710.33754
A3: 0.58887831 | B3: 0.5 | C3: 1 | D3: 0 | E3: =Size-a -> 1 | F3: =(EXP(alpha*(Tau+OldTau+zeta-2*a*psi))*((EXP(alpha*a*psi)-EXP(alpha*b*psi))^2))/((EXP(alpha*a*psi)-EXP(alpha*(2*OldTau+b*psi)))*(alpha^2)*(psi^2)) -> 0.12414874 | G3: =(EXP(alpha*(zeta+(2*b-a)*psi))*(-1+EXP(alpha*(-1)*Size*psi))*(EXP(alpha*(2*(Tau+OldTau)+a*psi))-EXP(alpha*(2*(Tau+OldTau)+b*psi))))/(((EXP(alpha*a*psi)-EXP(alpha*(2*OldTau+b*psi)))^2)*(alpha^2)*(psi^2)) -> 0.052632342 | H3: =-Beta/alpha -> 180 | I3: =(-EXP(alpha*zeta)*Beta*(-1+EXP(alpha*Size*psi)-Size*alpha*psi))/((alpha^3)*(psi^2)) -> 25.038896 | J3: =Beta*Theta -> 14.4 | K3: =Beta*Theta -> 14.4 | L3: =kappa -> 90 | M3: =Gamma*Size -> 0 | N3: =Size*Beta*Phi -> 3.24 | O3: =-(EXP(alpha*a*psi)+EXP(alpha*b*psi)*(-1+Size*psi*alpha))*(Beta*Phi)/((alpha*psi)*(EXP(alpha*a*psi)-EXP(alpha*b*psi))) -> 1.5795152 | P3: =(EXP(alpha*(zeta-a*psi))*Beta*Phi*(-EXP(alpha*a*psi)*(-2+(-1)*Size*alpha*psi)+EXP(alpha*b*psi)*(-2+Size*alpha*psi)))/((alpha^3)*(psi^3)) -> 0.14651555 | Q3: =Tau*Beta -> 105.9981 | R3: =Tau*Beta -> 105.9981 | S3: =Tau -> 0.58887831 | T3: =Profit+Utility -> -10.937944 | U3: =(2*ij*BRIJ)+(2)*jj*BRJJ -> 37.476916 | V3: =2*(ij*BCCIJ)+(2*jj*BCCJJ)+BCS+jj*BCPTJJ+2*(ij*BCPTIJ)+BCPTII+BCk -> 95.800529 | W3: =ij*BUTIJ+BUTII -> 47.385669 | X3: =Revenue-Cost -> -58.323613
A4: 0.58883912 | B4: 1 | C4: 1 | D4: 0 | E4: =Size-a -> 1 | F4: =(EXP(alpha*(Tau+OldTau+zeta-2*a*psi))*((EXP(alpha*a*psi)-EXP(alpha*b*psi))^2))/((EXP(alpha*a*psi)-EXP(alpha*(2*OldTau+b*psi)))*(alpha^2)*(psi^2)) -> 0.058243754 | G4: =(EXP(alpha*(zeta+(2*b-a)*psi))*(-1+EXP(alpha*(-1)*Size*psi))*(EXP(alpha*(2*(Tau+OldTau)+a*psi))-EXP(alpha*(2*(Tau+OldTau)+b*psi))))/(((EXP(alpha*a*psi)-EXP(alpha*(2*OldTau+b*psi)))^2)*(alpha^2)*(psi^2)) -> 0.01158422 | H4: =-Beta/alpha -> 180 | I4: =(-EXP(alpha*zeta)*Beta*(-1+EXP(alpha*Size*psi)-Size*alpha*psi))/((alpha^3)*(psi^2)) -> 25.038896 | J4: =Beta*Theta -> 14.4 | K4: =Beta*Theta -> 14.4 | L4: =kappa -> 90 | M4: =Gamma*Size -> 0 | N4: =Size*Beta*Phi -> 3.24 | O4: =-(EXP(alpha*a*psi)+EXP(alpha*b*psi)*(-1+Size*psi*alpha))*(Beta*Phi)/((alpha*psi)*(EXP(alpha*a*psi)-EXP(alpha*b*psi))) -> 1.5795152 | P4: =(EXP(alpha*(zeta-a*psi))*Beta*Phi*(-EXP(alpha*a*psi)*(-2+(-1)*Size*alpha*psi)+EXP(alpha*b*psi)*(-2+Size*alpha*psi)))/((alpha^3)*(psi^3)) -> 0.14651555 | Q4: =Tau*Beta -> 105.99104 | R4: =Tau*Beta -> 105.99104 | S4: =Tau -> 0.58883912 | T4: =Profit+Utility -> -42.054036 | U4: =(2*ij*BRIJ)+(2)*jj*BRJJ -> 14.802279 | V4: =2*(ij*BCCIJ)+(2*jj*BCCJJ)+BCS+jj*BCPTJJ+2*(ij*BCPTIJ)+BCPTII+BCk -> 92.379088 | W4: =ij*BUTIJ+BUTII -> 35.522772 | X4: =Revenue-Cost -> -77.576808
A5: 0.58881608 | B5: 1.5 | C5: 1 | D5: 0 | E5: =Size-a -> 1 | F5: =(EXP(alpha*(Tau+OldTau+zeta-2*a*psi))*((EXP(alpha*a*psi)-EXP(alpha*b*psi))^2))/((EXP(alpha*a*psi)-EXP(alpha*(2*OldTau+b*psi)))*(alpha^2)*(psi^2)) -> 0.032609747 | G5: =(EXP(alpha*(zeta+(2*b-a)*psi))*(-1+EXP(alpha*(-1)*Size*psi))*(EXP(alpha*(2*(Tau+OldTau)+a*psi))-EXP(alpha*(2*(Tau+OldTau)+b*psi))))/(((EXP(alpha*a*psi)-EXP(alpha*(2*OldTau+b*psi)))^2)*(alpha^2)*(psi^2)) -> 0.0036313066 | H5: =-Beta/alpha -> 180 | I5: =(-EXP(alpha*zeta)*Beta*(-1+EXP(alpha*Size*psi)-Size*alpha*psi))/((alpha^3)*(psi^2)) -> 25.038896 | J5: =Beta*Theta -> 14.4 | K5: =Beta*Theta -> 14.4 | L5: =kappa -> 90 | M5: =Gamma*Size -> 0 | N5: =Size*Beta*Phi -> 3.24 | O5: =-(EXP(alpha*a*psi)+EXP(alpha*b*psi)*(-1+Size*psi*alpha))*(Beta*Phi)/((alpha*psi)*(EXP(alpha*a*psi)-EXP(alpha*b*psi))) -> 1.5795152 | P5: =(EXP(alpha*(zeta-a*psi))*Beta*Phi*(-EXP(alpha*a*psi)*(-2+(-1)*Size*alpha*psi)+EXP(alpha*b*psi)*(-2+Size*alpha*psi)))/((alpha^3)*(psi^3)) -> 0.14651555 | Q5: =Tau*Beta -> 105.98689 | R5: =Tau*Beta -> 105.98689 | S5: =Tau -> 0.58881608 | T5: =Profit+Utility -> -52.714234 | U5: =(2*ij*BRIJ)+(2)*jj*BRJJ -> 7.6821534 | V5: =2*(ij*BCCIJ)+(2*jj*BCCJJ)+BCS+jj*BCPTJJ+2*(ij*BCPTIJ)+BCPTII+BCk -> 91.305039 | W5: =ij*BUTIJ+BUTII -> 30.908651 | X5: =Revenue-Cost -> -83.622885
A6: 0.58880122 | B6: 2 | C6: 1 | D6: 0 | E6: =Size-a -> 1 | F6: =(EXP(alpha*(Tau+OldTau+zeta-2*a*psi))*((EXP(alpha*a*psi)-EXP(alpha*b*psi))^2))/((EXP(alpha*a*psi)-EXP(alpha*(2*OldTau+b*psi)))*(alpha^2)*(psi^2)) -> 0.019234753 | G6: =(EXP(alpha*(zeta+(2*b-a)*psi))*(-1+EXP(alpha*(-1)*Size*psi))*(EXP(alpha*(2*(Tau+OldTau)+a*psi))-EXP(alpha*(2*(Tau+OldTau)+b*psi))))/(((EXP(alpha*a*psi)-EXP(alpha*(2*OldTau+b*psi)))^2)*(alpha^2)*(psi^2)) -> 0.0012634012 | H6: =-Beta/alpha -> 180 | I6: =(-EXP(alpha*zeta)*Beta*(-1+EXP(alpha*Size*psi)-Size*alpha*psi))/((alpha^3)*(psi^2)) -> 25.038896 | J6: =Beta*Theta -> 14.4 | K6: =Beta*Theta -> 14.4 | L6: =kappa -> 90 | M6: =Gamma*Size -> 0 | N6: =Size*Beta*Phi -> 3.24 | O6: =-(EXP(alpha*a*psi)+EXP(alpha*b*psi)*(-1+Size*psi*alpha))*(Beta*Phi)/((alpha*psi)*(EXP(alpha*a*psi)-EXP(alpha*b*psi))) -> 1.5795152 | P6: =(EXP(alpha*(zeta-a*psi))*Beta*Phi*(-EXP(alpha*a*psi)*(-2+(-1)*Size*alpha*psi)+EXP(alpha*b*psi)*(-2+Size*alpha*psi)))/((alpha^3)*(psi^3)) -> 0.14651555 | Q6: =Tau*Beta -> 105.98422 | R6: =Tau*Beta -> 105.98422 | S6: =Tau -> 0.58880122 | T6: =Profit+Utility -> -57.955605 | U6: =(2*ij*BRIJ)+(2)*jj*BRJJ -> 4.3449618 | V6: =2*(ij*BCCIJ)+(2*jj*BCCJJ)+BCS+jj*BCPTJJ+2*(ij*BCPTIJ)+BCPTII+BCk -> 90.801719 | W6: =ij*BUTIJ+BUTII -> 28.501152 | X6: =Revenue-Cost -> -86.456757
A7: 0.5889719 | B7: 2.5 | C7: 1 | D7: 0 | E7: =Size-a -> 1 | F7: =(EXP(alpha*(Tau+OldTau+zeta-2*a*psi))*((EXP(alpha*a*psi)-EXP(alpha*b*psi))^2))/((EXP(alpha*a*psi)-EXP(alpha*(2*OldTau+b*psi)))*(alpha^2)*(psi^2)) -> 0.011547562 | G7: =(EXP(alpha*(zeta+(2*b-a)*psi))*(-1+EXP(alpha*(-1)*Size*psi))*(EXP(alpha*(2*(Tau+OldTau)+a*psi))-EXP(alpha*(2*(Tau+OldTau)+b*psi))))/(((EXP(alpha*a*psi)-EXP(alpha*(2*OldTau+b*psi)))^2)*(alpha^2)*(psi^2)) -> 0.00045535348 | H7: =-Beta/alpha -> 180 | I7: =(-EXP(alpha*zeta)*Beta*(-1+EXP(alpha*Size*psi)-Size*alpha*psi))/((alpha^3)*(psi^2)) -> 25.038896 | J7: =Beta*Theta -> 14.4 | K7: =Beta*Theta -> 14.4 | L7: =kappa -> 90 | M7: =Gamma*Size -> 0 | N7: =Size*Beta*Phi -> 3.24 | O7: =-(EXP(alpha*a*psi)+EXP(alpha*b*psi)*(-1+Size*psi*alpha))*(Beta*Phi)/((alpha*psi)*(EXP(alpha*a*psi)-EXP(alpha*b*psi))) -> 1.5795152 | P7: =(EXP(alpha*(zeta-a*psi))*Beta*Phi*(-EXP(alpha*a*psi)*(-2+(-1)*Size*alpha*psi)+EXP(alpha*b*psi)*(-2+Size*alpha*psi)))/((alpha^3)*(psi^3)) -> 0.14651555 | Q7: =Tau*Beta -> 106.01494 | R7: =Tau*Beta -> 106.01494 | S7: =Tau -> 0.5889719 | T7: =Profit+Utility -> -60.86772 | U7: =(2*ij*BRIJ)+(2)*jj*BRJJ -> 2.5449767 | V7: =2*(ij*BCCIJ)+(2*jj*BCCJJ)+BCS+jj*BCPTJJ+2*(ij*BCPTIJ)+BCPTII+BCk -> 90.530154 | W7: =ij*BUTIJ+BUTII -> 27.117457 | X7: =Revenue-Cost -> -87.985177
A8: 0.5889719 | B8: 3 | C8: 1 | D8: 0 | E8: =Size-a -> 1 | F8: =(EXP(alpha*(Tau+OldTau+zeta-2*a*psi))*((EXP(alpha*a*psi)-EXP(alpha*b*psi))^2))/((EXP(alpha*a*psi)-EXP(alpha*(2*OldTau+b*psi)))*(alpha^2)*(psi^2)) -> 0.0069782195 | G8: =(EXP(alpha*(zeta+(2*b-a)*psi))*(-1+EXP(alpha*(-1)*Size*psi))*(EXP(alpha*(2*(Tau+OldTau)+a*psi))-EXP(alpha*(2*(Tau+OldTau)+b*psi))))/(((EXP(alpha*a*psi)-EXP(alpha*(2*OldTau+b*psi)))^2)*(alpha^2)*(psi^2)) -> 0.00016628662 | H8: =-Beta/alpha -> 180 | I8: =(-EXP(alpha*zeta)*Beta*(-1+EXP(alpha*Size*psi)-Size*alpha*psi))/((alpha^3)*(psi^2)) -> 25.038896 | J8: =Beta*Theta -> 14.4 | K8: =Beta*Theta -> 14.4 | L8: =kappa -> 90 | M8: =Gamma*Size -> 0 | N8: =Size*Beta*Phi -> 3.24 | O8: =-(EXP(alpha*a*psi)+EXP(alpha*b*psi)*(-1+Size*psi*alpha))*(Beta*Phi)/((alpha*psi)*(EXP(alpha*a*psi)-EXP(alpha*b*psi))) -> 1.5795152 | P8: =(EXP(alpha*(zeta-a*psi))*Beta*Phi*(-EXP(alpha*a*psi)*(-2+(-1)*Size*alpha*psi)+EXP(alpha*b*psi)*(-2+Size*alpha*psi)))/((alpha^3)*(psi^3)) -> 0.14651555 | Q8: =Tau*Beta -> 106.01494 | R8: =Tau*Beta -> 106.01494 | S8: =Tau -> 0.5889719 | T8: =Profit+Utility -> -62.565036 | U8: =(2*ij*BRIJ)+(2)*jj*BRJJ -> 1.5148488 | V8: =2*(ij*BCCIJ)+(2*jj*BCCJJ)+BCS+jj*BCPTJJ+2*(ij*BCPTIJ)+BCPTII+BCk -> 90.374861 | W8: =ij*BUTIJ+BUTII -> 26.294976 | X8: =Revenue-Cost -> -88.860012
A9: 0.5889719 | B9: 3.5 | C9: 1 | D9: 0 | E9: =Size-a -> 1 | F9: =(EXP(alpha*(Tau+OldTau+zeta-2*a*psi))*((EXP(alpha*a*psi)-EXP(alpha*b*psi))^2))/((EXP(alpha*a*psi)-EXP(alpha*(2*OldTau+b*psi)))*(alpha^2)*(psi^2)) -> 0.0042267915 | G9: =(EXP(alpha*(zeta+(2*b-a)*psi))*(-1+EXP(alpha*(-1)*Size*psi))*(EXP(alpha*(2*(Tau+OldTau)+a*psi))-EXP(alpha*(2*(Tau+OldTau)+b*psi))))/(((EXP(alpha*a*psi)-EXP(alpha*(2*OldTau+b*psi)))^2)*(alpha^2)*(psi^2)) -> 6.1008412e-05 | H9: =-Beta/alpha -> 180 | I9: =(-EXP(alpha*zeta)*Beta*(-1+EXP(alpha*Size*psi)-Size*alpha*psi))/((alpha^3)*(psi^2)) -> 25.038896 | J9: =Beta*Theta -> 14.4 | K9: =Beta*Theta -> 14.4 | L9: =kappa -> 90 | M9: =Gamma*Size -> 0 | N9: =Size*Beta*Phi -> 3.24 | O9: =-(EXP(alpha*a*psi)+EXP(alpha*b*psi)*(-1+Size*psi*alpha))*(Beta*Phi)/((alpha*psi)*(EXP(alpha*a*psi)-EXP(alpha*b*psi))) -> 1.5795152 | P9: =(EXP(alpha*(zeta-a*psi))*Beta*Phi*(-EXP(alpha*a*psi)*(-2+(-1)*Size*alpha*psi)+EXP(alpha*b*psi)*(-2+Size*alpha*psi)))/((alpha^3)*(psi^3)) -> 0.14651555 | Q9: =Tau*Beta -> 106.01494 | R9: =Tau*Beta -> 106.01494 | S9: =Tau -> 0.5889719 | T9: =Profit+Utility -> -63.574694 | U9: =(2*ij*BRIJ)+(2)*jj*BRJJ -> 0.90914172 | V9: =2*(ij*BCCIJ)+(2*jj*BCCJJ)+BCS+jj*BCPTJJ+2*(ij*BCPTIJ)+BCPTII+BCk -> 90.283554 | W9: =ij*BUTIJ+BUTII -> 25.799719 | X9: =Revenue-Cost -> -89.374413
A10: 0.5889719 | B10: 4 | C10: 1 | D10: 0 | E10: =Size-a -> 1 | F10: =(EXP(alpha*(Tau+OldTau+zeta-2*a*psi))*((EXP(alpha*a*psi)-EXP(alpha*b*psi))^2))/((EXP(alpha*a*psi)-EXP(alpha*(2*OldTau+b*psi)))*(alpha^2)*(psi^2)) -> 0.0025624064 | G10: =(EXP(alpha*(zeta+(2*b-a)*psi))*(-1+EXP(alpha*(-1)*Size*psi))*(EXP(alpha*(2*(Tau+OldTau)+a*psi))-EXP(alpha*(2*(Tau+OldTau)+b*psi))))/(((EXP(alpha*a*psi)-EXP(alpha*(2*OldTau+b*psi)))^2)*(alpha^2)*(psi^2)) -> 2.242147e-05 | H10: =-Beta/alpha -> 180 | I10: =(-EXP(alpha*zeta)*Beta*(-1+EXP(alpha*Size*psi)-Size*alpha*psi))/((alpha^3)*(psi^2)) -> 25.038896 | J10: =Beta*Theta -> 14.4 | K10: =Beta*Theta -> 14.4 | L10: =kappa -> 90 | M10: =Gamma*Size -> 0 | N10: =Size*Beta*Phi -> 3.24 | O10: =-(EXP(alpha*a*psi)+EXP(alpha*b*psi)*(-1+Size*psi*alpha))*(Beta*Phi)/((alpha*psi)*(EXP(alpha*a*psi)-EXP(alpha*b*psi))) -> 1.5795152 | P10: =(EXP(alpha*(zeta-a*psi))*Beta*Phi*(-EXP(alpha*a*psi)*(-2+(-1)*Size*alpha*psi)+EXP(alpha*b*psi)*(-2+Size*alpha*psi)))/((alpha^3)*(psi^3)) -> 0.14651555 | Q10: =Tau*Beta -> 106.01494 | R10: =Tau*Beta -> 106.01494 | S10: =Tau -> 0.5889719 | T10: =Profit+Utility -> -64.180936 | U10: =(2*ij*BRIJ)+(2)*jj*BRJJ -> 0.54806075 | V10: =2*(ij*BCCIJ)+(2*jj*BCCJJ)+BCS+jj*BCPTJJ+2*(ij*BCPTIJ)+BCPTII+BCk -> 90.229126 | W10: =ij*BUTIJ+BUTII -> 25.500129 | X10: =Revenue-Cost -> -89.681065
A11: 0.5889719 | B11: 4.5 | C11: 1 | D11: 0 | E11: =Size-a -> 1 | F11: =(EXP(alpha*(Tau+OldTau+zeta-2*a*psi))*((EXP(alpha*a*psi)-EXP(alpha*b*psi))^2))/((EXP(alpha*a*psi)-EXP(alpha*(2*OldTau+b*psi)))*(alpha^2)*(psi^2)) -> 0.0015538943 | G11: =(EXP(alpha*(zeta+(2*b-a)*psi))*(-1+EXP(alpha*(-1)*Size*psi))*(EXP(alpha*(2*(Tau+OldTau)+a*psi))-EXP(alpha*(2*(Tau+OldTau)+b*psi))))/(((EXP(alpha*a*psi)-EXP(alpha*(2*OldTau+b*psi)))^2)*(alpha^2)*(psi^2)) -> 8.2453868e-06 | H11: =-Beta/alpha -> 180 | I11: =(-EXP(alpha*zeta)*Beta*(-1+EXP(alpha*Size*psi)-Size*alpha*psi))/((alpha^3)*(psi^2)) -> 25.038896 | J11: =Beta*Theta -> 14.4 | K11: =Beta*Theta -> 14.4 | L11: =kappa -> 90 | M11: =Gamma*Size -> 0 | N11: =Size*Beta*Phi -> 3.24 | O11: =-(EXP(alpha*a*psi)+EXP(alpha*b*psi)*(-1+Size*psi*alpha))*(Beta*Phi)/((alpha*psi)*(EXP(alpha*a*psi)-EXP(alpha*b*psi))) -> 1.5795152 | P11: =(EXP(alpha*(zeta-a*psi))*Beta*Phi*(-EXP(alpha*a*psi)*(-2+(-1)*Size*alpha*psi)+EXP(alpha*b*psi)*(-2+Size*alpha*psi)))/((alpha^3)*(psi^3)) -> 0.14651555 | Q11: =Tau*Beta -> 106.01494 | R11: =Tau*Beta -> 106.01494 | S11: =Tau -> 0.5889719 | T11: =Profit+Utility -> -64.546623 | U11: =(2*ij*BRIJ)+(2)*jj*BRJJ -> 0.3312203 | V11: =2*(ij*BCCIJ)+(2*jj*BCCJJ)+BCS+jj*BCPTJJ+2*(ij*BCPTIJ)+BCPTII+BCk -> 90.196441 | W11: =ij*BUTIJ+BUTII -> 25.318597 | X11: =Revenue-Cost -> -89.86522
A12: 0.58934933 | B12: 5 | C12: 1 | D12: 0 | E12: =Size-a -> 1 | F12: =(EXP(alpha*(Tau+OldTau+zeta-2*a*psi))*((EXP(alpha*a*psi)-EXP(alpha*b*psi))^2))/((EXP(alpha*a*psi)-EXP(alpha*(2*OldTau+b*psi)))*(alpha^2)*(psi^2)) -> 0.00094206564 | G12: =(EXP(alpha*(zeta+(2*b-a)*psi))*(-1+EXP(alpha*(-1)*Size*psi))*(EXP(alpha*(2*(Tau+OldTau)+a*psi))-EXP(alpha*(2*(Tau+OldTau)+b*psi))))/(((EXP(alpha*a*psi)-EXP(alpha*(2*OldTau+b*psi)))^2)*(alpha^2)*(psi^2)) -> 3.0306123e-06 | H12: =-Beta/alpha -> 180 | I12: =(-EXP(alpha*zeta)*Beta*(-1+EXP(alpha*Size*psi)-Size*alpha*psi))/((alpha^3)*(psi^2)) -> 25.038896 | J12: =Beta*Theta -> 14.4 | K12: =Beta*Theta -> 14.4 | L12: =kappa -> 90 | M12: =Gamma*Size -> 0 | N12: =Size*Beta*Phi -> 3.24 | O12: =-(EXP(alpha*a*psi)+EXP(alpha*b*psi)*(-1+Size*psi*alpha))*(Beta*Phi)/((alpha*psi)*(EXP(alpha*a*psi)-EXP(alpha*b*psi))) -> 1.5795152 | P12: =(EXP(alpha*(zeta-a*psi))*Beta*Phi*(-EXP(alpha*a*psi)*(-2+(-1)*Size*alpha*psi)+EXP(alpha*b*psi)*(-2+Size*alpha*psi)))/((alpha^3)*(psi^3)) -> 0.14651555 | Q12: =Tau*Beta -> 106.08288 | R12: =Tau*Beta -> 106.08288 | S12: =Tau -> 0.58934933 | T12: =Profit+Utility -> -64.767735 | U12: =(2*ij*BRIJ)+(2)*jj*BRJJ -> 0.20051706 | V12: =2*(ij*BCCIJ)+(2*jj*BCCJJ)+BCS+jj*BCPTJJ+2*(ij*BCPTIJ)+BCPTII+BCk -> 90.17672 | W12: =ij*BUTIJ+BUTII -> 25.208468 | X12: =Revenue-Cost -> -89.976203

Sheet P-React-JS=10
A1: Tau | B1: OldTau | C1: Size | D1: a | E1: b | F1: ij | G1: jj | H1: BUTIJ | I1: BUTII | J1: BCCIJ | K1: BCCJJ | L1: BCk | M1: BCS | N1: BCPTJJ | O1: BCPTIJ | P1: BCPTII | Q1: BRIJ | R1: BRJJ | S1: Toll | T1: Welfare | U1: Revenue | V1: Cost | W1: Utility | X1: Profit
A2: 1.069541 | B2: 0 | C2: 10 | D2: 0 | E2: =Size-a -> 10 | F2: =(EXP(alpha*(Tau+OldTau+zeta-2*a*psi))*((EXP(alpha*a*psi)-EXP(alpha*b*psi))^2))/((EXP(alpha*a*psi)-EXP(alpha*(2*OldTau+b*psi)))*(alpha^2)*(psi^2)) -> 3.4632814 | G2: =(EXP(alpha*(zeta+(2*b-a)*psi))*(-1+EXP(alpha*(-1)*Size*psi))*(EXP(alpha*(2*(Tau+OldTau)+a*psi))-EXP(alpha*(2*(Tau+OldTau)+b*psi))))/(((EXP(alpha*a*psi)-EXP(alpha*(2*OldTau+b*psi)))^2)*(alpha^2)*(psi^2)) -> 0.34135169 | H2: =-Beta/alpha -> 180 | I2: =(-EXP(alpha*zeta)*Beta*(-1+EXP(alpha*Size*psi)-Size*alpha*psi))/((alpha^3)*(psi^2)) -> 1690.9246 | J2: =Beta*Theta -> 14.4 | K2: =Beta*Theta -> 14.4 | L2: =kappa -> 90 | M2: =Gamma*Size -> 0 | N2: =Size*Beta*Phi -> 32.4 | O2: =-(EXP(alpha*a*psi)+EXP(alpha*b*psi)*(-1+Size*psi*alpha))*(Beta*Phi)/((alpha*psi)*(EXP(alpha*a*psi)-EXP(alpha*b*psi))) -> 12.294172 | P2: =(EXP(alpha*(zeta-a*psi))*Beta*Phi*(-EXP(alpha*a*psi)*(-2+(-1)*Size*alpha*psi)+EXP(alpha*b*psi)*(-2+Size*alpha*psi)))/((alpha^3)*(psi^3)) -> 78.836376 | Q2: =Tau*Beta -> 192.51738 | R2: =Tau*Beta -> 192.51738 | S2: =Tau -> 1.069541 | T2: =Profit+Utility -> 3404.6053 | U2: =(2*ij*BRIJ)+(2)*jj*BRJJ -> 1464.916 | V2: =2*(ij*BCCIJ)+(2*jj*BCCJJ)+BCS+jj*BCPTJJ+2*(ij*BCPTIJ)+BCPTII+BCk -> 374.62596 | W2: =ij*BUTIJ+BUTII -> 2314.3153 | X2: =Revenue-Cost -> 1090.29
A3: 1.1057737 | B3: 0.5 | C3: 10 | D3: 0 | E3: =Size-a -> 10 | F3: =(EXP(alpha*(Tau+OldTau+zeta-2*a*psi))*((EXP(alpha*a*psi)-EXP(alpha*b*psi))^2))/((EXP(alpha*a*psi)-EXP(alpha*(2*OldTau+b*psi)))*(alpha^2)*(psi^2)) -> 1.714552 | G3: =(EXP(alpha*(zeta+(2*b-a)*psi))*(-1+EXP(alpha*(-1)*Size*psi))*(EXP(alpha*(2*(Tau+OldTau)+a*psi))-EXP(alpha*(2*(Tau+OldTau)+b*psi))))/(((EXP(alpha*a*psi)-EXP(alpha*(2*OldTau+b*psi)))^2)*(alpha^2)*(psi^2)) -> 0.083661916 | H3: =-Beta/alpha -> 180 | I3: =(-EXP(alpha*zeta)*Beta*(-1+EXP(alpha*Size*psi)-Size*alpha*psi))/((alpha^3)*(psi^2)) -> 1690.9246 | J3: =Beta*Theta -> 14.4 | K3: =Beta*Theta -> 14.4 | L3: =kappa -> 90 | M3: =Gamma*Size -> 0 | N3: =Size*Beta*Phi -> 32.4 | O3: =-(EXP(alpha*a*psi)+EXP(alpha*b*psi)*(-1+Size*psi*alpha))*(Beta*Phi)/((alpha*psi)*(EXP(alpha*a*psi)-EXP(alpha*b*psi))) -> 12.294172 | P3: =(EXP(alpha*(zeta-a*psi))*Beta*Phi*(-EXP(alpha*a*psi)*(-2+(-1)*Size*alpha*psi)+EXP(alpha*b*psi)*(-2+Size*alpha*psi)))/((alpha^3)*(psi^3)) -> 78.836376 | Q3: =Tau*Beta -> 199.03927 | R3: =Tau*Beta -> 199.03927 | S3: =Tau -> 1.1057737 | T3: =Profit+Utility -> 2449.8808 | U3: =(2*ij*BRIJ)+(2)*jj*BRJJ -> 715.83036 | V3: =2*(ij*BCCIJ)+(2*jj*BCCJJ)+BCS+jj*BCPTJJ+2*(ij*BCPTIJ)+BCPTII+BCk -> 265.49358 | W3: =ij*BUTIJ+BUTII -> 1999.544 | X3: =Revenue-Cost -> 450.33679
A4: 1.1233449 | B4: 1 | C4: 10 | D4: 0 | E4: =Size-a -> 10 | F4: =(EXP(alpha*(Tau+OldTau+zeta-2*a*psi))*((EXP(alpha*a*psi)-EXP(alpha*b*psi))^2))/((EXP(alpha*a*psi)-EXP(alpha*(2*OldTau+b*psi)))*(alpha^2)*(psi^2)) -> 0.96714469 | G4: =(EXP(alpha*(zeta+(2*b-a)*psi))*(-1+EXP(alpha*(-1)*Size*psi))*(EXP(alpha*(2*(Tau+OldTau)+a*psi))-EXP(alpha*(2*(Tau+OldTau)+b*psi))))/(((EXP(alpha*a*psi)-EXP(alpha*(2*OldTau+b*psi)))^2)*(alpha^2)*(psi^2)) -> 0.026620082 | H4: =-Beta/alpha -> 180 | I4: =(-EXP(alpha*zeta)*Beta*(-1+EXP(alpha*Size*psi)-Size*alpha*psi))/((alpha^3)*(psi^2)) -> 1690.9246 | J4: =Beta*Theta -> 14.4 | K4: =Beta*Theta -> 14.4 | L4: =kappa -> 90 | M4: =Gamma*Size -> 0 | N4: =Size*Beta*Phi -> 32.4 | O4: =-(EXP(alpha*a*psi)+EXP(alpha*b*psi)*(-1+Size*psi*alpha))*(Beta*Phi)/((alpha*psi)*(EXP(alpha*a*psi)-EXP(alpha*b*psi))) -> 12.294172 | P4: =(EXP(alpha*(zeta-a*psi))*Beta*Phi*(-EXP(alpha*a*psi)*(-2+(-1)*Size*alpha*psi)+EXP(alpha*b*psi)*(-2+Size*alpha*psi)))/((alpha^3)*(psi^3)) -> 78.836376 | Q4: =Tau*Beta -> 202.20209 | R4: =Tau*Beta -> 202.20209 | S4: =Tau -> 1.1233449 | T4: =Profit+Utility -> 2044.7935 | U4: =(2*ij*BRIJ)+(2)*jj*BRJJ -> 401.88262 | V4: =2*(ij*BCCIJ)+(2*jj*BCCJJ)+BCS+jj*BCPTJJ+2*(ij*BCPTIJ)+BCPTII+BCk -> 222.09978 | W4: =ij*BUTIJ+BUTII -> 1865.0107 | X4: =Revenue-Cost -> 179.78285
A5: 1.1332812 | B5: 1.5 | C5: 10 | D5: 0 | E5: =Size-a -> 10 | F5: =(EXP(alpha*(Tau+OldTau+zeta-2*a*psi))*((EXP(alpha*a*psi)-EXP(alpha*b*psi))^2))/((EXP(alpha*a*psi)-EXP(alpha*(2*OldTau+b*psi)))*(alpha^2)*(psi^2)) -> 0.56959196 | G5: =(EXP(alpha*(zeta+(2*b-a)*psi))*(-1+EXP(alpha*(-1)*Size*psi))*(EXP(alpha*(2*(Tau+OldTau)+a*psi))-EXP(alpha*(2*(Tau+OldTau)+b*psi))))/(((EXP(alpha*a*psi)-EXP(alpha*(2*OldTau+b*psi)))^2)*(alpha^2)*(psi^2)) -> 0.0092332414 | H5: =-Beta/alpha -> 180 | I5: =(-EXP(alpha*zeta)*Beta*(-1+EXP(alpha*Size*psi)-Size*alpha*psi))/((alpha^3)*(psi^2)) -> 1690.9246 | J5: =Beta*Theta -> 14.4 | K5: =Beta*Theta -> 14.4 | L5: =kappa -> 90 | M5: =Gamma*Size -> 0 | N5: =Size*Beta*Phi -> 32.4 | O5: =-(EXP(alpha*a*psi)+EXP(alpha*b*psi)*(-1+Size*psi*alpha))*(Beta*Phi)/((alpha*psi)*(EXP(alpha*a*psi)-EXP(alpha*b*psi))) -> 12.294172 | P5: =(EXP(alpha*(zeta-a*psi))*Beta*Phi*(-EXP(alpha*a*psi)*(-2+(-1)*Size*alpha*psi)+EXP(alpha*b*psi)*(-2+Size*alpha*psi)))/((alpha^3)*(psi^3)) -> 78.836376 | Q5: =Tau*Beta -> 203.99062 | R5: =Tau*Beta -> 203.99062 | S5: =Tau -> 1.1332812 | T5: =Profit+Utility -> 1829.79 | U5: =(2*ij*BRIJ)+(2)*jj*BRJJ -> 236.14983 | V5: =2*(ij*BCCIJ)+(2*jj*BCCJJ)+BCS+jj*BCPTJJ+2*(ij*BCPTIJ)+BCPTII+BCk -> 199.81102 | W5: =ij*BUTIJ+BUTII -> 1793.4512 | X5: =Revenue-Cost -> 36.338807
A6: 1.1391939 | B6: 2 | C6: 10 | D6: 0 | E6: =Size-a -> 10 | F6: =(EXP(alpha*(Tau+OldTau+zeta-2*a*psi))*((EXP(alpha*a*psi)-EXP(alpha*b*psi))^2))/((EXP(alpha*a*psi)-EXP(alpha*(2*OldTau+b*psi)))*(alpha^2)*(psi^2)) -> 0.34101675 | G6: =(EXP(alpha*(zeta+(2*b-a)*psi))*(-1+EXP(alpha*(-1)*Size*psi))*(EXP(alpha*(2*(Tau+OldTau)+a*psi))-EXP(alpha*(2*(Tau+OldTau)+b*psi))))/(((EXP(alpha*a*psi)-EXP(alpha*(2*OldTau+b*psi)))^2)*(alpha^2)*(psi^2)) -> 0.0033096183 | H6: =-Beta/alpha -> 180 | I6: =(-EXP(alpha*zeta)*Beta*(-1+EXP(alpha*Size*psi)-Size*alpha*psi))/((alpha^3)*(psi^2)) -> 1690.9246 | J6: =Beta*Theta -> 14.4 | K6: =Beta*Theta -> 14.4 | L6: =kappa -> 90 | M6: =Gamma*Size -> 0 | N6: =Size*Beta*Phi -> 32.4 | O6: =-(EXP(alpha*a*psi)+EXP(alpha*b*psi)*(-1+Size*psi*alpha))*(Beta*Phi)/((alpha*psi)*(EXP(alpha*a*psi)-EXP(alpha*b*psi))) -> 12.294172 | P6: =(EXP(alpha*(zeta-a*psi))*Beta*Phi*(-EXP(alpha*a*psi)*(-2+(-1)*Size*alpha*psi)+EXP(alpha*b*psi)*(-2+Size*alpha*psi)))/((alpha^3)*(psi^3)) -> 78.836376 | Q6: =Tau*Beta -> 205.0549 | R6: =Tau*Beta -> 205.0549 | S6: =Tau -> 1.1391939 | T6: =Profit+Utility -> 1706.274 | U6: =(2*ij*BRIJ)+(2)*jj*BRJJ -> 141.21162 | V6: =2*(ij*BCCIJ)+(2*jj*BCCJJ)+BCS+jj*BCPTJJ+2*(ij*BCPTIJ)+BCPTII+BCk -> 187.24524 | W6: =ij*BUTIJ+BUTII -> 1752.3076 | X6: =Revenue-Cost -> -46.033627
A7: 1.1427695 | B7: 2.5 | C7: 10 | D7: 0 | E7: =Size-a -> 10 | F7: =(EXP(alpha*(Tau+OldTau+zeta-2*a*psi))*((EXP(alpha*a*psi)-EXP(alpha*b*psi))^2))/((EXP(alpha*a*psi)-EXP(alpha*(2*OldTau+b*psi)))*(alpha^2)*(psi^2)) -> 0.20556563 | G7: =(EXP(alpha*(zeta+(2*b-a)*psi))*(-1+EXP(alpha*(-1)*Size*psi))*(EXP(alpha*(2*(Tau+OldTau)+a*psi))-EXP(alpha*(2*(Tau+OldTau)+b*psi))))/(((EXP(alpha*a*psi)-EXP(alpha*(2*OldTau+b*psi)))^2)*(alpha^2)*(psi^2)) -> 0.0012026175 | H7: =-Beta/alpha -> 180 | I7: =(-EXP(alpha*zeta)*Beta*(-1+EXP(alpha*Size*psi)-Size*alpha*psi))/((alpha^3)*(psi^2)) -> 1690.9246 | J7: =Beta*Theta -> 14.4 | K7: =Beta*Theta -> 14.4 | L7: =kappa -> 90 | M7: =Gamma*Size -> 0 | N7: =Size*Beta*Phi -> 32.4 | O7: =-(EXP(alpha*a*psi)+EXP(alpha*b*psi)*(-1+Size*psi*alpha))*(Beta*Phi)/((alpha*psi)*(EXP(alpha*a*psi)-EXP(alpha*b*psi))) -> 12.294172 | P7: =(EXP(alpha*(zeta-a*psi))*Beta*Phi*(-EXP(alpha*a*psi)*(-2+(-1)*Size*alpha*psi)+EXP(alpha*b*psi)*(-2+Size*alpha*psi)))/((alpha^3)*(psi^3)) -> 78.836376 | Q7: =Tau*Beta -> 205.69852 | R7: =Tau*Beta -> 205.69852 | S7: =Tau -> 1.1427695 | T7: =Profit+Utility -> 1633.1055 | U7: =(2*ij*BRIJ)+(2)*jj*BRJJ -> 85.063845 | V7: =2*(ij*BCCIJ)+(2*jj*BCCJJ)+BCS+jj*BCPTJJ+2*(ij*BCPTIJ)+BCPTII+BCk -> 179.88478 | W7: =ij*BUTIJ+BUTII -> 1727.9264 | X7: =Revenue-Cost -> -94.82094
A8: 1.1449412 | B8: 3 | C8: 10 | D8: 0 | E8: =Size-a -> 10 | F8: =(EXP(alpha*(Tau+OldTau+zeta-2*a*psi))*((EXP(alpha*a*psi)-EXP(alpha*b*psi))^2))/((EXP(alpha*a*psi)-EXP(alpha*(2*OldTau+b*psi)))*(alpha^2)*(psi^2)) -> 0.12429308 | G8: =(EXP(alpha*(zeta+(2*b-a)*psi))*(-1+EXP(alpha*(-1)*Size*psi))*(EXP(alpha*(2*(Tau+OldTau)+a*psi))-EXP(alpha*(2*(Tau+OldTau)+b*psi))))/(((EXP(alpha*a*psi)-EXP(alpha*(2*OldTau+b*psi)))^2)*(alpha^2)*(psi^2)) -> 0.0004396635 | H8: =-Beta/alpha -> 180 | I8: =(-EXP(alpha*zeta)*Beta*(-1+EXP(alpha*Size*psi)-Size*alpha*psi))/((alpha^3)*(psi^2)) -> 1690.9246 | J8: =Beta*Theta -> 14.4 | K8: =Beta*Theta -> 14.4 | L8: =kappa -> 90 | M8: =Gamma*Size -> 0 | N8: =Size*Beta*Phi -> 32.4 | O8: =-(EXP(alpha*a*psi)+EXP(alpha*b*psi)*(-1+Size*psi*alpha))*(Beta*Phi)/((alpha*psi)*(EXP(alpha*a*psi)-EXP(alpha*b*psi))) -> 12.294172 | P8: =(EXP(alpha*(zeta-a*psi))*Beta*Phi*(-EXP(alpha*a*psi)*(-2+(-1)*Size*alpha*psi)+EXP(alpha*b*psi)*(-2+Size*alpha*psi)))/((alpha^3)*(psi^3)) -> 78.836376 | Q8: =Tau*Beta -> 206.08942 | R8: =Tau*Beta -> 206.08942 | S8: =Tau -> 1.1449412 | T8: =Profit+Utility -> 1589.2105 | U8: =(2*ij*BRIJ)+(2)*jj*BRJJ -> 51.412199 | V8: =2*(ij*BCCIJ)+(2*jj*BCCJJ)+BCS+jj*BCPTJJ+2*(ij*BCPTIJ)+BCPTII+BCk -> 175.49909 | W8: =ij*BUTIJ+BUTII -> 1713.2974 | X8: =Revenue-Cost -> -124.08689
A9: 1.146261 | B9: 3.5 | C9: 10 | D9: 0 | E9: =Size-a -> 10 | F9: =(EXP(alpha*(Tau+OldTau+zeta-2*a*psi))*((EXP(alpha*a*psi)-EXP(alpha*b*psi))^2))/((EXP(alpha*a*psi)-EXP(alpha*(2*OldTau+b*psi)))*(alpha^2)*(psi^2)) -> 0.075261808 | G9: =(EXP(alpha*(zeta+(2*b-a)*psi))*(-1+EXP(alpha*(-1)*Size*psi))*(EXP(alpha*(2*(Tau+OldTau)+a*psi))-EXP(alpha*(2*(Tau+OldTau)+b*psi))))/(((EXP(alpha*a*psi)-EXP(alpha*(2*OldTau+b*psi)))^2)*(alpha^2)*(psi^2)) -> 0.00016120399 | H9: =-Beta/alpha -> 180 | I9: =(-EXP(alpha*zeta)*Beta*(-1+EXP(alpha*Size*psi)-Size*alpha*psi))/((alpha^3)*(psi^2)) -> 1690.9246 | J9: =Beta*Theta -> 14.4 | K9: =Beta*Theta -> 14.4 | L9: =kappa -> 90 | M9: =Gamma*Size -> 0 | N9: =Size*Beta*Phi -> 32.4 | O9: =-(EXP(alpha*a*psi)+EXP(alpha*b*psi)*(-1+Size*psi*alpha))*(Beta*Phi)/((alpha*psi)*(EXP(alpha*a*psi)-EXP(alpha*b*psi))) -> 12.294172 | P9: =(EXP(alpha*(zeta-a*psi))*Beta*Phi*(-EXP(alpha*a*psi)*(-2+(-1)*Size*alpha*psi)+EXP(alpha*b*psi)*(-2+Size*alpha*psi)))/((alpha^3)*(psi^3)) -> 78.836376 | Q9: =Tau*Beta -> 206.32698 | R9: =Tau*Beta -> 206.32698 | S9: =Tau -> 1.146261 | T9: =Profit+Utility -> 1562.731 | U9: =(2*ij*BRIJ)+(2)*jj*BRJJ -> 31.123605 | V9: =2*(ij*BCCIJ)+(2*jj*BCCJJ)+BCS+jj*BCPTJJ+2*(ij*BCPTIJ)+BCPTII+BCk -> 172.86434 | W9: =ij*BUTIJ+BUTII -> 1704.4718 | X9: =Revenue-Cost -> -141.74074
A10: 1.1470633 | B10: 4 | C10: 10 | D10: 0 | E10: =Size-a -> 10 | F10: =(EXP(alpha*(Tau+OldTau+zeta-2*a*psi))*((EXP(alpha*a*psi)-EXP(alpha*b*psi))^2))/((EXP(alpha*a*psi)-EXP(alpha*(2*OldTau+b*psi)))*(alpha^2)*(psi^2)) -> 0.045606119 | G10: =(EXP(alpha*(zeta+(2*b-a)*psi))*(-1+EXP(alpha*(-1)*Size*psi))*(EXP(alpha*(2*(Tau+OldTau)+a*psi))-EXP(alpha*(2*(Tau+OldTau)+b*psi))))/(((EXP(alpha*a*psi)-EXP(alpha*(2*OldTau+b*psi)))^2)*(alpha^2)*(psi^2)) -> 5.9193322e-05 | H10: =-Beta/alpha -> 180 | I10: =(-EXP(alpha*zeta)*Beta*(-1+EXP(alpha*Size*psi)-Size*alpha*psi))/((alpha^3)*(psi^2)) -> 1690.9246 | J10: =Beta*Theta -> 14.4 | K10: =Beta*Theta -> 14.4 | L10: =kappa -> 90 | M10: =Gamma*Size -> 0 | N10: =Size*Beta*Phi -> 32.4 | O10: =-(EXP(alpha*a*psi)+EXP(alpha*b*psi)*(-1+Size*psi*alpha))*(Beta*Phi)/((alpha*psi)*(EXP(alpha*a*psi)-EXP(alpha*b*psi))) -> 12.294172 | P10: =(EXP(alpha*(zeta-a*psi))*Beta*Phi*(-EXP(alpha*a*psi)*(-2+(-1)*Size*alpha*psi)+EXP(alpha*b*psi)*(-2+Size*alpha*psi)))/((alpha^3)*(psi^3)) -> 78.836376 | Q10: =Tau*Beta -> 206.47139 | R10: =Tau*Beta -> 206.47139 | S10: =Tau -> 1.1470633 | T10: =Profit+Utility -> 1546.7161 | U10: =(2*ij*BRIJ)+(2)*jj*BRJJ -> 18.857161 | V10: =2*(ij*BCCIJ)+(2*jj*BCCJJ)+BCS+jj*BCPTJJ+2*(ij*BCPTIJ)+BCPTII+BCk -> 171.27483 | W10: =ij*BUTIJ+BUTII -> 1699.1337 | X10: =Revenue-Cost -> -152.41767
A11: 1.1475503 | B11: 4.5 | C11: 10 | D11: 0 | E11: =Size-a -> 10 | F11: =(EXP(alpha*(Tau+OldTau+zeta-2*a*psi))*((EXP(alpha*a*psi)-EXP(alpha*b*psi))^2))/((EXP(alpha*a*psi)-EXP(alpha*(2*OldTau+b*psi)))*(alpha^2)*(psi^2)) -> 0.027646734 | G11: =(EXP(alpha*(zeta+(2*b-a)*psi))*(-1+EXP(alpha*(-1)*Size*psi))*(EXP(alpha*(2*(Tau+OldTau)+a*psi))-EXP(alpha*(2*(Tau+OldTau)+b*psi))))/(((EXP(alpha*a*psi)-EXP(alpha*(2*OldTau+b*psi)))^2)*(alpha^2)*(psi^2)) -> 2.1752749e-05 | H11: =-Beta/alpha -> 180 | I11: =(-EXP(alpha*zeta)*Beta*(-1+EXP(alpha*Size*psi)-Size*alpha*psi))/((alpha^3)*(psi^2)) -> 1690.9246 | J11: =Beta*Theta -> 14.4 | K11: =Beta*Theta -> 14.4 | L11: =kappa -> 90 | M11: =Gamma*Size -> 0 | N11: =Size*Beta*Phi -> 32.4 | O11: =-(EXP(alpha*a*psi)+EXP(alpha*b*psi)*(-1+Size*psi*alpha))*(Beta*Phi)/((alpha*psi)*(EXP(alpha*a*psi)-EXP(alpha*b*psi))) -> 12.294172 | P11: =(EXP(alpha*(zeta-a*psi))*Beta*Phi*(-EXP(alpha*a*psi)*(-2+(-1)*Size*alpha*psi)+EXP(alpha*b*psi)*(-2+Size*alpha*psi)))/((alpha^3)*(psi^3)) -> 78.836376 | Q11: =Tau*Beta -> 206.55905 | R11: =Tau*Beta -> 206.55905 | S11: =Tau -> 1.1475503 | T11: =Profit+Utility -> 1537.0177 | U11: =(2*ij*BRIJ)+(2)*jj*BRJJ -> 11.430353 | V11: =2*(ij*BCCIJ)+(2*jj*BCCJJ)+BCS+jj*BCPTJJ+2*(ij*BCPTIJ)+BCPTII+BCk -> 170.31372 | W11: =ij*BUTIJ+BUTII -> 1695.901 | X11: =Revenue-Cost -> -158.88337
A12: 1.1478455 | B12: 5 | C12: 10 | D12: 0 | E12: =Size-a -> 10 | F12: =(EXP(alpha*(Tau+OldTau+zeta-2*a*psi))*((EXP(alpha*a*psi)-EXP(alpha*b*psi))^2))/((EXP(alpha*a*psi)-EXP(alpha*(2*OldTau+b*psi)))*(alpha^2)*(psi^2)) -> 0.016763349 | G12: =(EXP(alpha*(zeta+(2*b-a)*psi))*(-1+EXP(alpha*(-1)*Size*psi))*(EXP(alpha*(2*(Tau+OldTau)+a*psi))-EXP(alpha*(2*(Tau+OldTau)+b*psi))))/(((EXP(alpha*a*psi)-EXP(alpha*(2*OldTau+b*psi)))^2)*(alpha^2)*(psi^2)) -> 7.9973865e-06 | H12: =-Beta/alpha -> 180 | I12: =(-EXP(alpha*zeta)*Beta*(-1+EXP(alpha*Size*psi)-Size*alpha*psi))/((alpha^3)*(psi^2)) -> 1690.9246 | J12: =Beta*Theta -> 14.4 | K12: =Beta*Theta -> 14.4 | L12: =kappa -> 90 | M12: =Gamma*Size -> 0 | N12: =Size*Beta*Phi -> 32.4 | O12: =-(EXP(alpha*a*psi)+EXP(alpha*b*psi)*(-1+Size*psi*alpha))*(Beta*Phi)/((alpha*psi)*(EXP(alpha*a*psi)-EXP(alpha*b*psi))) -> 12.294172 | P12: =(EXP(alpha*(zeta-a*psi))*Beta*Phi*(-EXP(alpha*a*psi)*(-2+(-1)*Size*alpha*psi)+EXP(alpha*b*psi)*(-2+Size*alpha*psi)))/((alpha^3)*(psi^3)) -> 78.836376 | Q12: =Tau*Beta -> 206.6122 | R12: =Tau*Beta -> 206.6122 | S12: =Tau -> 1.1478455 | T12: =Profit+Utility -> 1531.1405 | U12: =(2*ij*BRIJ)+(2)*jj*BRJJ -> 6.9303296 | V12: =2*(ij*BCCIJ)+(2*jj*BCCJJ)+BCS+jj*BCPTJJ+2*(ij*BCPTIJ)+BCPTII+BCk -> 169.73183 | W12: =ij*BUTIJ+BUTII -> 1693.942 | X12: =Revenue-Cost -> -162.8015

Sheet P-React-JS=1
A1: Tau | B1: OldTau | C1: Size | D1: a | E1: b | F1: ij | G1: jj | H1: BUTIJ | I1: BUTII | J1: BCCIJ | K1: BCCJJ | L1: BCk | M1: BCS | N1: BCPTJJ | O1: BCPTIJ | P1: BCPTII | Q1: BRIJ | R1: BRJJ | S1: Toll | T1: Welfare | U1: Revenue | V1: Cost | W1: Utility | X1: Profit
A2: 0.65644469 | B2: 0 | C2: 1 | D2: 0 | E2: =Size-a -> 1 | F2: =(EXP(alpha*(Tau+OldTau+zeta-2*a*psi))*((EXP(alpha*a*psi)-EXP(alpha*b*psi))^2))/((EXP(alpha*a*psi)-EXP(alpha*(2*OldTau+b*psi)))*(alpha^2)*(psi^2)) -> 0.93857982 | G2: =(EXP(alpha*(zeta+(2*b-a)*psi))*(-1+EXP(alpha*(-1)*Size*psi))*(EXP(alpha*(2*(Tau+OldTau)+a*psi))-EXP(alpha*(2*(Tau+OldTau)+b*psi))))/(((EXP(alpha*a*psi)-EXP(alpha*(2*OldTau+b*psi)))^2)*(alpha^2)*(psi^2)) -> 3.0082262 | H2: =-Beta/alpha -> 180 | I2: =(-EXP(alpha*zeta)*Beta*(-1+EXP(alpha*Size*psi)-Size*alpha*psi))/((alpha^3)*(psi^2)) -> 25.038896 | J2: =Beta*Theta -> 14.4 | K2: =Beta*Theta -> 14.4 | L2: =kappa -> 90 | M2: =Gamma*Size -> 0 | N2: =Size*Beta*Phi -> 3.24 | O2: =-(EXP(alpha*a*psi)+EXP(alpha*b*psi)*(-1+Size*psi*alpha))*(Beta*Phi)/((alpha*psi)*(EXP(alpha*a*psi)-EXP(alpha*b*psi))) -> 1.5795152 | P2: =(EXP(alpha*(zeta-a*psi))*Beta*Phi*(-EXP(alpha*a*psi)*(-2+(-1)*Size*alpha*psi)+EXP(alpha*b*psi)*(-2+Size*alpha*psi)))/((alpha^3)*(psi^3)) -> 0.14651555 | Q2: =Tau*Beta -> 118.16004 | R2: =Tau*Beta -> 118.16004 | S2: =Tau -> 0.65644469 | T2: =Profit+Utility -> 910.16662 | U2: =(2*ij*BRIJ)+(2)*jj*BRJJ -> 932.70954 | V2: =2*(ij*BCCIJ)+(2*jj*BCCJJ)+BCS+jj*BCPTJJ+2*(ij*BCPTIJ)+BCPTII+BCk -> 216.52618 | W2: =ij*BUTIJ+BUTII -> 193.98326 | X2: =Revenue-Cost -> 716.18335
A3: 0.89691323 | B3: 0.5 | C3: 1 | D3: 0 | E3: =Size-a -> 1 | F3: =(EXP(alpha*(Tau+OldTau+zeta-2*a*psi))*((EXP(alpha*a*psi)-EXP(alpha*b*psi))^2))/((EXP(alpha*a*psi)-EXP(alpha*(2*OldTau+b*psi)))*(alpha^2)*(psi^2)) -> 0.091235624 | G3: =(EXP(alpha*(zeta+(2*b-a)*psi))*(-1+EXP(alpha*(-1)*Size*psi))*(EXP(alpha*(2*(Tau+OldTau)+a*psi))-EXP(alpha*(2*(Tau+OldTau)+b*psi))))/(((EXP(alpha*a*psi)-EXP(alpha*(2*OldTau+b*psi)))^2)*(alpha^2)*(psi^2)) -> 0.02842477 | H3: =-Beta/alpha -> 180 | I3: =(-EXP(alpha*zeta)*Beta*(-1+EXP(alpha*Size*psi)-Size*alpha*psi))/((alpha^3)*(psi^2)) -> 25.038896 | J3: =Beta*Theta -> 14.4 | K3: =Beta*Theta -> 14.4 | L3: =kappa -> 90 | M3: =Gamma*Size -> 0 | N3: =Size*Beta*Phi -> 3.24 | O3: =-(EXP(alpha*a*psi)+EXP(alpha*b*psi)*(-1+Size*psi*alpha))*(Beta*Phi)/((alpha*psi)*(EXP(alpha*a*psi)-EXP(alpha*b*psi))) -> 1.5795152 | P3: =(EXP(alpha*(zeta-a*psi))*Beta*Phi*(-EXP(alpha*a*psi)*(-2+(-1)*Size*alpha*psi)+EXP(alpha*b*psi)*(-2+Size*alpha*psi)))/((alpha^3)*(psi^3)) -> 0.14651555 | Q3: =Tau*Beta -> 161.44438 | R3: =Tau*Beta -> 161.44438 | S3: =Tau -> 0.89691323 | T3: =Profit+Utility -> -13.874742 | U3: =(2*ij*BRIJ)+(2)*jj*BRJJ -> 38.636997 | V3: =2*(ij*BCCIJ)+(2*jj*BCCJJ)+BCS+jj*BCPTJJ+2*(ij*BCPTIJ)+BCPTII+BCk -> 93.973047 | W3: =ij*BUTIJ+BUTII -> 41.461309 | X3: =Revenue-Cost -> -55.33605
A4: 0.98308833 | B4: 1 | C4: 1 | D4: 0 | E4: =Size-a -> 1 | F4: =(EXP(alpha*(Tau+OldTau+zeta-2*a*psi))*((EXP(alpha*a*psi)-EXP(alpha*b*psi))^2))/((EXP(alpha*a*psi)-EXP(alpha*(2*OldTau+b*psi)))*(alpha^2)*(psi^2)) -> 0.039267125 | G4: =(EXP(alpha*(zeta+(2*b-a)*psi))*(-1+EXP(alpha*(-1)*Size*psi))*(EXP(alpha*(2*(Tau+OldTau)+a*psi))-EXP(alpha*(2*(Tau+OldTau)+b*psi))))/(((EXP(alpha*a*psi)-EXP(alpha*(2*OldTau+b*psi)))^2)*(alpha^2)*(psi^2)) -> 0.0052653382 | H4: =-Beta/alpha -> 180 | I4: =(-EXP(alpha*zeta)*Beta*(-1+EXP(alpha*Size*psi)-Size*alpha*psi))/((alpha^3)*(psi^2)) -> 25.038896 | J4: =Beta*Theta -> 14.4 | K4: =Beta*Theta -> 14.4 | L4: =kappa -> 90 | M4: =Gamma*Size -> 0 | N4: =Size*Beta*Phi -> 3.24 | O4: =-(EXP(alpha*a*psi)+EXP(alpha*b*psi)*(-1+Size*psi*alpha))*(Beta*Phi)/((alpha*psi)*(EXP(alpha*a*psi)-EXP(alpha*b*psi))) -> 1.5795152 | P4: =(EXP(alpha*(zeta-a*psi))*Beta*Phi*(-EXP(alpha*a*psi)*(-2+(-1)*Size*alpha*psi)+EXP(alpha*b*psi)*(-2+Size*alpha*psi)))/((alpha^3)*(psi^3)) -> 0.14651555 | Q4: =Tau*Beta -> 176.9559 | R4: =Tau*Beta -> 176.9559 | S4: =Tau -> 0.98308833 | T4: =Profit+Utility -> -43.702613 | U4: =(2*ij*BRIJ)+(2)*jj*BRJJ -> 15.760564 | V4: =2*(ij*BCCIJ)+(2*jj*BCCJJ)+BCS+jj*BCPTJJ+2*(ij*BCPTIJ)+BCPTII+BCk -> 91.570156 | W4: =ij*BUTIJ+BUTII -> 32.106979 | X4: =Revenue-Cost -> -75.809592
A5: 1.0259236 | B5: 1.5 | C5: 1 | D5: 0 | E5: =Size-a -> 1 | F5: =(EXP(alpha*(Tau+OldTau+zeta-2*a*psi))*((EXP(alpha*a*psi)-EXP(alpha*b*psi))^2))/((EXP(alpha*a*psi)-EXP(alpha*(2*OldTau+b*psi)))*(alpha^2)*(psi^2)) -> 0.021062701 | G5: =(EXP(alpha*(zeta+(2*b-a)*psi))*(-1+EXP(alpha*(-1)*Size*psi))*(EXP(alpha*(2*(Tau+OldTau)+a*psi))-EXP(alpha*(2*(Tau+OldTau)+b*psi))))/(((EXP(alpha*a*psi)-EXP(alpha*(2*OldTau+b*psi)))^2)*(alpha^2)*(psi^2)) -> 0.0015149426 | H5: =-Beta/alpha -> 180 | I5: =(-EXP(alpha*zeta)*Beta*(-1+EXP(alpha*Size*psi)-Size*alpha*psi))/((alpha^3)*(psi^2)) -> 25.038896 | J5: =Beta*Theta -> 14.4 | K5: =Beta*Theta -> 14.4 | L5: =kappa -> 90 | M5: =Gamma*Size -> 0 | N5: =Size*Beta*Phi -> 3.24 | O5: =-(EXP(alpha*a*psi)+EXP(alpha*b*psi)*(-1+Size*psi*alpha))*(Beta*Phi)/((alpha*psi)*(EXP(alpha*a*psi)-EXP(alpha*b*psi))) -> 1.5795152 | P5: =(EXP(alpha*(zeta-a*psi))*Beta*Phi*(-EXP(alpha*a*psi)*(-2+(-1)*Size*alpha*psi)+EXP(alpha*b*psi)*(-2+Size*alpha*psi)))/((alpha^3)*(psi^3)) -> 0.14651555 | Q5: =Tau*Beta -> 184.66624 | R5: =Tau*Beta -> 184.66624 | S5: =Tau -> 1.0259236 | T5: =Profit+Utility -> -53.699358 | U5: =(2*ij*BRIJ)+(2)*jj*BRJJ -> 8.3386571 | V5: =2*(ij*BCCIJ)+(2*jj*BCCJJ)+BCS+jj*BCPTJJ+2*(ij*BCPTIJ)+BCPTII+BCk -> 90.868198 | W5: =ij*BUTIJ+BUTII -> 28.830182 | X5: =Revenue-Cost -> -82.529541
A6: 1.0505653 | B6: 2 | C6: 1 | D6: 0 | E6: =Size-a -> 1 | F6: =(EXP(alpha*(Tau+OldTau+zeta-2*a*psi))*((EXP(alpha*a*psi)-EXP(alpha*b*psi))^2))/((EXP(alpha*a*psi)-EXP(alpha*(2*OldTau+b*psi)))*(alpha^2)*(psi^2)) -> 0.012121183 | G6: =(EXP(alpha*(zeta+(2*b-a)*psi))*(-1+EXP(alpha*(-1)*Size*psi))*(EXP(alpha*(2*(Tau+OldTau)+a*psi))-EXP(alpha*(2*(Tau+OldTau)+b*psi))))/(((EXP(alpha*a*psi)-EXP(alpha*(2*OldTau+b*psi)))^2)*(alpha^2)*(psi^2)) -> 0.00050171619 | H6: =-Beta/alpha -> 180 | I6: =(-EXP(alpha*zeta)*Beta*(-1+EXP(alpha*Size*psi)-Size*alpha*psi))/((alpha^3)*(psi^2)) -> 25.038896 | J6: =Beta*Theta -> 14.4 | K6: =Beta*Theta -> 14.4 | L6: =kappa -> 90 | M6: =Gamma*Size -> 0 | N6: =Size*Beta*Phi -> 3.24 | O6: =-(EXP(alpha*a*psi)+EXP(alpha*b*psi)*(-1+Size*psi*alpha))*(Beta*Phi)/((alpha*psi)*(EXP(alpha*a*psi)-EXP(alpha*b*psi))) -> 1.5795152 | P6: =(EXP(alpha*(zeta-a*psi))*Beta*Phi*(-EXP(alpha*a*psi)*(-2+(-1)*Size*alpha*psi)+EXP(alpha*b*psi)*(-2+Size*alpha*psi)))/((alpha^3)*(psi^3)) -> 0.14651555 | Q6: =Tau*Beta -> 189.10175 | R6: =Tau*Beta -> 189.10175 | S6: =Tau -> 1.0505653 | T6: =Profit+Utility -> -58.555238 | U6: =(2*ij*BRIJ)+(2)*jj*BRJJ -> 4.7740249 | V6: =2*(ij*BCCIJ)+(2*jj*BCCJJ)+BCS+jj*BCPTJJ+2*(ij*BCPTIJ)+BCPTII+BCk -> 90.549972 | W6: =ij*BUTIJ+BUTII -> 27.220709 | X6: =Revenue-Cost -> -85.775947
A7: 1.0654426 | B7: 2.5 | C7: 1 | D7: 0 | E7: =Size-a -> 1 | F7: =(EXP(alpha*(Tau+OldTau+zeta-2*a*psi))*((EXP(alpha*a*psi)-EXP(alpha*b*psi))^2))/((EXP(alpha*a*psi)-EXP(alpha*(2*OldTau+b*psi)))*(alpha^2)*(psi^2)) -> 0.0071707024 | G7: =(EXP(alpha*(zeta+(2*b-a)*psi))*(-1+EXP(alpha*(-1)*Size*psi))*(EXP(alpha*(2*(Tau+OldTau)+a*psi))-EXP(alpha*(2*(Tau+OldTau)+b*psi))))/(((EXP(alpha*a*psi)-EXP(alpha*(2*OldTau+b*psi)))^2)*(alpha^2)*(psi^2)) -> 0.00017558663 | H7: =-Beta/alpha -> 180 | I7: =(-EXP(alpha*zeta)*Beta*(-1+EXP(alpha*Size*psi)-Size*alpha*psi))/((alpha^3)*(psi^2)) -> 25.038896 | J7: =Beta*Theta -> 14.4 | K7: =Beta*Theta -> 14.4 | L7: =kappa -> 90 | M7: =Gamma*Size -> 0 | N7: =Size*Beta*Phi -> 3.24 | O7: =-(EXP(alpha*a*psi)+EXP(alpha*b*psi)*(-1+Size*psi*alpha))*(Beta*Phi)/((alpha*psi)*(EXP(alpha*a*psi)-EXP(alpha*b*psi))) -> 1.5795152 | P7: =(EXP(alpha*(zeta-a*psi))*Beta*Phi*(-EXP(alpha*a*psi)*(-2+(-1)*Size*alpha*psi)+EXP(alpha*b*psi)*(-2+Size*alpha*psi)))/((alpha^3)*(psi^3)) -> 0.14651555 | Q7: =Tau*Beta -> 191.77967 | R7: =Tau*Beta -> 191.77967 | S7: =Tau -> 1.0654426 | T7: =Profit+Utility -> -61.23395 | U7: =(2*ij*BRIJ)+(2)*jj*BRJJ -> 2.8177377 | V7: =2*(ij*BCCIJ)+(2*jj*BCCJJ)+BCS+jj*BCPTJJ+2*(ij*BCPTIJ)+BCPTII+BCk -> 90.38131 | W7: =ij*BUTIJ+BUTII -> 26.329623 | X7: =Revenue-Cost -> -87.563572
A8: 1.0745368 | B8: 3 | C8: 1 | D8: 0 | E8: =Size-a -> 1 | F8: =(EXP(alpha*(Tau+OldTau+zeta-2*a*psi))*((EXP(alpha*a*psi)-EXP(alpha*b*psi))^2))/((EXP(alpha*a*psi)-EXP(alpha*(2*OldTau+b*psi)))*(alpha^2)*(psi^2)) -> 0.0042940437 | G8: =(EXP(alpha*(zeta+(2*b-a)*psi))*(-1+EXP(alpha*(-1)*Size*psi))*(EXP(alpha*(2*(Tau+OldTau)+a*psi))-EXP(alpha*(2*(Tau+OldTau)+b*psi))))/(((EXP(alpha*a*psi)-EXP(alpha*(2*OldTau+b*psi)))^2)*(alpha^2)*(psi^2)) -> 6.2965258e-05 | H8: =-Beta/alpha -> 180 | I8: =(-EXP(alpha*zeta)*Beta*(-1+EXP(alpha*Size*psi)-Size*alpha*psi))/((alpha^3)*(psi^2)) -> 25.038896 | J8: =Beta*Theta -> 14.4 | K8: =Beta*Theta -> 14.4 | L8: =kappa -> 90 | M8: =Gamma*Size -> 0 | N8: =Size*Beta*Phi -> 3.24 | O8: =-(EXP(alpha*a*psi)+EXP(alpha*b*psi)*(-1+Size*psi*alpha))*(Beta*Phi)/((alpha*psi)*(EXP(alpha*a*psi)-EXP(alpha*b*psi))) -> 1.5795152 | P8: =(EXP(alpha*(zeta-a*psi))*Beta*Phi*(-EXP(alpha*a*psi)*(-2+(-1)*Size*alpha*psi)+EXP(alpha*b*psi)*(-2+Size*alpha*psi)))/((alpha^3)*(psi^3)) -> 0.14651555 | Q8: =Tau*Beta -> 193.41663 | R8: =Tau*Beta -> 193.41663 | S8: =Tau -> 1.0745368 | T8: =Profit+Utility -> -62.788506 | U8: =(2*ij*BRIJ)+(2)*jj*BRJJ -> 1.6854359 | V8: =2*(ij*BCCIJ)+(2*jj*BCCJJ)+BCS+jj*BCPTJJ+2*(ij*BCPTIJ)+BCPTII+BCk -> 90.285766 | W8: =ij*BUTIJ+BUTII -> 25.811824 | X8: =Revenue-Cost -> -88.60033
A9: 1.0807961 | B9: 3.5 | C9: 1 | D9: 0 | E9: =Size-a -> 1 | F9: =(EXP(alpha*(Tau+OldTau+zeta-2*a*psi))*((EXP(alpha*a*psi)-EXP(alpha*b*psi))^2))/((EXP(alpha*a*psi)-EXP(alpha*(2*OldTau+b*psi)))*(alpha^2)*(psi^2)) -> 0.0025847247 | G9: =(EXP(alpha*(zeta+(2*b-a)*psi))*(-1+EXP(alpha*(-1)*Size*psi))*(EXP(alpha*(2*(Tau+OldTau)+a*psi))-EXP(alpha*(2*(Tau+OldTau)+b*psi))))/(((EXP(alpha*a*psi)-EXP(alpha*(2*OldTau+b*psi)))^2)*(alpha^2)*(psi^2)) -> 2.2813749e-05 | H9: =-Beta/alpha -> 180 | I9: =(-EXP(alpha*zeta)*Beta*(-1+EXP(alpha*Size*psi)-Size*alpha*psi))/((alpha^3)*(psi^2)) -> 25.038896 | J9: =Beta*Theta -> 14.4 | K9: =Beta*Theta -> 14.4 | L9: =kappa -> 90 | M9: =Gamma*Size -> 0 | N9: =Size*Beta*Phi -> 3.24 | O9: =-(EXP(alpha*a*psi)+EXP(alpha*b*psi)*(-1+Size*psi*alpha))*(Beta*Phi)/((alpha*psi)*(EXP(alpha*a*psi)-EXP(alpha*b*psi))) -> 1.5795152 | P9: =(EXP(alpha*(zeta-a*psi))*Beta*Phi*(-EXP(alpha*a*psi)*(-2+(-1)*Size*alpha*psi)+EXP(alpha*b*psi)*(-2+Size*alpha*psi)))/((alpha^3)*(psi^3)) -> 0.14651555 | Q9: =Tau*Beta -> 194.54329 | R9: =Tau*Beta -> 194.54329 | S9: =Tau -> 1.0807961 | T9: =Profit+Utility -> -63.711147 | U9: =(2*ij*BRIJ)+(2)*jj*BRJJ -> 1.0145583 | V9: =2*(ij*BCCIJ)+(2*jj*BCCJJ)+BCS+jj*BCPTJJ+2*(ij*BCPTIJ)+BCPTII+BCk -> 90.229852 | W9: =ij*BUTIJ+BUTII -> 25.504147 | X9: =Revenue-Cost -> -89.215294
A10: 1.0842066 | B10: 4 | C10: 1 | D10: 0 | E10: =Size-a -> 1 | F10: =(EXP(alpha*(Tau+OldTau+zeta-2*a*psi))*((EXP(alpha*a*psi)-EXP(alpha*b*psi))^2))/((EXP(alpha*a*psi)-EXP(alpha*(2*OldTau+b*psi)))*(alpha^2)*(psi^2)) -> 0.0015616019 | G10: =(EXP(alpha*(zeta+(2*b-a)*psi))*(-1+EXP(alpha*(-1)*Size*psi))*(EXP(alpha*(2*(Tau+OldTau)+a*psi))-EXP(alpha*(2*(Tau+OldTau)+b*psi))))/(((EXP(alpha*a*psi)-EXP(alpha*(2*OldTau+b*psi)))^2)*(alpha^2)*(psi^2)) -> 8.3273864e-06 | H10: =-Beta/alpha -> 180 | I10: =(-EXP(alpha*zeta)*Beta*(-1+EXP(alpha*Size*psi)-Size*alpha*psi))/((alpha^3)*(psi^2)) -> 25.038896 | J10: =Beta*Theta -> 14.4 | K10: =Beta*Theta -> 14.4 | L10: =kappa -> 90 | M10: =Gamma*Size -> 0 | N10: =Size*Beta*Phi -> 3.24 | O10: =-(EXP(alpha*a*psi)+EXP(alpha*b*psi)*(-1+Size*psi*alpha))*(Beta*Phi)/((alpha*psi)*(EXP(alpha*a*psi)-EXP(alpha*b*psi))) -> 1.5795152 | P10: =(EXP(alpha*(zeta-a*psi))*Beta*Phi*(-EXP(alpha*a*psi)*(-2+(-1)*Size*alpha*psi)+EXP(alpha*b*psi)*(-2+Size*alpha*psi)))/((alpha^3)*(psi^3)) -> 0.14651555 | Q10: =Tau*Beta -> 195.15718 | R10: =Tau*Beta -> 195.15718 | S10: =Tau -> 1.0842066 | T10: =Profit+Utility -> -64.263939 | U10: =(2*ij*BRIJ)+(2)*jj*BRJJ -> 0.61276594 | V10: =2*(ij*BCCIJ)+(2*jj*BCCJJ)+BCS+jj*BCPTJJ+2*(ij*BCPTIJ)+BCPTII+BCk -> 90.19669 | W10: =ij*BUTIJ+BUTII -> 25.319985 | X10: =Revenue-Cost -> -89.583924
A11: 1.0862846 | B11: 4.5 | C11: 1 | D11: 0 | E11: =Size-a -> 1 | F11: =(EXP(alpha*(Tau+OldTau+zeta-2*a*psi))*((EXP(alpha*a*psi)-EXP(alpha*b*psi))^2))/((EXP(alpha*a*psi)-EXP(alpha*(2*OldTau+b*psi)))*(alpha^2)*(psi^2)) -> 0.00094502068 | G11: =(EXP(alpha*(zeta+(2*b-a)*psi))*(-1+EXP(alpha*(-1)*Size*psi))*(EXP(alpha*(2*(Tau+OldTau)+a*psi))-EXP(alpha*(2*(Tau+OldTau)+b*psi))))/(((EXP(alpha*a*psi)-EXP(alpha*(2*OldTau+b*psi)))^2)*(alpha^2)*(psi^2)) -> 3.0496549e-06 | H11: =-Beta/alpha -> 180 | I11: =(-EXP(alpha*zeta)*Beta*(-1+EXP(alpha*Size*psi)-Size*alpha*psi))/((alpha^3)*(psi^2)) -> 25.038896 | J11: =Beta*Theta -> 14.4 | K11: =Beta*Theta -> 14.4 | L11: =kappa -> 90 | M11: =Gamma*Size -> 0 | N11: =Size*Beta*Phi -> 3.24 | O11: =-(EXP(alpha*a*psi)+EXP(alpha*b*psi)*(-1+Size*psi*alpha))*(Beta*Phi)/((alpha*psi)*(EXP(alpha*a*psi)-EXP(alpha*b*psi))) -> 1.5795152 | P11: =(EXP(alpha*(zeta-a*psi))*Beta*Phi*(-EXP(alpha*a*psi)*(-2+(-1)*Size*alpha*psi)+EXP(alpha*b*psi)*(-2+Size*alpha*psi)))/((alpha^3)*(psi^3)) -> 0.14651555 | Q11: =Tau*Beta -> 195.53123 | R11: =Tau*Beta -> 195.53123 | S11: =Tau -> 1.0862846 | T11: =Profit+Utility -> -64.597061 | U11: =(2*ij*BRIJ)+(2)*jj*BRJJ -> 0.37075472 | V11: =2*(ij*BCCIJ)+(2*jj*BCCJJ)+BCS+jj*BCPTJJ+2*(ij*BCPTIJ)+BCPTII+BCk -> 90.176815 | W11: =ij*BUTIJ+BUTII -> 25.209 | X11: =Revenue-Cost -> -89.80606
A12: 1.0875488 | B12: 5 | C12: 1 | D12: 0 | E12: =Size-a -> 1 | F12: =(EXP(alpha*(Tau+OldTau+zeta-2*a*psi))*((EXP(alpha*a*psi)-EXP(alpha*b*psi))^2))/((EXP(alpha*a*psi)-EXP(alpha*(2*OldTau+b*psi)))*(alpha^2)*(psi^2)) -> 0.00057242143 | G12: =(EXP(alpha*(zeta+(2*b-a)*psi))*(-1+EXP(alpha*(-1)*Size*psi))*(EXP(alpha*(2*(Tau+OldTau)+a*psi))-EXP(alpha*(2*(Tau+OldTau)+b*psi))))/(((EXP(alpha*a*psi)-EXP(alpha*(2*OldTau+b*psi)))^2)*(alpha^2)*(psi^2)) -> 1.1189221e-06 | H12: =-Beta/alpha -> 180 | I12: =(-EXP(alpha*zeta)*Beta*(-1+EXP(alpha*Size*psi)-Size*alpha*psi))/((alpha^3)*(psi^2)) -> 25.038896 | J12: =Beta*Theta -> 14.4 | K12: =Beta*Theta -> 14.4 | L12: =kappa -> 90 | M12: =Gamma*Size -> 0 | N12: =Size*Beta*Phi -> 3.24 | O12: =-(EXP(alpha*a*psi)+EXP(alpha*b*psi)*(-1+Size*psi*alpha))*(Beta*Phi)/((alpha*psi)*(EXP(alpha*a*psi)-EXP(alpha*b*psi))) -> 1.5795152 | P12: =(EXP(alpha*(zeta-a*psi))*Beta*Phi*(-EXP(alpha*a*psi)*(-2+(-1)*Size*alpha*psi)+EXP(alpha*b*psi)*(-2+Size*alpha*psi)))/((alpha^3)*(psi^3)) -> 0.14651555 | Q12: =Tau*Beta -> 195.75878 | R12: =Tau*Beta -> 195.75878 | S12: =Tau -> 1.0875488 | T12: =Profit+Utility -> -64.798362 | U12: =(2*ij*BRIJ)+(2)*jj*BRJJ -> 0.22455112 | V12: =2*(ij*BCCIJ)+(2*jj*BCCJJ)+BCS+jj*BCPTJJ+2*(ij*BCPTIJ)+BCPTII+BCk -> 90.164845 | W12: =ij*BUTIJ+BUTII -> 25.141932 | X12: =Revenue-Cost -> -89.940294

Sheet Toll-Compare
A1: OldTau | B1: ∏-Jurisdiction Size=10 km | C1: W-Jurisdiction Size=10 km | D1: ∏-Jurisdiction Size=1 km | E1: W-Jurisdiction Size=1 km
A2: 0 | B2: ='P-React-JS=10'!A2 -> 1.069541 | C2: ='W-React-JS=10'!A2 -> 0.65329456 | D2: ='P-React-JS=1'!A2 -> 0.65644469 | E2: ='W-React-JS=1'!A2 -> 0.5889719
A3: 0.5 | B3: ='P-React-JS=10'!A3 -> 1.1057737 | C3: ='W-React-JS=10'!A3 -> 0.65119307 | D3: ='P-React-JS=1'!A3 -> 0.89691323 | E3: ='W-React-JS=1'!A3 -> 0.58887831
A4: 1 | B4: ='P-React-JS=10'!A4 -> 1.1233449 | C4: ='W-React-JS=10'!A4 -> 0.6500633 | D4: ='P-React-JS=1'!A4 -> 0.98308833 | E4: ='W-React-JS=1'!A4 -> 0.58883912
A5: 1.5 | B5: ='P-React-JS=10'!A5 -> 1.1332812 | C5: ='W-React-JS=10'!A5 -> 0.64938564 | D5: ='P-React-JS=1'!A5 -> 1.0259236 | E5: ='W-React-JS=1'!A5 -> 0.58881608
A6: 2 | B6: ='P-React-JS=10'!A6 -> 1.1391939 | C6: ='W-React-JS=10'!A6 -> 0.64896782 | D6: ='P-React-JS=1'!A6 -> 1.0505653 | E6: ='W-React-JS=1'!A6 -> 0.58880122
A7: 2.5 | B7: ='P-React-JS=10'!A7 -> 1.1427695 | C7: ='W-React-JS=10'!A7 -> 0.64870987 | D7: ='P-React-JS=1'!A7 -> 1.0654426 | E7: ='W-React-JS=1'!A7 -> 0.5889719
A8: 3 | B8: ='P-React-JS=10'!A8 -> 1.1449412 | C8: ='W-React-JS=10'!A8 -> 0.64855112 | D8: ='P-React-JS=1'!A8 -> 1.0745368 | E8: ='W-React-JS=1'!A8 -> 0.5889719
A9: 3.5 | B9: ='P-React-JS=10'!A9 -> 1.146261 | C9: ='W-React-JS=10'!A9 -> 0.64845367 | D9: ='P-React-JS=1'!A9 -> 1.0807961 | E9: ='W-React-JS=1'!A9 -> 0.5889719
A10: 4 | B10: ='P-React-JS=10'!A10 -> 1.1470633 | C10: ='W-React-JS=10'!A10 -> 0.64901074 | D10: ='P-React-JS=1'!A10 -> 1.0842066 | E10: ='W-React-JS=1'!A10 -> 0.5889719
A11: 4.5 | B11: ='P-React-JS=10'!A11 -> 1.1475503 | C11: ='W-React-JS=10'!A11 -> 0.64899801 | D11: ='P-React-JS=1'!A11 -> 1.0862846 | E11: ='W-React-JS=1'!A11 -> 0.5889719
A12: 5 | B12: ='P-React-JS=10'!A12 -> 1.1478455 | C12: ='W-React-JS=10'!A12 -> 0.64897531 | D12: ='P-React-JS=1'!A12 -> 1.0875488 | E12: ='W-React-JS=1'!A12 -> 0.58934933

Sheet W-UNIQUE-JS=1
A1: Tau | B1: OldTau | C1: Size | D1: a | E1: b | F1: ij | G1: jj | H1: BUTIJ | I1: BUTII | J1: BCCIJ | K1: BCCJJ | L1: BCk | M1: BCS | N1: BCPTJJ | O1: BCPTIJ | P1: BCPTII | Q1: BRIJ | R1: BRJJ | S1: Toll | T1: Welfare | U1: Revenue | V1: Cost | W1: Utility | X1: Profit
A2: 0.58897138 | B2: 0 | C2: 1 | D2: 0 | E2: =Size-a -> 1 | F2: =(EXP(alpha*(Tau+OldTau+zeta-2*a*psi))*((EXP(alpha*a*psi)-EXP(alpha*b*psi))^2))/((EXP(alpha*a*psi)-EXP(alpha*(2*OldTau+b*psi)))*(alpha^2)*(psi^2)) -> 1.0040943 | G2: =(EXP(alpha*(zeta+(2*b-a)*psi))*(-1+EXP(alpha*(-1)*Size*psi))*(EXP(alpha*(2*(Tau+OldTau)+a*psi))-EXP(alpha*(2*(Tau+OldTau)+b*psi))))/(((EXP(alpha*a*psi)-EXP(alpha*(2*OldTau+b*psi)))^2)*(alpha^2)*(psi^2)) -> 3.4428417 | H2: =-Beta/alpha -> 180 | I2: =(-EXP(alpha*zeta)*Beta*(-1+EXP(alpha*Size*psi)-Size*alpha*psi))/((alpha^3)*(psi^2)) -> 25.038896 | J2: =Beta*Theta -> 14.4 | K2: =Beta*Theta -> 14.4 | L2: =kappa -> 90 | M2: =Gamma*Size -> 0 | N2: =Size*Beta*Phi -> 3.24 | O2: =-(EXP(alpha*a*psi)+EXP(alpha*b*psi)*(-1+Size*psi*alpha))*(Beta*Phi)/((alpha*psi)*(EXP(alpha*a*psi)-EXP(alpha*b*psi))) -> 1.5795152 | P2: =(EXP(alpha*(zeta-a*psi))*Beta*Phi*(-EXP(alpha*a*psi)*(-2+(-1)*Size*alpha*psi)+EXP(alpha*b*psi)*(-2+Size*alpha*psi)))/((alpha^3)*(psi^3)) -> 0.14651555 | Q2: =Tau*Beta -> 106.01485 | R2: =Tau*Beta -> 106.01485 | S2: =Tau -> 0.58897138 | T2: =Profit+Utility -> 916.11332 | U2: =(2*ij*BRIJ)+(2)*jj*BRJJ -> 942.88249 | V2: =2*(ij*BCCIJ)+(2*jj*BCCJJ)+BCS+jj*BCPTJJ+2*(ij*BCPTIJ)+BCPTII+BCk -> 232.54504 | W2: =ij*BUTIJ+BUTII -> 205.77587 | X2: =Revenue-Cost -> 710.33745
A3: 0.58886935 | B3: =A2 -> 0.58897138 | C3: 1 | D3: 0 | E3: =Size-a -> 1 | F3: =(EXP(alpha*(Tau+OldTau+zeta-2*a*psi))*((EXP(alpha*a*psi)-EXP(alpha*b*psi))^2))/((EXP(alpha*a*psi)-EXP(alpha*(2*OldTau+b*psi)))*(alpha^2)*(psi^2)) -> 0.1056048 | G3: =(EXP(alpha*(zeta+(2*b-a)*psi))*(-1+EXP(alpha*(-1)*Size*psi))*(EXP(alpha*(2*(Tau+OldTau)+a*psi))-EXP(alpha*(2*(Tau+OldTau)+b*psi))))/(((EXP(alpha*a*psi)-EXP(alpha*(2*OldTau+b*psi)))^2)*(alpha^2)*(psi^2)) -> 0.038083369 | H3: =-Beta/alpha -> 180 | I3: =(-EXP(alpha*zeta)*Beta*(-1+EXP(alpha*Size*psi)-Size*alpha*psi))/((alpha^3)*(psi^2)) -> 25.038896 | J3: =Beta*Theta -> 14.4 | K3: =Beta*Theta -> 14.4 | L3: =kappa -> 90 | M3: =Gamma*Size -> 0 | N3: =Size*Beta*Phi -> 3.24 | O3: =-(EXP(alpha*a*psi)+EXP(alpha*b*psi)*(-1+Size*psi*alpha))*(Beta*Phi)/((alpha*psi)*(EXP(alpha*a*psi)-EXP(alpha*b*psi))) -> 1.5795152 | P3: =(EXP(alpha*(zeta-a*psi))*Beta*Phi*(-EXP(alpha*a*psi)*(-2+(-1)*Size*alpha*psi)+EXP(alpha*b*psi)*(-2+Size*alpha*psi)))/((alpha^3)*(psi^3)) -> 0.14651555 | Q3: =Tau*Beta -> 105.99648 | R3: =Tau*Beta -> 105.99648 | S3: =Tau -> 0.58886935 | T3: =Profit+Utility -> -20.233093 | U3: =(2*ij*BRIJ)+(2)*jj*BRJJ -> 30.460881 | V3: =2*(ij*BCCIJ)+(2*jj*BCCJJ)+BCS+jj*BCPTJJ+2*(ij*BCPTIJ)+BCPTII+BCk -> 94.741734 | W3: =ij*BUTIJ+BUTII -> 44.04776 | X3: =Revenue-Cost -> -64.280853
A4: 0.58886936 | B4: =A3 -> 0.58886935 | C4: 1 | D4: 0 | E4: =Size-a -> 1 | F4: =(EXP(alpha*(Tau+OldTau+zeta-2*a*psi))*((EXP(alpha*a*psi)-EXP(alpha*b*psi))^2))/((EXP(alpha*a*psi)-EXP(alpha*(2*OldTau+b*psi)))*(alpha^2)*(psi^2)) -> 0.10562334 | G4: =(EXP(alpha*(zeta+(2*b-a)*psi))*(-1+EXP(alpha*(-1)*Size*psi))*(EXP(alpha*(2*(Tau+OldTau)+a*psi))-EXP(alpha*(2*(Tau+OldTau)+b*psi))))/(((EXP(alpha*a*psi)-EXP(alpha*(2*OldTau+b*psi)))^2)*(alpha^2)*(psi^2)) -> 0.038096746 | H4: =-Beta/alpha -> 180 | I4: =(-EXP(alpha*zeta)*Beta*(-1+EXP(alpha*Size*psi)-Size*alpha*psi))/((alpha^3)*(psi^2)) -> 25.038896 | J4: =Beta*Theta -> 14.4 | K4: =Beta*Theta -> 14.4 | L4: =kappa -> 90 | M4: =Gamma*Size -> 0 | N4: =Size*Beta*Phi -> 3.24 | O4: =-(EXP(alpha*a*psi)+EXP(alpha*b*psi)*(-1+Size*psi*alpha))*(Beta*Phi)/((alpha*psi)*(EXP(alpha*a*psi)-EXP(alpha*b*psi))) -> 1.5795152 | P4: =(EXP(alpha*(zeta-a*psi))*Beta*Phi*(-EXP(alpha*a*psi)*(-2+(-1)*Size*alpha*psi)+EXP(alpha*b*psi)*(-2+Size*alpha*psi)))/((alpha^3)*(psi^3)) -> 0.14651555 | Q4: =Tau*Beta -> 105.99648 | R4: =Tau*Beta -> 105.99648 | S4: =Tau -> 0.58886936 | T4: =Profit+Utility -> -20.224008 | U4: =(2*ij*BRIJ)+(2)*jj*BRJJ -> 30.467649 | V4: =2*(ij*BCCIJ)+(2*jj*BCCJJ)+BCS+jj*BCPTJJ+2*(ij*BCPTIJ)+BCPTII+BCk -> 94.742755 | W4: =ij*BUTIJ+BUTII -> 44.051098 | X4: =Revenue-Cost -> -64.275106
A5: 0.58886936 | B5: =A4 -> 0.58886936 | C5: 1 | D5: 0 | E5: =Size-a -> 1 | F5: =(EXP(alpha*(Tau+OldTau+zeta-2*a*psi))*((EXP(alpha*a*psi)-EXP(alpha*b*psi))^2))/((EXP(alpha*a*psi)-EXP(alpha*(2*OldTau+b*psi)))*(alpha^2)*(psi^2)) -> 0.10562334 | G5: =(EXP(alpha*(zeta+(2*b-a)*psi))*(-1+EXP(alpha*(-1)*Size*psi))*(EXP(alpha*(2*(Tau+OldTau)+a*psi))-EXP(alpha*(2*(Tau+OldTau)+b*psi))))/(((EXP(alpha*a*psi)-EXP(alpha*(2*OldTau+b*psi)))^2)*(alpha^2)*(psi^2)) -> 0.038096745 | H5: =-Beta/alpha -> 180 | I5: =(-EXP(alpha*zeta)*Beta*(-1+EXP(alpha*Size*psi)-Size*alpha*psi))/((alpha^3)*(psi^2)) -> 25.038896 | J5: =Beta*Theta -> 14.4 | K5: =Beta*Theta -> 14.4 | L5: =kappa -> 90 | M5: =Gamma*Size -> 0 | N5: =Size*Beta*Phi -> 3.24 | O5: =-(EXP(alpha*a*psi)+EXP(alpha*b*psi)*(-1+Size*psi*alpha))*(Beta*Phi)/((alpha*psi)*(EXP(alpha*a*psi)-EXP(alpha*b*psi))) -> 1.5795152 | P5: =(EXP(alpha*(zeta-a*psi))*Beta*Phi*(-EXP(alpha*a*psi)*(-2+(-1)*Size*alpha*psi)+EXP(alpha*b*psi)*(-2+Size*alpha*psi)))/((alpha^3)*(psi^3)) -> 0.14651555 | Q5: =Tau*Beta -> 105.99648 | R5: =Tau*Beta -> 105.99648 | S5: =Tau -> 0.58886936 | T5: =Profit+Utility -> -20.224009 | U5: =(2*ij*BRIJ)+(2)*jj*BRJJ -> 30.467648 | V5: =2*(ij*BCCIJ)+(2*jj*BCCJJ)+BCS+jj*BCPTJJ+2*(ij*BCPTIJ)+BCPTII+BCk -> 94.742755 | W5: =ij*BUTIJ+BUTII -> 44.051098 | X5: =Revenue-Cost -> -64.275107
A6: 0.58886936 | B6: =A5 -> 0.58886936 | C6: 1 | D6: 0 | E6: =Size-a -> 1 | F6: =(EXP(alpha*(Tau+OldTau+zeta-2*a*psi))*((EXP(alpha*a*psi)-EXP(alpha*b*psi))^2))/((EXP(alpha*a*psi)-EXP(alpha*(2*OldTau+b*psi)))*(alpha^2)*(psi^2)) -> 0.10562334 | G6: =(EXP(alpha*(zeta+(2*b-a)*psi))*(-1+EXP(alpha*(-1)*Size*psi))*(EXP(alpha*(2*(Tau+OldTau)+a*psi))-EXP(alpha*(2*(Tau+OldTau)+b*psi))))/(((EXP(alpha*a*psi)-EXP(alpha*(2*OldTau+b*psi)))^2)*(alpha^2)*(psi^2)) -> 0.038096745 | H6: =-Beta/alpha -> 180 | I6: =(-EXP(alpha*zeta)*Beta*(-1+EXP(alpha*Size*psi)-Size*alpha*psi))/((alpha^3)*(psi^2)) -> 25.038896 | J6: =Beta*Theta -> 14.4 | K6: =Beta*Theta -> 14.4 | L6: =kappa -> 90 | M6: =Gamma*Size -> 0 | N6: =Size*Beta*Phi -> 3.24 | O6: =-(EXP(alpha*a*psi)+EXP(alpha*b*psi)*(-1+Size*psi*alpha))*(Beta*Phi)/((alpha*psi)*(EXP(alpha*a*psi)-EXP(alpha*b*psi))) -> 1.5795152 | P6: =(EXP(alpha*(zeta-a*psi))*Beta*Phi*(-EXP(alpha*a*psi)*(-2+(-1)*Size*alpha*psi)+EXP(alpha*b*psi)*(-2+Size*alpha*psi)))/((alpha^3)*(psi^3)) -> 0.14651555 | Q6: =Tau*Beta -> 105.99648 | R6: =Tau*Beta -> 105.99648 | S6: =Tau -> 0.58886936 | T6: =Profit+Utility -> -20.224009 | U6: =(2*ij*BRIJ)+(2)*jj*BRJJ -> 30.467648 | V6: =2*(ij*BCCIJ)+(2*jj*BCCJJ)+BCS+jj*BCPTJJ+2*(ij*BCPTIJ)+BCPTII+BCk -> 94.742755 | W6: =ij*BUTIJ+BUTII -> 44.051098 | X6: =Revenue-Cost -> -64.275107
A8: 0.58883909 | B8: 1 | C8: 1 | D8: 0 | E8: =Size-a -> 1 | F8: =(EXP(alpha*(Tau+OldTau+zeta-2*a*psi))*((EXP(alpha*a*psi)-EXP(alpha*b*psi))^2))/((EXP(alpha*a*psi)-EXP(alpha*(2*OldTau+b*psi)))*(alpha^2)*(psi^2)) -> 0.058243756 | G8: =(EXP(alpha*(zeta+(2*b-a)*psi))*(-1+EXP(alpha*(-1)*Size*psi))*(EXP(alpha*(2*(Tau+OldTau)+a*psi))-EXP(alpha*(2*(Tau+OldTau)+b*psi))))/(((EXP(alpha*a*psi)-EXP(alpha*(2*OldTau+b*psi)))^2)*(alpha^2)*(psi^2)) -> 0.01158422 | H8: =-Beta/alpha -> 180 | I8: =(-EXP(alpha*zeta)*Beta*(-1+EXP(alpha*Size*psi)-Size*alpha*psi))/((alpha^3)*(psi^2)) -> 25.038896 | J8: =Beta*Theta -> 14.4 | K8: =Beta*Theta -> 14.4 | L8: =kappa -> 90 | M8: =Gamma*Size -> 0 | N8: =Size*Beta*Phi -> 3.24 | O8: =-(EXP(alpha*a*psi)+EXP(alpha*b*psi)*(-1+Size*psi*alpha))*(Beta*Phi)/((alpha*psi)*(EXP(alpha*a*psi)-EXP(alpha*b*psi))) -> 1.5795152 | P8: =(EXP(alpha*(zeta-a*psi))*Beta*Phi*(-EXP(alpha*a*psi)*(-2+(-1)*Size*alpha*psi)+EXP(alpha*b*psi)*(-2+Size*alpha*psi)))/((alpha^3)*(psi^3)) -> 0.14651555 | Q8: =Tau*Beta -> 105.99104 | R8: =Tau*Beta -> 105.99104 | S8: =Tau -> 0.58883909 | T8: =Profit+Utility -> -42.054036 | U8: =(2*ij*BRIJ)+(2)*jj*BRJJ -> 14.802279 | V8: =2*(ij*BCCIJ)+(2*jj*BCCJJ)+BCS+jj*BCPTJJ+2*(ij*BCPTIJ)+BCPTII+BCk -> 92.379088 | W8: =ij*BUTIJ+BUTII -> 35.522772 | X8: =Revenue-Cost -> -77.576809
A9: 0.58886936 | B9: =A8 -> 0.58883909 | C9: 1 | D9: 0 | E9: =Size-a -> 1 | F9: =(EXP(alpha*(Tau+OldTau+zeta-2*a*psi))*((EXP(alpha*a*psi)-EXP(alpha*b*psi))^2))/((EXP(alpha*a*psi)-EXP(alpha*(2*OldTau+b*psi)))*(alpha^2)*(psi^2)) -> 0.10562884 | G9: =(EXP(alpha*(zeta+(2*b-a)*psi))*(-1+EXP(alpha*(-1)*Size*psi))*(EXP(alpha*(2*(Tau+OldTau)+a*psi))-EXP(alpha*(2*(Tau+OldTau)+b*psi))))/(((EXP(alpha*a*psi)-EXP(alpha*(2*OldTau+b*psi)))^2)*(alpha^2)*(psi^2)) -> 0.038100715 | H9: =-Beta/alpha -> 180 | I9: =(-EXP(alpha*zeta)*Beta*(-1+EXP(alpha*Size*psi)-Size*alpha*psi))/((alpha^3)*(psi^2)) -> 25.038896 | J9: =Beta*Theta -> 14.4 | K9: =Beta*Theta -> 14.4 | L9: =kappa -> 90 | M9: =Gamma*Size -> 0 | N9: =Size*Beta*Phi -> 3.24 | O9: =-(EXP(alpha*a*psi)+EXP(alpha*b*psi)*(-1+Size*psi*alpha))*(Beta*Phi)/((alpha*psi)*(EXP(alpha*a*psi)-EXP(alpha*b*psi))) -> 1.5795152 | P9: =(EXP(alpha*(zeta-a*psi))*Beta*Phi*(-EXP(alpha*a*psi)*(-2+(-1)*Size*alpha*psi)+EXP(alpha*b*psi)*(-2+Size*alpha*psi)))/((alpha^3)*(psi^3)) -> 0.14651555 | Q9: =Tau*Beta -> 105.99649 | R9: =Tau*Beta -> 105.99649 | S9: =Tau -> 0.58886936 | T9: =Profit+Utility -> -20.221313 | U9: =(2*ij*BRIJ)+(2)*jj*BRJJ -> 30.469656 | V9: =2*(ij*BCCIJ)+(2*jj*BCCJJ)+BCS+jj*BCPTJJ+2*(ij*BCPTIJ)+BCPTII+BCk -> 94.743058 | W9: =ij*BUTIJ+BUTII -> 44.052088 | X9: =Revenue-Cost -> -64.273402
A10: 0.58886936 | B10: =A9 -> 0.58886936 | C10: 1 | D10: 0 | E10: =Size-a -> 1 | F10: =(EXP(alpha*(Tau+OldTau+zeta-2*a*psi))*((EXP(alpha*a*psi)-EXP(alpha*b*psi))^2))/((EXP(alpha*a*psi)-EXP(alpha*(2*OldTau+b*psi)))*(alpha^2)*(psi^2)) -> 0.10562334 | G10: =(EXP(alpha*(zeta+(2*b-a)*psi))*(-1+EXP(alpha*(-1)*Size*psi))*(EXP(alpha*(2*(Tau+OldTau)+a*psi))-EXP(alpha*(2*(Tau+OldTau)+b*psi))))/(((EXP(alpha*a*psi)-EXP(alpha*(2*OldTau+b*psi)))^2)*(alpha^2)*(psi^2)) -> 0.038096744 | H10: =-Beta/alpha -> 180 | I10: =(-EXP(alpha*zeta)*Beta*(-1+EXP(alpha*Size*psi)-Size*alpha*psi))/((alpha^3)*(psi^2)) -> 25.038896 | J10: =Beta*Theta -> 14.4 | K10: =Beta*Theta -> 14.4 | L10: =kappa -> 90 | M10: =Gamma*Size -> 0 | N10: =Size*Beta*Phi -> 3.24 | O10: =-(EXP(alpha*a*psi)+EXP(alpha*b*psi)*(-1+Size*psi*alpha))*(Beta*Phi)/((alpha*psi)*(EXP(alpha*a*psi)-EXP(alpha*b*psi))) -> 1.5795152 | P10: =(EXP(alpha*(zeta-a*psi))*Beta*Phi*(-EXP(alpha*a*psi)*(-2+(-1)*Size*alpha*psi)+EXP(alpha*b*psi)*(-2+Size*alpha*psi)))/((alpha^3)*(psi^3)) -> 0.14651555 | Q10: =Tau*Beta -> 105.99648 | R10: =Tau*Beta -> 105.99648 | S10: =Tau -> 0.58886936 | T10: =Profit+Utility -> -20.224009 | U10: =(2*ij*BRIJ)+(2)*jj*BRJJ -> 30.467648 | V10: =2*(ij*BCCIJ)+(2*jj*BCCJJ)+BCS+jj*BCPTJJ+2*(ij*BCPTIJ)+BCPTII+BCk -> 94.742755 | W10: =ij*BUTIJ+BUTII -> 44.051098 | X10: =Revenue-Cost -> -64.275107
A11: 0.58886936 | B11: =A10 -> 0.58886936 | C11: 1 | D11: 0 | E11: =Size-a -> 1 | F11: =(EXP(alpha*(Tau+OldTau+zeta-2*a*psi))*((EXP(alpha*a*psi)-EXP(alpha*b*psi))^2))/((EXP(alpha*a*psi)-EXP(alpha*(2*OldTau+b*psi)))*(alpha^2)*(psi^2)) -> 0.10562334 | G11: =(EXP(alpha*(zeta+(2*b-a)*psi))*(-1+EXP(alpha*(-1)*Size*psi))*(EXP(alpha*(2*(Tau+OldTau)+a*psi))-EXP(alpha*(2*(Tau+OldTau)+b*psi))))/(((EXP(alpha*a*psi)-EXP(alpha*(2*OldTau+b*psi)))^2)*(alpha^2)*(psi^2)) -> 0.038096745 | H11: =-Beta/alpha -> 180 | I11: =(-EXP(alpha*zeta)*Beta*(-1+EXP(alpha*Size*psi)-Size*alpha*psi))/((alpha^3)*(psi^2)) -> 25.038896 | J11: =Beta*Theta -> 14.4 | K11: =Beta*Theta -> 14.4 | L11: =kappa -> 90 | M11: =Gamma*Size -> 0 | N11: =Size*Beta*Phi -> 3.24 | O11: =-(EXP(alpha*a*psi)+EXP(alpha*b*psi)*(-1+Size*psi*alpha))*(Beta*Phi)/((alpha*psi)*(EXP(alpha*a*psi)-EXP(alpha*b*psi))) -> 1.5795152 | P11: =(EXP(alpha*(zeta-a*psi))*Beta*Phi*(-EXP(alpha*a*psi)*(-2+(-1)*Size*alpha*psi)+EXP(alpha*b*psi)*(-2+Size*alpha*psi)))/((alpha^3)*(psi^3)) -> 0.14651555 | Q11: =Tau*Beta -> 105.99648 | R11: =Tau*Beta -> 105.99648 | S11: =Tau -> 0.58886936 | T11: =Profit+Utility -> -20.224009 | U11: =(2*ij*BRIJ)+(2)*jj*BRJJ -> 30.467648 | V11: =2*(ij*BCCIJ)+(2*jj*BCCJJ)+BCS+jj*BCPTJJ+2*(ij*BCPTIJ)+BCPTII+BCk -> 94.742755 | W11: =ij*BUTIJ+BUTII -> 44.051098 | X11: =Revenue-Cost -> -64.275107
A12: 0.58886936 | B12: =A11 -> 0.58886936 | C12: 1 | D12: 0 | E12: =Size-a -> 1 | F12: =(EXP(alpha*(Tau+OldTau+zeta-2*a*psi))*((EXP(alpha*a*psi)-EXP(alpha*b*psi))^2))/((EXP(alpha*a*psi)-EXP(alpha*(2*OldTau+b*psi)))*(alpha^2)*(psi^2)) -> 0.10562334 | G12: =(EXP(alpha*(zeta+(2*b-a)*psi))*(-1+EXP(alpha*(-1)*Size*psi))*(EXP(alpha*(2*(Tau+OldTau)+a*psi))-EXP(alpha*(2*(Tau+OldTau)+b*psi))))/(((EXP(alpha*a*psi)-EXP(alpha*(2*OldTau+b*psi)))^2)*(alpha^2)*(psi^2)) -> 0.038096745 | H12: =-Beta/alpha -> 180 | I12: =(-EXP(alpha*zeta)*Beta*(-1+EXP(alpha*Size*psi)-Size*alpha*psi))/((alpha^3)*(psi^2)) -> 25.038896 | J12: =Beta*Theta -> 14.4 | K12: =Beta*Theta -> 14.4 | L12: =kappa -> 90 | M12: =Gamma*Size -> 0 | N12: =Size*Beta*Phi -> 3.24 | O12: =-(EXP(alpha*a*psi)+EXP(alpha*b*psi)*(-1+Size*psi*alpha))*(Beta*Phi)/((alpha*psi)*(EXP(alpha*a*psi)-EXP(alpha*b*psi))) -> 1.5795152 | P12: =(EXP(alpha*(zeta-a*psi))*Beta*Phi*(-EXP(alpha*a*psi)*(-2+(-1)*Size*alpha*psi)+EXP(alpha*b*psi)*(-2+Size*alpha*psi)))/((alpha^3)*(psi^3)) -> 0.14651555 | Q12: =Tau*Beta -> 105.99648 | R12: =Tau*Beta -> 105.99648 | S12: =Tau -> 0.58886936 | T12: =Profit+Utility -> -20.224009 | U12: =(2*ij*BRIJ)+(2)*jj*BRJJ -> 30.467648 | V12: =2*(ij*BCCIJ)+(2*jj*BCCJJ)+BCS+jj*BCPTJJ+2*(ij*BCPTIJ)+BCPTII+BCk -> 94.742755 | W12: =ij*BUTIJ+BUTII -> 44.051098 | X12: =Revenue-Cost -> -64.275107
A14: 0.60395341 | B14: 10 | C14: 1 | D14: 0 | E14: =Size-a -> 1 | F14: =(EXP(alpha*(Tau+OldTau+zeta-2*a*psi))*((EXP(alpha*a*psi)-EXP(alpha*b*psi))^2))/((EXP(alpha*a*psi)-EXP(alpha*(2*OldTau+b*psi)))*(alpha^2)*(psi^2)) -> 6.2553168e-06 | G14: =(EXP(alpha*(zeta+(2*b-a)*psi))*(-1+EXP(alpha*(-1)*Size*psi))*(EXP(alpha*(2*(Tau+OldTau)+a*psi))-EXP(alpha*(2*(Tau+OldTau)+b*psi))))/(((EXP(alpha*a*psi)-EXP(alpha*(2*OldTau+b*psi)))^2)*(alpha^2)*(psi^2)) -> 1.3361853e-10 | H14: =-Beta/alpha -> 180 | I14: =(-EXP(alpha*zeta)*Beta*(-1+EXP(alpha*Size*psi)-Size*alpha*psi))/((alpha^3)*(psi^2)) -> 25.038896 | J14: =Beta*Theta -> 14.4 | K14: =Beta*Theta -> 14.4 | L14: =kappa -> 90 | M14: =Gamma*Size -> 0 | N14: =Size*Beta*Phi -> 3.24 | O14: =-(EXP(alpha*a*psi)+EXP(alpha*b*psi)*(-1+Size*psi*alpha))*(Beta*Phi)/((alpha*psi)*(EXP(alpha*a*psi)-EXP(alpha*b*psi))) -> 1.5795152 | P14: =(EXP(alpha*(zeta-a*psi))*Beta*Phi*(-EXP(alpha*a*psi)*(-2+(-1)*Size*alpha*psi)+EXP(alpha*b*psi)*(-2+Size*alpha*psi)))/((alpha^3)*(psi^3)) -> 0.14651555 | Q14: =Tau*Beta -> 108.71161 | R14: =Tau*Beta -> 108.71161 | S14: =Tau -> 0.60395341 | T14: =Profit+Utility -> -65.105333 | U14: =(2*ij*BRIJ)+(2)*jj*BRJJ -> 0.0013600802 | V14: =2*(ij*BCCIJ)+(2*jj*BCCJJ)+BCS+jj*BCPTJJ+2*(ij*BCPTIJ)+BCPTII+BCk -> 90.146715 | W14: =ij*BUTIJ+BUTII -> 25.040022 | X14: =Revenue-Cost -> -90.145355
A15: 0.58886796 | B15: =A14 -> 0.60395341 | C15: 1 | D15: 0 | E15: =Size-a -> 1 | F15: =(EXP(alpha*(Tau+OldTau+zeta-2*a*psi))*((EXP(alpha*a*psi)-EXP(alpha*b*psi))^2))/((EXP(alpha*a*psi)-EXP(alpha*(2*OldTau+b*psi)))*(alpha^2)*(psi^2)) -> 0.10293885 | G15: =(EXP(alpha*(zeta+(2*b-a)*psi))*(-1+EXP(alpha*(-1)*Size*psi))*(EXP(alpha*(2*(Tau+OldTau)+a*psi))-EXP(alpha*(2*(Tau+OldTau)+b*psi))))/(((EXP(alpha*a*psi)-EXP(alpha*(2*OldTau+b*psi)))^2)*(alpha^2)*(psi^2)) -> 0.03618484 | H15: =-Beta/alpha -> 180 | I15: =(-EXP(alpha*zeta)*Beta*(-1+EXP(alpha*Size*psi)-Size*alpha*psi))/((alpha^3)*(psi^2)) -> 25.038896 | J15: =Beta*Theta -> 14.4 | K15: =Beta*Theta -> 14.4 | L15: =kappa -> 90 | M15: =Gamma*Size -> 0 | N15: =Size*Beta*Phi -> 3.24 | O15: =-(EXP(alpha*a*psi)+EXP(alpha*b*psi)*(-1+Size*psi*alpha))*(Beta*Phi)/((alpha*psi)*(EXP(alpha*a*psi)-EXP(alpha*b*psi))) -> 1.5795152 | P15: =(EXP(alpha*(zeta-a*psi))*Beta*Phi*(-EXP(alpha*a*psi)*(-2+(-1)*Size*alpha*psi)+EXP(alpha*b*psi)*(-2+Size*alpha*psi)))/((alpha^3)*(psi^3)) -> 0.14651555 | Q15: =Tau*Beta -> 105.99623 | R15: =Tau*Beta -> 105.99623 | S15: =Tau -> 0.58886796 | T15: =Profit+Utility -> -21.534642 | U15: =(2*ij*BRIJ)+(2)*jj*BRJJ -> 29.493173 | V15: =2*(ij*BCCIJ)+(2*jj*BCCJJ)+BCS+jj*BCPTJJ+2*(ij*BCPTIJ)+BCPTII+BCk -> 94.595704 | W15: =ij*BUTIJ+BUTII -> 43.567889 | X15: =Revenue-Cost -> -65.10253
A16: 0.58886936 | B16: =A15 -> 0.58886796 | C16: 1 | D16: 0 | E16: =Size-a -> 1 | F16: =(EXP(alpha*(Tau+OldTau+zeta-2*a*psi))*((EXP(alpha*a*psi)-EXP(alpha*b*psi))^2))/((EXP(alpha*a*psi)-EXP(alpha*(2*OldTau+b*psi)))*(alpha^2)*(psi^2)) -> 0.1056236 | G16: =(EXP(alpha*(zeta+(2*b-a)*psi))*(-1+EXP(alpha*(-1)*Size*psi))*(EXP(alpha*(2*(Tau+OldTau)+a*psi))-EXP(alpha*(2*(Tau+OldTau)+b*psi))))/(((EXP(alpha*a*psi)-EXP(alpha*(2*OldTau+b*psi)))^2)*(alpha^2)*(psi^2)) -> 0.038096929 | H16: =-Beta/alpha -> 180 | I16: =(-EXP(alpha*zeta)*Beta*(-1+EXP(alpha*Size*psi)-Size*alpha*psi))/((alpha^3)*(psi^2)) -> 25.038896 | J16: =Beta*Theta -> 14.4 | K16: =Beta*Theta -> 14.4 | L16: =kappa -> 90 | M16: =Gamma*Size -> 0 | N16: =Size*Beta*Phi -> 3.24 | O16: =-(EXP(alpha*a*psi)+EXP(alpha*b*psi)*(-1+Size*psi*alpha))*(Beta*Phi)/((alpha*psi)*(EXP(alpha*a*psi)-EXP(alpha*b*psi))) -> 1.5795152 | P16: =(EXP(alpha*(zeta-a*psi))*Beta*Phi*(-EXP(alpha*a*psi)*(-2+(-1)*Size*alpha*psi)+EXP(alpha*b*psi)*(-2+Size*alpha*psi)))/((alpha^3)*(psi^3)) -> 0.14651555 | Q16: =Tau*Beta -> 105.99649 | R16: =Tau*Beta -> 105.99649 | S16: =Tau -> 0.58886936 | T16: =Profit+Utility -> -20.223884 | U16: =(2*ij*BRIJ)+(2)*jj*BRJJ -> 30.467741 | V16: =2*(ij*BCCIJ)+(2*jj*BCCJJ)+BCS+jj*BCPTJJ+2*(ij*BCPTIJ)+BCPTII+BCk -> 94.742769 | W16: =ij*BUTIJ+BUTII -> 44.051144 | X16: =Revenue-Cost -> -64.275028
A17: 0.58886936 | B17: =A16 -> 0.58886936 | C17: 1 | D17: 0 | E17: =Size-a -> 1 | F17: =(EXP(alpha*(Tau+OldTau+zeta-2*a*psi))*((EXP(alpha*a*psi)-EXP(alpha*b*psi))^2))/((EXP(alpha*a*psi)-EXP(alpha*(2*OldTau+b*psi)))*(alpha^2)*(psi^2)) -> 0.10562334 | G17: =(EXP(alpha*(zeta+(2*b-a)*psi))*(-1+EXP(alpha*(-1)*Size*psi))*(EXP(alpha*(2*(Tau+OldTau)+a*psi))-EXP(alpha*(2*(Tau+OldTau)+b*psi))))/(((EXP(alpha*a*psi)-EXP(alpha*(2*OldTau+b*psi)))^2)*(alpha^2)*(psi^2)) -> 0.038096745 | H17: =-Beta/alpha -> 180 | I17: =(-EXP(alpha*zeta)*Beta*(-1+EXP(alpha*Size*psi)-Size*alpha*psi))/((alpha^3)*(psi^2)) -> 25.038896 | J17: =Beta*Theta -> 14.4 | K17: =Beta*Theta -> 14.4 | L17: =kappa -> 90 | M17: =Gamma*Size -> 0 | N17: =Size*Beta*Phi -> 3.24 | O17: =-(EXP(alpha*a*psi)+EXP(alpha*b*psi)*(-1+Size*psi*alpha))*(Beta*Phi)/((alpha*psi)*(EXP(alpha*a*psi)-EXP(alpha*b*psi))) -> 1.5795152 | P17: =(EXP(alpha*(zeta-a*psi))*Beta*Phi*(-EXP(alpha*a*psi)*(-2+(-1)*Size*alpha*psi)+EXP(alpha*b*psi)*(-2+Size*alpha*psi)))/((alpha^3)*(psi^3)) -> 0.14651555 | Q17: =Tau*Beta -> 105.99648 | R17: =Tau*Beta -> 105.99648 | S17: =Tau -> 0.58886936 | T17: =Profit+Utility -> -20.224009 | U17: =(2*ij*BRIJ)+(2)*jj*BRJJ -> 30.467648 | V17: =2*(ij*BCCIJ)+(2*jj*BCCJJ)+BCS+jj*BCPTJJ+2*(ij*BCPTIJ)+BCPTII+BCk -> 94.742755 | W17: =ij*BUTIJ+BUTII -> 44.051098 | X17: =Revenue-Cost -> -64.275107
A18: 0.58886936 | B18: =A17 -> 0.58886936 | C18: 1 | D18: 0 | E18: =Size-a -> 1 | F18: =(EXP(alpha*(Tau+OldTau+zeta-2*a*psi))*((EXP(alpha*a*psi)-EXP(alpha*b*psi))^2))/((EXP(alpha*a*psi)-EXP(alpha*(2*OldTau+b*psi)))*(alpha^2)*(psi^2)) -> 0.10562334 | G18: =(EXP(alpha*(zeta+(2*b-a)*psi))*(-1+EXP(alpha*(-1)*Size*psi))*(EXP(alpha*(2*(Tau+OldTau)+a*psi))-EXP(alpha*(2*(Tau+OldTau)+b*psi))))/(((EXP(alpha*a*psi)-EXP(alpha*(2*OldTau+b*psi)))^2)*(alpha^2)*(psi^2)) -> 0.038096745 | H18: =-Beta/alpha -> 180 | I18: =(-EXP(alpha*zeta)*Beta*(-1+EXP(alpha*Size*psi)-Size*alpha*psi))/((alpha^3)*(psi^2)) -> 25.038896 | J18: =Beta*Theta -> 14.4 | K18: =Beta*Theta -> 14.4 | L18: =kappa -> 90 | M18: =Gamma*Size -> 0 | N18: =Size*Beta*Phi -> 3.24 | O18: =-(EXP(alpha*a*psi)+EXP(alpha*b*psi)*(-1+Size*psi*alpha))*(Beta*Phi)/((alpha*psi)*(EXP(alpha*a*psi)-EXP(alpha*b*psi))) -> 1.5795152 | P18: =(EXP(alpha*(zeta-a*psi))*Beta*Phi*(-EXP(alpha*a*psi)*(-2+(-1)*Size*alpha*psi)+EXP(alpha*b*psi)*(-2+Size*alpha*psi)))/((alpha^3)*(psi^3)) -> 0.14651555 | Q18: =Tau*Beta -> 105.99648 | R18: =Tau*Beta -> 105.99648 | S18: =Tau -> 0.58886936 | T18: =Profit+Utility -> -20.224009 | U18: =(2*ij*BRIJ)+(2)*jj*BRJJ -> 30.467648 | V18: =2*(ij*BCCIJ)+(2*jj*BCCJJ)+BCS+jj*BCPTJJ+2*(ij*BCPTIJ)+BCPTII+BCk -> 94.742755 | W18: =ij*BUTIJ+BUTII -> 44.051098 | X18: =Revenue-Cost -> -64.275107
A20: -0.13547262 | B20: -1 | C20: 1 | D20: 0 | E20: =Size-a -> 1 | F20: =(EXP(alpha*(Tau+OldTau+zeta-2*a*psi))*((EXP(alpha*a*psi)-EXP(alpha*b*psi))^2))/((EXP(alpha*a*psi)-EXP(alpha*(2*OldTau+b*psi)))*(alpha^2)*(psi^2)) -> -0.14637506 | G20: =(EXP(alpha*(zeta+(2*b-a)*psi))*(-1+EXP(alpha*(-1)*Size*psi))*(EXP(alpha*(2*(Tau+OldTau)+a*psi))-EXP(alpha*(2*(Tau+OldTau)+b*psi))))/(((EXP(alpha*a*psi)-EXP(alpha*(2*OldTau+b*psi)))^2)*(alpha^2)*(psi^2)) -> 0.07316481 | H20: =-Beta/alpha -> 180 | I20: =(-EXP(alpha*zeta)*Beta*(-1+EXP(alpha*Size*psi)-Size*alpha*psi))/((alpha^3)*(psi^2)) -> 25.038896 | J20: =Beta*Theta -> 14.4 | K20: =Beta*Theta -> 14.4 | L20: =kappa -> 90 | M20: =Gamma*Size -> 0 | N20: =Size*Beta*Phi -> 3.24 | O20: =-(EXP(alpha*a*psi)+EXP(alpha*b*psi)*(-1+Size*psi*alpha))*(Beta*Phi)/((alpha*psi)*(EXP(alpha*a*psi)-EXP(alpha*b*psi))) -> 1.5795152 | P20: =(EXP(alpha*(zeta-a*psi))*Beta*Phi*(-EXP(alpha*a*psi)*(-2+(-1)*Size*alpha*psi)+EXP(alpha*b*psi)*(-2+Size*alpha*psi)))/((alpha^3)*(psi^3)) -> 0.14651555 | Q20: =Tau*Beta -> -24.385072 | R20: =Tau*Beta -> -24.385072 | S20: =Tau -> -0.13547262 | T20: =Profit+Utility -> -85.550851 | U20: =(2*ij*BRIJ)+(2)*jj*BRJJ -> 3.5704745 | V20: =2*(ij*BCCIJ)+(2*jj*BCCJJ)+BCS+jj*BCPTJJ+2*(ij*BCPTIJ)+BCPTII+BCk -> 87.812711 | W20: =ij*BUTIJ+BUTII -> -1.3086149 | X20: =Revenue-Cost -> -84.242237
A21: 0.58903166 | B21: =A20 -> -0.13547262 | C21: 1 | D21: 0 | E21: =Size-a -> 1 | F21: =(EXP(alpha*(Tau+OldTau+zeta-2*a*psi))*((EXP(alpha*a*psi)-EXP(alpha*b*psi))^2))/((EXP(alpha*a*psi)-EXP(alpha*(2*OldTau+b*psi)))*(alpha^2)*(psi^2)) -> -1.2456419 | G21: =(EXP(alpha*(zeta+(2*b-a)*psi))*(-1+EXP(alpha*(-1)*Size*psi))*(EXP(alpha*(2*(Tau+OldTau)+a*psi))-EXP(alpha*(2*(Tau+OldTau)+b*psi))))/(((EXP(alpha*a*psi)-EXP(alpha*(2*OldTau+b*psi)))^2)*(alpha^2)*(psi^2)) -> 5.2985187 | H21: =-Beta/alpha -> 180 | I21: =(-EXP(alpha*zeta)*Beta*(-1+EXP(alpha*Size*psi)-Size*alpha*psi))/((alpha^3)*(psi^2)) -> 25.038896 | J21: =Beta*Theta -> 14.4 | K21: =Beta*Theta -> 14.4 | L21: =kappa -> 90 | M21: =Gamma*Size -> 0 | N21: =Size*Beta*Phi -> 3.24 | O21: =-(EXP(alpha*a*psi)+EXP(alpha*b*psi)*(-1+Size*psi*alpha))*(Beta*Phi)/((alpha*psi)*(EXP(alpha*a*psi)-EXP(alpha*b*psi))) -> 1.5795152 | P21: =(EXP(alpha*(zeta-a*psi))*Beta*Phi*(-EXP(alpha*a*psi)*(-2+(-1)*Size*alpha*psi)+EXP(alpha*b*psi)*(-2+Size*alpha*psi)))/((alpha^3)*(psi^3)) -> 0.14651555 | Q21: =Tau*Beta -> 106.0257 | R21: =Tau*Beta -> 106.0257 | S21: =Tau -> 0.58903166 | T21: =Profit+Utility -> 440.14 | U21: =(2*ij*BRIJ)+(2)*jj*BRJJ -> 859.41819 | V21: =2*(ij*BCCIJ)+(2*jj*BCCJJ)+BCS+jj*BCPTJJ+2*(ij*BCPTIJ)+BCPTII+BCk -> 220.10155 | W21: =ij*BUTIJ+BUTII -> -199.17664 | X21: =Revenue-Cost -> 639.31665
A22: 0.58886935 | B22: =A21 -> 0.58903166 | C22: 1 | D22: 0 | E22: =Size-a -> 1 | F22: =(EXP(alpha*(Tau+OldTau+zeta-2*a*psi))*((EXP(alpha*a*psi)-EXP(alpha*b*psi))^2))/((EXP(alpha*a*psi)-EXP(alpha*(2*OldTau+b*psi)))*(alpha^2)*(psi^2)) -> 0.10559384 | G22: =(EXP(alpha*(zeta+(2*b-a)*psi))*(-1+EXP(alpha*(-1)*Size*psi))*(EXP(alpha*(2*(Tau+OldTau)+a*psi))-EXP(alpha*(2*(Tau+OldTau)+b*psi))))/(((EXP(alpha*a*psi)-EXP(alpha*(2*OldTau+b*psi)))^2)*(alpha^2)*(psi^2)) -> 0.038075468 | H22: =-Beta/alpha -> 180 | I22: =(-EXP(alpha*zeta)*Beta*(-1+EXP(alpha*Size*psi)-Size*alpha*psi))/((alpha^3)*(psi^2)) -> 25.038896 | J22: =Beta*Theta -> 14.4 | K22: =Beta*Theta -> 14.4 | L22: =kappa -> 90 | M22: =Gamma*Size -> 0 | N22: =Size*Beta*Phi -> 3.24 | O22: =-(EXP(alpha*a*psi)+EXP(alpha*b*psi)*(-1+Size*psi*alpha))*(Beta*Phi)/((alpha*psi)*(EXP(alpha*a*psi)-EXP(alpha*b*psi))) -> 1.5795152 | P22: =(EXP(alpha*(zeta-a*psi))*Beta*Phi*(-EXP(alpha*a*psi)*(-2+(-1)*Size*alpha*psi)+EXP(alpha*b*psi)*(-2+Size*alpha*psi)))/((alpha^3)*(psi^3)) -> 0.14651555 | Q22: =Tau*Beta -> 105.99648 | R22: =Tau*Beta -> 105.99648 | S22: =Tau -> 0.58886935 | T22: =Profit+Utility -> -20.23846 | U22: =(2*ij*BRIJ)+(2)*jj*BRJJ -> 30.456883 | V22: =2*(ij*BCCIJ)+(2*jj*BCCJJ)+BCS+jj*BCPTJJ+2*(ij*BCPTIJ)+BCPTII+BCk -> 94.74113 | W22: =ij*BUTIJ+BUTII -> 44.045788 | X22: =Revenue-Cost -> -64.284247
A23: 0.58886936 | B23: =A22 -> 0.58886935 | C23: 1 | D23: 0 | E23: =Size-a -> 1 | F23: =(EXP(alpha*(Tau+OldTau+zeta-2*a*psi))*((EXP(alpha*a*psi)-EXP(alpha*b*psi))^2))/((EXP(alpha*a*psi)-EXP(alpha*(2*OldTau+b*psi)))*(alpha^2)*(psi^2)) -> 0.10562334 | G23: =(EXP(alpha*(zeta+(2*b-a)*psi))*(-1+EXP(alpha*(-1)*Size*psi))*(EXP(alpha*(2*(Tau+OldTau)+a*psi))-EXP(alpha*(2*(Tau+OldTau)+b*psi))))/(((EXP(alpha*a*psi)-EXP(alpha*(2*OldTau+b*psi)))^2)*(alpha^2)*(psi^2)) -> 0.038096747 | H23: =-Beta/alpha -> 180 | I23: =(-EXP(alpha*zeta)*Beta*(-1+EXP(alpha*Size*psi)-Size*alpha*psi))/((alpha^3)*(psi^2)) -> 25.038896 | J23: =Beta*Theta -> 14.4 | K23: =Beta*Theta -> 14.4 | L23: =kappa -> 90 | M23: =Gamma*Size -> 0 | N23: =Size*Beta*Phi -> 3.24 | O23: =-(EXP(alpha*a*psi)+EXP(alpha*b*psi)*(-1+Size*psi*alpha))*(Beta*Phi)/((alpha*psi)*(EXP(alpha*a*psi)-EXP(alpha*b*psi))) -> 1.5795152 | P23: =(EXP(alpha*(zeta-a*psi))*Beta*Phi*(-EXP(alpha*a*psi)*(-2+(-1)*Size*alpha*psi)+EXP(alpha*b*psi)*(-2+Size*alpha*psi)))/((alpha^3)*(psi^3)) -> 0.14651555 | Q23: =Tau*Beta -> 105.99648 | R23: =Tau*Beta -> 105.99648 | S23: =Tau -> 0.58886936 | T23: =Profit+Utility -> -20.224008 | U23: =(2*ij*BRIJ)+(2)*jj*BRJJ -> 30.467649 | V23: =2*(ij*BCCIJ)+(2*jj*BCCJJ)+BCS+jj*BCPTJJ+2*(ij*BCPTIJ)+BCPTII+BCk -> 94.742755 | W23: =ij*BUTIJ+BUTII -> 44.051098 | X23: =Revenue-Cost -> -64.275106
A24: 0.58886936 | B24: =A23 -> 0.58886936 | C24: 1 | D24: 0 | E24: =Size-a -> 1 | F24: =(EXP(alpha*(Tau+OldTau+zeta-2*a*psi))*((EXP(alpha*a*psi)-EXP(alpha*b*psi))^2))/((EXP(alpha*a*psi)-EXP(alpha*(2*OldTau+b*psi)))*(alpha^2)*(psi^2)) -> 0.10562334 | G24: =(EXP(alpha*(zeta+(2*b-a)*psi))*(-1+EXP(alpha*(-1)*Size*psi))*(EXP(alpha*(2*(Tau+OldTau)+a*psi))-EXP(alpha*(2*(Tau+OldTau)+b*psi))))/(((EXP(alpha*a*psi)-EXP(alpha*(2*OldTau+b*psi)))^2)*(alpha^2)*(psi^2)) -> 0.038096745 | H24: =-Beta/alpha -> 180 | I24: =(-EXP(alpha*zeta)*Beta*(-1+EXP(alpha*Size*psi)-Size*alpha*psi))/((alpha^3)*(psi^2)) -> 25.038896 | J24: =Beta*Theta -> 14.4 | K24: =Beta*Theta -> 14.4 | L24: =kappa -> 90 | M24: =Gamma*Size -> 0 | N24: =Size*Beta*Phi -> 3.24 | O24: =-(EXP(alpha*a*psi)+EXP(alpha*b*psi)*(-1+Size*psi*alpha))*(Beta*Phi)/((alpha*psi)*(EXP(alpha*a*psi)-EXP(alpha*b*psi))) -> 1.5795152 | P24: =(EXP(alpha*(zeta-a*psi))*Beta*Phi*(-EXP(alpha*a*psi)*(-2+(-1)*Size*alpha*psi)+EXP(alpha*b*psi)*(-2+Size*alpha*psi)))/((alpha^3)*(psi^3)) -> 0.14651555 | Q24: =Tau*Beta -> 105.99648 | R24: =Tau*Beta -> 105.99648 | S24: =Tau -> 0.58886936 | T24: =Profit+Utility -> -20.224009 | U24: =(2*ij*BRIJ)+(2)*jj*BRJJ -> 30.467648 | V24: =2*(ij*BCCIJ)+(2*jj*BCCJJ)+BCS+jj*BCPTJJ+2*(ij*BCPTIJ)+BCPTII+BCk -> 94.742755 | W24: =ij*BUTIJ+BUTII -> 44.051098 | X24: =Revenue-Cost -> -64.275107
B27: Iteration | C27: S=-1 | D27: S=0 | E27: S=1 | F27: S=10
B28: 0 | C28: -1 | D28: 0 | E28: 1 | F28: 10
B29: 1 | C29: =A20 -> -0.13547262 | D29: =A2 -> 0.58897138 | E29: =A8 -> 0.58883909 | F29: =A14 -> 0.60395341
B30: 2 | C30: =A21 -> 0.58903166 | D30: =A3 -> 0.58886935 | E30: =A9 -> 0.58886936 | F30: =A15 -> 0.58886796
B31: 3 | C31: =A22 -> 0.58886935 | D31: =A4 -> 0.58886936 | E31: =A10 -> 0.58886936 | F31: =A16 -> 0.58886936
B32: 4 | C32: =A23 -> 0.58886936 | D32: =A5 -> 0.58886936 | E32: =A11 -> 0.58886936 | F32: =A17 -> 0.58886936
B33: 5 | C33: =A24 -> 0.58886936 | D33: =A6 -> 0.58886936 | E33: =A12 -> 0.58886936 | F33: =A18 -> 0.58886936

Sheet Module1
