Workbook

Sheet Defaults
B1: Values in Model | C1: Original
A2: v | B2: =1/psi -> 6.6666667 | C2: =1/psi -> 6.6666667
A3: w | B3: =1/alpha -> -1 | C3: =1/alpha -> -1
A4: y | B4: =EXP(alpha*zeta) -> 0.29229258 | C4: =EXP(alpha*zeta) -> 0.29229258
A5: Beta | B5: 180 | C5: 180
A6: Theta | B6: 0.08 | C6: 0.017
A7: Gamma | B7: 0 | C7: 0
A8: Phi | B8: 0.018 | C8: 0.018
A9: alpha | B9: -1 | C9: -1
A10: psi | B10: 0.15 | C10: 0.15
A11: zeta | B11: 1.23 | C11: 1.23
A12: kappa | B12: 90 | C12: 90

Sheet W-Tax(All-Tax)
A1: Tau | B1: OldTau | C1: Size | D1: a | E1: b | F1: ij | G1: jj | H1: BUTIJ | I1: BUTII | J1: BCCIJ | K1: BCCJJ | L1: BCk | M1: BCS | N1: BCPTJJ | O1: BCPTIJ | P1: BCPTII | Q1: BRIJ | R1: BRJJ | S1: Toll | T1: Welfare | U1: Revenue | V1: Cost | W1: Utility | X1: Profit | Y1: Size2 | Z1: W/Size | AA1: ∏/Size | AB1: U/Size
A2: 0 | B2: =Tau -> 0 | C2: 1 | D2: 0 | E2: =Size-a -> 1 | F2: =(EXP(alpha*(Tau+OldTau+zeta-2*a*psi))*((EXP(alpha*a*psi)-EXP(alpha*b*psi))^2))/((EXP(alpha*a*psi)-EXP(alpha*(2*OldTau+b*psi)))*(alpha^2)*(psi^2)) -> 1.8095122 | G2: =(EXP(alpha*(zeta+(2*b-a)*psi))*(-1+EXP(alpha*(-1)*Size*psi))*(EXP(alpha*(2*(Tau+OldTau)+a*psi))-EXP(alpha*(2*(Tau+OldTau)+b*psi))))/(((EXP(alpha*a*psi)-EXP(alpha*(2*OldTau+b*psi)))^2)*(alpha^2)*(psi^2)) -> 11.181269 | H2: =-Beta/alpha -> 180 | I2: =(-EXP(alpha*zeta)*Beta*(-1+EXP(alpha*Size*psi)-Size*alpha*psi))/((alpha^3)*(psi^2)) -> 25.038896 | J2: 0 | K2: 0 | L2: 0 | M2: =Gamma*Size -> 0 | N2: =Size*Beta*Phi -> 3.24 | O2: =-(EXP(alpha*a*psi)+EXP(alpha*b*psi)*(-1+Size*psi*alpha))*(Beta*Phi)/((alpha*psi)*(EXP(alpha*a*psi)-EXP(alpha*b*psi))) -> 1.5795152 | P2: =(EXP(alpha*(zeta-a*psi))*Beta*Phi*(-EXP(alpha*a*psi)*(-2+(-1)*Size*alpha*psi)+EXP(alpha*b*psi)*(-2+Size*alpha*psi)))/((alpha^3)*(psi^3)) -> 0.14651555 | Q2: =Tau*Beta -> 0 | R2: =Tau*Beta -> 0 | S2: =Tau -> 0 | T2: =Profit+Utility -> 308.66096 | U2: =(2*ij*BRIJ)+2*jj*BRJJ -> 0 | V2: =2*(ij*BCCIJ)+(2*jj*BCCJJ)+BCS+jj*BCPTJJ+2*(ij*BCPTIJ)+BCPTII+BCk -> 42.090131 | W2: =ij*BUTIJ+BUTII -> 350.75109 | X2: =Revenue-Cost -> -42.090131 | Y2: =Size -> 1 | Z2: =Welfare/(Size) -> 308.66096 | AA2: =Profit/(Size) -> -42.090131 | AB2: =Utility/(Size) -> 350.75109
A3: 0 | B3: =Tau -> 0 | C3: 2 | D3: 0 | E3: =Size-a -> 2 | F3: =(EXP(alpha*(Tau+OldTau+zeta-2*a*psi))*((EXP(alpha*a*psi)-EXP(alpha*b*psi))^2))/((EXP(alpha*a*psi)-EXP(alpha*(2*OldTau+b*psi)))*(alpha^2)*(psi^2)) -> 3.3669738 | G3: =(EXP(alpha*(zeta+(2*b-a)*psi))*(-1+EXP(alpha*(-1)*Size*psi))*(EXP(alpha*(2*(Tau+OldTau)+a*psi))-EXP(alpha*(2*(Tau+OldTau)+b*psi))))/(((EXP(alpha*a*psi)-EXP(alpha*(2*OldTau+b*psi)))^2)*(alpha^2)*(psi^2)) -> 9.6238074 | H3: =-Beta/alpha -> 180 | I3: =(-EXP(alpha*zeta)*Beta*(-1+EXP(alpha*Size*psi)-Size*alpha*psi))/((alpha^3)*(psi^2)) -> 95.446904 | J3: 0 | K3: 0 | L3: 0 | M3: =Gamma*Size -> 0 | N3: =Size*Beta*Phi -> 6.48 | O3: =-(EXP(alpha*a*psi)+EXP(alpha*b*psi)*(-1+Size*psi*alpha))*(Beta*Phi)/((alpha*psi)*(EXP(alpha*a*psi)-EXP(alpha*b*psi))) -> 3.0782425 | P3: =(EXP(alpha*(zeta-a*psi))*Beta*Phi*(-EXP(alpha*a*psi)*(-2+(-1)*Size*alpha*psi)+EXP(alpha*b*psi)*(-2+Size*alpha*psi)))/((alpha^3)*(psi^3)) -> 1.0892667 | Q3: =Tau*Beta -> 0 | R3: =Tau*Beta -> 0 | S3: =Tau -> 0 | T3: =Profit+Utility -> 617.32192 | U3: =(2*ij*BRIJ)+2*jj*BRJJ -> 0 | V3: =2*(ij*BCCIJ)+(2*jj*BCCJJ)+BCS+jj*BCPTJJ+2*(ij*BCPTIJ)+BCPTII+BCk -> 84.180262 | W3: =ij*BUTIJ+BUTII -> 701.50219 | X3: =Revenue-Cost -> -84.180262 | Y3: =Size -> 2 | Z3: =Welfare/(Size) -> 308.66096 | AA3: =Profit/(Size) -> -42.090131 | AB3: =Utility/(Size) -> 350.75109
A4: 0 | B4: =Tau -> 0 | C4: 5 | D4: 0 | E4: =Size-a -> 5 | F4: =(EXP(alpha*(Tau+OldTau+zeta-2*a*psi))*((EXP(alpha*a*psi)-EXP(alpha*b*psi))^2))/((EXP(alpha*a*psi)-EXP(alpha*(2*OldTau+b*psi)))*(alpha^2)*(psi^2)) -> 6.8543707 | G4: =(EXP(alpha*(zeta+(2*b-a)*psi))*(-1+EXP(alpha*(-1)*Size*psi))*(EXP(alpha*(2*(Tau+OldTau)+a*psi))-EXP(alpha*(2*(Tau+OldTau)+b*psi))))/(((EXP(alpha*a*psi)-EXP(alpha*(2*OldTau+b*psi)))^2)*(alpha^2)*(psi^2)) -> 6.1364105 | H4: =-Beta/alpha -> 180 | I4: =(-EXP(alpha*zeta)*Beta*(-1+EXP(alpha*Size*psi)-Size*alpha*psi))/((alpha^3)*(psi^2)) -> 519.96874 | J4: 0 | K4: 0 | L4: 0 | M4: =Gamma*Size -> 0 | N4: =Size*Beta*Phi -> 16.2 | O4: =-(EXP(alpha*a*psi)+EXP(alpha*b*psi)*(-1+Size*psi*alpha))*(Beta*Phi)/((alpha*psi)*(EXP(alpha*a*psi)-EXP(alpha*b*psi))) -> 7.0968668 | P4: =(EXP(alpha*(zeta-a*psi))*Beta*Phi*(-EXP(alpha*a*psi)*(-2+(-1)*Size*alpha*psi)+EXP(alpha*b*psi)*(-2+Size*alpha*psi)))/((alpha^3)*(psi^3)) -> 13.751693 | Q4: =Tau*Beta -> 0 | R4: =Tau*Beta -> 0 | S4: =Tau -> 0 | T4: =Profit+Utility -> 1543.3048 | U4: =(2*ij*BRIJ)+2*jj*BRJJ -> 0 | V4: =2*(ij*BCCIJ)+(2*jj*BCCJJ)+BCS+jj*BCPTJJ+2*(ij*BCPTIJ)+BCPTII+BCk -> 210.45066 | W4: =ij*BUTIJ+BUTII -> 1753.7555 | X4: =Revenue-Cost -> -210.45066 | Y4: =Size -> 5 | Z4: =Welfare/(Size) -> 308.66096 | AA4: =Profit/(Size) -> -42.090131 | AB4: =Utility/(Size) -> 350.75109
A5: 0 | B5: =Tau -> 0 | C5: 10 | D5: 0 | E5: =Size-a -> 10 | F5: =(EXP(alpha*(Tau+OldTau+zeta-2*a*psi))*((EXP(alpha*a*psi)-EXP(alpha*b*psi))^2))/((EXP(alpha*a*psi)-EXP(alpha*(2*OldTau+b*psi)))*(alpha^2)*(psi^2)) -> 10.092146 | G5: =(EXP(alpha*(zeta+(2*b-a)*psi))*(-1+EXP(alpha*(-1)*Size*psi))*(EXP(alpha*(2*(Tau+OldTau)+a*psi))-EXP(alpha*(2*(Tau+OldTau)+b*psi))))/(((EXP(alpha*a*psi)-EXP(alpha*(2*OldTau+b*psi)))^2)*(alpha^2)*(psi^2)) -> 2.8986351 | H5: =-Beta/alpha -> 180 | I5: =(-EXP(alpha*zeta)*Beta*(-1+EXP(alpha*Size*psi)-Size*alpha*psi))/((alpha^3)*(psi^2)) -> 1690.9246 | J5: 0 | K5: 0 | L5: 0 | M5: =Gamma*Size -> 0 | N5: =Size*Beta*Phi -> 32.4 | O5: =-(EXP(alpha*a*psi)+EXP(alpha*b*psi)*(-1+Size*psi*alpha))*(Beta*Phi)/((alpha*psi)*(EXP(alpha*a*psi)-EXP(alpha*b*psi))) -> 12.294172 | P5: =(EXP(alpha*(zeta-a*psi))*Beta*Phi*(-EXP(alpha*a*psi)*(-2+(-1)*Size*alpha*psi)+EXP(alpha*b*psi)*(-2+Size*alpha*psi)))/((alpha^3)*(psi^3)) -> 78.836376 | Q5: =Tau*Beta -> 0 | R5: =Tau*Beta -> 0 | S5: =Tau -> 0 | T5: =Profit+Utility -> 3086.6096 | U5: =(2*ij*BRIJ)+2*jj*BRJJ -> 0 | V5: =2*(ij*BCCIJ)+(2*jj*BCCJJ)+BCS+jj*BCPTJJ+2*(ij*BCPTIJ)+BCPTII+BCk -> 420.90131 | W5: =ij*BUTIJ+BUTII -> 3507.5109 | X5: =Revenue-Cost -> -420.90131 | Y5: =Size -> 10 | Z5: =Welfare/(Size) -> 308.66096 | AA5: =Profit/(Size) -> -42.090131 | AB5: =Utility/(Size) -> 350.75109
A6: 0 | B6: =Tau -> 0 | C6: 20 | D6: 0 | E6: =Size-a -> 20 | F6: =(EXP(alpha*(Tau+OldTau+zeta-2*a*psi))*((EXP(alpha*a*psi)-EXP(alpha*b*psi))^2))/((EXP(alpha*a*psi)-EXP(alpha*(2*OldTau+b*psi)))*(alpha^2)*(psi^2)) -> 12.344008 | G6: =(EXP(alpha*(zeta+(2*b-a)*psi))*(-1+EXP(alpha*(-1)*Size*psi))*(EXP(alpha*(2*(Tau+OldTau)+a*psi))-EXP(alpha*(2*(Tau+OldTau)+b*psi))))/(((EXP(alpha*a*psi)-EXP(alpha*(2*OldTau+b*psi)))^2)*(alpha^2)*(psi^2)) -> 0.64677291 | H6: =-Beta/alpha -> 180 | I6: =(-EXP(alpha*zeta)*Beta*(-1+EXP(alpha*Size*psi)-Size*alpha*psi))/((alpha^3)*(psi^2)) -> 4793.1004 | J6: 0 | K6: 0 | L6: 0 | M6: =Gamma*Size -> 0 | N6: =Size*Beta*Phi -> 64.8 | O6: =-(EXP(alpha*a*psi)+EXP(alpha*b*psi)*(-1+Size*psi*alpha))*(Beta*Phi)/((alpha*psi)*(EXP(alpha*a*psi)-EXP(alpha*b*psi))) -> 18.204759 | P6: =(EXP(alpha*(zeta-a*psi))*Beta*Phi*(-EXP(alpha*a*psi)*(-2+(-1)*Size*alpha*psi)+EXP(alpha*b*psi)*(-2+Size*alpha*psi)))/((alpha^3)*(psi^3)) -> 350.45235 | Q6: =Tau*Beta -> 0 | R6: =Tau*Beta -> 0 | S6: =Tau -> 0 | T6: =Profit+Utility -> 6173.2192 | U6: =(2*ij*BRIJ)+2*jj*BRJJ -> 0 | V6: =2*(ij*BCCIJ)+(2*jj*BCCJJ)+BCS+jj*BCPTJJ+2*(ij*BCPTIJ)+BCPTII+BCk -> 841.80262 | W6: =ij*BUTIJ+BUTII -> 7015.0219 | X6: =Revenue-Cost -> -841.80262 | Y6: =Size -> 20 | Z6: =Welfare/(Size) -> 308.66096 | AA6: =Profit/(Size) -> -42.090131 | AB6: =Utility/(Size) -> 350.75109
A7: 0 | B7: =Tau -> 0 | C7: 50 | D7: 0 | E7: =Size-a -> 50 | F7: =(EXP(alpha*(Tau+OldTau+zeta-2*a*psi))*((EXP(alpha*a*psi)-EXP(alpha*b*psi))^2))/((EXP(alpha*a*psi)-EXP(alpha*(2*OldTau+b*psi)))*(alpha^2)*(psi^2)) -> 12.983596 | G7: =(EXP(alpha*(zeta+(2*b-a)*psi))*(-1+EXP(alpha*(-1)*Size*psi))*(EXP(alpha*(2*(Tau+OldTau)+a*psi))-EXP(alpha*(2*(Tau+OldTau)+b*psi))))/(((EXP(alpha*a*psi)-EXP(alpha*(2*OldTau+b*psi)))^2)*(alpha^2)*(psi^2)) -> 0.0071849981 | H7: =-Beta/alpha -> 180 | I7: =(-EXP(alpha*zeta)*Beta*(-1+EXP(alpha*Size*psi)-Size*alpha*psi))/((alpha^3)*(psi^2)) -> 15200.507 | J7: 0 | K7: 0 | L7: 0 | M7: =Gamma*Size -> 0 | N7: =Size*Beta*Phi -> 162 | O7: =-(EXP(alpha*a*psi)+EXP(alpha*b*psi)*(-1+Size*psi*alpha))*(Beta*Phi)/((alpha*psi)*(EXP(alpha*a*psi)-EXP(alpha*b*psi))) -> 21.510351 | P7: =(EXP(alpha*(zeta-a*psi))*Beta*Phi*(-EXP(alpha*a*psi)*(-2+(-1)*Size*alpha*psi)+EXP(alpha*b*psi)*(-2+Size*alpha*psi)))/((alpha^3)*(psi^3)) -> 1544.7792 | Q7: =Tau*Beta -> 0 | R7: =Tau*Beta -> 0 | S7: =Tau -> 0 | T7: =Profit+Utility -> 15433.048 | U7: =(2*ij*BRIJ)+2*jj*BRJJ -> 0 | V7: =2*(ij*BCCIJ)+(2*jj*BCCJJ)+BCS+jj*BCPTJJ+2*(ij*BCPTIJ)+BCPTII+BCk -> 2104.5066 | W7: =ij*BUTIJ+BUTII -> 17537.555 | X7: =Revenue-Cost -> -2104.5066 | Y7: =Size -> 50 | Z7: =Welfare/(Size) -> 308.66096 | AA7: =Profit/(Size) -> -42.090131 | AB7: =Utility/(Size) -> 350.75109
A8: 0 | B8: =Tau -> 0 | C8: 100 | D8: 0 | E8: =Size-a -> 100 | F8: =(EXP(alpha*(Tau+OldTau+zeta-2*a*psi))*((EXP(alpha*a*psi)-EXP(alpha*b*psi))^2))/((EXP(alpha*a*psi)-EXP(alpha*(2*OldTau+b*psi)))*(alpha^2)*(psi^2)) -> 12.990777 | G8: =(EXP(alpha*(zeta+(2*b-a)*psi))*(-1+EXP(alpha*(-1)*Size*psi))*(EXP(alpha*(2*(Tau+OldTau)+a*psi))-EXP(alpha*(2*(Tau+OldTau)+b*psi))))/(((EXP(alpha*a*psi)-EXP(alpha*(2*OldTau+b*psi)))^2)*(alpha^2)*(psi^2)) -> 3.9739101e-06 | H8: =-Beta/alpha -> 180 | I8: =(-EXP(alpha*zeta)*Beta*(-1+EXP(alpha*Size*psi)-Size*alpha*psi))/((alpha^3)*(psi^2)) -> 32736.769 | J8: 0 | K8: 0 | L8: 0 | M8: =Gamma*Size -> 0 | N8: =Size*Beta*Phi -> 324 | O8: =-(EXP(alpha*a*psi)+EXP(alpha*b*psi)*(-1+Size*psi*alpha))*(Beta*Phi)/((alpha*psi)*(EXP(alpha*a*psi)-EXP(alpha*b*psi))) -> 21.599901 | P8: =(EXP(alpha*(zeta-a*psi))*Beta*Phi*(-EXP(alpha*a*psi)*(-2+(-1)*Size*alpha*psi)+EXP(alpha*b*psi)*(-2+Size*alpha*psi)))/((alpha^3)*(psi^3)) -> 3647.8128 | Q8: =Tau*Beta -> 0 | R8: =Tau*Beta -> 0 | S8: =Tau -> 0 | T8: =Profit+Utility -> 30866.096 | U8: =(2*ij*BRIJ)+2*jj*BRJJ -> 0 | V8: =2*(ij*BCCIJ)+(2*jj*BCCJJ)+BCS+jj*BCPTJJ+2*(ij*BCPTIJ)+BCPTII+BCk -> 4209.0131 | W8: =ij*BUTIJ+BUTII -> 35075.109 | X8: =Revenue-Cost -> -4209.0131 | Y8: =Size -> 100 | Z8: =Welfare/(Size) -> 308.66096 | AA8: =Profit/(Size) -> -42.090131 | AB8: =Utility/(Size) -> 350.75109
A9: 0 | B9: =Tau -> 0 | C9: 200 | D9: 0 | E9: =Size-a -> 200 | F9: =(EXP(alpha*(Tau+OldTau+zeta-2*a*psi))*((EXP(alpha*a*psi)-EXP(alpha*b*psi))^2))/((EXP(alpha*a*psi)-EXP(alpha*(2*OldTau+b*psi)))*(alpha^2)*(psi^2)) -> 12.990781 | G9: =(EXP(alpha*(zeta+(2*b-a)*psi))*(-1+EXP(alpha*(-1)*Size*psi))*(EXP(alpha*(2*(Tau+OldTau)+a*psi))-EXP(alpha*(2*(Tau+OldTau)+b*psi))))/(((EXP(alpha*a*psi)-EXP(alpha*(2*OldTau+b*psi)))^2)*(alpha^2)*(psi^2)) -> 1.2156283e-12 | H9: =-Beta/alpha -> 180 | I9: =(-EXP(alpha*zeta)*Beta*(-1+EXP(alpha*Size*psi)-Size*alpha*psi))/((alpha^3)*(psi^2)) -> 67811.878 | J9: 0 | K9: 0 | L9: 0 | M9: =Gamma*Size -> 0 | N9: =Size*Beta*Phi -> 648 | O9: =-(EXP(alpha*a*psi)+EXP(alpha*b*psi)*(-1+Size*psi*alpha))*(Beta*Phi)/((alpha*psi)*(EXP(alpha*a*psi)-EXP(alpha*b*psi))) -> 21.6 | P9: =(EXP(alpha*(zeta-a*psi))*Beta*Phi*(-EXP(alpha*a*psi)*(-2+(-1)*Size*alpha*psi)+EXP(alpha*b*psi)*(-2+Size*alpha*psi)))/((alpha^3)*(psi^3)) -> 7856.8245 | Q9: =Tau*Beta -> 0 | R9: =Tau*Beta -> 0 | S9: =Tau -> 0 | T9: =Profit+Utility -> 61732.192 | U9: =(2*ij*BRIJ)+2*jj*BRJJ -> 0 | V9: =2*(ij*BCCIJ)+(2*jj*BCCJJ)+BCS+jj*BCPTJJ+2*(ij*BCPTIJ)+BCPTII+BCk -> 8418.0262 | W9: =ij*BUTIJ+BUTII -> 70150.219 | X9: =Revenue-Cost -> -8418.0262 | Y9: =Size -> 200 | Z9: =Welfare/(Size) -> 308.66096 | AA9: =Profit/(Size) -> -42.090131 | AB9: =Utility/(Size) -> 350.75109
A10: 0 | B10: =Tau -> 0 | C10: 500 | D10: 0 | E10: =Size-a -> 500 | F10: =(EXP(alpha*(Tau+OldTau+zeta-2*a*psi))*((EXP(alpha*a*psi)-EXP(alpha*b*psi))^2))/((EXP(alpha*a*psi)-EXP(alpha*(2*OldTau+b*psi)))*(alpha^2)*(psi^2)) -> 12.990781 | G10: =(EXP(alpha*(zeta+(2*b-a)*psi))*(-1+EXP(alpha*(-1)*Size*psi))*(EXP(alpha*(2*(Tau+OldTau)+a*psi))-EXP(alpha*(2*(Tau+OldTau)+b*psi))))/(((EXP(alpha*a*psi)-EXP(alpha*(2*OldTau+b*psi)))^2)*(alpha^2)*(psi^2)) -> 3.4797587e-32 | H10: =-Beta/alpha -> 180 | I10: =(-EXP(alpha*zeta)*Beta*(-1+EXP(alpha*Size*psi)-Size*alpha*psi))/((alpha^3)*(psi^2)) -> 173037.21 | J10: 0 | K10: 0 | L10: 0 | M10: =Gamma*Size -> 0 | N10: =Size*Beta*Phi -> 1620 | O10: =-(EXP(alpha*a*psi)+EXP(alpha*b*psi)*(-1+Size*psi*alpha))*(Beta*Phi)/((alpha*psi)*(EXP(alpha*a*psi)-EXP(alpha*b*psi))) -> 21.6 | P10: =(EXP(alpha*(zeta-a*psi))*Beta*Phi*(-EXP(alpha*a*psi)*(-2+(-1)*Size*alpha*psi)+EXP(alpha*b*psi)*(-2+Size*alpha*psi)))/((alpha^3)*(psi^3)) -> 20483.864 | Q10: =Tau*Beta -> 0 | R10: =Tau*Beta -> 0 | S10: =Tau -> 0 | T10: =Profit+Utility -> 154330.48 | U10: =(2*ij*BRIJ)+2*jj*BRJJ -> 0 | V10: =2*(ij*BCCIJ)+(2*jj*BCCJJ)+BCS+jj*BCPTJJ+2*(ij*BCPTIJ)+BCPTII+BCk -> 21045.066 | W10: =ij*BUTIJ+BUTII -> 175375.55 | X10: =Revenue-Cost -> -21045.066 | Y10: =Size -> 500 | Z10: =Welfare/(Size) -> 308.66096 | AA10: =Profit/(Size) -> -42.090131 | AB10: =Utility/(Size) -> 350.75109
A11: 0 | B11: =Tau -> 0 | C11: 1000 | D11: 0 | E11: =Size-a -> 1000 | F11: =(EXP(alpha*(Tau+OldTau+zeta-2*a*psi))*((EXP(alpha*a*psi)-EXP(alpha*b*psi))^2))/((EXP(alpha*a*psi)-EXP(alpha*(2*OldTau+b*psi)))*(alpha^2)*(psi^2)) -> 12.990781 | G11: =(EXP(alpha*(zeta+(2*b-a)*psi))*(-1+EXP(alpha*(-1)*Size*psi))*(EXP(alpha*(2*(Tau+OldTau)+a*psi))-EXP(alpha*(2*(Tau+OldTau)+b*psi))))/(((EXP(alpha*a*psi)-EXP(alpha*(2*OldTau+b*psi)))^2)*(alpha^2)*(psi^2)) -> 9.3210102e-65 | H11: =-Beta/alpha -> 180 | I11: =(-EXP(alpha*zeta)*Beta*(-1+EXP(alpha*Size*psi)-Size*alpha*psi))/((alpha^3)*(psi^2)) -> 348412.75 | J11: 0 | K11: 0 | L11: 0 | M11: =Gamma*Size -> 0 | N11: =Size*Beta*Phi -> 3240 | O11: =-(EXP(alpha*a*psi)+EXP(alpha*b*psi)*(-1+Size*psi*alpha))*(Beta*Phi)/((alpha*psi)*(EXP(alpha*a*psi)-EXP(alpha*b*psi))) -> 21.6 | P11: =(EXP(alpha*(zeta-a*psi))*Beta*Phi*(-EXP(alpha*a*psi)*(-2+(-1)*Size*alpha*psi)+EXP(alpha*b*psi)*(-2+Size*alpha*psi)))/((alpha^3)*(psi^3)) -> 41528.929 | Q11: =Tau*Beta -> 0 | R11: =Tau*Beta -> 0 | S11: =Tau -> 0 | T11: =Profit+Utility -> 308660.96 | U11: =(2*ij*BRIJ)+2*jj*BRJJ -> 0 | V11: =2*(ij*BCCIJ)+(2*jj*BCCJJ)+BCS+jj*BCPTJJ+2*(ij*BCPTIJ)+BCPTII+BCk -> 42090.131 | W11: =ij*BUTIJ+BUTII -> 350751.09 | X11: =Revenue-Cost -> -42090.131 | Y11: =Size -> 1000 | Z11: =Welfare/(Size) -> 308.66096 | AA11: =Profit/(Size) -> -42.090131 | AB11: =Utility/(Size) -> 350.75109

Sheet W-Toll(All-Tax)
A1: Tau | B1: OldTau | C1: Size | D1: a | E1: b | F1: ij | G1: jj | H1: BUTIJ | I1: BUTII | J1: BCCIJ | K1: BCCJJ | L1: BCk | M1: BCS | N1: BCPTJJ | O1: BCPTIJ | P1: BCPTII | Q1: BRIJ | R1: BRJJ | S1: Toll | T1: Welfare | U1: Revenue | V1: Cost | W1: Utility | X1: Profit | Y1: Size2 | Z1: W-Toll/Size | AA1: ∏/Size | AB1: U/Size | AC1: W-Tax/Size
A2: 0.5889719 | B2: 0 | C2: 1 | D2: 0 | E2: =Size-a -> 1 | F2: =(EXP(alpha*(Tau+OldTau+zeta-2*a*psi))*((EXP(alpha*a*psi)-EXP(alpha*b*psi))^2))/((EXP(alpha*a*psi)-EXP(alpha*(2*OldTau+b*psi)))*(alpha^2)*(psi^2)) -> 1.0040938 | G2: =(EXP(alpha*(zeta+(2*b-a)*psi))*(-1+EXP(alpha*(-1)*Size*psi))*(EXP(alpha*(2*(Tau+OldTau)+a*psi))-EXP(alpha*(2*(Tau+OldTau)+b*psi))))/(((EXP(alpha*a*psi)-EXP(alpha*(2*OldTau+b*psi)))^2)*(alpha^2)*(psi^2)) -> 3.4428382 | H2: =-Beta/alpha -> 180 | I2: =(-EXP(alpha*zeta)*Beta*(-1+EXP(alpha*Size*psi)-Size*alpha*psi))/((alpha^3)*(psi^2)) -> 25.038896 | J2: =Beta*Theta -> 14.4 | K2: =Beta*Theta -> 14.4 | L2: =kappa -> 90 | M2: =Gamma*Size -> 0 | N2: =Size*Beta*Phi -> 3.24 | O2: =-(EXP(alpha*a*psi)+EXP(alpha*b*psi)*(-1+Size*psi*alpha))*(Beta*Phi)/((alpha*psi)*(EXP(alpha*a*psi)-EXP(alpha*b*psi))) -> 1.5795152 | P2: =(EXP(alpha*(zeta-a*psi))*Beta*Phi*(-EXP(alpha*a*psi)*(-2+(-1)*Size*alpha*psi)+EXP(alpha*b*psi)*(-2+Size*alpha*psi)))/((alpha^3)*(psi^3)) -> 0.14651555 | Q2: =Tau*Beta -> 106.01494 | R2: =Tau*Beta -> 106.01494 | S2: =Tau -> 0.5889719 | T2: =Profit+Utility -> 916.11332 | U2: =(2*ij*BRIJ)+2*jj*BRJJ -> 942.88245 | V2: =2*(ij*BCCIJ)+(2*jj*BCCJJ)+BCS+jj*BCPTJJ+2*(ij*BCPTIJ)+BCPTII+BCk -> 232.54491 | W2: =ij*BUTIJ+BUTII -> 205.77577 | X2: =Revenue-Cost -> 710.33754 | Y2: =Size -> 1 | Z2: =Welfare/(Size) -> 916.11332 | AA2: =Profit/(Size) -> 710.33754 | AB2: =Utility/(Size) -> 205.77577 | AC2: 308.66096
A3: 0.5977839 | B3: 0 | C3: 2 | D3: 0 | E3: =Size-a -> 2 | F3: =(EXP(alpha*(Tau+OldTau+zeta-2*a*psi))*((EXP(alpha*a*psi)-EXP(alpha*b*psi))^2))/((EXP(alpha*a*psi)-EXP(alpha*(2*OldTau+b*psi)))*(alpha^2)*(psi^2)) -> 1.8519339 | G3: =(EXP(alpha*(zeta+(2*b-a)*psi))*(-1+EXP(alpha*(-1)*Size*psi))*(EXP(alpha*(2*(Tau+OldTau)+a*psi))-EXP(alpha*(2*(Tau+OldTau)+b*psi))))/(((EXP(alpha*a*psi)-EXP(alpha*(2*OldTau+b*psi)))^2)*(alpha^2)*(psi^2)) -> 2.9115109 | H3: =-Beta/alpha -> 180 | I3: =(-EXP(alpha*zeta)*Beta*(-1+EXP(alpha*Size*psi)-Size*alpha*psi))/((alpha^3)*(psi^2)) -> 95.446904 | J3: =Beta*Theta -> 14.4 | K3: =Beta*Theta -> 14.4 | L3: =kappa -> 90 | M3: =Gamma*Size -> 0 | N3: =Size*Beta*Phi -> 6.48 | O3: =-(EXP(alpha*a*psi)+EXP(alpha*b*psi)*(-1+Size*psi*alpha))*(Beta*Phi)/((alpha*psi)*(EXP(alpha*a*psi)-EXP(alpha*b*psi))) -> 3.0782425 | P3: =(EXP(alpha*(zeta-a*psi))*Beta*Phi*(-EXP(alpha*a*psi)*(-2+(-1)*Size*alpha*psi)+EXP(alpha*b*psi)*(-2+Size*alpha*psi)))/((alpha^3)*(psi^3)) -> 1.0892667 | Q3: =Tau*Beta -> 107.6011 | R3: =Tau*Beta -> 107.6011 | S3: =Tau -> 0.5977839 | T3: =Profit+Utility -> 1195.3544 | U3: =(2*ij*BRIJ)+2*jj*BRJJ -> 1025.1038 | V3: =2*(ij*BCCIJ)+(2*jj*BCCJJ)+BCS+jj*BCPTJJ+2*(ij*BCPTIJ)+BCPTII+BCk -> 258.54447 | W3: =ij*BUTIJ+BUTII -> 428.79501 | X3: =Revenue-Cost -> 766.55936 | Y3: =Size -> 2 | Z3: =Welfare/(Size) -> 597.67718 | AA3: =Profit/(Size) -> 383.27968 | AB3: =Utility/(Size) -> 214.3975 | AC3: 308.66096
A4: 0.62215872 | B4: 0 | C4: 5 | D4: 0 | E4: =Size-a -> 5 | F4: =(EXP(alpha*(Tau+OldTau+zeta-2*a*psi))*((EXP(alpha*a*psi)-EXP(alpha*b*psi))^2))/((EXP(alpha*a*psi)-EXP(alpha*(2*OldTau+b*psi)))*(alpha^2)*(psi^2)) -> 3.6793194 | G4: =(EXP(alpha*(zeta+(2*b-a)*psi))*(-1+EXP(alpha*(-1)*Size*psi))*(EXP(alpha*(2*(Tau+OldTau)+a*psi))-EXP(alpha*(2*(Tau+OldTau)+b*psi))))/(((EXP(alpha*a*psi)-EXP(alpha*(2*OldTau+b*psi)))^2)*(alpha^2)*(psi^2)) -> 1.7681301 | H4: =-Beta/alpha -> 180 | I4: =(-EXP(alpha*zeta)*Beta*(-1+EXP(alpha*Size*psi)-Size*alpha*psi))/((alpha^3)*(psi^2)) -> 519.96874 | J4: =Beta*Theta -> 14.4 | K4: =Beta*Theta -> 14.4 | L4: =kappa -> 90 | M4: =Gamma*Size -> 0 | N4: =Size*Beta*Phi -> 16.2 | O4: =-(EXP(alpha*a*psi)+EXP(alpha*b*psi)*(-1+Size*psi*alpha))*(Beta*Phi)/((alpha*psi)*(EXP(alpha*a*psi)-EXP(alpha*b*psi))) -> 7.0968668 | P4: =(EXP(alpha*(zeta-a*psi))*Beta*Phi*(-EXP(alpha*a*psi)*(-2+(-1)*Size*alpha*psi)+EXP(alpha*b*psi)*(-2+Size*alpha*psi)))/((alpha^3)*(psi^3)) -> 13.751693 | Q4: =Tau*Beta -> 111.98857 | R4: =Tau*Beta -> 111.98857 | S4: =Tau -> 0.62215872 | T4: =Profit+Utility -> 2060.8452 | U4: =(2*ij*BRIJ)+2*jj*BRJJ -> 1220.1041 | V4: =2*(ij*BCCIJ)+(2*jj*BCCJJ)+BCS+jj*BCPTJJ+2*(ij*BCPTIJ)+BCPTII+BCk -> 341.50522 | W4: =ij*BUTIJ+BUTII -> 1182.2462 | X4: =Revenue-Cost -> 878.59892 | Y4: =Size -> 5 | Z4: =Welfare/(Size) -> 412.16903 | AA4: =Profit/(Size) -> 175.71978 | AB4: =Utility/(Size) -> 236.44925 | AC4: 308.66096
A5: 0.65329456 | B5: 0 | C5: 10 | D5: 0 | E5: =Size-a -> 10 | F5: =(EXP(alpha*(Tau+OldTau+zeta-2*a*psi))*((EXP(alpha*a*psi)-EXP(alpha*b*psi))^2))/((EXP(alpha*a*psi)-EXP(alpha*(2*OldTau+b*psi)))*(alpha^2)*(psi^2)) -> 5.2512332 | G5: =(EXP(alpha*(zeta+(2*b-a)*psi))*(-1+EXP(alpha*(-1)*Size*psi))*(EXP(alpha*(2*(Tau+OldTau)+a*psi))-EXP(alpha*(2*(Tau+OldTau)+b*psi))))/(((EXP(alpha*a*psi)-EXP(alpha*(2*OldTau+b*psi)))^2)*(alpha^2)*(psi^2)) -> 0.78478212 | H5: =-Beta/alpha -> 180 | I5: =(-EXP(alpha*zeta)*Beta*(-1+EXP(alpha*Size*psi)-Size*alpha*psi))/((alpha^3)*(psi^2)) -> 1690.9246 | J5: =Beta*Theta -> 14.4 | K5: =Beta*Theta -> 14.4 | L5: =kappa -> 90 | M5: =Gamma*Size -> 0 | N5: =Size*Beta*Phi -> 32.4 | O5: =-(EXP(alpha*a*psi)+EXP(alpha*b*psi)*(-1+Size*psi*alpha))*(Beta*Phi)/((alpha*psi)*(EXP(alpha*a*psi)-EXP(alpha*b*psi))) -> 12.294172 | P5: =(EXP(alpha*(zeta-a*psi))*Beta*Phi*(-EXP(alpha*a*psi)*(-2+(-1)*Size*alpha*psi)+EXP(alpha*b*psi)*(-2+Size*alpha*psi)))/((alpha^3)*(psi^3)) -> 78.836376 | Q5: =Tau*Beta -> 117.59302 | R5: =Tau*Beta -> 117.59302 | S5: =Tau -> 0.65329456 | T5: =Profit+Utility -> 3558.5135 | U5: =(2*ij*BRIJ)+2*jj*BRJJ -> 1419.5866 | V5: =2*(ij*BCCIJ)+(2*jj*BCCJJ)+BCS+jj*BCPTJJ+2*(ij*BCPTIJ)+BCPTII+BCk -> 497.21969 | W5: =ij*BUTIJ+BUTII -> 2636.1466 | X5: =Revenue-Cost -> 922.36687 | Y5: =Size -> 10 | Z5: =Welfare/(Size) -> 355.85135 | AA5: =Profit/(Size) -> 92.236687 | AB5: =Utility/(Size) -> 263.61466 | AC5: 308.66096
A6: 0.68509426 | B6: 0 | C6: 20 | D6: 0 | E6: =Size-a -> 20 | F6: =(EXP(alpha*(Tau+OldTau+zeta-2*a*psi))*((EXP(alpha*a*psi)-EXP(alpha*b*psi))^2))/((EXP(alpha*a*psi)-EXP(alpha*(2*OldTau+b*psi)))*(alpha^2)*(psi^2)) -> 6.2219075 | G6: =(EXP(alpha*(zeta+(2*b-a)*psi))*(-1+EXP(alpha*(-1)*Size*psi))*(EXP(alpha*(2*(Tau+OldTau)+a*psi))-EXP(alpha*(2*(Tau+OldTau)+b*psi))))/(((EXP(alpha*a*psi)-EXP(alpha*(2*OldTau+b*psi)))^2)*(alpha^2)*(psi^2)) -> 0.16431852 | H6: =-Beta/alpha -> 180 | I6: =(-EXP(alpha*zeta)*Beta*(-1+EXP(alpha*Size*psi)-Size*alpha*psi))/((alpha^3)*(psi^2)) -> 4793.1004 | J6: =Beta*Theta -> 14.4 | K6: =Beta*Theta -> 14.4 | L6: =kappa -> 90 | M6: =Gamma*Size -> 0 | N6: =Size*Beta*Phi -> 64.8 | O6: =-(EXP(alpha*a*psi)+EXP(alpha*b*psi)*(-1+Size*psi*alpha))*(Beta*Phi)/((alpha*psi)*(EXP(alpha*a*psi)-EXP(alpha*b*psi))) -> 18.204759 | P6: =(EXP(alpha*(zeta-a*psi))*Beta*Phi*(-EXP(alpha*a*psi)*(-2+(-1)*Size*alpha*psi)+EXP(alpha*b*psi)*(-2+Size*alpha*psi)))/((alpha^3)*(psi^3)) -> 350.45235 | Q6: =Tau*Beta -> 123.31697 | R6: =Tau*Beta -> 123.31697 | S6: =Tau -> 0.68509426 | T6: =Profit+Utility -> 6626.5436 | U6: =(2*ij*BRIJ)+2*jj*BRJJ -> 1575.06 | V6: =2*(ij*BCCIJ)+(2*jj*BCCJJ)+BCS+jj*BCPTJJ+2*(ij*BCPTIJ)+BCPTII+BCk -> 861.56015 | W6: =ij*BUTIJ+BUTII -> 5913.0437 | X6: =Revenue-Cost -> 713.49989 | Y6: =Size -> 20 | Z6: =Welfare/(Size) -> 331.32718 | AA6: =Profit/(Size) -> 35.674995 | AB6: =Utility/(Size) -> 295.65219 | AC6: 308.66096
A7: 0.69968374 | B7: 0 | C7: 50 | D7: 0 | E7: =Size-a -> 50 | F7: =(EXP(alpha*(Tau+OldTau+zeta-2*a*psi))*((EXP(alpha*a*psi)-EXP(alpha*b*psi))^2))/((EXP(alpha*a*psi)-EXP(alpha*(2*OldTau+b*psi)))*(alpha^2)*(psi^2)) -> 6.4495025 | G7: =(EXP(alpha*(zeta+(2*b-a)*psi))*(-1+EXP(alpha*(-1)*Size*psi))*(EXP(alpha*(2*(Tau+OldTau)+a*psi))-EXP(alpha*(2*(Tau+OldTau)+b*psi))))/(((EXP(alpha*a*psi)-EXP(alpha*(2*OldTau+b*psi)))^2)*(alpha^2)*(psi^2)) -> 0.0017729198 | H7: =-Beta/alpha -> 180 | I7: =(-EXP(alpha*zeta)*Beta*(-1+EXP(alpha*Size*psi)-Size*alpha*psi))/((alpha^3)*(psi^2)) -> 15200.507 | J7: =Beta*Theta -> 14.4 | K7: =Beta*Theta -> 14.4 | L7: =kappa -> 90 | M7: =Gamma*Size -> 0 | N7: =Size*Beta*Phi -> 162 | O7: =-(EXP(alpha*a*psi)+EXP(alpha*b*psi)*(-1+Size*psi*alpha))*(Beta*Phi)/((alpha*psi)*(EXP(alpha*a*psi)-EXP(alpha*b*psi))) -> 21.510351 | P7: =(EXP(alpha*(zeta-a*psi))*Beta*Phi*(-EXP(alpha*a*psi)*(-2+(-1)*Size*alpha*psi)+EXP(alpha*b*psi)*(-2+Size*alpha*psi)))/((alpha^3)*(psi^3)) -> 1544.7792 | Q7: =Tau*Beta -> 125.94307 | R7: =Tau*Beta -> 125.94307 | S7: =Tau -> 0.69968374 | T7: =Profit+Utility -> 15888.079 | U7: =(2*ij*BRIJ)+2*jj*BRJJ -> 1624.9869 | V7: =2*(ij*BCCIJ)+(2*jj*BCCJJ)+BCS+jj*BCPTJJ+2*(ij*BCPTIJ)+BCPTII+BCk -> 2098.3252 | W7: =ij*BUTIJ+BUTII -> 16361.418 | X7: =Revenue-Cost -> -473.33834 | Y7: =Size -> 50 | Z7: =Welfare/(Size) -> 317.76159 | AA7: =Profit/(Size) -> -9.4667667 | AB7: =Utility/(Size) -> 327.22836 | AC7: 308.66096
A8: 0.70000022 | B8: 0 | C8: 100 | D8: 0 | E8: =Size-a -> 100 | F8: =(EXP(alpha*(Tau+OldTau+zeta-2*a*psi))*((EXP(alpha*a*psi)-EXP(alpha*b*psi))^2))/((EXP(alpha*a*psi)-EXP(alpha*(2*OldTau+b*psi)))*(alpha^2)*(psi^2)) -> 6.4510276 | G8: =(EXP(alpha*(zeta+(2*b-a)*psi))*(-1+EXP(alpha*(-1)*Size*psi))*(EXP(alpha*(2*(Tau+OldTau)+a*psi))-EXP(alpha*(2*(Tau+OldTau)+b*psi))))/(((EXP(alpha*a*psi)-EXP(alpha*(2*OldTau+b*psi)))^2)*(alpha^2)*(psi^2)) -> 9.7995373e-07 | H8: =-Beta/alpha -> 180 | I8: =(-EXP(alpha*zeta)*Beta*(-1+EXP(alpha*Size*psi)-Size*alpha*psi))/((alpha^3)*(psi^2)) -> 32736.769 | J8: =Beta*Theta -> 14.4 | K8: =Beta*Theta -> 14.4 | L8: =kappa -> 90 | M8: =Gamma*Size -> 0 | N8: =Size*Beta*Phi -> 324 | O8: =-(EXP(alpha*a*psi)+EXP(alpha*b*psi)*(-1+Size*psi*alpha))*(Beta*Phi)/((alpha*psi)*(EXP(alpha*a*psi)-EXP(alpha*b*psi))) -> 21.599901 | P8: =(EXP(alpha*(zeta-a*psi))*Beta*Phi*(-EXP(alpha*a*psi)*(-2+(-1)*Size*alpha*psi)+EXP(alpha*b*psi)*(-2+Size*alpha*psi)))/((alpha^3)*(psi^3)) -> 3647.8128 | Q8: =Tau*Beta -> 126.00004 | R8: =Tau*Beta -> 126.00004 | S8: =Tau -> 0.70000022 | T8: =Profit+Utility -> 31321.328 | U8: =(2*ij*BRIJ)+2*jj*BRJJ -> 1625.6597 | V8: =2*(ij*BCCIJ)+(2*jj*BCCJJ)+BCS+jj*BCPTJJ+2*(ij*BCPTIJ)+BCPTII+BCk -> 4202.2859 | W8: =ij*BUTIJ+BUTII -> 33897.954 | X8: =Revenue-Cost -> -2576.6262 | Y8: =Size -> 100 | Z8: =Welfare/(Size) -> 313.21328 | AA8: =Profit/(Size) -> -25.766262 | AB8: =Utility/(Size) -> 338.97954 | AC8: 308.66096
A9: 0.70000093 | B9: 0 | C9: 200 | D9: 0 | E9: =Size-a -> 200 | F9: =(EXP(alpha*(Tau+OldTau+zeta-2*a*psi))*((EXP(alpha*a*psi)-EXP(alpha*b*psi))^2))/((EXP(alpha*a*psi)-EXP(alpha*(2*OldTau+b*psi)))*(alpha^2)*(psi^2)) -> 6.451025 | G9: =(EXP(alpha*(zeta+(2*b-a)*psi))*(-1+EXP(alpha*(-1)*Size*psi))*(EXP(alpha*(2*(Tau+OldTau)+a*psi))-EXP(alpha*(2*(Tau+OldTau)+b*psi))))/(((EXP(alpha*a*psi)-EXP(alpha*(2*OldTau+b*psi)))^2)*(alpha^2)*(psi^2)) -> 2.997697e-13 | H9: =-Beta/alpha -> 180 | I9: =(-EXP(alpha*zeta)*Beta*(-1+EXP(alpha*Size*psi)-Size*alpha*psi))/((alpha^3)*(psi^2)) -> 67811.878 | J9: =Beta*Theta -> 14.4 | K9: =Beta*Theta -> 14.4 | L9: =kappa -> 90 | M9: =Gamma*Size -> 0 | N9: =Size*Beta*Phi -> 648 | O9: =-(EXP(alpha*a*psi)+EXP(alpha*b*psi)*(-1+Size*psi*alpha))*(Beta*Phi)/((alpha*psi)*(EXP(alpha*a*psi)-EXP(alpha*b*psi))) -> 21.6 | P9: =(EXP(alpha*(zeta-a*psi))*Beta*Phi*(-EXP(alpha*a*psi)*(-2+(-1)*Size*alpha*psi)+EXP(alpha*b*psi)*(-2+Size*alpha*psi)))/((alpha^3)*(psi^3)) -> 7856.8245 | Q9: =Tau*Beta -> 126.00017 | R9: =Tau*Beta -> 126.00017 | S9: =Tau -> 0.70000093 | T9: =Profit+Utility -> 62187.425 | U9: =(2*ij*BRIJ)+2*jj*BRJJ -> 1625.6605 | V9: =2*(ij*BCCIJ)+(2*jj*BCCJJ)+BCS+jj*BCPTJJ+2*(ij*BCPTIJ)+BCPTII+BCk -> 8411.2983 | W9: =ij*BUTIJ+BUTII -> 68973.063 | X9: =Revenue-Cost -> -6785.6378 | Y9: =Size -> 200 | Z9: =Welfare/(Size) -> 310.93712 | AA9: =Profit/(Size) -> -33.928189 | AB9: =Utility/(Size) -> 344.86531 | AC9: 308.66096
A10: 0.70065908 | B10: 0 | C10: 500 | D10: 0 | E10: =Size-a -> 500 | F10: =(EXP(alpha*(Tau+OldTau+zeta-2*a*psi))*((EXP(alpha*a*psi)-EXP(alpha*b*psi))^2))/((EXP(alpha*a*psi)-EXP(alpha*(2*OldTau+b*psi)))*(alpha^2)*(psi^2)) -> 6.4467807 | G10: =(EXP(alpha*(zeta+(2*b-a)*psi))*(-1+EXP(alpha*(-1)*Size*psi))*(EXP(alpha*(2*(Tau+OldTau)+a*psi))-EXP(alpha*(2*(Tau+OldTau)+b*psi))))/(((EXP(alpha*a*psi)-EXP(alpha*(2*OldTau+b*psi)))^2)*(alpha^2)*(psi^2)) -> 8.5696755e-33 | H10: =-Beta/alpha -> 180 | I10: =(-EXP(alpha*zeta)*Beta*(-1+EXP(alpha*Size*psi)-Size*alpha*psi))/((alpha^3)*(psi^2)) -> 173037.21 | J10: =Beta*Theta -> 14.4 | K10: =Beta*Theta -> 14.4 | L10: =kappa -> 90 | M10: =Gamma*Size -> 0 | N10: =Size*Beta*Phi -> 1620 | O10: =-(EXP(alpha*a*psi)+EXP(alpha*b*psi)*(-1+Size*psi*alpha))*(Beta*Phi)/((alpha*psi)*(EXP(alpha*a*psi)-EXP(alpha*b*psi))) -> 21.6 | P10: =(EXP(alpha*(zeta-a*psi))*Beta*Phi*(-EXP(alpha*a*psi)*(-2+(-1)*Size*alpha*psi)+EXP(alpha*b*psi)*(-2+Size*alpha*psi)))/((alpha^3)*(psi^3)) -> 20483.864 | Q10: =Tau*Beta -> 126.11864 | R10: =Tau*Beta -> 126.11864 | S10: =Tau -> 0.70065908 | T10: =Profit+Utility -> 154785.71 | U10: =(2*ij*BRIJ)+2*jj*BRJJ -> 1626.1184 | V10: =2*(ij*BCCIJ)+(2*jj*BCCJJ)+BCS+jj*BCPTJJ+2*(ij*BCPTIJ)+BCPTII+BCk -> 21038.032 | W10: =ij*BUTIJ+BUTII -> 174197.63 | X10: =Revenue-Cost -> -19411.914 | Y10: =Size -> 500 | Z10: =Welfare/(Size) -> 309.57143 | AA10: =Profit/(Size) -> -38.823827 | AB10: =Utility/(Size) -> 348.39525 | AC10: 308.66096
A11: 0.70065908 | B11: 0 | C11: 1000 | D11: 0 | E11: =Size-a -> 1000 | F11: =(EXP(alpha*(Tau+OldTau+zeta-2*a*psi))*((EXP(alpha*a*psi)-EXP(alpha*b*psi))^2))/((EXP(alpha*a*psi)-EXP(alpha*(2*OldTau+b*psi)))*(alpha^2)*(psi^2)) -> 6.4467807 | G11: =(EXP(alpha*(zeta+(2*b-a)*psi))*(-1+EXP(alpha*(-1)*Size*psi))*(EXP(alpha*(2*(Tau+OldTau)+a*psi))-EXP(alpha*(2*(Tau+OldTau)+b*psi))))/(((EXP(alpha*a*psi)-EXP(alpha*(2*OldTau+b*psi)))^2)*(alpha^2)*(psi^2)) -> 2.295505e-65 | H11: =-Beta/alpha -> 180 | I11: =(-EXP(alpha*zeta)*Beta*(-1+EXP(alpha*Size*psi)-Size*alpha*psi))/((alpha^3)*(psi^2)) -> 348412.75 | J11: =Beta*Theta -> 14.4 | K11: =Beta*Theta -> 14.4 | L11: =kappa -> 90 | M11: =Gamma*Size -> 0 | N11: =Size*Beta*Phi -> 3240 | O11: =-(EXP(alpha*a*psi)+EXP(alpha*b*psi)*(-1+Size*psi*alpha))*(Beta*Phi)/((alpha*psi)*(EXP(alpha*a*psi)-EXP(alpha*b*psi))) -> 21.6 | P11: =(EXP(alpha*(zeta-a*psi))*Beta*Phi*(-EXP(alpha*a*psi)*(-2+(-1)*Size*alpha*psi)+EXP(alpha*b*psi)*(-2+Size*alpha*psi)))/((alpha^3)*(psi^3)) -> 41528.929 | Q11: =Tau*Beta -> 126.11864 | R11: =Tau*Beta -> 126.11864 | S11: =Tau -> 0.70065908 | T11: =Profit+Utility -> 309116.19 | U11: =(2*ij*BRIJ)+2*jj*BRJJ -> 1626.1184 | V11: =2*(ij*BCCIJ)+(2*jj*BCCJJ)+BCS+jj*BCPTJJ+2*(ij*BCPTIJ)+BCPTII+BCk -> 42083.098 | W11: =ij*BUTIJ+BUTII -> 349573.17 | X11: =Revenue-Cost -> -40456.979 | Y11: =Size -> 1000 | Z11: =Welfare/(Size) -> 309.11619 | AA11: =Profit/(Size) -> -40.456979 | AB11: =Utility/(Size) -> 349.57317 | AC11: 308.66096

Sheet W-Toll(All-Tax) (theta)
A1: Theta | B1: Ccv' | C1: Theta-necessary | D1: Tau | E1: OldTau | F1: Size | G1: a | H1: b | I1: ij | J1: jj | K1: BUTIJ | L1: BUTII | M1: BCCIJ | N1: BCCJJ | O1: BCk | P1: BCS | Q1: BCPTJJ | R1: BCPTIJ | S1: BCPTII | T1: BRIJ | U1: BRJJ | V1: Toll | W1: Welfare | X1: Revenue | Y1: Cost | Z1: Utility | AA1: Profit | AB1: Size2 | AC1: W/Size | AD1: ∏/Size | AE1: U/Size | AF1: W-Tax(All-Tax)
A2: 0.08 | B2: =(I2+J2)*Beta*2 -> 1600.8953 | C2: =(W2+B2*Theta-'W-Tax(All-Tax)'!$T$2)/B2 -> 0.4594454 | D2: 0.58897197 | E2: 0 | F2: 1 | G2: 0 | H2: =Size-a -> 1 | I2: =(EXP(alpha*(Tau+OldTau+zeta-2*a*psi))*((EXP(alpha*a*psi)-EXP(alpha*b*psi))^2))/((EXP(alpha*a*psi)-EXP(alpha*(2*OldTau+b*psi)))*(alpha^2)*(psi^2)) -> 1.0040937 | J2: =(EXP(alpha*(zeta+(2*b-a)*psi))*(-1+EXP(alpha*(-1)*Size*psi))*(EXP(alpha*(2*(Tau+OldTau)+a*psi))-EXP(alpha*(2*(Tau+OldTau)+b*psi))))/(((EXP(alpha*a*psi)-EXP(alpha*(2*OldTau+b*psi)))^2)*(alpha^2)*(psi^2)) -> 3.4428377 | K2: =-Beta/alpha -> 180 | L2: =(-EXP(alpha*zeta)*Beta*(-1+EXP(alpha*Size*psi)-Size*alpha*psi))/((alpha^3)*(psi^2)) -> 25.038896 | M2: =Beta*Theta -> 14.4 | N2: =Beta*Theta -> 14.4 | O2: =kappa -> 90 | P2: =Gamma*Size -> 0 | Q2: =Size*Beta*Phi -> 3.24 | R2: =-(EXP(alpha*a*psi)+EXP(alpha*b*psi)*(-1+Size*psi*alpha))*(Beta*Phi)/((alpha*psi)*(EXP(alpha*a*psi)-EXP(alpha*b*psi))) -> 1.5795152 | S2: =(EXP(alpha*(zeta-a*psi))*Beta*Phi*(-EXP(alpha*a*psi)*(-2+(-1)*Size*alpha*psi)+EXP(alpha*b*psi)*(-2+Size*alpha*psi)))/((alpha^3)*(psi^3)) -> 0.14651555 | T2: =Tau*Beta -> 106.01495 | U2: =Tau*Beta -> 106.01495 | V2: =Tau -> 0.58897197 | W2: =Profit+Utility -> 916.11332 | X2: =(2*ij*BRIJ)+2*jj*BRJJ -> 942.88245 | Y2: =2*(ij*BCCIJ)+(2*jj*BCCJJ)+BCS+jj*BCPTJJ+2*(ij*BCPTIJ)+BCPTII+BCk -> 232.5449 | Z2: =ij*BUTIJ+BUTII -> 205.77576 | AA2: =Revenue-Cost -> 710.33755 | AB2: =Size -> 1 | AC2: =Welfare/(Size) -> 916.11332 | AD2: =Profit/(Size) -> 710.33755 | AE2: =Utility/(Size) -> 205.77576 | AF2: 308.66096
A3: =C2 -> 0.4594454 | B3: =(I3+J3)*Beta*2 -> 827.6302 | C3: =(W3+B3*Theta-'W-Tax(All-Tax)'!$T$2)/B3 -> 0.65728556 | D3: 0.96840601 | E3: 0 | F3: 1 | G3: 0 | H3: =Size-a -> 1 | I3: =(EXP(alpha*(Tau+OldTau+zeta-2*a*psi))*((EXP(alpha*a*psi)-EXP(alpha*b*psi))^2))/((EXP(alpha*a*psi)-EXP(alpha*(2*OldTau+b*psi)))*(alpha^2)*(psi^2)) -> 0.68704966 | J3: =(EXP(alpha*(zeta+(2*b-a)*psi))*(-1+EXP(alpha*(-1)*Size*psi))*(EXP(alpha*(2*(Tau+OldTau)+a*psi))-EXP(alpha*(2*(Tau+OldTau)+b*psi))))/(((EXP(alpha*a*psi)-EXP(alpha*(2*OldTau+b*psi)))^2)*(alpha^2)*(psi^2)) -> 1.6119231 | K3: =-Beta/alpha -> 180 | L3: =(-EXP(alpha*zeta)*Beta*(-1+EXP(alpha*Size*psi)-Size*alpha*psi))/((alpha^3)*(psi^2)) -> 25.038896 | M3: =Beta*Theta -> 82.700172 | N3: =Beta*Theta -> 82.700172 | O3: =kappa -> 90 | P3: =Gamma*Size -> 0 | Q3: =Size*Beta*Phi -> 3.24 | R3: =-(EXP(alpha*a*psi)+EXP(alpha*b*psi)*(-1+Size*psi*alpha))*(Beta*Phi)/((alpha*psi)*(EXP(alpha*a*psi)-EXP(alpha*b*psi))) -> 1.5795152 | S3: =(EXP(alpha*(zeta-a*psi))*Beta*Phi*(-EXP(alpha*a*psi)*(-2+(-1)*Size*alpha*psi)+EXP(alpha*b*psi)*(-2+Size*alpha*psi)))/((alpha^3)*(psi^3)) -> 0.14651555 | T3: =Tau*Beta -> 174.31308 | U3: =Tau*Beta -> 174.31308 | V3: =Tau -> 0.96840601 | W3: =Profit+Utility -> 472.39945 | X3: =(2*ij*BRIJ)+2*jj*BRJJ -> 801.48206 | Y3: =2*(ij*BCCIJ)+(2*jj*BCCJJ)+BCS+jj*BCPTJJ+2*(ij*BCPTIJ)+BCPTII+BCk -> 477.79045 | Z3: =ij*BUTIJ+BUTII -> 148.70784 | AA3: =Revenue-Cost -> 323.69161 | AB3: =Size -> 1 | AC3: =Welfare/(Size) -> 472.39945 | AD3: =Profit/(Size) -> 323.69161 | AE3: =Utility/(Size) -> 148.70784 | AF3: 308.66096
A4: =C3 -> 0.65728556 | B4: =(I4+J4)*Beta*2 -> 593.61334 | C4: =(W4+B4*Theta-'W-Tax(All-Tax)'!$T$2)/B4 -> 0.69860437 | D4: 1.1662392 | E4: 0 | F4: 1 | G4: 0 | H4: =Size-a -> 1 | I4: =(EXP(alpha*(Tau+OldTau+zeta-2*a*psi))*((EXP(alpha*a*psi)-EXP(alpha*b*psi))^2))/((EXP(alpha*a*psi)-EXP(alpha*(2*OldTau+b*psi)))*(alpha^2)*(psi^2)) -> 0.56372887 | J4: =(EXP(alpha*(zeta+(2*b-a)*psi))*(-1+EXP(alpha*(-1)*Size*psi))*(EXP(alpha*(2*(Tau+OldTau)+a*psi))-EXP(alpha*(2*(Tau+OldTau)+b*psi))))/(((EXP(alpha*a*psi)-EXP(alpha*(2*OldTau+b*psi)))^2)*(alpha^2)*(psi^2)) -> 1.0851971 | K4: =-Beta/alpha -> 180 | L4: =(-EXP(alpha*zeta)*Beta*(-1+EXP(alpha*Size*psi)-Size*alpha*psi))/((alpha^3)*(psi^2)) -> 25.038896 | M4: =Beta*Theta -> 118.3114 | N4: =Beta*Theta -> 118.3114 | O4: =kappa -> 90 | P4: =Gamma*Size -> 0 | Q4: =Size*Beta*Phi -> 3.24 | R4: =-(EXP(alpha*a*psi)+EXP(alpha*b*psi)*(-1+Size*psi*alpha))*(Beta*Phi)/((alpha*psi)*(EXP(alpha*a*psi)-EXP(alpha*b*psi))) -> 1.5795152 | S4: =(EXP(alpha*(zeta-a*psi))*Beta*Phi*(-EXP(alpha*a*psi)*(-2+(-1)*Size*alpha*psi)+EXP(alpha*b*psi)*(-2+Size*alpha*psi)))/((alpha^3)*(psi^3)) -> 0.14651555 | T4: =Tau*Beta -> 209.92305 | U4: =Tau*Beta -> 209.92305 | V4: =Tau -> 1.1662392 | W4: =Profit+Utility -> 333.18836 | X4: =(2*ij*BRIJ)+2*jj*BRJJ -> 692.29514 | Y4: =2*(ij*BCCIJ)+(2*jj*BCCJJ)+BCS+jj*BCPTJJ+2*(ij*BCPTIJ)+BCPTII+BCk -> 485.61686 | Z4: =ij*BUTIJ+BUTII -> 126.51009 | AA4: =Revenue-Cost -> 206.67827 | AB4: =Size -> 1 | AC4: =Welfare/(Size) -> 333.18836 | AD4: =Profit/(Size) -> 206.67827 | AE4: =Utility/(Size) -> 126.51009 | AF4: 308.66096
A5: =C4 -> 0.69860437 | B5: =(I5+J5)*Beta*2 -> 554.41407 | C5: =(W5+B5*Theta-'W-Tax(All-Tax)'!$T$2)/B5 -> 0.70008308 | D5: 1.2075565 | E5: 0 | F5: 1 | G5: 0 | H5: =Size-a -> 1 | I5: =(EXP(alpha*(Tau+OldTau+zeta-2*a*psi))*((EXP(alpha*a*psi)-EXP(alpha*b*psi))^2))/((EXP(alpha*a*psi)-EXP(alpha*(2*OldTau+b*psi)))*(alpha^2)*(psi^2)) -> 0.54091172 | J5: =(EXP(alpha*(zeta+(2*b-a)*psi))*(-1+EXP(alpha*(-1)*Size*psi))*(EXP(alpha*(2*(Tau+OldTau)+a*psi))-EXP(alpha*(2*(Tau+OldTau)+b*psi))))/(((EXP(alpha*a*psi)-EXP(alpha*(2*OldTau+b*psi)))^2)*(alpha^2)*(psi^2)) -> 0.99912736 | K5: =-Beta/alpha -> 180 | L5: =(-EXP(alpha*zeta)*Beta*(-1+EXP(alpha*Size*psi)-Size*alpha*psi))/((alpha^3)*(psi^2)) -> 25.038896 | M5: =Beta*Theta -> 125.74879 | N5: =Beta*Theta -> 125.74879 | O5: =kappa -> 90 | P5: =Gamma*Size -> 0 | Q5: =Size*Beta*Phi -> 3.24 | R5: =-(EXP(alpha*a*psi)+EXP(alpha*b*psi)*(-1+Size*psi*alpha))*(Beta*Phi)/((alpha*psi)*(EXP(alpha*a*psi)-EXP(alpha*b*psi))) -> 1.5795152 | S5: =(EXP(alpha*(zeta-a*psi))*Beta*Phi*(-EXP(alpha*a*psi)*(-2+(-1)*Size*alpha*psi)+EXP(alpha*b*psi)*(-2+Size*alpha*psi)))/((alpha^3)*(psi^3)) -> 0.14651555 | T5: =Tau*Beta -> 217.36017 | U5: =Tau*Beta -> 217.36017 | V5: =Tau -> 1.2075565 | W5: =Profit+Utility -> 309.48078 | X5: =(2*ij*BRIJ)+2*jj*BRJJ -> 669.48631 | Y5: =2*(ij*BCCIJ)+(2*jj*BCCJJ)+BCS+jj*BCPTJJ+2*(ij*BCPTIJ)+BCPTII+BCk -> 482.40854 | Z5: =ij*BUTIJ+BUTII -> 122.40301 | AA5: =Revenue-Cost -> 187.07777 | AB5: =Size -> 1 | AC5: =Welfare/(Size) -> 309.48078 | AD5: =Profit/(Size) -> 187.07777 | AE5: =Utility/(Size) -> 122.40301 | AF5: 308.66096
A6: =C5 -> 0.70008308 | B6: =(I6+J6)*Beta*2 -> 553.06425 | C6: =(W6+B6*Theta-'W-Tax(All-Tax)'!$T$2)/B6 -> 0.70008489 | D6: 1.2090351 | E6: 0 | F6: 1 | G6: 0 | H6: =Size-a -> 1 | I6: =(EXP(alpha*(Tau+OldTau+zeta-2*a*psi))*((EXP(alpha*a*psi)-EXP(alpha*b*psi))^2))/((EXP(alpha*a*psi)-EXP(alpha*(2*OldTau+b*psi)))*(alpha^2)*(psi^2)) -> 0.54011251 | J6: =(EXP(alpha*(zeta+(2*b-a)*psi))*(-1+EXP(alpha*(-1)*Size*psi))*(EXP(alpha*(2*(Tau+OldTau)+a*psi))-EXP(alpha*(2*(Tau+OldTau)+b*psi))))/(((EXP(alpha*a*psi)-EXP(alpha*(2*OldTau+b*psi)))^2)*(alpha^2)*(psi^2)) -> 0.99617707 | K6: =-Beta/alpha -> 180 | L6: =(-EXP(alpha*zeta)*Beta*(-1+EXP(alpha*Size*psi)-Size*alpha*psi))/((alpha^3)*(psi^2)) -> 25.038896 | M6: =Beta*Theta -> 126.01495 | N6: =Beta*Theta -> 126.01495 | O6: =kappa -> 90 | P6: =Gamma*Size -> 0 | Q6: =Size*Beta*Phi -> 3.24 | R6: =-(EXP(alpha*a*psi)+EXP(alpha*b*psi)*(-1+Size*psi*alpha))*(Beta*Phi)/((alpha*psi)*(EXP(alpha*a*psi)-EXP(alpha*b*psi))) -> 1.5795152 | S6: =(EXP(alpha*(zeta-a*psi))*Beta*Phi*(-EXP(alpha*a*psi)*(-2+(-1)*Size*alpha*psi)+EXP(alpha*b*psi)*(-2+Size*alpha*psi)))/((alpha^3)*(psi^3)) -> 0.14651555 | T6: =Tau*Beta -> 217.62632 | U6: =Tau*Beta -> 217.62632 | V6: =Tau -> 1.2090351 | W6: =Profit+Utility -> 308.66196 | X6: =(2*ij*BRIJ)+2*jj*BRJJ -> 668.6741 | Y6: =2*(ij*BCCIJ)+(2*jj*BCCJJ)+BCS+jj*BCPTJJ+2*(ij*BCPTIJ)+BCPTII+BCk -> 482.27129 | Z6: =ij*BUTIJ+BUTII -> 122.25915 | AA6: =Revenue-Cost -> 186.40281 | AB6: =Size -> 1 | AC6: =Welfare/(Size) -> 308.66196 | AD6: =Profit/(Size) -> 186.40281 | AE6: =Utility/(Size) -> 122.25915 | AF6: 308.66096
A7: =C6 -> 0.70008489 | B7: =(I7+J7)*Beta*2 -> 553.0626 | C7: =(W7+B7*Theta-'W-Tax(All-Tax)'!$T$2)/B7 -> 0.70008489 | D7: 1.2090369 | E7: 0 | F7: 1 | G7: 0 | H7: =Size-a -> 1 | I7: =(EXP(alpha*(Tau+OldTau+zeta-2*a*psi))*((EXP(alpha*a*psi)-EXP(alpha*b*psi))^2))/((EXP(alpha*a*psi)-EXP(alpha*(2*OldTau+b*psi)))*(alpha^2)*(psi^2)) -> 0.54011154 | J7: =(EXP(alpha*(zeta+(2*b-a)*psi))*(-1+EXP(alpha*(-1)*Size*psi))*(EXP(alpha*(2*(Tau+OldTau)+a*psi))-EXP(alpha*(2*(Tau+OldTau)+b*psi))))/(((EXP(alpha*a*psi)-EXP(alpha*(2*OldTau+b*psi)))^2)*(alpha^2)*(psi^2)) -> 0.99617347 | K7: =-Beta/alpha -> 180 | L7: =(-EXP(alpha*zeta)*Beta*(-1+EXP(alpha*Size*psi)-Size*alpha*psi))/((alpha^3)*(psi^2)) -> 25.038896 | M7: =Beta*Theta -> 126.01528 | N7: =Beta*Theta -> 126.01528 | O7: =kappa -> 90 | P7: =Gamma*Size -> 0 | Q7: =Size*Beta*Phi -> 3.24 | R7: =-(EXP(alpha*a*psi)+EXP(alpha*b*psi)*(-1+Size*psi*alpha))*(Beta*Phi)/((alpha*psi)*(EXP(alpha*a*psi)-EXP(alpha*b*psi))) -> 1.5795152 | S7: =(EXP(alpha*(zeta-a*psi))*Beta*Phi*(-EXP(alpha*a*psi)*(-2+(-1)*Size*alpha*psi)+EXP(alpha*b*psi)*(-2+Size*alpha*psi)))/((alpha^3)*(psi^3)) -> 0.14651555 | T7: =Tau*Beta -> 217.62665 | U7: =Tau*Beta -> 217.62665 | V7: =Tau -> 1.2090369 | W7: =Profit+Utility -> 308.66096 | X7: =(2*ij*BRIJ)+2*jj*BRJJ -> 668.67311 | Y7: =2*(ij*BCCIJ)+(2*jj*BCCJJ)+BCS+jj*BCPTJJ+2*(ij*BCPTIJ)+BCPTII+BCk -> 482.27112 | Z7: =ij*BUTIJ+BUTII -> 122.25897 | AA7: =Revenue-Cost -> 186.40199 | AB7: =Size -> 1 | AC7: =Welfare/(Size) -> 308.66096 | AD7: =Profit/(Size) -> 186.40199 | AE7: =Utility/(Size) -> 122.25897 | AF7: 308.66096
A9: 0.08 | B9: =(I9+J9)*Beta*2 -> 2172.9655 | C9: =(W9+B9*Theta-'W-Tax(All-Tax)'!$T$5)/B9 -> 0.29717043 | D9: 0.65329456 | E9: 0 | F9: 10 | G9: 0 | H9: =Size-a -> 10 | I9: =(EXP(alpha*(Tau+OldTau+zeta-2*a*psi))*((EXP(alpha*a*psi)-EXP(alpha*b*psi))^2))/((EXP(alpha*a*psi)-EXP(alpha*(2*OldTau+b*psi)))*(alpha^2)*(psi^2)) -> 5.2512332 | J9: =(EXP(alpha*(zeta+(2*b-a)*psi))*(-1+EXP(alpha*(-1)*Size*psi))*(EXP(alpha*(2*(Tau+OldTau)+a*psi))-EXP(alpha*(2*(Tau+OldTau)+b*psi))))/(((EXP(alpha*a*psi)-EXP(alpha*(2*OldTau+b*psi)))^2)*(alpha^2)*(psi^2)) -> 0.78478212 | K9: =-Beta/alpha -> 180 | L9: =(-EXP(alpha*zeta)*Beta*(-1+EXP(alpha*Size*psi)-Size*alpha*psi))/((alpha^3)*(psi^2)) -> 1690.9246 | M9: =Beta*Theta -> 14.4 | N9: =Beta*Theta -> 14.4 | O9: =kappa -> 90 | P9: =Gamma*Size -> 0 | Q9: =Size*Beta*Phi -> 32.4 | R9: =-(EXP(alpha*a*psi)+EXP(alpha*b*psi)*(-1+Size*psi*alpha))*(Beta*Phi)/((alpha*psi)*(EXP(alpha*a*psi)-EXP(alpha*b*psi))) -> 12.294172 | S9: =(EXP(alpha*(zeta-a*psi))*Beta*Phi*(-EXP(alpha*a*psi)*(-2+(-1)*Size*alpha*psi)+EXP(alpha*b*psi)*(-2+Size*alpha*psi)))/((alpha^3)*(psi^3)) -> 78.836376 | T9: =Tau*Beta -> 117.59302 | U9: =Tau*Beta -> 117.59302 | V9: =Tau -> 0.65329456 | W9: =Profit+Utility -> 3558.5135 | X9: =(2*ij*BRIJ)+2*jj*BRJJ -> 1419.5866 | Y9: =2*(ij*BCCIJ)+(2*jj*BCCJJ)+BCS+jj*BCPTJJ+2*(ij*BCPTIJ)+BCPTII+BCk -> 497.21969 | Z9: =ij*BUTIJ+BUTII -> 2636.1466 | AA9: =Revenue-Cost -> 922.36687 | AB9: =Size -> 10 | AC9: =Welfare/(Size) -> 355.85135 | AD9: =Profit/(Size) -> 92.236687 | AE9: =Utility/(Size) -> 263.61466 | AF9: 308.66096
A10: =C9 -> 0.29717043 | B10: =(I10+J10)*Beta*2 -> 1705.8818 | C10: =(W10+B10*Theta-'W-Tax(All-Tax)'!$T$5)/B10 -> 0.32819765 | D10: 0.86968159 | E10: 0 | F10: 10 | G10: 0 | H10: =Size-a -> 10 | I10: =(EXP(alpha*(Tau+OldTau+zeta-2*a*psi))*((EXP(alpha*a*psi)-EXP(alpha*b*psi))^2))/((EXP(alpha*a*psi)-EXP(alpha*(2*OldTau+b*psi)))*(alpha^2)*(psi^2)) -> 4.2294667 | J10: =(EXP(alpha*(zeta+(2*b-a)*psi))*(-1+EXP(alpha*(-1)*Size*psi))*(EXP(alpha*(2*(Tau+OldTau)+a*psi))-EXP(alpha*(2*(Tau+OldTau)+b*psi))))/(((EXP(alpha*a*psi)-EXP(alpha*(2*OldTau+b*psi)))^2)*(alpha^2)*(psi^2)) -> 0.50909369 | K10: =-Beta/alpha -> 180 | L10: =(-EXP(alpha*zeta)*Beta*(-1+EXP(alpha*Size*psi)-Size*alpha*psi))/((alpha^3)*(psi^2)) -> 1690.9246 | M10: =Beta*Theta -> 53.490678 | N10: =Beta*Theta -> 53.490678 | O10: =kappa -> 90 | P10: =Gamma*Size -> 0 | Q10: =Size*Beta*Phi -> 32.4 | R10: =-(EXP(alpha*a*psi)+EXP(alpha*b*psi)*(-1+Size*psi*alpha))*(Beta*Phi)/((alpha*psi)*(EXP(alpha*a*psi)-EXP(alpha*b*psi))) -> 12.294172 | S10: =(EXP(alpha*(zeta-a*psi))*Beta*Phi*(-EXP(alpha*a*psi)*(-2+(-1)*Size*alpha*psi)+EXP(alpha*b*psi)*(-2+Size*alpha*psi)))/((alpha^3)*(psi^3)) -> 78.836376 | T10: =Tau*Beta -> 156.54269 | U10: =Tau*Beta -> 156.54269 | V10: =Tau -> 0.86968159 | W10: =Profit+Utility -> 3139.5384 | X10: =(2*ij*BRIJ)+2*jj*BRJJ -> 1483.574 | Y10: =2*(ij*BCCIJ)+(2*jj*BCCJJ)+BCS+jj*BCPTJJ+2*(ij*BCPTIJ)+BCPTII+BCk -> 796.26421 | Z10: =ij*BUTIJ+BUTII -> 2452.2286 | AA10: =Revenue-Cost -> 687.30975 | AB10: =Size -> 10 | AC10: =Welfare/(Size) -> 313.95384 | AD10: =Profit/(Size) -> 68.730975 | AE10: =Utility/(Size) -> 245.22286 | AF10: 308.66096
A11: =C10 -> 0.32819765 | B11: =(I11+J11)*Beta*2 -> 1648.5268 | C11: =(W11+B11*Theta-'W-Tax(All-Tax)'!$T$5)/B11 -> 0.32874071 | D11: 0.90060487 | E11: 0 | F11: 10 | G11: 0 | H11: =Size-a -> 10 | I11: =(EXP(alpha*(Tau+OldTau+zeta-2*a*psi))*((EXP(alpha*a*psi)-EXP(alpha*b*psi))^2))/((EXP(alpha*a*psi)-EXP(alpha*(2*OldTau+b*psi)))*(alpha^2)*(psi^2)) -> 4.1006793 | J11: =(EXP(alpha*(zeta+(2*b-a)*psi))*(-1+EXP(alpha*(-1)*Size*psi))*(EXP(alpha*(2*(Tau+OldTau)+a*psi))-EXP(alpha*(2*(Tau+OldTau)+b*psi))))/(((EXP(alpha*a*psi)-EXP(alpha*(2*OldTau+b*psi)))^2)*(alpha^2)*(psi^2)) -> 0.47856187 | K11: =-Beta/alpha -> 180 | L11: =(-EXP(alpha*zeta)*Beta*(-1+EXP(alpha*Size*psi)-Size*alpha*psi))/((alpha^3)*(psi^2)) -> 1690.9246 | M11: =Beta*Theta -> 59.075577 | N11: =Beta*Theta -> 59.075577 | O11: =kappa -> 90 | P11: =Gamma*Size -> 0 | Q11: =Size*Beta*Phi -> 32.4 | R11: =-(EXP(alpha*a*psi)+EXP(alpha*b*psi)*(-1+Size*psi*alpha))*(Beta*Phi)/((alpha*psi)*(EXP(alpha*a*psi)-EXP(alpha*b*psi))) -> 12.294172 | S11: =(EXP(alpha*(zeta-a*psi))*Beta*Phi*(-EXP(alpha*a*psi)*(-2+(-1)*Size*alpha*psi)+EXP(alpha*b*psi)*(-2+Size*alpha*psi)))/((alpha^3)*(psi^3)) -> 78.836376 | T11: =Tau*Beta -> 162.10888 | U11: =Tau*Beta -> 162.10888 | V11: =Tau -> 0.90060487 | W11: =Profit+Utility -> 3087.5049 | X11: =(2*ij*BRIJ)+2*jj*BRJJ -> 1484.6713 | Y11: =2*(ij*BCCIJ)+(2*jj*BCCJJ)+BCS+jj*BCPTJJ+2*(ij*BCPTIJ)+BCPTII+BCk -> 826.21332 | Z11: =ij*BUTIJ+BUTII -> 2429.0469 | AA11: =Revenue-Cost -> 658.45796 | AB11: =Size -> 10 | AC11: =Welfare/(Size) -> 308.75049 | AD11: =Profit/(Size) -> 65.845796 | AE11: =Utility/(Size) -> 242.90469 | AF11: 308.66096
A12: =C11 -> 0.32874071 | B12: =(I12+J12)*Beta*2 -> 1647.5416 | C12: =(W12+B12*Theta-'W-Tax(All-Tax)'!$T$5)/B12 -> 0.32874087 | D12: 0.90114613 | E12: 0 | F12: 10 | G12: 0 | H12: =Size-a -> 10 | I12: =(EXP(alpha*(Tau+OldTau+zeta-2*a*psi))*((EXP(alpha*a*psi)-EXP(alpha*b*psi))^2))/((EXP(alpha*a*psi)-EXP(alpha*(2*OldTau+b*psi)))*(alpha^2)*(psi^2)) -> 4.0984604 | J12: =(EXP(alpha*(zeta+(2*b-a)*psi))*(-1+EXP(alpha*(-1)*Size*psi))*(EXP(alpha*(2*(Tau+OldTau)+a*psi))-EXP(alpha*(2*(Tau+OldTau)+b*psi))))/(((EXP(alpha*a*psi)-EXP(alpha*(2*OldTau+b*psi)))^2)*(alpha^2)*(psi^2)) -> 0.47804411 | K12: =-Beta/alpha -> 180 | L12: =(-EXP(alpha*zeta)*Beta*(-1+EXP(alpha*Size*psi)-Size*alpha*psi))/((alpha^3)*(psi^2)) -> 1690.9246 | M12: =Beta*Theta -> 59.173327 | N12: =Beta*Theta -> 59.173327 | O12: =kappa -> 90 | P12: =Gamma*Size -> 0 | Q12: =Size*Beta*Phi -> 32.4 | R12: =-(EXP(alpha*a*psi)+EXP(alpha*b*psi)*(-1+Size*psi*alpha))*(Beta*Phi)/((alpha*psi)*(EXP(alpha*a*psi)-EXP(alpha*b*psi))) -> 12.294172 | S12: =(EXP(alpha*(zeta-a*psi))*Beta*Phi*(-EXP(alpha*a*psi)*(-2+(-1)*Size*alpha*psi)+EXP(alpha*b*psi)*(-2+Size*alpha*psi)))/((alpha^3)*(psi^3)) -> 78.836376 | T12: =Tau*Beta -> 162.2063 | U12: =Tau*Beta -> 162.2063 | V12: =Tau -> 0.90114613 | W12: =Profit+Utility -> 3086.6099 | X12: =(2*ij*BRIJ)+2*jj*BRJJ -> 1484.6757 | Y12: =2*(ij*BCCIJ)+(2*jj*BCCJJ)+BCS+jj*BCPTJJ+2*(ij*BCPTIJ)+BCPTII+BCk -> 826.71335 | Z12: =ij*BUTIJ+BUTII -> 2428.6475 | AA12: =Revenue-Cost -> 657.96239 | AB12: =Size -> 10 | AC12: =Welfare/(Size) -> 308.66099 | AD12: =Profit/(Size) -> 65.796239 | AE12: =Utility/(Size) -> 242.86475 | AF12: 308.66096
A14: 0.08 | B14: =(I14+J14)*Beta*2 -> 2322.0114 | C14: =(W14+B14*Theta-'W-Tax(All-Tax)'!$T$8)/B14 -> 0.27605072 | D14: 0.70015477 | E14: 0 | F14: 100 | G14: 0 | H14: =Size-a -> 100 | I14: =(EXP(alpha*(Tau+OldTau+zeta-2*a*psi))*((EXP(alpha*a*psi)-EXP(alpha*b*psi))^2))/((EXP(alpha*a*psi)-EXP(alpha*(2*OldTau+b*psi)))*(alpha^2)*(psi^2)) -> 6.4500307 | J14: =(EXP(alpha*(zeta+(2*b-a)*psi))*(-1+EXP(alpha*(-1)*Size*psi))*(EXP(alpha*(2*(Tau+OldTau)+a*psi))-EXP(alpha*(2*(Tau+OldTau)+b*psi))))/(((EXP(alpha*a*psi)-EXP(alpha*(2*OldTau+b*psi)))^2)*(alpha^2)*(psi^2)) -> 9.7965089e-07 | K14: =-Beta/alpha -> 180 | L14: =(-EXP(alpha*zeta)*Beta*(-1+EXP(alpha*Size*psi)-Size*alpha*psi))/((alpha^3)*(psi^2)) -> 32736.769 | M14: =Beta*Theta -> 14.4 | N14: =Beta*Theta -> 14.4 | O14: =kappa -> 90 | P14: =Gamma*Size -> 0 | Q14: =Size*Beta*Phi -> 324 | R14: =-(EXP(alpha*a*psi)+EXP(alpha*b*psi)*(-1+Size*psi*alpha))*(Beta*Phi)/((alpha*psi)*(EXP(alpha*a*psi)-EXP(alpha*b*psi))) -> 21.599901 | S14: =(EXP(alpha*(zeta-a*psi))*Beta*Phi*(-EXP(alpha*a*psi)*(-2+(-1)*Size*alpha*psi)+EXP(alpha*b*psi)*(-2+Size*alpha*psi)))/((alpha^3)*(psi^3)) -> 3647.8128 | T14: =Tau*Beta -> 126.02786 | U14: =Tau*Beta -> 126.02786 | V14: =Tau -> 0.70015477 | W14: =Profit+Utility -> 31321.328 | X14: =(2*ij*BRIJ)+2*jj*BRJJ -> 1625.7674 | Y14: =2*(ij*BCCIJ)+(2*jj*BCCJJ)+BCS+jj*BCPTJJ+2*(ij*BCPTIJ)+BCPTII+BCk -> 4202.2141 | Z14: =ij*BUTIJ+BUTII -> 33897.775 | AA14: =Revenue-Cost -> -2576.4467 | AB14: =Size -> 100 | AC14: =Welfare/(Size) -> 313.21328 | AD14: =Profit/(Size) -> -25.764467 | AE14: =Utility/(Size) -> 338.97775 | AF14: 308.66096
A15: =C14 -> 0.27605072 | B15: =(I15+J15)*Beta*2 -> 1908.9209 | C15: =(W15+B15*Theta-'W-Tax(All-Tax)'!$T$8)/B15 -> 0.29793821 | D15: 0.89605044 | E15: 0 | F15: 100 | G15: 0 | H15: =Size-a -> 100 | I15: =(EXP(alpha*(Tau+OldTau+zeta-2*a*psi))*((EXP(alpha*a*psi)-EXP(alpha*b*psi))^2))/((EXP(alpha*a*psi)-EXP(alpha*(2*OldTau+b*psi)))*(alpha^2)*(psi^2)) -> 5.3025574 | J15: =(EXP(alpha*(zeta+(2*b-a)*psi))*(-1+EXP(alpha*(-1)*Size*psi))*(EXP(alpha*(2*(Tau+OldTau)+a*psi))-EXP(alpha*(2*(Tau+OldTau)+b*psi))))/(((EXP(alpha*a*psi)-EXP(alpha*(2*OldTau+b*psi)))^2)*(alpha^2)*(psi^2)) -> 6.6209227e-07 | K15: =-Beta/alpha -> 180 | L15: =(-EXP(alpha*zeta)*Beta*(-1+EXP(alpha*Size*psi)-Size*alpha*psi))/((alpha^3)*(psi^2)) -> 32736.769 | M15: =Beta*Theta -> 49.689129 | N15: =Beta*Theta -> 49.689129 | O15: =kappa -> 90 | P15: =Gamma*Size -> 0 | Q15: =Size*Beta*Phi -> 324 | R15: =-(EXP(alpha*a*psi)+EXP(alpha*b*psi)*(-1+Size*psi*alpha))*(Beta*Phi)/((alpha*psi)*(EXP(alpha*a*psi)-EXP(alpha*b*psi))) -> 21.599901 | S15: =(EXP(alpha*(zeta-a*psi))*Beta*Phi*(-EXP(alpha*a*psi)*(-2+(-1)*Size*alpha*psi)+EXP(alpha*b*psi)*(-2+Size*alpha*psi)))/((alpha^3)*(psi^3)) -> 3647.8128 | T15: =Tau*Beta -> 161.28908 | U15: =Tau*Beta -> 161.28908 | V15: =Tau -> 0.89605044 | W15: =Profit+Utility -> 30907.878 | X15: =(2*ij*BRIJ)+2*jj*BRJJ -> 1710.4894 | Y15: =2*(ij*BCCIJ)+(2*jj*BCCJJ)+BCS+jj*BCPTJJ+2*(ij*BCPTIJ)+BCPTII+BCk -> 4493.8414 | Z15: =ij*BUTIJ+BUTII -> 33691.23 | AA15: =Revenue-Cost -> -2783.352 | AB15: =Size -> 100 | AC15: =Welfare/(Size) -> 309.07878 | AD15: =Profit/(Size) -> -27.83352 | AE15: =Utility/(Size) -> 336.9123 | AF15: 308.66096
A16: =C15 -> 0.29793821 | B16: =(I16+J16)*Beta*2 -> 1867.3263 | C16: =(W16+B16*Theta-'W-Tax(All-Tax)'!$T$8)/B16 -> 0.29818128 | D16: 0.91808092 | E16: 0 | F16: 100 | G16: 0 | H16: =Size-a -> 100 | I16: =(EXP(alpha*(Tau+OldTau+zeta-2*a*psi))*((EXP(alpha*a*psi)-EXP(alpha*b*psi))^2))/((EXP(alpha*a*psi)-EXP(alpha*(2*OldTau+b*psi)))*(alpha^2)*(psi^2)) -> 5.1870169 | J16: =(EXP(alpha*(zeta+(2*b-a)*psi))*(-1+EXP(alpha*(-1)*Size*psi))*(EXP(alpha*(2*(Tau+OldTau)+a*psi))-EXP(alpha*(2*(Tau+OldTau)+b*psi))))/(((EXP(alpha*a*psi)-EXP(alpha*(2*OldTau+b*psi)))^2)*(alpha^2)*(psi^2)) -> 6.335532e-07 | K16: =-Beta/alpha -> 180 | L16: =(-EXP(alpha*zeta)*Beta*(-1+EXP(alpha*Size*psi)-Size*alpha*psi))/((alpha^3)*(psi^2)) -> 32736.769 | M16: =Beta*Theta -> 53.628877 | N16: =Beta*Theta -> 53.628877 | O16: =kappa -> 90 | P16: =Gamma*Size -> 0 | Q16: =Size*Beta*Phi -> 324 | R16: =-(EXP(alpha*a*psi)+EXP(alpha*b*psi)*(-1+Size*psi*alpha))*(Beta*Phi)/((alpha*psi)*(EXP(alpha*a*psi)-EXP(alpha*b*psi))) -> 21.599901 | S16: =(EXP(alpha*(zeta-a*psi))*Beta*Phi*(-EXP(alpha*a*psi)*(-2+(-1)*Size*alpha*psi)+EXP(alpha*b*psi)*(-2+Size*alpha*psi)))/((alpha^3)*(psi^3)) -> 3647.8128 | T16: =Tau*Beta -> 165.25457 | U16: =Tau*Beta -> 165.25457 | V16: =Tau -> 0.91808092 | W16: =Profit+Utility -> 30866.55 | X16: =(2*ij*BRIJ)+2*jj*BRJJ -> 1714.3566 | Y16: =2*(ij*BCCIJ)+(2*jj*BCCJJ)+BCS+jj*BCPTJJ+2*(ij*BCPTIJ)+BCPTII+BCk -> 4518.239 | Z16: =ij*BUTIJ+BUTII -> 33670.432 | AA16: =Revenue-Cost -> -2803.8823 | AB16: =Size -> 100 | AC16: =Welfare/(Size) -> 308.6655 | AD16: =Profit/(Size) -> -28.038823 | AE16: =Utility/(Size) -> 336.70432 | AF16: 308.66096
A17: =C16 -> 0.29818128 | B17: =(I17+J17)*Beta*2 -> 1866.8782 | C17: =(W17+B17*Theta-'W-Tax(All-Tax)'!$T$8)/B17 -> 0.29818128 | D17: 0.91832091 | E17: 0 | F17: 100 | G17: 0 | H17: =Size-a -> 100 | I17: =(EXP(alpha*(Tau+OldTau+zeta-2*a*psi))*((EXP(alpha*a*psi)-EXP(alpha*b*psi))^2))/((EXP(alpha*a*psi)-EXP(alpha*(2*OldTau+b*psi)))*(alpha^2)*(psi^2)) -> 5.1857721 | J17: =(EXP(alpha*(zeta+(2*b-a)*psi))*(-1+EXP(alpha*(-1)*Size*psi))*(EXP(alpha*(2*(Tau+OldTau)+a*psi))-EXP(alpha*(2*(Tau+OldTau)+b*psi))))/(((EXP(alpha*a*psi)-EXP(alpha*(2*OldTau+b*psi)))^2)*(alpha^2)*(psi^2)) -> 6.3324917e-07 | K17: =-Beta/alpha -> 180 | L17: =(-EXP(alpha*zeta)*Beta*(-1+EXP(alpha*Size*psi)-Size*alpha*psi))/((alpha^3)*(psi^2)) -> 32736.769 | M17: =Beta*Theta -> 53.672631 | N17: =Beta*Theta -> 53.672631 | O17: =kappa -> 90 | P17: =Gamma*Size -> 0 | Q17: =Size*Beta*Phi -> 324 | R17: =-(EXP(alpha*a*psi)+EXP(alpha*b*psi)*(-1+Size*psi*alpha))*(Beta*Phi)/((alpha*psi)*(EXP(alpha*a*psi)-EXP(alpha*b*psi))) -> 21.599901 | S17: =(EXP(alpha*(zeta-a*psi))*Beta*Phi*(-EXP(alpha*a*psi)*(-2+(-1)*Size*alpha*psi)+EXP(alpha*b*psi)*(-2+Size*alpha*psi)))/((alpha^3)*(psi^3)) -> 3647.8128 | T17: =Tau*Beta -> 165.29776 | U17: =Tau*Beta -> 165.29776 | V17: =Tau -> 0.91832091 | W17: =Profit+Utility -> 30866.096 | X17: =(2*ij*BRIJ)+2*jj*BRJJ -> 1714.3933 | Y17: =2*(ij*BCCIJ)+(2*jj*BCCJJ)+BCS+jj*BCPTJJ+2*(ij*BCPTIJ)+BCPTII+BCk -> 4518.5055 | Z17: =ij*BUTIJ+BUTII -> 33670.208 | AA17: =Revenue-Cost -> -2804.1122 | AB17: =Size -> 100 | AC17: =Welfare/(Size) -> 308.66096 | AD17: =Profit/(Size) -> -28.041122 | AE17: =Utility/(Size) -> 336.70208 | AF17: 308.66096
A18: =C17 -> 0.29818128 | B18: =(I18+J18)*Beta*2 -> 1866.8782 | C18: =(W18+B18*Theta-'W-Tax(All-Tax)'!$T$8)/B18 -> 0.29818128 | D18: 0.91832091 | E18: 0 | F18: 100 | G18: 0 | H18: =Size-a -> 100 | I18: =(EXP(alpha*(Tau+OldTau+zeta-2*a*psi))*((EXP(alpha*a*psi)-EXP(alpha*b*psi))^2))/((EXP(alpha*a*psi)-EXP(alpha*(2*OldTau+b*psi)))*(alpha^2)*(psi^2)) -> 5.1857721 | J18: =(EXP(alpha*(zeta+(2*b-a)*psi))*(-1+EXP(alpha*(-1)*Size*psi))*(EXP(alpha*(2*(Tau+OldTau)+a*psi))-EXP(alpha*(2*(Tau+OldTau)+b*psi))))/(((EXP(alpha*a*psi)-EXP(alpha*(2*OldTau+b*psi)))^2)*(alpha^2)*(psi^2)) -> 6.3324917e-07 | K18: =-Beta/alpha -> 180 | L18: =(-EXP(alpha*zeta)*Beta*(-1+EXP(alpha*Size*psi)-Size*alpha*psi))/((alpha^3)*(psi^2)) -> 32736.769 | M18: =Beta*Theta -> 53.67263 | N18: =Beta*Theta -> 53.67263 | O18: =kappa -> 90 | P18: =Gamma*Size -> 0 | Q18: =Size*Beta*Phi -> 324 | R18: =-(EXP(alpha*a*psi)+EXP(alpha*b*psi)*(-1+Size*psi*alpha))*(Beta*Phi)/((alpha*psi)*(EXP(alpha*a*psi)-EXP(alpha*b*psi))) -> 21.599901 | S18: =(EXP(alpha*(zeta-a*psi))*Beta*Phi*(-EXP(alpha*a*psi)*(-2+(-1)*Size*alpha*psi)+EXP(alpha*b*psi)*(-2+Size*alpha*psi)))/((alpha^3)*(psi^3)) -> 3647.8128 | T18: =Tau*Beta -> 165.29776 | U18: =Tau*Beta -> 165.29776 | V18: =Tau -> 0.91832091 | W18: =Profit+Utility -> 30866.096 | X18: =(2*ij*BRIJ)+2*jj*BRJJ -> 1714.3933 | Y18: =2*(ij*BCCIJ)+(2*jj*BCCJJ)+BCS+jj*BCPTJJ+2*(ij*BCPTIJ)+BCPTII+BCk -> 4518.5055 | Z18: =ij*BUTIJ+BUTII -> 33670.208 | AA18: =Revenue-Cost -> -2804.1122 | AB18: =Size -> 100 | AC18: =Welfare/(Size) -> 308.66096 | AD18: =Profit/(Size) -> -28.041122 | AE18: =Utility/(Size) -> 336.70208 | AF18: 308.66096
A20: 0.08 | B20: =(I20+J20)*Beta*2 -> 2322.369 | C20: =(W20+B20*Theta-'W-Tax(All-Tax)'!$T$11)/B20 -> 0.27602066 | D20: 0.70000093 | E20: 0 | F20: 1000 | G20: 0 | H20: =Size-a -> 1000 | I20: =(EXP(alpha*(Tau+OldTau+zeta-2*a*psi))*((EXP(alpha*a*psi)-EXP(alpha*b*psi))^2))/((EXP(alpha*a*psi)-EXP(alpha*(2*OldTau+b*psi)))*(alpha^2)*(psi^2)) -> 6.451025 | J20: =(EXP(alpha*(zeta+(2*b-a)*psi))*(-1+EXP(alpha*(-1)*Size*psi))*(EXP(alpha*(2*(Tau+OldTau)+a*psi))-EXP(alpha*(2*(Tau+OldTau)+b*psi))))/(((EXP(alpha*a*psi)-EXP(alpha*(2*OldTau+b*psi)))^2)*(alpha^2)*(psi^2)) -> 2.2985285e-65 | K20: =-Beta/alpha -> 180 | L20: =(-EXP(alpha*zeta)*Beta*(-1+EXP(alpha*Size*psi)-Size*alpha*psi))/((alpha^3)*(psi^2)) -> 348412.75 | M20: =Beta*Theta -> 14.4 | N20: =Beta*Theta -> 14.4 | O20: =kappa -> 90 | P20: =Gamma*Size -> 0 | Q20: =Size*Beta*Phi -> 3240 | R20: =-(EXP(alpha*a*psi)+EXP(alpha*b*psi)*(-1+Size*psi*alpha))*(Beta*Phi)/((alpha*psi)*(EXP(alpha*a*psi)-EXP(alpha*b*psi))) -> 21.6 | S20: =(EXP(alpha*(zeta-a*psi))*Beta*Phi*(-EXP(alpha*a*psi)*(-2+(-1)*Size*alpha*psi)+EXP(alpha*b*psi)*(-2+Size*alpha*psi)))/((alpha^3)*(psi^3)) -> 41528.929 | T20: =Tau*Beta -> 126.00017 | U20: =Tau*Beta -> 126.00017 | V20: =Tau -> 0.70000093 | W20: =Profit+Utility -> 309116.19 | X20: =(2*ij*BRIJ)+2*jj*BRJJ -> 1625.6605 | Y20: =2*(ij*BCCIJ)+(2*jj*BCCJJ)+BCS+jj*BCPTJJ+2*(ij*BCPTIJ)+BCPTII+BCk -> 42083.403 | Z20: =ij*BUTIJ+BUTII -> 349573.94 | AA20: =Revenue-Cost -> -40457.743 | AB20: =Size -> 1000 | AC20: =Welfare/(Size) -> 309.11619 | AD20: =Profit/(Size) -> -40.457743 | AE20: =Utility/(Size) -> 349.57394 | AF20: 308.66096
A21: =C20 -> 0.27602066 | B21: =(I21+J21)*Beta*2 -> 1906.0267 | C21: =(W21+B21*Theta-'W-Tax(All-Tax)'!$T$11)/B21 -> 0.29797047 | D21: 0.8975679 | E21: 0 | F21: 1000 | G21: 0 | H21: =Size-a -> 1000 | I21: =(EXP(alpha*(Tau+OldTau+zeta-2*a*psi))*((EXP(alpha*a*psi)-EXP(alpha*b*psi))^2))/((EXP(alpha*a*psi)-EXP(alpha*(2*OldTau+b*psi)))*(alpha^2)*(psi^2)) -> 5.2945187 | J21: =(EXP(alpha*(zeta+(2*b-a)*psi))*(-1+EXP(alpha*(-1)*Size*psi))*(EXP(alpha*(2*(Tau+OldTau)+a*psi))-EXP(alpha*(2*(Tau+OldTau)+b*psi))))/(((EXP(alpha*a*psi)-EXP(alpha*(2*OldTau+b*psi)))^2)*(alpha^2)*(psi^2)) -> 1.5482654e-65 | K21: =-Beta/alpha -> 180 | L21: =(-EXP(alpha*zeta)*Beta*(-1+EXP(alpha*Size*psi)-Size*alpha*psi))/((alpha^3)*(psi^2)) -> 348412.75 | M21: =Beta*Theta -> 49.683719 | N21: =Beta*Theta -> 49.683719 | O21: =kappa -> 90 | P21: =Gamma*Size -> 0 | Q21: =Size*Beta*Phi -> 3240 | R21: =-(EXP(alpha*a*psi)+EXP(alpha*b*psi)*(-1+Size*psi*alpha))*(Beta*Phi)/((alpha*psi)*(EXP(alpha*a*psi)-EXP(alpha*b*psi))) -> 21.6 | S21: =(EXP(alpha*(zeta-a*psi))*Beta*Phi*(-EXP(alpha*a*psi)*(-2+(-1)*Size*alpha*psi)+EXP(alpha*b*psi)*(-2+Size*alpha*psi)))/((alpha^3)*(psi^3)) -> 41528.929 | T21: =Tau*Beta -> 161.56222 | U21: =Tau*Beta -> 161.56222 | V21: =Tau -> 0.8975679 | W21: =Profit+Utility -> 308702.8 | X21: =(2*ij*BRIJ)+2*jj*BRJJ -> 1710.7884 | Y21: =2*(ij*BCCIJ)+(2*jj*BCCJJ)+BCS+jj*BCPTJJ+2*(ij*BCPTIJ)+BCPTII+BCk -> 42373.755 | Z21: =ij*BUTIJ+BUTII -> 349365.77 | AA21: =Revenue-Cost -> -40662.967 | AB21: =Size -> 1000 | AC21: =Welfare/(Size) -> 308.7028 | AD21: =Profit/(Size) -> -40.662967 | AE21: =Utility/(Size) -> 349.36577 | AF21: 308.66096
A22: =C21 -> 0.29797047 | B22: =(I22+J22)*Beta*2 -> 2.2295919e-12 | C22: =(W22+B22*Theta-'W-Tax(All-Tax)'!$T$11)/B22 -> -837435263089555 | D22: 35.279547 | E22: 0 | F22: 1000 | G22: 0 | H22: =Size-a -> 1000 | I22: =(EXP(alpha*(Tau+OldTau+zeta-2*a*psi))*((EXP(alpha*a*psi)-EXP(alpha*b*psi))^2))/((EXP(alpha*a*psi)-EXP(alpha*(2*OldTau+b*psi)))*(alpha^2)*(psi^2)) -> 6.1933108e-15 | J22: =(EXP(alpha*(zeta+(2*b-a)*psi))*(-1+EXP(alpha*(-1)*Size*psi))*(EXP(alpha*(2*(Tau+OldTau)+a*psi))-EXP(alpha*(2*(Tau+OldTau)+b*psi))))/(((EXP(alpha*a*psi)-EXP(alpha*(2*OldTau+b*psi)))^2)*(alpha^2)*(psi^2)) -> 2.1185475e-95 | K22: =-Beta/alpha -> 180 | L22: =(-EXP(alpha*zeta)*Beta*(-1+EXP(alpha*Size*psi)-Size*alpha*psi))/((alpha^3)*(psi^2)) -> 348412.75 | M22: =Beta*Theta -> 53.634685 | N22: =Beta*Theta -> 53.634685 | O22: =kappa -> 90 | P22: =Gamma*Size -> 0 | Q22: =Size*Beta*Phi -> 3240 | R22: =-(EXP(alpha*a*psi)+EXP(alpha*b*psi)*(-1+Size*psi*alpha))*(Beta*Phi)/((alpha*psi)*(EXP(alpha*a*psi)-EXP(alpha*b*psi))) -> 21.6 | S22: =(EXP(alpha*(zeta-a*psi))*Beta*Phi*(-EXP(alpha*a*psi)*(-2+(-1)*Size*alpha*psi)+EXP(alpha*b*psi)*(-2+Size*alpha*psi)))/((alpha^3)*(psi^3)) -> 41528.929 | T22: =Tau*Beta -> 6350.3184 | U22: =Tau*Beta -> 6350.3184 | V22: =Tau -> 35.279547 | W22: =Profit+Utility -> 306793.82 | X22: =(2*ij*BRIJ)+2*jj*BRJJ -> 7.8658991e-11 | Y22: =2*(ij*BCCIJ)+(2*jj*BCCJJ)+BCS+jj*BCPTJJ+2*(ij*BCPTIJ)+BCPTII+BCk -> 41618.929 | Z22: =ij*BUTIJ+BUTII -> 348412.75 | AA22: =Revenue-Cost -> -41618.929 | AB22: =Size -> 1000 | AC22: =Welfare/(Size) -> 306.79382 | AD22: =Profit/(Size) -> -41.618929 | AE22: =Utility/(Size) -> 348.41275 | AF22: 308.66096
A23: =C22 -> -837435263089555 | B23: =(I23+J23)*Beta*2 -> #NUM! | C23: =(W23+B23*Theta-'W-Tax(All-Tax)'!$T$11)/B23 -> #NUM! | D23: -427.71441 | E23: 0 | F23: 1000 | G23: 0 | H23: =Size-a -> 1000 | I23: =(EXP(alpha*(Tau+OldTau+zeta-2*a*psi))*((EXP(alpha*a*psi)-EXP(alpha*b*psi))^2))/((EXP(alpha*a*psi)-EXP(alpha*(2*OldTau+b*psi)))*(alpha^2)*(psi^2)) -> 7.3729667e+186 | J23: =(EXP(alpha*(zeta+(2*b-a)*psi))*(-1+EXP(alpha*(-1)*Size*psi))*(EXP(alpha*(2*(Tau+OldTau)+a*psi))-EXP(alpha*(2*(Tau+OldTau)+b*psi))))/(((EXP(alpha*a*psi)-EXP(alpha*(2*OldTau+b*psi)))^2)*(alpha^2)*(psi^2)) -> #NUM! | K23: =-Beta/alpha -> 180 | L23: =(-EXP(alpha*zeta)*Beta*(-1+EXP(alpha*Size*psi)-Size*alpha*psi))/((alpha^3)*(psi^2)) -> 348412.75 | M23: =Beta*Theta -> -1.5073835e+17 | N23: =Beta*Theta -> -1.5073835e+17 | O23: =kappa -> 90 | P23: =Gamma*Size -> 0 | Q23: =Size*Beta*Phi -> 3240 | R23: =-(EXP(alpha*a*psi)+EXP(alpha*b*psi)*(-1+Size*psi*alpha))*(Beta*Phi)/((alpha*psi)*(EXP(alpha*a*psi)-EXP(alpha*b*psi))) -> 21.6 | S23: =(EXP(alpha*(zeta-a*psi))*Beta*Phi*(-EXP(alpha*a*psi)*(-2+(-1)*Size*alpha*psi)+EXP(alpha*b*psi)*(-2+Size*alpha*psi)))/((alpha^3)*(psi^3)) -> 41528.929 | T23: =Tau*Beta -> -76988.593 | U23: =Tau*Beta -> -76988.593 | V23: =Tau -> -427.71441 | W23: =Profit+Utility -> #NUM! | X23: =(2*ij*BRIJ)+2*jj*BRJJ -> #NUM! | Y23: =2*(ij*BCCIJ)+(2*jj*BCCJJ)+BCS+jj*BCPTJJ+2*(ij*BCPTIJ)+BCPTII+BCk -> #NUM! | Z23: =ij*BUTIJ+BUTII -> 1.327134e+189 | AA23: =Revenue-Cost -> #NUM! | AB23: =Size -> 1000 | AC23: =Welfare/(Size) -> #NUM! | AD23: =Profit/(Size) -> #NUM! | AE23: =Utility/(Size) -> 1.327134e+186 | AF23: 308.66096
A24: =C23 -> #NUM! | B24: =(I24+J24)*Beta*2 -> 2320.841 | C24: =(W24+B24*Theta-'W-Tax(All-Tax)'!$T$11)/B24 -> #NUM! | D24: 0.70065908 | E24: 0 | F24: 1000 | G24: 0 | H24: =Size-a -> 1000 | I24: =(EXP(alpha*(Tau+OldTau+zeta-2*a*psi))*((EXP(alpha*a*psi)-EXP(alpha*b*psi))^2))/((EXP(alpha*a*psi)-EXP(alpha*(2*OldTau+b*psi)))*(alpha^2)*(psi^2)) -> 6.4467807 | J24: =(EXP(alpha*(zeta+(2*b-a)*psi))*(-1+EXP(alpha*(-1)*Size*psi))*(EXP(alpha*(2*(Tau+OldTau)+a*psi))-EXP(alpha*(2*(Tau+OldTau)+b*psi))))/(((EXP(alpha*a*psi)-EXP(alpha*(2*OldTau+b*psi)))^2)*(alpha^2)*(psi^2)) -> 2.295505e-65 | K24: =-Beta/alpha -> 180 | L24: =(-EXP(alpha*zeta)*Beta*(-1+EXP(alpha*Size*psi)-Size*alpha*psi))/((alpha^3)*(psi^2)) -> 348412.75 | M24: =Beta*Theta -> #NUM! | N24: =Beta*Theta -> #NUM! | O24: =kappa -> 90 | P24: =Gamma*Size -> 0 | Q24: =Size*Beta*Phi -> 3240 | R24: =-(EXP(alpha*a*psi)+EXP(alpha*b*psi)*(-1+Size*psi*alpha))*(Beta*Phi)/((alpha*psi)*(EXP(alpha*a*psi)-EXP(alpha*b*psi))) -> 21.6 | S24: =(EXP(alpha*(zeta-a*psi))*Beta*Phi*(-EXP(alpha*a*psi)*(-2+(-1)*Size*alpha*psi)+EXP(alpha*b*psi)*(-2+Size*alpha*psi)))/((alpha^3)*(psi^3)) -> 41528.929 | T24: =Tau*Beta -> 126.11864 | U24: =Tau*Beta -> 126.11864 | V24: =Tau -> 0.70065908 | W24: =Profit+Utility -> #NUM! | X24: =(2*ij*BRIJ)+2*jj*BRJJ -> 1626.1184 | Y24: =2*(ij*BCCIJ)+(2*jj*BCCJJ)+BCS+jj*BCPTJJ+2*(ij*BCPTIJ)+BCPTII+BCk -> #NUM! | Z24: =ij*BUTIJ+BUTII -> 349573.17 | AA24: =Revenue-Cost -> #NUM! | AB24: =Size -> 1000 | AC24: =Welfare/(Size) -> #NUM! | AD24: =Profit/(Size) -> #NUM! | AE24: =Utility/(Size) -> 349.57317 | AF24: 308.66096
D26: 0
D27: -58.799244
D28: -57.799244
D29: 0.70065908

Sheet W-Tax(All-Toll)-NONC
A1: Tau | B1: OldTau | C1: Size | D1: a | E1: b | F1: ij | G1: jj | H1: BUTIJ | I1: BUTII | J1: BCCIJ | K1: BCCJJ | L1: BCk | M1: BCS | N1: BCPTJJ | O1: BCPTIJ | P1: BCPTII | Q1: BRIJ | R1: BRJJ | S1: Toll | T1: Welfare | U1: Revenue | V1: Cost | W1: Utility | X1: Profit | Y1: Size2 | Z1: W/Size | AA1: ∏/Size | AB1: U/Size
A2: 0 | B2: ='W-Toll(All-Toll)-NONC'!A2 -> 0.58886934 | C2: 1 | D2: 0 | E2: =Size-a -> 1 | F2: =(EXP(alpha*(Tau+OldTau+zeta-2*a*psi))*((EXP(alpha*a*psi)-EXP(alpha*b*psi))^2))/((EXP(alpha*a*psi)-EXP(alpha*(2*OldTau+b*psi)))*(alpha^2)*(psi^2)) -> 0.19032798 | G2: =(EXP(alpha*(zeta+(2*b-a)*psi))*(-1+EXP(alpha*(-1)*Size*psi))*(EXP(alpha*(2*(Tau+OldTau)+a*psi))-EXP(alpha*(2*(Tau+OldTau)+b*psi))))/(((EXP(alpha*a*psi)-EXP(alpha*(2*OldTau+b*psi)))^2)*(alpha^2)*(psi^2)) -> 0.12370103 | H2: =-Beta/alpha -> 180 | I2: =(-EXP(alpha*zeta)*Beta*(-1+EXP(alpha*Size*psi)-Size*alpha*psi))/((alpha^3)*(psi^2)) -> 25.038896 | J2: =Beta*Theta -> 14.4 | K2: =Beta*Theta -> 14.4 | L2: =kappa -> 90 | M2: =Gamma*Size -> 0 | N2: =Size*Beta*Phi -> 3.24 | O2: =-(EXP(alpha*a*psi)+EXP(alpha*b*psi)*(-1+Size*psi*alpha))*(Beta*Phi)/((alpha*psi)*(EXP(alpha*a*psi)-EXP(alpha*b*psi))) -> 1.5795152 | P2: =(EXP(alpha*(zeta-a*psi))*Beta*Phi*(-EXP(alpha*a*psi)*(-2+(-1)*Size*alpha*psi)+EXP(alpha*b*psi)*(-2+Size*alpha*psi)))/((alpha^3)*(psi^3)) -> 0.14651555 | Q2: =Tau*Beta -> 0 | R2: =Tau*Beta -> 0 | S2: =Tau -> 0 | T2: =Profit+Utility -> -40.894662 | U2: =(2*ij*BRIJ)+2*jj*BRJJ -> 0 | V2: =2*(ij*BCCIJ)+(2*jj*BCCJJ)+BCS+jj*BCPTJJ+2*(ij*BCPTIJ)+BCPTII+BCk -> 100.19259 | W2: =ij*BUTIJ+BUTII -> 59.297932 | X2: =Revenue-Cost -> -100.19259 | Y2: =Size -> 1 | Z2: =Welfare/(Size) -> -40.894662 | AA2: =Profit/(Size) -> -100.19259 | AB2: =Utility/(Size) -> 59.297932
A3: 0 | B3: ='W-Toll(All-Toll)-NONC'!A3 -> 0.5974306 | C3: 2 | D3: 0 | E3: =Size-a -> 2 | F3: =(EXP(alpha*(Tau+OldTau+zeta-2*a*psi))*((EXP(alpha*a*psi)-EXP(alpha*b*psi))^2))/((EXP(alpha*a*psi)-EXP(alpha*(2*OldTau+b*psi)))*(alpha^2)*(psi^2)) -> 0.61898233 | G3: =(EXP(alpha*(zeta+(2*b-a)*psi))*(-1+EXP(alpha*(-1)*Size*psi))*(EXP(alpha*(2*(Tau+OldTau)+a*psi))-EXP(alpha*(2*(Tau+OldTau)+b*psi))))/(((EXP(alpha*a*psi)-EXP(alpha*(2*OldTau+b*psi)))^2)*(alpha^2)*(psi^2)) -> 0.32525498 | H3: =-Beta/alpha -> 180 | I3: =(-EXP(alpha*zeta)*Beta*(-1+EXP(alpha*Size*psi)-Size*alpha*psi))/((alpha^3)*(psi^2)) -> 95.446904 | J3: =Beta*Theta -> 14.4 | K3: =Beta*Theta -> 14.4 | L3: =kappa -> 90 | M3: =Gamma*Size -> 0 | N3: =Size*Beta*Phi -> 6.48 | O3: =-(EXP(alpha*a*psi)+EXP(alpha*b*psi)*(-1+Size*psi*alpha))*(Beta*Phi)/((alpha*psi)*(EXP(alpha*a*psi)-EXP(alpha*b*psi))) -> 3.0782425 | P3: =(EXP(alpha*(zeta-a*psi))*Beta*Phi*(-EXP(alpha*a*psi)*(-2+(-1)*Size*alpha*psi)+EXP(alpha*b*psi)*(-2+Size*alpha*psi)))/((alpha^3)*(psi^3)) -> 1.0892667 | Q3: =Tau*Beta -> 0 | R3: =Tau*Beta -> 0 | S3: =Tau -> 0 | T3: =Profit+Utility -> 82.662014 | U3: =(2*ij*BRIJ)+2*jj*BRJJ -> 0 | V3: =2*(ij*BCCIJ)+(2*jj*BCCJJ)+BCS+jj*BCPTJJ+2*(ij*BCPTIJ)+BCPTII+BCk -> 124.20171 | W3: =ij*BUTIJ+BUTII -> 206.86372 | X3: =Revenue-Cost -> -124.20171 | Y3: =Size -> 2 | Z3: =Welfare/(Size) -> 41.331007 | AA3: =Profit/(Size) -> -62.100855 | AB3: =Utility/(Size) -> 103.43186
A4: 0 | B4: ='W-Toll(All-Toll)-NONC'!A4 -> 0.62076551 | C4: 5 | D4: 0 | E4: =Size-a -> 5 | F4: =(EXP(alpha*(Tau+OldTau+zeta-2*a*psi))*((EXP(alpha*a*psi)-EXP(alpha*b*psi))^2))/((EXP(alpha*a*psi)-EXP(alpha*(2*OldTau+b*psi)))*(alpha^2)*(psi^2)) -> 2.2513117 | G4: =(EXP(alpha*(zeta+(2*b-a)*psi))*(-1+EXP(alpha*(-1)*Size*psi))*(EXP(alpha*(2*(Tau+OldTau)+a*psi))-EXP(alpha*(2*(Tau+OldTau)+b*psi))))/(((EXP(alpha*a*psi)-EXP(alpha*(2*OldTau+b*psi)))^2)*(alpha^2)*(psi^2)) -> 0.66198859 | H4: =-Beta/alpha -> 180 | I4: =(-EXP(alpha*zeta)*Beta*(-1+EXP(alpha*Size*psi)-Size*alpha*psi))/((alpha^3)*(psi^2)) -> 519.96874 | J4: =Beta*Theta -> 14.4 | K4: =Beta*Theta -> 14.4 | L4: =kappa -> 90 | M4: =Gamma*Size -> 0 | N4: =Size*Beta*Phi -> 16.2 | O4: =-(EXP(alpha*a*psi)+EXP(alpha*b*psi)*(-1+Size*psi*alpha))*(Beta*Phi)/((alpha*psi)*(EXP(alpha*a*psi)-EXP(alpha*b*psi))) -> 7.0968668 | P4: =(EXP(alpha*(zeta-a*psi))*Beta*Phi*(-EXP(alpha*a*psi)*(-2+(-1)*Size*alpha*psi)+EXP(alpha*b*psi)*(-2+Size*alpha*psi)))/((alpha^3)*(psi^3)) -> 13.751693 | Q4: =Tau*Beta -> 0 | R4: =Tau*Beta -> 0 | S4: =Tau -> 0 | T4: =Profit+Utility -> 694.87138 | U4: =(2*ij*BRIJ)+2*jj*BRJJ -> 0 | V4: =2*(ij*BCCIJ)+(2*jj*BCCJJ)+BCS+jj*BCPTJJ+2*(ij*BCPTIJ)+BCPTII+BCk -> 230.33348 | W4: =ij*BUTIJ+BUTII -> 925.20486 | X4: =Revenue-Cost -> -230.33348 | Y4: =Size -> 5 | Z4: =Welfare/(Size) -> 138.97428 | AA4: =Profit/(Size) -> -46.066695 | AB4: =Utility/(Size) -> 185.04097
A5: 0 | B5: ='W-Toll(All-Toll)-NONC'!A5 -> 0.65078468 | C5: 10 | D5: 0 | E5: =Size-a -> 10 | F5: =(EXP(alpha*(Tau+OldTau+zeta-2*a*psi))*((EXP(alpha*a*psi)-EXP(alpha*b*psi))^2))/((EXP(alpha*a*psi)-EXP(alpha*(2*OldTau+b*psi)))*(alpha^2)*(psi^2)) -> 4.3541368 | G5: =(EXP(alpha*(zeta+(2*b-a)*psi))*(-1+EXP(alpha*(-1)*Size*psi))*(EXP(alpha*(2*(Tau+OldTau)+a*psi))-EXP(alpha*(2*(Tau+OldTau)+b*psi))))/(((EXP(alpha*a*psi)-EXP(alpha*(2*OldTau+b*psi)))^2)*(alpha^2)*(psi^2)) -> 0.53954868 | H5: =-Beta/alpha -> 180 | I5: =(-EXP(alpha*zeta)*Beta*(-1+EXP(alpha*Size*psi)-Size*alpha*psi))/((alpha^3)*(psi^2)) -> 1690.9246 | J5: =Beta*Theta -> 14.4 | K5: =Beta*Theta -> 14.4 | L5: =kappa -> 90 | M5: =Gamma*Size -> 0 | N5: =Size*Beta*Phi -> 32.4 | O5: =-(EXP(alpha*a*psi)+EXP(alpha*b*psi)*(-1+Size*psi*alpha))*(Beta*Phi)/((alpha*psi)*(EXP(alpha*a*psi)-EXP(alpha*b*psi))) -> 12.294172 | P5: =(EXP(alpha*(zeta-a*psi))*Beta*Phi*(-EXP(alpha*a*psi)*(-2+(-1)*Size*alpha*psi)+EXP(alpha*b*psi)*(-2+Size*alpha*psi)))/((alpha^3)*(psi^3)) -> 78.836376 | Q5: =Tau*Beta -> 0 | R5: =Tau*Beta -> 0 | S5: =Tau -> 0 | T5: =Profit+Utility -> 2040.3523 | U5: =(2*ij*BRIJ)+2*jj*BRJJ -> 0 | V5: =2*(ij*BCCIJ)+(2*jj*BCCJJ)+BCS+jj*BCPTJJ+2*(ij*BCPTIJ)+BCPTII+BCk -> 434.31691 | W5: =ij*BUTIJ+BUTII -> 2474.6693 | X5: =Revenue-Cost -> -434.31691 | Y5: =Size -> 10 | Z5: =Welfare/(Size) -> 204.03523 | AA5: =Profit/(Size) -> -43.431691 | AB5: =Utility/(Size) -> 247.46693
A6: 0 | B6: ='W-Toll(All-Toll)-NONC'!A6 -> 0.68311516 | C6: 20 | D6: 0 | E6: =Size-a -> 20 | F6: =(EXP(alpha*(Tau+OldTau+zeta-2*a*psi))*((EXP(alpha*a*psi)-EXP(alpha*b*psi))^2))/((EXP(alpha*a*psi)-EXP(alpha*(2*OldTau+b*psi)))*(alpha^2)*(psi^2)) -> 6.0000439 | G6: =(EXP(alpha*(zeta+(2*b-a)*psi))*(-1+EXP(alpha*(-1)*Size*psi))*(EXP(alpha*(2*(Tau+OldTau)+a*psi))-EXP(alpha*(2*(Tau+OldTau)+b*psi))))/(((EXP(alpha*a*psi)-EXP(alpha*(2*OldTau+b*psi)))^2)*(alpha^2)*(psi^2)) -> 0.15280877 | H6: =-Beta/alpha -> 180 | I6: =(-EXP(alpha*zeta)*Beta*(-1+EXP(alpha*Size*psi)-Size*alpha*psi))/((alpha^3)*(psi^2)) -> 4793.1004 | J6: =Beta*Theta -> 14.4 | K6: =Beta*Theta -> 14.4 | L6: =kappa -> 90 | M6: =Gamma*Size -> 0 | N6: =Size*Beta*Phi -> 64.8 | O6: =-(EXP(alpha*a*psi)+EXP(alpha*b*psi)*(-1+Size*psi*alpha))*(Beta*Phi)/((alpha*psi)*(EXP(alpha*a*psi)-EXP(alpha*b*psi))) -> 18.204759 | P6: =(EXP(alpha*(zeta-a*psi))*Beta*Phi*(-EXP(alpha*a*psi)*(-2+(-1)*Size*alpha*psi)+EXP(alpha*b*psi)*(-2+Size*alpha*psi)))/((alpha^3)*(psi^3)) -> 350.45235 | Q6: =Tau*Beta -> 0 | R6: =Tau*Beta -> 0 | S6: =Tau -> 0 | T6: =Profit+Utility -> 5027.0931 | U6: =(2*ij*BRIJ)+2*jj*BRJJ -> 0 | V6: =2*(ij*BCCIJ)+(2*jj*BCCJJ)+BCS+jj*BCPTJJ+2*(ij*BCPTIJ)+BCPTII+BCk -> 846.01522 | W6: =ij*BUTIJ+BUTII -> 5873.1083 | X6: =Revenue-Cost -> -846.01522 | Y6: =Size -> 20 | Z6: =Welfare/(Size) -> 251.35465 | AA6: =Profit/(Size) -> -42.300761 | AB6: =Utility/(Size) -> 293.65541
A7: 0 | B7: ='W-Toll(All-Toll)-NONC'!A7 -> 0.69959844 | C7: 50 | D7: 0 | E7: =Size-a -> 50 | F7: =(EXP(alpha*(Tau+OldTau+zeta-2*a*psi))*((EXP(alpha*a*psi)-EXP(alpha*b*psi))^2))/((EXP(alpha*a*psi)-EXP(alpha*(2*OldTau+b*psi)))*(alpha^2)*(psi^2)) -> 6.4473653 | G7: =(EXP(alpha*(zeta+(2*b-a)*psi))*(-1+EXP(alpha*(-1)*Size*psi))*(EXP(alpha*(2*(Tau+OldTau)+a*psi))-EXP(alpha*(2*(Tau+OldTau)+b*psi))))/(((EXP(alpha*a*psi)-EXP(alpha*(2*OldTau+b*psi)))^2)*(alpha^2)*(psi^2)) -> 0.0017717449 | H7: =-Beta/alpha -> 180 | I7: =(-EXP(alpha*zeta)*Beta*(-1+EXP(alpha*Size*psi)-Size*alpha*psi))/((alpha^3)*(psi^2)) -> 15200.507 | J7: =Beta*Theta -> 14.4 | K7: =Beta*Theta -> 14.4 | L7: =kappa -> 90 | M7: =Gamma*Size -> 0 | N7: =Size*Beta*Phi -> 162 | O7: =-(EXP(alpha*a*psi)+EXP(alpha*b*psi)*(-1+Size*psi*alpha))*(Beta*Phi)/((alpha*psi)*(EXP(alpha*a*psi)-EXP(alpha*b*psi))) -> 21.510351 | P7: =(EXP(alpha*(zeta-a*psi))*Beta*Phi*(-EXP(alpha*a*psi)*(-2+(-1)*Size*alpha*psi)+EXP(alpha*b*psi)*(-2+Size*alpha*psi)))/((alpha^3)*(psi^3)) -> 1544.7792 | Q7: =Tau*Beta -> 0 | R7: =Tau*Beta -> 0 | S7: =Tau -> 0 | T7: =Profit+Utility -> 14262.862 | U7: =(2*ij*BRIJ)+2*jj*BRJJ -> 0 | V7: =2*(ij*BCCIJ)+(2*jj*BCCJJ)+BCS+jj*BCPTJJ+2*(ij*BCPTIJ)+BCPTII+BCk -> 2098.1715 | W7: =ij*BUTIJ+BUTII -> 16361.033 | X7: =Revenue-Cost -> -2098.1715 | Y7: =Size -> 50 | Z7: =Welfare/(Size) -> 285.25723 | AA7: =Profit/(Size) -> -41.96343 | AB7: =Utility/(Size) -> 327.22066
A8: 0 | B8: ='W-Toll(All-Toll)-NONC'!A8 -> 0.70000052 | C8: 100 | D8: 0 | E8: =Size-a -> 100 | F8: =(EXP(alpha*(Tau+OldTau+zeta-2*a*psi))*((EXP(alpha*a*psi)-EXP(alpha*b*psi))^2))/((EXP(alpha*a*psi)-EXP(alpha*(2*OldTau+b*psi)))*(alpha^2)*(psi^2)) -> 6.4510242 | G8: =(EXP(alpha*(zeta+(2*b-a)*psi))*(-1+EXP(alpha*(-1)*Size*psi))*(EXP(alpha*(2*(Tau+OldTau)+a*psi))-EXP(alpha*(2*(Tau+OldTau)+b*psi))))/(((EXP(alpha*a*psi)-EXP(alpha*(2*OldTau+b*psi)))^2)*(alpha^2)*(psi^2)) -> 9.799527e-07 | H8: =-Beta/alpha -> 180 | I8: =(-EXP(alpha*zeta)*Beta*(-1+EXP(alpha*Size*psi)-Size*alpha*psi))/((alpha^3)*(psi^2)) -> 32736.769 | J8: =Beta*Theta -> 14.4 | K8: =Beta*Theta -> 14.4 | L8: =kappa -> 90 | M8: =Gamma*Size -> 0 | N8: =Size*Beta*Phi -> 324 | O8: =-(EXP(alpha*a*psi)+EXP(alpha*b*psi)*(-1+Size*psi*alpha))*(Beta*Phi)/((alpha*psi)*(EXP(alpha*a*psi)-EXP(alpha*b*psi))) -> 21.599901 | P8: =(EXP(alpha*(zeta-a*psi))*Beta*Phi*(-EXP(alpha*a*psi)*(-2+(-1)*Size*alpha*psi)+EXP(alpha*b*psi)*(-2+Size*alpha*psi)))/((alpha^3)*(psi^3)) -> 3647.8128 | Q8: =Tau*Beta -> 0 | R8: =Tau*Beta -> 0 | S8: =Tau -> 0 | T8: =Profit+Utility -> 29695.668 | U8: =(2*ij*BRIJ)+2*jj*BRJJ -> 0 | V8: =2*(ij*BCCIJ)+(2*jj*BCCJJ)+BCS+jj*BCPTJJ+2*(ij*BCPTIJ)+BCPTII+BCk -> 4202.2856 | W8: =ij*BUTIJ+BUTII -> 33897.954 | X8: =Revenue-Cost -> -4202.2856 | Y8: =Size -> 100 | Z8: =Welfare/(Size) -> 296.95668 | AA8: =Profit/(Size) -> -42.022856 | AB8: =Utility/(Size) -> 338.97954
A9: 0 | B9: ='W-Toll(All-Toll)-NONC'!A9 -> 0.70065908 | C9: 200 | D9: 0 | E9: =Size-a -> 200 | F9: =(EXP(alpha*(Tau+OldTau+zeta-2*a*psi))*((EXP(alpha*a*psi)-EXP(alpha*b*psi))^2))/((EXP(alpha*a*psi)-EXP(alpha*(2*OldTau+b*psi)))*(alpha^2)*(psi^2)) -> 6.4467807 | G9: =(EXP(alpha*(zeta+(2*b-a)*psi))*(-1+EXP(alpha*(-1)*Size*psi))*(EXP(alpha*(2*(Tau+OldTau)+a*psi))-EXP(alpha*(2*(Tau+OldTau)+b*psi))))/(((EXP(alpha*a*psi)-EXP(alpha*(2*OldTau+b*psi)))^2)*(alpha^2)*(psi^2)) -> 2.9937537e-13 | H9: =-Beta/alpha -> 180 | I9: =(-EXP(alpha*zeta)*Beta*(-1+EXP(alpha*Size*psi)-Size*alpha*psi))/((alpha^3)*(psi^2)) -> 67811.878 | J9: =Beta*Theta -> 14.4 | K9: =Beta*Theta -> 14.4 | L9: =kappa -> 90 | M9: =Gamma*Size -> 0 | N9: =Size*Beta*Phi -> 648 | O9: =-(EXP(alpha*a*psi)+EXP(alpha*b*psi)*(-1+Size*psi*alpha))*(Beta*Phi)/((alpha*psi)*(EXP(alpha*a*psi)-EXP(alpha*b*psi))) -> 21.6 | P9: =(EXP(alpha*(zeta-a*psi))*Beta*Phi*(-EXP(alpha*a*psi)*(-2+(-1)*Size*alpha*psi)+EXP(alpha*b*psi)*(-2+Size*alpha*psi)))/((alpha^3)*(psi^3)) -> 7856.8245 | Q9: =Tau*Beta -> 0 | R9: =Tau*Beta -> 0 | S9: =Tau -> 0 | T9: =Profit+Utility -> 60561.306 | U9: =(2*ij*BRIJ)+2*jj*BRJJ -> 0 | V9: =2*(ij*BCCIJ)+(2*jj*BCCJJ)+BCS+jj*BCPTJJ+2*(ij*BCPTIJ)+BCPTII+BCk -> 8410.9927 | W9: =ij*BUTIJ+BUTII -> 68972.299 | X9: =Revenue-Cost -> -8410.9927 | Y9: =Size -> 200 | Z9: =Welfare/(Size) -> 302.80653 | AA9: =Profit/(Size) -> -42.054963 | AB9: =Utility/(Size) -> 344.86149
A10: 0 | B10: ='W-Toll(All-Toll)-NONC'!A10 -> 0.70065908 | C10: 500 | D10: 0 | E10: =Size-a -> 500 | F10: =(EXP(alpha*(Tau+OldTau+zeta-2*a*psi))*((EXP(alpha*a*psi)-EXP(alpha*b*psi))^2))/((EXP(alpha*a*psi)-EXP(alpha*(2*OldTau+b*psi)))*(alpha^2)*(psi^2)) -> 6.4467807 | G10: =(EXP(alpha*(zeta+(2*b-a)*psi))*(-1+EXP(alpha*(-1)*Size*psi))*(EXP(alpha*(2*(Tau+OldTau)+a*psi))-EXP(alpha*(2*(Tau+OldTau)+b*psi))))/(((EXP(alpha*a*psi)-EXP(alpha*(2*OldTau+b*psi)))^2)*(alpha^2)*(psi^2)) -> 8.5696755e-33 | H10: =-Beta/alpha -> 180 | I10: =(-EXP(alpha*zeta)*Beta*(-1+EXP(alpha*Size*psi)-Size*alpha*psi))/((alpha^3)*(psi^2)) -> 173037.21 | J10: =Beta*Theta -> 14.4 | K10: =Beta*Theta -> 14.4 | L10: =kappa -> 90 | M10: =Gamma*Size -> 0 | N10: =Size*Beta*Phi -> 1620 | O10: =-(EXP(alpha*a*psi)+EXP(alpha*b*psi)*(-1+Size*psi*alpha))*(Beta*Phi)/((alpha*psi)*(EXP(alpha*a*psi)-EXP(alpha*b*psi))) -> 21.6 | P10: =(EXP(alpha*(zeta-a*psi))*Beta*Phi*(-EXP(alpha*a*psi)*(-2+(-1)*Size*alpha*psi)+EXP(alpha*b*psi)*(-2+Size*alpha*psi)))/((alpha^3)*(psi^3)) -> 20483.864 | Q10: =Tau*Beta -> 0 | R10: =Tau*Beta -> 0 | S10: =Tau -> 0 | T10: =Profit+Utility -> 153159.59 | U10: =(2*ij*BRIJ)+2*jj*BRJJ -> 0 | V10: =2*(ij*BCCIJ)+(2*jj*BCCJJ)+BCS+jj*BCPTJJ+2*(ij*BCPTIJ)+BCPTII+BCk -> 21038.032 | W10: =ij*BUTIJ+BUTII -> 174197.63 | X10: =Revenue-Cost -> -21038.032 | Y10: =Size -> 500 | Z10: =Welfare/(Size) -> 306.31919 | AA10: =Profit/(Size) -> -42.076064 | AB10: =Utility/(Size) -> 348.39525
A11: 0 | B11: ='W-Toll(All-Toll)-NONC'!A11 -> 0.70065908 | C11: 1000 | D11: 0 | E11: =Size-a -> 1000 | F11: =(EXP(alpha*(Tau+OldTau+zeta-2*a*psi))*((EXP(alpha*a*psi)-EXP(alpha*b*psi))^2))/((EXP(alpha*a*psi)-EXP(alpha*(2*OldTau+b*psi)))*(alpha^2)*(psi^2)) -> 6.4467807 | G11: =(EXP(alpha*(zeta+(2*b-a)*psi))*(-1+EXP(alpha*(-1)*Size*psi))*(EXP(alpha*(2*(Tau+OldTau)+a*psi))-EXP(alpha*(2*(Tau+OldTau)+b*psi))))/(((EXP(alpha*a*psi)-EXP(alpha*(2*OldTau+b*psi)))^2)*(alpha^2)*(psi^2)) -> 2.295505e-65 | H11: =-Beta/alpha -> 180 | I11: =(-EXP(alpha*zeta)*Beta*(-1+EXP(alpha*Size*psi)-Size*alpha*psi))/((alpha^3)*(psi^2)) -> 348412.75 | J11: =Beta*Theta -> 14.4 | K11: =Beta*Theta -> 14.4 | L11: =kappa -> 90 | M11: =Gamma*Size -> 0 | N11: =Size*Beta*Phi -> 3240 | O11: =-(EXP(alpha*a*psi)+EXP(alpha*b*psi)*(-1+Size*psi*alpha))*(Beta*Phi)/((alpha*psi)*(EXP(alpha*a*psi)-EXP(alpha*b*psi))) -> 21.6 | P11: =(EXP(alpha*(zeta-a*psi))*Beta*Phi*(-EXP(alpha*a*psi)*(-2+(-1)*Size*alpha*psi)+EXP(alpha*b*psi)*(-2+Size*alpha*psi)))/((alpha^3)*(psi^3)) -> 41528.929 | Q11: =Tau*Beta -> 0 | R11: =Tau*Beta -> 0 | S11: =Tau -> 0 | T11: =Profit+Utility -> 307490.08 | U11: =(2*ij*BRIJ)+2*jj*BRJJ -> 0 | V11: =2*(ij*BCCIJ)+(2*jj*BCCJJ)+BCS+jj*BCPTJJ+2*(ij*BCPTIJ)+BCPTII+BCk -> 42083.098 | W11: =ij*BUTIJ+BUTII -> 349573.17 | X11: =Revenue-Cost -> -42083.098 | Y11: =Size -> 1000 | Z11: =Welfare/(Size) -> 307.49008 | AA11: =Profit/(Size) -> -42.083098 | AB11: =Utility/(Size) -> 349.57317

Sheet W-Tax(All-Toll)-Coop
A1: Tau | B1: OldTau | C1: Size | D1: a | E1: b | F1: ij | G1: jj | H1: BUTIJ | I1: BUTII | J1: BCCIJ | K1: BCCJJ | L1: BCk | M1: BCS | N1: BCPTJJ | O1: BCPTIJ | P1: BCPTII | Q1: BRIJ | R1: BRJJ | S1: Toll | T1: Welfare | U1: Revenue | V1: Cost | W1: Utility | X1: Profit | Y1: Size2 | Z1: W/Size | AA1: ∏/Size | AB1: U/Size
A2: 0 | B2: ='W-Toll(All-Toll)-Coop'!A2 -> 0.088963449 | C2: 1 | D2: 0 | E2: =Size-a -> 1 | F2: =(EXP(alpha*(Tau+OldTau+zeta-2*a*psi))*((EXP(alpha*a*psi)-EXP(alpha*b*psi))^2))/((EXP(alpha*a*psi)-EXP(alpha*(2*OldTau+b*psi)))*(alpha^2)*(psi^2)) -> 0.82478095 | G2: =(EXP(alpha*(zeta+(2*b-a)*psi))*(-1+EXP(alpha*(-1)*Size*psi))*(EXP(alpha*(2*(Tau+OldTau)+a*psi))-EXP(alpha*(2*(Tau+OldTau)+b*psi))))/(((EXP(alpha*a*psi)-EXP(alpha*(2*OldTau+b*psi)))^2)*(alpha^2)*(psi^2)) -> 2.3229791 | H2: =-Beta/alpha -> 180 | I2: =(-EXP(alpha*zeta)*Beta*(-1+EXP(alpha*Size*psi)-Size*alpha*psi))/((alpha^3)*(psi^2)) -> 25.038896 | J2: =Beta*Theta -> 14.4 | K2: =Beta*Theta -> 14.4 | L2: =kappa -> 90 | M2: =Gamma*Size -> 0 | N2: =Size*Beta*Phi -> 3.24 | O2: =-(EXP(alpha*a*psi)+EXP(alpha*b*psi)*(-1+Size*psi*alpha))*(Beta*Phi)/((alpha*psi)*(EXP(alpha*a*psi)-EXP(alpha*b*psi))) -> 1.5795152 | P2: =(EXP(alpha*(zeta-a*psi))*Beta*Phi*(-EXP(alpha*a*psi)*(-2+(-1)*Size*alpha*psi)+EXP(alpha*b*psi)*(-2+Size*alpha*psi)))/((alpha^3)*(psi^3)) -> 0.14651555 | Q2: =Tau*Beta -> 0 | R2: =Tau*Beta -> 0 | S2: =Tau -> 0 | T2: =Profit+Utility -> -17.434499 | U2: =(2*ij*BRIJ)+2*jj*BRJJ -> 0 | V2: =2*(ij*BCCIJ)+(2*jj*BCCJJ)+BCS+jj*BCPTJJ+2*(ij*BCPTIJ)+BCPTII+BCk -> 190.93397 | W2: =ij*BUTIJ+BUTII -> 173.49947 | X2: =Revenue-Cost -> -190.93397 | Y2: =Size -> 1 | Z2: =Welfare/(Size) -> -17.434499 | AA2: =Profit/(Size) -> -190.93397 | AB2: =Utility/(Size) -> 173.49947
A3: 0 | B3: ='W-Toll(All-Toll)-Coop'!A3 -> 0.097781815 | C3: 2 | D3: 0 | E3: =Size-a -> 2 | F3: =(EXP(alpha*(Tau+OldTau+zeta-2*a*psi))*((EXP(alpha*a*psi)-EXP(alpha*b*psi))^2))/((EXP(alpha*a*psi)-EXP(alpha*(2*OldTau+b*psi)))*(alpha^2)*(psi^2)) -> 2.0251352 | G3: =(EXP(alpha*(zeta+(2*b-a)*psi))*(-1+EXP(alpha*(-1)*Size*psi))*(EXP(alpha*(2*(Tau+OldTau)+a*psi))-EXP(alpha*(2*(Tau+OldTau)+b*psi))))/(((EXP(alpha*a*psi)-EXP(alpha*(2*OldTau+b*psi)))^2)*(alpha^2)*(psi^2)) -> 3.4815731 | H3: =-Beta/alpha -> 180 | I3: =(-EXP(alpha*zeta)*Beta*(-1+EXP(alpha*Size*psi)-Size*alpha*psi))/((alpha^3)*(psi^2)) -> 95.446904 | J3: =Beta*Theta -> 14.4 | K3: =Beta*Theta -> 14.4 | L3: =kappa -> 90 | M3: =Gamma*Size -> 0 | N3: =Size*Beta*Phi -> 6.48 | O3: =-(EXP(alpha*a*psi)+EXP(alpha*b*psi)*(-1+Size*psi*alpha))*(Beta*Phi)/((alpha*psi)*(EXP(alpha*a*psi)-EXP(alpha*b*psi))) -> 3.0782425 | P3: =(EXP(alpha*(zeta-a*psi))*Beta*Phi*(-EXP(alpha*a*psi)*(-2+(-1)*Size*alpha*psi)+EXP(alpha*b*psi)*(-2+Size*alpha*psi)))/((alpha^3)*(psi^3)) -> 1.0892667 | Q3: =Tau*Beta -> 0 | R3: =Tau*Beta -> 0 | S3: =Tau -> 0 | T3: =Profit+Utility -> 175.26047 | U3: =(2*ij*BRIJ)+2*jj*BRJJ -> 0 | V3: =2*(ij*BCCIJ)+(2*jj*BCCJJ)+BCS+jj*BCPTJJ+2*(ij*BCPTIJ)+BCPTII+BCk -> 284.71077 | W3: =ij*BUTIJ+BUTII -> 459.97125 | X3: =Revenue-Cost -> -284.71077 | Y3: =Size -> 2 | Z3: =Welfare/(Size) -> 87.630236 | AA3: =Profit/(Size) -> -142.35539 | AB3: =Utility/(Size) -> 229.98562
A4: 0 | B4: ='W-Toll(All-Toll)-Coop'!A4 -> 0.12245057 | C4: 5 | D4: 0 | E4: =Size-a -> 5 | F4: =(EXP(alpha*(Tau+OldTau+zeta-2*a*psi))*((EXP(alpha*a*psi)-EXP(alpha*b*psi))^2))/((EXP(alpha*a*psi)-EXP(alpha*(2*OldTau+b*psi)))*(alpha^2)*(psi^2)) -> 5.0770838 | G4: =(EXP(alpha*(zeta+(2*b-a)*psi))*(-1+EXP(alpha*(-1)*Size*psi))*(EXP(alpha*(2*(Tau+OldTau)+a*psi))-EXP(alpha*(2*(Tau+OldTau)+b*psi))))/(((EXP(alpha*a*psi)-EXP(alpha*(2*OldTau+b*psi)))^2)*(alpha^2)*(psi^2)) -> 3.366727 | H4: =-Beta/alpha -> 180 | I4: =(-EXP(alpha*zeta)*Beta*(-1+EXP(alpha*Size*psi)-Size*alpha*psi))/((alpha^3)*(psi^2)) -> 519.96874 | J4: =Beta*Theta -> 14.4 | K4: =Beta*Theta -> 14.4 | L4: =kappa -> 90 | M4: =Gamma*Size -> 0 | N4: =Size*Beta*Phi -> 16.2 | O4: =-(EXP(alpha*a*psi)+EXP(alpha*b*psi)*(-1+Size*psi*alpha))*(Beta*Phi)/((alpha*psi)*(EXP(alpha*a*psi)-EXP(alpha*b*psi))) -> 7.0968668 | P4: =(EXP(alpha*(zeta-a*psi))*Beta*Phi*(-EXP(alpha*a*psi)*(-2+(-1)*Size*alpha*psi)+EXP(alpha*b*psi)*(-2+Size*alpha*psi)))/((alpha^3)*(psi^3)) -> 13.751693 | Q4: =Tau*Beta -> 0 | R4: =Tau*Beta -> 0 | S4: =Tau -> 0 | T4: =Profit+Utility -> 960.30664 | U4: =(2*ij*BRIJ)+2*jj*BRJJ -> 0 | V4: =2*(ij*BCCIJ)+(2*jj*BCCJJ)+BCS+jj*BCPTJJ+2*(ij*BCPTIJ)+BCPTII+BCk -> 473.5372 | W4: =ij*BUTIJ+BUTII -> 1433.8438 | X4: =Revenue-Cost -> -473.5372 | Y4: =Size -> 5 | Z4: =Welfare/(Size) -> 192.06133 | AA4: =Profit/(Size) -> -94.70744 | AB4: =Utility/(Size) -> 286.76877
A5: 0 | B5: ='W-Toll(All-Toll)-Coop'!A5 -> 0.15441518 | C5: 10 | D5: 0 | E5: =Size-a -> 10 | F5: =(EXP(alpha*(Tau+OldTau+zeta-2*a*psi))*((EXP(alpha*a*psi)-EXP(alpha*b*psi))^2))/((EXP(alpha*a*psi)-EXP(alpha*(2*OldTau+b*psi)))*(alpha^2)*(psi^2)) -> 8.0349594 | G5: =(EXP(alpha*(zeta+(2*b-a)*psi))*(-1+EXP(alpha*(-1)*Size*psi))*(EXP(alpha*(2*(Tau+OldTau)+a*psi))-EXP(alpha*(2*(Tau+OldTau)+b*psi))))/(((EXP(alpha*a*psi)-EXP(alpha*(2*OldTau+b*psi)))^2)*(alpha^2)*(psi^2)) -> 1.8373583 | H5: =-Beta/alpha -> 180 | I5: =(-EXP(alpha*zeta)*Beta*(-1+EXP(alpha*Size*psi)-Size*alpha*psi))/((alpha^3)*(psi^2)) -> 1690.9246 | J5: =Beta*Theta -> 14.4 | K5: =Beta*Theta -> 14.4 | L5: =kappa -> 90 | M5: =Gamma*Size -> 0 | N5: =Size*Beta*Phi -> 32.4 | O5: =-(EXP(alpha*a*psi)+EXP(alpha*b*psi)*(-1+Size*psi*alpha))*(Beta*Phi)/((alpha*psi)*(EXP(alpha*a*psi)-EXP(alpha*b*psi))) -> 12.294172 | P5: =(EXP(alpha*(zeta-a*psi))*Beta*Phi*(-EXP(alpha*a*psi)*(-2+(-1)*Size*alpha*psi)+EXP(alpha*b*psi)*(-2+Size*alpha*psi)))/((alpha^3)*(psi^3)) -> 78.836376 | Q5: =Tau*Beta -> 0 | R5: =Tau*Beta -> 0 | S5: =Tau -> 0 | T5: =Profit+Utility -> 2426.9614 | U5: =(2*ij*BRIJ)+2*jj*BRJJ -> 0 | V5: =2*(ij*BCCIJ)+(2*jj*BCCJJ)+BCS+jj*BCPTJJ+2*(ij*BCPTIJ)+BCPTII+BCk -> 710.25588 | W5: =ij*BUTIJ+BUTII -> 3137.2173 | X5: =Revenue-Cost -> -710.25588 | Y5: =Size -> 10 | Z5: =Welfare/(Size) -> 242.69614 | AA5: =Profit/(Size) -> -71.025588 | AB5: =Utility/(Size) -> 313.72173
A6: 0 | B6: ='W-Toll(All-Toll)-Coop'!A6 -> 0.18637005 | C6: 20 | D6: 0 | E6: =Size-a -> 20 | F6: =(EXP(alpha*(Tau+OldTau+zeta-2*a*psi))*((EXP(alpha*a*psi)-EXP(alpha*b*psi))^2))/((EXP(alpha*a*psi)-EXP(alpha*(2*OldTau+b*psi)))*(alpha^2)*(psi^2)) -> 10.080763 | G6: =(EXP(alpha*(zeta+(2*b-a)*psi))*(-1+EXP(alpha*(-1)*Size*psi))*(EXP(alpha*(2*(Tau+OldTau)+a*psi))-EXP(alpha*(2*(Tau+OldTau)+b*psi))))/(((EXP(alpha*a*psi)-EXP(alpha*(2*OldTau+b*psi)))^2)*(alpha^2)*(psi^2)) -> 0.43134647 | H6: =-Beta/alpha -> 180 | I6: =(-EXP(alpha*zeta)*Beta*(-1+EXP(alpha*Size*psi)-Size*alpha*psi))/((alpha^3)*(psi^2)) -> 4793.1004 | J6: =Beta*Theta -> 14.4 | K6: =Beta*Theta -> 14.4 | L6: =kappa -> 90 | M6: =Gamma*Size -> 0 | N6: =Size*Beta*Phi -> 64.8 | O6: =-(EXP(alpha*a*psi)+EXP(alpha*b*psi)*(-1+Size*psi*alpha))*(Beta*Phi)/((alpha*psi)*(EXP(alpha*a*psi)-EXP(alpha*b*psi))) -> 18.204759 | P6: =(EXP(alpha*(zeta-a*psi))*Beta*Phi*(-EXP(alpha*a*psi)*(-2+(-1)*Size*alpha*psi)+EXP(alpha*b*psi)*(-2+Size*alpha*psi)))/((alpha^3)*(psi^3)) -> 350.45235 | Q6: =Tau*Beta -> 0 | R6: =Tau*Beta -> 0 | S6: =Tau -> 0 | T6: =Profit+Utility -> 5469.4497 | U6: =(2*ij*BRIJ)+2*jj*BRJJ -> 0 | V6: =2*(ij*BCCIJ)+(2*jj*BCCJJ)+BCS+jj*BCPTJJ+2*(ij*BCPTIJ)+BCPTII+BCk -> 1138.1881 | W6: =ij*BUTIJ+BUTII -> 6607.6378 | X6: =Revenue-Cost -> -1138.1881 | Y6: =Size -> 20 | Z6: =Welfare/(Size) -> 273.47248 | AA6: =Profit/(Size) -> -56.909405 | AB6: =Utility/(Size) -> 330.38189
A7: 0 | B7: ='W-Toll(All-Toll)-Coop'!A7 -> 0.19974985 | C7: 50 | D7: 0 | E7: =Size-a -> 50 | F7: =(EXP(alpha*(Tau+OldTau+zeta-2*a*psi))*((EXP(alpha*a*psi)-EXP(alpha*b*psi))^2))/((EXP(alpha*a*psi)-EXP(alpha*(2*OldTau+b*psi)))*(alpha^2)*(psi^2)) -> 10.630791 | G7: =(EXP(alpha*(zeta+(2*b-a)*psi))*(-1+EXP(alpha*(-1)*Size*psi))*(EXP(alpha*(2*(Tau+OldTau)+a*psi))-EXP(alpha*(2*(Tau+OldTau)+b*psi))))/(((EXP(alpha*a*psi)-EXP(alpha*(2*OldTau+b*psi)))^2)*(alpha^2)*(psi^2)) -> 0.0048169024 | H7: =-Beta/alpha -> 180 | I7: =(-EXP(alpha*zeta)*Beta*(-1+EXP(alpha*Size*psi)-Size*alpha*psi))/((alpha^3)*(psi^2)) -> 15200.507 | J7: =Beta*Theta -> 14.4 | K7: =Beta*Theta -> 14.4 | L7: =kappa -> 90 | M7: =Gamma*Size -> 0 | N7: =Size*Beta*Phi -> 162 | O7: =-(EXP(alpha*a*psi)+EXP(alpha*b*psi)*(-1+Size*psi*alpha))*(Beta*Phi)/((alpha*psi)*(EXP(alpha*a*psi)-EXP(alpha*b*psi))) -> 21.510351 | P7: =(EXP(alpha*(zeta-a*psi))*Beta*Phi*(-EXP(alpha*a*psi)*(-2+(-1)*Size*alpha*psi)+EXP(alpha*b*psi)*(-2+Size*alpha*psi)))/((alpha^3)*(psi^3)) -> 1544.7792 | Q7: =Tau*Beta -> 0 | R7: =Tau*Beta -> 0 | S7: =Tau -> 0 | T7: =Profit+Utility -> 14714.841 | U7: =(2*ij*BRIJ)+2*jj*BRJJ -> 0 | V7: =2*(ij*BCCIJ)+(2*jj*BCCJJ)+BCS+jj*BCPTJJ+2*(ij*BCPTIJ)+BCPTII+BCk -> 2399.2091 | W7: =ij*BUTIJ+BUTII -> 17114.05 | X7: =Revenue-Cost -> -2399.2091 | Y7: =Size -> 50 | Z7: =Welfare/(Size) -> 294.29681 | AA7: =Profit/(Size) -> -47.984183 | AB7: =Utility/(Size) -> 342.281
A8: 0 | B8: ='W-Toll(All-Toll)-Coop'!A8 -> 0.20000258 | C8: 100 | D8: 0 | E8: =Size-a -> 100 | F8: =(EXP(alpha*(Tau+OldTau+zeta-2*a*psi))*((EXP(alpha*a*psi)-EXP(alpha*b*psi))^2))/((EXP(alpha*a*psi)-EXP(alpha*(2*OldTau+b*psi)))*(alpha^2)*(psi^2)) -> 10.63592 | G8: =(EXP(alpha*(zeta+(2*b-a)*psi))*(-1+EXP(alpha*(-1)*Size*psi))*(EXP(alpha*(2*(Tau+OldTau)+a*psi))-EXP(alpha*(2*(Tau+OldTau)+b*psi))))/(((EXP(alpha*a*psi)-EXP(alpha*(2*OldTau+b*psi)))^2)*(alpha^2)*(psi^2)) -> 2.6637773e-06 | H8: =-Beta/alpha -> 180 | I8: =(-EXP(alpha*zeta)*Beta*(-1+EXP(alpha*Size*psi)-Size*alpha*psi))/((alpha^3)*(psi^2)) -> 32736.769 | J8: =Beta*Theta -> 14.4 | K8: =Beta*Theta -> 14.4 | L8: =kappa -> 90 | M8: =Gamma*Size -> 0 | N8: =Size*Beta*Phi -> 324 | O8: =-(EXP(alpha*a*psi)+EXP(alpha*b*psi)*(-1+Size*psi*alpha))*(Beta*Phi)/((alpha*psi)*(EXP(alpha*a*psi)-EXP(alpha*b*psi))) -> 21.599901 | P8: =(EXP(alpha*(zeta-a*psi))*Beta*Phi*(-EXP(alpha*a*psi)*(-2+(-1)*Size*alpha*psi)+EXP(alpha*b*psi)*(-2+Size*alpha*psi)))/((alpha^3)*(psi^3)) -> 3647.8128 | Q8: =Tau*Beta -> 0 | R8: =Tau*Beta -> 0 | S8: =Tau -> 0 | T8: =Profit+Utility -> 30147.637 | U8: =(2*ij*BRIJ)+2*jj*BRJJ -> 0 | V8: =2*(ij*BCCIJ)+(2*jj*BCCJJ)+BCS+jj*BCPTJJ+2*(ij*BCPTIJ)+BCPTII+BCk -> 4503.5979 | W8: =ij*BUTIJ+BUTII -> 34651.235 | X8: =Revenue-Cost -> -4503.5979 | Y8: =Size -> 100 | Z8: =Welfare/(Size) -> 301.47637 | AA8: =Profit/(Size) -> -45.035979 | AB8: =Utility/(Size) -> 346.51235
A9: 0 | B9: ='W-Toll(All-Toll)-Coop'!A9 -> 0.20000281 | C9: 200 | D9: 0 | E9: =Size-a -> 200 | F9: =(EXP(alpha*(Tau+OldTau+zeta-2*a*psi))*((EXP(alpha*a*psi)-EXP(alpha*b*psi))^2))/((EXP(alpha*a*psi)-EXP(alpha*(2*OldTau+b*psi)))*(alpha^2)*(psi^2)) -> 10.635922 | G9: =(EXP(alpha*(zeta+(2*b-a)*psi))*(-1+EXP(alpha*(-1)*Size*psi))*(EXP(alpha*(2*(Tau+OldTau)+a*psi))-EXP(alpha*(2*(Tau+OldTau)+b*psi))))/(((EXP(alpha*a*psi)-EXP(alpha*(2*OldTau+b*psi)))^2)*(alpha^2)*(psi^2)) -> 8.1485545e-13 | H9: =-Beta/alpha -> 180 | I9: =(-EXP(alpha*zeta)*Beta*(-1+EXP(alpha*Size*psi)-Size*alpha*psi))/((alpha^3)*(psi^2)) -> 67811.878 | J9: =Beta*Theta -> 14.4 | K9: =Beta*Theta -> 14.4 | L9: =kappa -> 90 | M9: =Gamma*Size -> 0 | N9: =Size*Beta*Phi -> 648 | O9: =-(EXP(alpha*a*psi)+EXP(alpha*b*psi)*(-1+Size*psi*alpha))*(Beta*Phi)/((alpha*psi)*(EXP(alpha*a*psi)-EXP(alpha*b*psi))) -> 21.6 | P9: =(EXP(alpha*(zeta-a*psi))*Beta*Phi*(-EXP(alpha*a*psi)*(-2+(-1)*Size*alpha*psi)+EXP(alpha*b*psi)*(-2+Size*alpha*psi)))/((alpha^3)*(psi^3)) -> 7856.8245 | Q9: =Tau*Beta -> 0 | R9: =Tau*Beta -> 0 | S9: =Tau -> 0 | T9: =Profit+Utility -> 61013.733 | U9: =(2*ij*BRIJ)+2*jj*BRJJ -> 0 | V9: =2*(ij*BCCIJ)+(2*jj*BCCJJ)+BCS+jj*BCPTJJ+2*(ij*BCPTIJ)+BCPTII+BCk -> 8712.6109 | W9: =ij*BUTIJ+BUTII -> 69726.344 | X9: =Revenue-Cost -> -8712.6109 | Y9: =Size -> 200 | Z9: =Welfare/(Size) -> 305.06867 | AA9: =Profit/(Size) -> -43.563054 | AB9: =Utility/(Size) -> 348.63172
A10: 0 | B10: ='W-Toll(All-Toll)-Coop'!A10 -> 0.20115999 | C10: 500 | D10: 0 | E10: =Size-a -> 500 | F10: =(EXP(alpha*(Tau+OldTau+zeta-2*a*psi))*((EXP(alpha*a*psi)-EXP(alpha*b*psi))^2))/((EXP(alpha*a*psi)-EXP(alpha*(2*OldTau+b*psi)))*(alpha^2)*(psi^2)) -> 10.623622 | G10: =(EXP(alpha*(zeta+(2*b-a)*psi))*(-1+EXP(alpha*(-1)*Size*psi))*(EXP(alpha*(2*(Tau+OldTau)+a*psi))-EXP(alpha*(2*(Tau+OldTau)+b*psi))))/(((EXP(alpha*a*psi)-EXP(alpha*(2*OldTau+b*psi)))^2)*(alpha^2)*(psi^2)) -> 2.3271468e-32 | H10: =-Beta/alpha -> 180 | I10: =(-EXP(alpha*zeta)*Beta*(-1+EXP(alpha*Size*psi)-Size*alpha*psi))/((alpha^3)*(psi^2)) -> 173037.21 | J10: =Beta*Theta -> 14.4 | K10: =Beta*Theta -> 14.4 | L10: =kappa -> 90 | M10: =Gamma*Size -> 0 | N10: =Size*Beta*Phi -> 1620 | O10: =-(EXP(alpha*a*psi)+EXP(alpha*b*psi)*(-1+Size*psi*alpha))*(Beta*Phi)/((alpha*psi)*(EXP(alpha*a*psi)-EXP(alpha*b*psi))) -> 21.6 | P10: =(EXP(alpha*(zeta-a*psi))*Beta*Phi*(-EXP(alpha*a*psi)*(-2+(-1)*Size*alpha*psi)+EXP(alpha*b*psi)*(-2+Size*alpha*psi)))/((alpha^3)*(psi^3)) -> 20483.864 | Q10: =Tau*Beta -> 0 | R10: =Tau*Beta -> 0 | S10: =Tau -> 0 | T10: =Profit+Utility -> 153610.69 | U10: =(2*ij*BRIJ)+2*jj*BRJJ -> 0 | V10: =2*(ij*BCCIJ)+(2*jj*BCCJJ)+BCS+jj*BCPTJJ+2*(ij*BCPTIJ)+BCPTII+BCk -> 21338.765 | W10: =ij*BUTIJ+BUTII -> 174949.46 | X10: =Revenue-Cost -> -21338.765 | Y10: =Size -> 500 | Z10: =Welfare/(Size) -> 307.22139 | AA10: =Profit/(Size) -> -42.677529 | AB10: =Utility/(Size) -> 349.89892
A11: 0 | B11: ='W-Toll(All-Toll)-Coop'!A11 -> 0.20115999 | C11: 1000 | D11: 0 | E11: =Size-a -> 1000 | F11: =(EXP(alpha*(Tau+OldTau+zeta-2*a*psi))*((EXP(alpha*a*psi)-EXP(alpha*b*psi))^2))/((EXP(alpha*a*psi)-EXP(alpha*(2*OldTau+b*psi)))*(alpha^2)*(psi^2)) -> 10.623622 | G11: =(EXP(alpha*(zeta+(2*b-a)*psi))*(-1+EXP(alpha*(-1)*Size*psi))*(EXP(alpha*(2*(Tau+OldTau)+a*psi))-EXP(alpha*(2*(Tau+OldTau)+b*psi))))/(((EXP(alpha*a*psi)-EXP(alpha*(2*OldTau+b*psi)))^2)*(alpha^2)*(psi^2)) -> 6.2335814e-65 | H11: =-Beta/alpha -> 180 | I11: =(-EXP(alpha*zeta)*Beta*(-1+EXP(alpha*Size*psi)-Size*alpha*psi))/((alpha^3)*(psi^2)) -> 348412.75 | J11: =Beta*Theta -> 14.4 | K11: =Beta*Theta -> 14.4 | L11: =kappa -> 90 | M11: =Gamma*Size -> 0 | N11: =Size*Beta*Phi -> 3240 | O11: =-(EXP(alpha*a*psi)+EXP(alpha*b*psi)*(-1+Size*psi*alpha))*(Beta*Phi)/((alpha*psi)*(EXP(alpha*a*psi)-EXP(alpha*b*psi))) -> 21.6 | P11: =(EXP(alpha*(zeta-a*psi))*Beta*Phi*(-EXP(alpha*a*psi)*(-2+(-1)*Size*alpha*psi)+EXP(alpha*b*psi)*(-2+Size*alpha*psi)))/((alpha^3)*(psi^3)) -> 41528.929 | Q11: =Tau*Beta -> 0 | R11: =Tau*Beta -> 0 | S11: =Tau -> 0 | T11: =Profit+Utility -> 307941.17 | U11: =(2*ij*BRIJ)+2*jj*BRJJ -> 0 | V11: =2*(ij*BCCIJ)+(2*jj*BCCJJ)+BCS+jj*BCPTJJ+2*(ij*BCPTIJ)+BCPTII+BCk -> 42383.83 | W11: =ij*BUTIJ+BUTII -> 350325 | X11: =Revenue-Cost -> -42383.83 | Y11: =Size -> 1000 | Z11: =Welfare/(Size) -> 307.94117 | AA11: =Profit/(Size) -> -42.38383 | AB11: =Utility/(Size) -> 350.325

Sheet W-Toll(All-Toll)-NONC
A1: Tau | B1: OldTau | C1: Size | D1: a | E1: b | F1: ij | G1: jj | H1: BUTIJ | I1: BUTII | J1: BCCIJ | K1: BCCJJ | L1: BCk | M1: BCS | N1: BCPTJJ | O1: BCPTIJ | P1: BCPTII | Q1: BRIJ | R1: BRJJ | S1: Toll | T1: Welfare | U1: Revenue | V1: Cost | W1: Utility | X1: Profit | Y1: Size2 | Z1: W-Toll/Size | AA1: ∏/Size | AB1: U/Size | AC1: W-Tax/Size
A2: 0.58886934 | B2: 0.58887567 | C2: 1 | D2: 0 | E2: =Size-a -> 1 | F2: =(EXP(alpha*(Tau+OldTau+zeta-2*a*psi))*((EXP(alpha*a*psi)-EXP(alpha*b*psi))^2))/((EXP(alpha*a*psi)-EXP(alpha*(2*OldTau+b*psi)))*(alpha^2)*(psi^2)) -> 0.1056222 | G2: =(EXP(alpha*(zeta+(2*b-a)*psi))*(-1+EXP(alpha*(-1)*Size*psi))*(EXP(alpha*(2*(Tau+OldTau)+a*psi))-EXP(alpha*(2*(Tau+OldTau)+b*psi))))/(((EXP(alpha*a*psi)-EXP(alpha*(2*OldTau+b*psi)))^2)*(alpha^2)*(psi^2)) -> 0.038095918 | H2: =-Beta/alpha -> 180 | I2: =(-EXP(alpha*zeta)*Beta*(-1+EXP(alpha*Size*psi)-Size*alpha*psi))/((alpha^3)*(psi^2)) -> 25.038896 | J2: =Beta*Theta -> 14.4 | K2: =Beta*Theta -> 14.4 | L2: =kappa -> 90 | M2: =Gamma*Size -> 0 | N2: =Size*Beta*Phi -> 3.24 | O2: =-(EXP(alpha*a*psi)+EXP(alpha*b*psi)*(-1+Size*psi*alpha))*(Beta*Phi)/((alpha*psi)*(EXP(alpha*a*psi)-EXP(alpha*b*psi))) -> 1.5795152 | P2: =(EXP(alpha*(zeta-a*psi))*Beta*Phi*(-EXP(alpha*a*psi)*(-2+(-1)*Size*alpha*psi)+EXP(alpha*b*psi)*(-2+Size*alpha*psi)))/((alpha^3)*(psi^3)) -> 0.14651555 | Q2: =Tau*Beta -> 105.99648 | R2: =Tau*Beta -> 105.99648 | S2: =Tau -> 0.58886934 | T2: =Profit+Utility -> -20.224571 | U2: =(2*ij*BRIJ)+2*jj*BRJJ -> 30.467229 | V2: =2*(ij*BCCIJ)+(2*jj*BCCJJ)+BCS+jj*BCPTJJ+2*(ij*BCPTIJ)+BCPTII+BCk -> 94.742692 | W2: =ij*BUTIJ+BUTII -> 44.050892 | X2: =Revenue-Cost -> -64.275463 | Y2: =Size -> 1 | Z2: =Welfare/(Size) -> -20.224571 | AA2: =Profit/(Size) -> -64.275463 | AB2: =Utility/(Size) -> 44.050892 | AC2: -40.894662
A3: 0.5974306 | B3: 0.59745247 | C3: 2 | D3: 0 | E3: =Size-a -> 2 | F3: =(EXP(alpha*(Tau+OldTau+zeta-2*a*psi))*((EXP(alpha*a*psi)-EXP(alpha*b*psi))^2))/((EXP(alpha*a*psi)-EXP(alpha*(2*OldTau+b*psi)))*(alpha^2)*(psi^2)) -> 0.34056691 | G3: =(EXP(alpha*(zeta+(2*b-a)*psi))*(-1+EXP(alpha*(-1)*Size*psi))*(EXP(alpha*(2*(Tau+OldTau)+a*psi))-EXP(alpha*(2*(Tau+OldTau)+b*psi))))/(((EXP(alpha*a*psi)-EXP(alpha*(2*OldTau+b*psi)))^2)*(alpha^2)*(psi^2)) -> 0.098462838 | H3: =-Beta/alpha -> 180 | I3: =(-EXP(alpha*zeta)*Beta*(-1+EXP(alpha*Size*psi)-Size*alpha*psi))/((alpha^3)*(psi^2)) -> 95.446904 | J3: =Beta*Theta -> 14.4 | K3: =Beta*Theta -> 14.4 | L3: =kappa -> 90 | M3: =Gamma*Size -> 0 | N3: =Size*Beta*Phi -> 6.48 | O3: =-(EXP(alpha*a*psi)+EXP(alpha*b*psi)*(-1+Size*psi*alpha))*(Beta*Phi)/((alpha*psi)*(EXP(alpha*a*psi)-EXP(alpha*b*psi))) -> 3.0782425 | P3: =(EXP(alpha*(zeta-a*psi))*Beta*Phi*(-EXP(alpha*a*psi)*(-2+(-1)*Size*alpha*psi)+EXP(alpha*b*psi)*(-2+Size*alpha*psi)))/((alpha^3)*(psi^3)) -> 1.0892667 | Q3: =Tau*Beta -> 107.53751 | R3: =Tau*Beta -> 107.53751 | S3: =Tau -> 0.5974306 | T3: =Profit+Utility -> 144.70522 | U3: =(2*ij*BRIJ)+2*jj*BRJJ -> 94.42433 | V3: =2*(ij*BCCIJ)+(2*jj*BCCJJ)+BCS+jj*BCPTJJ+2*(ij*BCPTIJ)+BCPTII+BCk -> 106.46806 | W3: =ij*BUTIJ+BUTII -> 156.74895 | X3: =Revenue-Cost -> -12.043728 | Y3: =Size -> 2 | Z3: =Welfare/(Size) -> 72.35261 | AA3: =Profit/(Size) -> -6.021864 | AB3: =Utility/(Size) -> 78.374474 | AC3: 41.331007
A4: 0.62076551 | B4: 0.6208517 | C4: 5 | D4: 0 | E4: =Size-a -> 5 | F4: =(EXP(alpha*(Tau+OldTau+zeta-2*a*psi))*((EXP(alpha*a*psi)-EXP(alpha*b*psi))^2))/((EXP(alpha*a*psi)-EXP(alpha*(2*OldTau+b*psi)))*(alpha^2)*(psi^2)) -> 1.2100166 | G4: =(EXP(alpha*(zeta+(2*b-a)*psi))*(-1+EXP(alpha*(-1)*Size*psi))*(EXP(alpha*(2*(Tau+OldTau)+a*psi))-EXP(alpha*(2*(Tau+OldTau)+b*psi))))/(((EXP(alpha*a*psi)-EXP(alpha*(2*OldTau+b*psi)))^2)*(alpha^2)*(psi^2)) -> 0.19123259 | H4: =-Beta/alpha -> 180 | I4: =(-EXP(alpha*zeta)*Beta*(-1+EXP(alpha*Size*psi)-Size*alpha*psi))/((alpha^3)*(psi^2)) -> 519.96874 | J4: =Beta*Theta -> 14.4 | K4: =Beta*Theta -> 14.4 | L4: =kappa -> 90 | M4: =Gamma*Size -> 0 | N4: =Size*Beta*Phi -> 16.2 | O4: =-(EXP(alpha*a*psi)+EXP(alpha*b*psi)*(-1+Size*psi*alpha))*(Beta*Phi)/((alpha*psi)*(EXP(alpha*a*psi)-EXP(alpha*b*psi))) -> 7.0968668 | P4: =(EXP(alpha*(zeta-a*psi))*Beta*Phi*(-EXP(alpha*a*psi)*(-2+(-1)*Size*alpha*psi)+EXP(alpha*b*psi)*(-2+Size*alpha*psi)))/((alpha^3)*(psi^3)) -> 13.751693 | Q4: =Tau*Beta -> 111.73779 | R4: =Tau*Beta -> 111.73779 | S4: =Tau -> 0.62076551 | T4: =Profit+Utility -> 886.53643 | U4: =(2*ij*BRIJ)+2*jj*BRJJ -> 313.14499 | V4: =2*(ij*BCCIJ)+(2*jj*BCCJJ)+BCS+jj*BCPTJJ+2*(ij*BCPTIJ)+BCPTII+BCk -> 164.38029 | W4: =ij*BUTIJ+BUTII -> 737.77174 | X4: =Revenue-Cost -> 148.7647 | Y4: =Size -> 5 | Z4: =Welfare/(Size) -> 177.30729 | AA4: =Profit/(Size) -> 29.752939 | AB4: =Utility/(Size) -> 147.55435 | AC4: 138.97428
A5: 0.65078468 | B5: 0.65094108 | C5: 10 | D5: 0 | E5: =Size-a -> 10 | F5: =(EXP(alpha*(Tau+OldTau+zeta-2*a*psi))*((EXP(alpha*a*psi)-EXP(alpha*b*psi))^2))/((EXP(alpha*a*psi)-EXP(alpha*(2*OldTau+b*psi)))*(alpha^2)*(psi^2)) -> 2.2708747 | G5: =(EXP(alpha*(zeta+(2*b-a)*psi))*(-1+EXP(alpha*(-1)*Size*psi))*(EXP(alpha*(2*(Tau+OldTau)+a*psi))-EXP(alpha*(2*(Tau+OldTau)+b*psi))))/(((EXP(alpha*a*psi)-EXP(alpha*(2*OldTau+b*psi)))^2)*(alpha^2)*(psi^2)) -> 0.14676173 | H5: =-Beta/alpha -> 180 | I5: =(-EXP(alpha*zeta)*Beta*(-1+EXP(alpha*Size*psi)-Size*alpha*psi))/((alpha^3)*(psi^2)) -> 1690.9246 | J5: =Beta*Theta -> 14.4 | K5: =Beta*Theta -> 14.4 | L5: =kappa -> 90 | M5: =Gamma*Size -> 0 | N5: =Size*Beta*Phi -> 32.4 | O5: =-(EXP(alpha*a*psi)+EXP(alpha*b*psi)*(-1+Size*psi*alpha))*(Beta*Phi)/((alpha*psi)*(EXP(alpha*a*psi)-EXP(alpha*b*psi))) -> 12.294172 | P5: =(EXP(alpha*(zeta-a*psi))*Beta*Phi*(-EXP(alpha*a*psi)*(-2+(-1)*Size*alpha*psi)+EXP(alpha*b*psi)*(-2+Size*alpha*psi)))/((alpha^3)*(psi^3)) -> 78.836376 | Q5: =Tau*Beta -> 117.14124 | R5: =Tau*Beta -> 117.14124 | S5: =Tau -> 0.65078468 | T5: =Profit+Utility -> 2367.0355 | U5: =(2*ij*BRIJ)+2*jj*BRJJ -> 566.40987 | V5: =2*(ij*BCCIJ)+(2*jj*BCCJJ)+BCS+jj*BCPTJJ+2*(ij*BCPTIJ)+BCPTII+BCk -> 299.05643 | W5: =ij*BUTIJ+BUTII -> 2099.6821 | X5: =Revenue-Cost -> 267.35344 | Y5: =Size -> 10 | Z5: =Welfare/(Size) -> 236.70355 | AA5: =Profit/(Size) -> 26.735344 | AB5: =Utility/(Size) -> 209.96821 | AC5: 204.03523
A6: 0.68311516 | B6: 0.68324075 | C6: 20 | D6: 0 | E6: =Size-a -> 20 | F6: =(EXP(alpha*(Tau+OldTau+zeta-2*a*psi))*((EXP(alpha*a*psi)-EXP(alpha*b*psi))^2))/((EXP(alpha*a*psi)-EXP(alpha*(2*OldTau+b*psi)))*(alpha^2)*(psi^2)) -> 3.0298794 | G6: =(EXP(alpha*(zeta+(2*b-a)*psi))*(-1+EXP(alpha*(-1)*Size*psi))*(EXP(alpha*(2*(Tau+OldTau)+a*psi))-EXP(alpha*(2*(Tau+OldTau)+b*psi))))/(((EXP(alpha*a*psi)-EXP(alpha*(2*OldTau+b*psi)))^2)*(alpha^2)*(psi^2)) -> 0.038966383 | H6: =-Beta/alpha -> 180 | I6: =(-EXP(alpha*zeta)*Beta*(-1+EXP(alpha*Size*psi)-Size*alpha*psi))/((alpha^3)*(psi^2)) -> 4793.1004 | J6: =Beta*Theta -> 14.4 | K6: =Beta*Theta -> 14.4 | L6: =kappa -> 90 | M6: =Gamma*Size -> 0 | N6: =Size*Beta*Phi -> 64.8 | O6: =-(EXP(alpha*a*psi)+EXP(alpha*b*psi)*(-1+Size*psi*alpha))*(Beta*Phi)/((alpha*psi)*(EXP(alpha*a*psi)-EXP(alpha*b*psi))) -> 18.204759 | P6: =(EXP(alpha*(zeta-a*psi))*Beta*Phi*(-EXP(alpha*a*psi)*(-2+(-1)*Size*alpha*psi)+EXP(alpha*b*psi)*(-2+Size*alpha*psi)))/((alpha^3)*(psi^3)) -> 350.45235 | Q6: =Tau*Beta -> 122.96073 | R6: =Tau*Beta -> 122.96073 | S6: =Tau -> 0.68311516 | T6: =Profit+Utility -> 5451.4971 | U6: =(2*ij*BRIJ)+2*jj*BRJJ -> 754.69503 | V6: =2*(ij*BCCIJ)+(2*jj*BCCJJ)+BCS+jj*BCPTJJ+2*(ij*BCPTIJ)+BCPTII+BCk -> 641.67658 | W6: =ij*BUTIJ+BUTII -> 5338.4787 | X6: =Revenue-Cost -> 113.01845 | Y6: =Size -> 20 | Z6: =Welfare/(Size) -> 272.57486 | AA6: =Profit/(Size) -> 5.6509226 | AB6: =Utility/(Size) -> 266.92393 | AC6: 251.35465
A7: 0.69959844 | B7: 0.69959844 | C7: 50 | D7: 0 | E7: =Size-a -> 50 | F7: =(EXP(alpha*(Tau+OldTau+zeta-2*a*psi))*((EXP(alpha*a*psi)-EXP(alpha*b*psi))^2))/((EXP(alpha*a*psi)-EXP(alpha*(2*OldTau+b*psi)))*(alpha^2)*(psi^2)) -> 3.2029528 | G7: =(EXP(alpha*(zeta+(2*b-a)*psi))*(-1+EXP(alpha*(-1)*Size*psi))*(EXP(alpha*(2*(Tau+OldTau)+a*psi))-EXP(alpha*(2*(Tau+OldTau)+b*psi))))/(((EXP(alpha*a*psi)-EXP(alpha*(2*OldTau+b*psi)))^2)*(alpha^2)*(psi^2)) -> 0.00043725795 | H7: =-Beta/alpha -> 180 | I7: =(-EXP(alpha*zeta)*Beta*(-1+EXP(alpha*Size*psi)-Size*alpha*psi))/((alpha^3)*(psi^2)) -> 15200.507 | J7: =Beta*Theta -> 14.4 | K7: =Beta*Theta -> 14.4 | L7: =kappa -> 90 | M7: =Gamma*Size -> 0 | N7: =Size*Beta*Phi -> 162 | O7: =-(EXP(alpha*a*psi)+EXP(alpha*b*psi)*(-1+Size*psi*alpha))*(Beta*Phi)/((alpha*psi)*(EXP(alpha*a*psi)-EXP(alpha*b*psi))) -> 21.510351 | P7: =(EXP(alpha*(zeta-a*psi))*Beta*Phi*(-EXP(alpha*a*psi)*(-2+(-1)*Size*alpha*psi)+EXP(alpha*b*psi)*(-2+Size*alpha*psi)))/((alpha^3)*(psi^3)) -> 1544.7792 | Q7: =Tau*Beta -> 125.92772 | R7: =Tau*Beta -> 125.92772 | S7: =Tau -> 0.69959844 | T7: =Profit+Utility -> 14718.929 | U7: =(2*ij*BRIJ)+2*jj*BRJJ -> 806.7912 | V7: =2*(ij*BCCIJ)+(2*jj*BCCJJ)+BCS+jj*BCPTJJ+2*(ij*BCPTIJ)+BCPTII+BCk -> 1864.9009 | W7: =ij*BUTIJ+BUTII -> 15777.039 | X7: =Revenue-Cost -> -1058.1097 | Y7: =Size -> 50 | Z7: =Welfare/(Size) -> 294.37858 | AA7: =Profit/(Size) -> -21.162194 | AB7: =Utility/(Size) -> 315.54078 | AC7: 285.25723
A8: 0.70000052 | B8: 0.70000052 | C8: 100 | D8: 0 | E8: =Size-a -> 100 | F8: =(EXP(alpha*(Tau+OldTau+zeta-2*a*psi))*((EXP(alpha*a*psi)-EXP(alpha*b*psi))^2))/((EXP(alpha*a*psi)-EXP(alpha*(2*OldTau+b*psi)))*(alpha^2)*(psi^2)) -> 3.2034822 | G8: =(EXP(alpha*(zeta+(2*b-a)*psi))*(-1+EXP(alpha*(-1)*Size*psi))*(EXP(alpha*(2*(Tau+OldTau)+a*psi))-EXP(alpha*(2*(Tau+OldTau)+b*psi))))/(((EXP(alpha*a*psi)-EXP(alpha*(2*OldTau+b*psi)))^2)*(alpha^2)*(psi^2)) -> 2.4165311e-07 | H8: =-Beta/alpha -> 180 | I8: =(-EXP(alpha*zeta)*Beta*(-1+EXP(alpha*Size*psi)-Size*alpha*psi))/((alpha^3)*(psi^2)) -> 32736.769 | J8: =Beta*Theta -> 14.4 | K8: =Beta*Theta -> 14.4 | L8: =kappa -> 90 | M8: =Gamma*Size -> 0 | N8: =Size*Beta*Phi -> 324 | O8: =-(EXP(alpha*a*psi)+EXP(alpha*b*psi)*(-1+Size*psi*alpha))*(Beta*Phi)/((alpha*psi)*(EXP(alpha*a*psi)-EXP(alpha*b*psi))) -> 21.599901 | P8: =(EXP(alpha*(zeta-a*psi))*Beta*Phi*(-EXP(alpha*a*psi)*(-2+(-1)*Size*alpha*psi)+EXP(alpha*b*psi)*(-2+Size*alpha*psi)))/((alpha^3)*(psi^3)) -> 3647.8128 | Q8: =Tau*Beta -> 126.00009 | R8: =Tau*Beta -> 126.00009 | S8: =Tau -> 0.70000052 | T8: =Profit+Utility -> 30152.211 | U8: =(2*ij*BRIJ)+2*jj*BRJJ -> 807.27816 | V8: =2*(ij*BCCIJ)+(2*jj*BCCJJ)+BCS+jj*BCPTJJ+2*(ij*BCPTIJ)+BCPTII+BCk -> 3968.463 | W8: =ij*BUTIJ+BUTII -> 33313.396 | X8: =Revenue-Cost -> -3161.1848 | Y8: =Size -> 100 | Z8: =Welfare/(Size) -> 301.52211 | AA8: =Profit/(Size) -> -31.611848 | AB8: =Utility/(Size) -> 333.13396 | AC8: 296.95668
A9: 0.70065908 | B9: 0.70065908 | C9: 200 | D9: 0 | E9: =Size-a -> 200 | F9: =(EXP(alpha*(Tau+OldTau+zeta-2*a*psi))*((EXP(alpha*a*psi)-EXP(alpha*b*psi))^2))/((EXP(alpha*a*psi)-EXP(alpha*(2*OldTau+b*psi)))*(alpha^2)*(psi^2)) -> 3.1992673 | G9: =(EXP(alpha*(zeta+(2*b-a)*psi))*(-1+EXP(alpha*(-1)*Size*psi))*(EXP(alpha*(2*(Tau+OldTau)+a*psi))-EXP(alpha*(2*(Tau+OldTau)+b*psi))))/(((EXP(alpha*a*psi)-EXP(alpha*(2*OldTau+b*psi)))^2)*(alpha^2)*(psi^2)) -> 7.3727807e-14 | H9: =-Beta/alpha -> 180 | I9: =(-EXP(alpha*zeta)*Beta*(-1+EXP(alpha*Size*psi)-Size*alpha*psi))/((alpha^3)*(psi^2)) -> 67811.878 | J9: =Beta*Theta -> 14.4 | K9: =Beta*Theta -> 14.4 | L9: =kappa -> 90 | M9: =Gamma*Size -> 0 | N9: =Size*Beta*Phi -> 648 | O9: =-(EXP(alpha*a*psi)+EXP(alpha*b*psi)*(-1+Size*psi*alpha))*(Beta*Phi)/((alpha*psi)*(EXP(alpha*a*psi)-EXP(alpha*b*psi))) -> 21.6 | P9: =(EXP(alpha*(zeta-a*psi))*Beta*Phi*(-EXP(alpha*a*psi)*(-2+(-1)*Size*alpha*psi)+EXP(alpha*b*psi)*(-2+Size*alpha*psi)))/((alpha^3)*(psi^3)) -> 7856.8245 | Q9: =Tau*Beta -> 126.11864 | R9: =Tau*Beta -> 126.11864 | S9: =Tau -> 0.70065908 | T9: =Profit+Utility -> 61017.549 | U9: =(2*ij*BRIJ)+2*jj*BRJJ -> 806.97444 | V9: =2*(ij*BCCIJ)+(2*jj*BCCJJ)+BCS+jj*BCPTJJ+2*(ij*BCPTIJ)+BCPTII+BCk -> 8177.1717 | W9: =ij*BUTIJ+BUTII -> 68387.746 | X9: =Revenue-Cost -> -7370.1973 | Y9: =Size -> 200 | Z9: =Welfare/(Size) -> 305.08774 | AA9: =Profit/(Size) -> -36.850986 | AB9: =Utility/(Size) -> 341.93873 | AC9: 302.80653
A10: 0.70065908 | B10: 0.70065908 | C10: 500 | D10: 0 | E10: =Size-a -> 500 | F10: =(EXP(alpha*(Tau+OldTau+zeta-2*a*psi))*((EXP(alpha*a*psi)-EXP(alpha*b*psi))^2))/((EXP(alpha*a*psi)-EXP(alpha*(2*OldTau+b*psi)))*(alpha^2)*(psi^2)) -> 3.1992673 | G10: =(EXP(alpha*(zeta+(2*b-a)*psi))*(-1+EXP(alpha*(-1)*Size*psi))*(EXP(alpha*(2*(Tau+OldTau)+a*psi))-EXP(alpha*(2*(Tau+OldTau)+b*psi))))/(((EXP(alpha*a*psi)-EXP(alpha*(2*OldTau+b*psi)))^2)*(alpha^2)*(psi^2)) -> 2.1104722e-33 | H10: =-Beta/alpha -> 180 | I10: =(-EXP(alpha*zeta)*Beta*(-1+EXP(alpha*Size*psi)-Size*alpha*psi))/((alpha^3)*(psi^2)) -> 173037.21 | J10: =Beta*Theta -> 14.4 | K10: =Beta*Theta -> 14.4 | L10: =kappa -> 90 | M10: =Gamma*Size -> 0 | N10: =Size*Beta*Phi -> 1620 | O10: =-(EXP(alpha*a*psi)+EXP(alpha*b*psi)*(-1+Size*psi*alpha))*(Beta*Phi)/((alpha*psi)*(EXP(alpha*a*psi)-EXP(alpha*b*psi))) -> 21.6 | P10: =(EXP(alpha*(zeta-a*psi))*Beta*Phi*(-EXP(alpha*a*psi)*(-2+(-1)*Size*alpha*psi)+EXP(alpha*b*psi)*(-2+Size*alpha*psi)))/((alpha^3)*(psi^3)) -> 20483.864 | Q10: =Tau*Beta -> 126.11864 | R10: =Tau*Beta -> 126.11864 | S10: =Tau -> 0.70065908 | T10: =Profit+Utility -> 153615.84 | U10: =(2*ij*BRIJ)+2*jj*BRJJ -> 806.97444 | V10: =2*(ij*BCCIJ)+(2*jj*BCCJJ)+BCS+jj*BCPTJJ+2*(ij*BCPTIJ)+BCPTII+BCk -> 20804.211 | W10: =ij*BUTIJ+BUTII -> 173613.07 | X10: =Revenue-Cost -> -19997.237 | Y10: =Size -> 500 | Z10: =Welfare/(Size) -> 307.23167 | AA10: =Profit/(Size) -> -39.994473 | AB10: =Utility/(Size) -> 347.22615 | AC10: 306.31919
A11: 0.70065908 | B11: 0.70065908 | C11: 1000 | D11: 0 | E11: =Size-a -> 1000 | F11: =(EXP(alpha*(Tau+OldTau+zeta-2*a*psi))*((EXP(alpha*a*psi)-EXP(alpha*b*psi))^2))/((EXP(alpha*a*psi)-EXP(alpha*(2*OldTau+b*psi)))*(alpha^2)*(psi^2)) -> 3.1992673 | G11: =(EXP(alpha*(zeta+(2*b-a)*psi))*(-1+EXP(alpha*(-1)*Size*psi))*(EXP(alpha*(2*(Tau+OldTau)+a*psi))-EXP(alpha*(2*(Tau+OldTau)+b*psi))))/(((EXP(alpha*a*psi)-EXP(alpha*(2*OldTau+b*psi)))^2)*(alpha^2)*(psi^2)) -> 5.6531888e-66 | H11: =-Beta/alpha -> 180 | I11: =(-EXP(alpha*zeta)*Beta*(-1+EXP(alpha*Size*psi)-Size*alpha*psi))/((alpha^3)*(psi^2)) -> 348412.75 | J11: =Beta*Theta -> 14.4 | K11: =Beta*Theta -> 14.4 | L11: =kappa -> 90 | M11: =Gamma*Size -> 0 | N11: =Size*Beta*Phi -> 3240 | O11: =-(EXP(alpha*a*psi)+EXP(alpha*b*psi)*(-1+Size*psi*alpha))*(Beta*Phi)/((alpha*psi)*(EXP(alpha*a*psi)-EXP(alpha*b*psi))) -> 21.6 | P11: =(EXP(alpha*(zeta-a*psi))*Beta*Phi*(-EXP(alpha*a*psi)*(-2+(-1)*Size*alpha*psi)+EXP(alpha*b*psi)*(-2+Size*alpha*psi)))/((alpha^3)*(psi^3)) -> 41528.929 | Q11: =Tau*Beta -> 126.11864 | R11: =Tau*Beta -> 126.11864 | S11: =Tau -> 0.70065908 | T11: =Profit+Utility -> 307946.32 | U11: =(2*ij*BRIJ)+2*jj*BRJJ -> 806.97444 | V11: =2*(ij*BCCIJ)+(2*jj*BCCJJ)+BCS+jj*BCPTJJ+2*(ij*BCPTIJ)+BCPTII+BCk -> 41849.277 | W11: =ij*BUTIJ+BUTII -> 348988.62 | X11: =Revenue-Cost -> -41042.302 | Y11: =Size -> 1000 | Z11: =Welfare/(Size) -> 307.94632 | AA11: =Profit/(Size) -> -41.042302 | AB11: =Utility/(Size) -> 348.98862 | AC11: 307.49008

Sheet W-Theta-Compare-NONC
A1: Size | B1: Theta-Default | C1: All-Tax:Theta-Necessary | D1: All-Toll:Theta-Necessary | E1: All-Tax: Toll | F1: All-Toll: Toll
A2: 1 | B2: 0.08 | C2: ='W-Toll(All-Tax) (theta)'!A7 -> 0.70008489 | E2: ='W-Toll(All-Tax) (theta)'!D7 -> 1.2090369
A3: 10 | B3: 0.08 | C3: ='W-Toll(All-Tax) (theta)'!A12 -> 0.32874071 | D3: ='W-Toll(All-Toll)-NONC(theta)'!A32 -> 0.30945654 | E3: ='W-Toll(All-Tax) (theta)'!D12 -> 0.90114613 | F3: ='W-Toll(All-Toll)-NONC(theta)'!D32 -> 0.8793935
A4: 100 | B4: 0.08 | C4: ='W-Toll(All-Tax) (theta)'!A18 -> 0.29818128 | D4: ='W-Toll(All-Toll)-NONC(theta)'!A44 -> 0.33237068 | E4: ='W-Toll(All-Tax) (theta)'!D18 -> 0.91832091 | F4: ='W-Toll(All-Toll)-NONC(theta)'!D44 -> 0.95237349
A5: 1000 | B5: 0.08 | D5: ='W-Toll(All-Toll)-NONC(theta)'!A50 -> 0.33232128 | F5: ='W-Toll(All-Toll)-NONC(theta)'!D50 -> 0.70000093

Sheet W-Toll(All-Toll)-NONC(theta)
A1: Theta | B1: Ccv' | C1: Theta-necessary | D1: Tau | E1: OldTau | F1: Size | G1: a | H1: b | I1: ij | J1: jj | K1: BUTIJ | L1: BUTII | M1: BCCIJ | N1: BCCJJ | O1: BCk | P1: BCS | Q1: BCPTJJ | R1: BCPTIJ | S1: BCPTII | T1: BRIJ | U1: BRJJ | V1: Toll | W1: Welfare | X1: Revenue | Y1: Cost | Z1: Utility | AA1: Profit | AB1: Size2 | AC1: W/Size | AD1: ∏/Size | AE1: U/Size | AF1: W-Tax(All-Tax)
A2: 0.08 | B2: =(I2+J2)*Beta*2 -> 51.727673 | C2: =(W2+B2*Theta-'W-Tax(All-Toll)-NONC'!$T$2)/B2 -> 0.47942868 | D2: 0.58886936 | E2: 0.58897197 | F2: 1 | G2: 0 | H2: =Size-a -> 1 | I2: =(EXP(alpha*(Tau+OldTau+zeta-2*a*psi))*((EXP(alpha*a*psi)-EXP(alpha*b*psi))^2))/((EXP(alpha*a*psi)-EXP(alpha*(2*OldTau+b*psi)))*(alpha^2)*(psi^2)) -> 0.10560469 | J2: =(EXP(alpha*(zeta+(2*b-a)*psi))*(-1+EXP(alpha*(-1)*Size*psi))*(EXP(alpha*(2*(Tau+OldTau)+a*psi))-EXP(alpha*(2*(Tau+OldTau)+b*psi))))/(((EXP(alpha*a*psi)-EXP(alpha*(2*OldTau+b*psi)))^2)*(alpha^2)*(psi^2)) -> 0.038083291 | K2: =-Beta/alpha -> 180 | L2: =(-EXP(alpha*zeta)*Beta*(-1+EXP(alpha*Size*psi)-Size*alpha*psi))/((alpha^3)*(psi^2)) -> 25.038896 | M2: =Beta*Theta -> 14.4 | N2: =Beta*Theta -> 14.4 | O2: =kappa -> 90 | P2: =Gamma*Size -> 0 | Q2: =Size*Beta*Phi -> 3.24 | R2: =-(EXP(alpha*a*psi)+EXP(alpha*b*psi)*(-1+Size*psi*alpha))*(Beta*Phi)/((alpha*psi)*(EXP(alpha*a*psi)-EXP(alpha*b*psi))) -> 1.5795152 | S2: =(EXP(alpha*(zeta-a*psi))*Beta*Phi*(-EXP(alpha*a*psi)*(-2+(-1)*Size*alpha*psi)+EXP(alpha*b*psi)*(-2+Size*alpha*psi)))/((alpha^3)*(psi^3)) -> 0.14651555 | T2: =Tau*Beta -> 105.99648 | U2: =Tau*Beta -> 105.99648 | V2: =Tau -> 0.58886936 | W2: =Profit+Utility -> -20.233146 | X2: =(2*ij*BRIJ)+2*jj*BRJJ -> 30.460841 | Y2: =2*(ij*BCCIJ)+(2*jj*BCCJJ)+BCS+jj*BCPTJJ+2*(ij*BCPTIJ)+BCPTII+BCk -> 94.741728 | Z2: =ij*BUTIJ+BUTII -> 44.04774 | AA2: =Revenue-Cost -> -64.280886 | AB2: =Size -> 1 | AC2: =Welfare/(Size) -> -20.233146 | AD2: =Profit/(Size) -> -64.280886 | AE2: =Utility/(Size) -> 44.04774 | AF2: 308.66096
A3: =C2 -> 0.47942868 | B3: =(I3+J3)*Beta*2 -> 16.207008 | C3: =(W3+B3*Theta-'W-Tax(All-Toll)-NONC'!$T$2)/B3 -> -0.074156554 | D3: 0.98825268 | E3: 0.98825268 | F3: 1 | G3: 0 | H3: =Size-a -> 1 | I3: =(EXP(alpha*(Tau+OldTau+zeta-2*a*psi))*((EXP(alpha*a*psi)-EXP(alpha*b*psi))^2))/((EXP(alpha*a*psi)-EXP(alpha*(2*OldTau+b*psi)))*(alpha^2)*(psi^2)) -> 0.039650747 | J3: =(EXP(alpha*(zeta+(2*b-a)*psi))*(-1+EXP(alpha*(-1)*Size*psi))*(EXP(alpha*(2*(Tau+OldTau)+a*psi))-EXP(alpha*(2*(Tau+OldTau)+b*psi))))/(((EXP(alpha*a*psi)-EXP(alpha*(2*OldTau+b*psi)))^2)*(alpha^2)*(psi^2)) -> 0.0053687207 | K3: =-Beta/alpha -> 180 | L3: =(-EXP(alpha*zeta)*Beta*(-1+EXP(alpha*Size*psi)-Size*alpha*psi))/((alpha^3)*(psi^2)) -> 25.038896 | M3: =Beta*Theta -> 86.297162 | N3: =Beta*Theta -> 86.297162 | O3: =kappa -> 90 | P3: =Gamma*Size -> 0 | Q3: =Size*Beta*Phi -> 3.24 | R3: =-(EXP(alpha*a*psi)+EXP(alpha*b*psi)*(-1+Size*psi*alpha))*(Beta*Phi)/((alpha*psi)*(EXP(alpha*a*psi)-EXP(alpha*b*psi))) -> 1.5795152 | S3: =(EXP(alpha*(zeta-a*psi))*Beta*Phi*(-EXP(alpha*a*psi)*(-2+(-1)*Size*alpha*psi)+EXP(alpha*b*psi)*(-2+Size*alpha*psi)))/((alpha^3)*(psi^3)) -> 0.14651555 | T3: =Tau*Beta -> 177.88548 | U3: =Tau*Beta -> 177.88548 | V3: =Tau -> 0.98825268 | W3: =Profit+Utility -> -49.866623 | X3: =(2*ij*BRIJ)+2*jj*BRJJ -> 16.016619 | Y3: =2*(ij*BCCIJ)+(2*jj*BCCJJ)+BCS+jj*BCPTJJ+2*(ij*BCPTIJ)+BCPTII+BCk -> 98.059273 | Z3: =ij*BUTIJ+BUTII -> 32.176031 | AA3: =Revenue-Cost -> -82.042653 | AB3: =Size -> 1 | AC3: =Welfare/(Size) -> -49.866623 | AD3: =Profit/(Size) -> -82.042653 | AE3: =Utility/(Size) -> 32.176031 | AF3: 308.66096
A4: =C3 -> -0.074156554 | B4: =(I4+J4)*Beta*2 -> 93.101983 | C4: =(W4+B4*Theta-'W-Tax(All-Toll)-NONC'!$T$2)/B4 -> 0.48540624 | D4: 0.43473781 | E4: 0.43468035 | F4: 1 | G4: 0 | H4: =Size-a -> 1 | I4: =(EXP(alpha*(Tau+OldTau+zeta-2*a*psi))*((EXP(alpha*a*psi)-EXP(alpha*b*psi))^2))/((EXP(alpha*a*psi)-EXP(alpha*(2*OldTau+b*psi)))*(alpha^2)*(psi^2)) -> 0.16530456 | J4: =(EXP(alpha*(zeta+(2*b-a)*psi))*(-1+EXP(alpha*(-1)*Size*psi))*(EXP(alpha*(2*(Tau+OldTau)+a*psi))-EXP(alpha*(2*(Tau+OldTau)+b*psi))))/(((EXP(alpha*a*psi)-EXP(alpha*(2*OldTau+b*psi)))^2)*(alpha^2)*(psi^2)) -> 0.093312055 | K4: =-Beta/alpha -> 180 | L4: =(-EXP(alpha*zeta)*Beta*(-1+EXP(alpha*Size*psi)-Size*alpha*psi))/((alpha^3)*(psi^2)) -> 25.038896 | M4: =Beta*Theta -> -13.34818 | N4: =Beta*Theta -> -13.34818 | O4: =kappa -> 90 | P4: =Gamma*Size -> 0 | Q4: =Size*Beta*Phi -> 3.24 | R4: =-(EXP(alpha*a*psi)+EXP(alpha*b*psi)*(-1+Size*psi*alpha))*(Beta*Phi)/((alpha*psi)*(EXP(alpha*a*psi)-EXP(alpha*b*psi))) -> 1.5795152 | S4: =(EXP(alpha*(zeta-a*psi))*Beta*Phi*(-EXP(alpha*a*psi)*(-2+(-1)*Size*alpha*psi)+EXP(alpha*b*psi)*(-2+Size*alpha*psi)))/((alpha^3)*(psi^3)) -> 0.14651555 | T4: =Tau*Beta -> 78.252806 | U4: =Tau*Beta -> 78.252806 | V4: =Tau -> 0.43473781 | W4: =Profit+Utility -> 11.201744 | X4: =(2*ij*BRIJ)+2*jj*BRJJ -> 40.474952 | Y4: =2*(ij*BCCIJ)+(2*jj*BCCJJ)+BCS+jj*BCPTJJ+2*(ij*BCPTIJ)+BCPTII+BCk -> 84.066927 | Z4: =ij*BUTIJ+BUTII -> 54.793718 | AA4: =Revenue-Cost -> -43.591974 | AB4: =Size -> 1 | AC4: =Welfare/(Size) -> 11.201744 | AD4: =Profit/(Size) -> -43.591974 | AE4: =Utility/(Size) -> 54.793718 | AF4: 308.66096
A5: =C4 -> 0.48540624 | B5: =(I5+J5)*Beta*2 -> 15.962322 | C5: =(W5+B5*Theta-'W-Tax(All-Toll)-NONC'!$T$2)/B5 -> -0.090352791 | D5: 0.99424681 | E5: 0.99424681 | F5: 1 | G5: 0 | H5: =Size-a -> 1 | I5: =(EXP(alpha*(Tau+OldTau+zeta-2*a*psi))*((EXP(alpha*a*psi)-EXP(alpha*b*psi))^2))/((EXP(alpha*a*psi)-EXP(alpha*(2*OldTau+b*psi)))*(alpha^2)*(psi^2)) -> 0.039115128 | J5: =(EXP(alpha*(zeta+(2*b-a)*psi))*(-1+EXP(alpha*(-1)*Size*psi))*(EXP(alpha*(2*(Tau+OldTau)+a*psi))-EXP(alpha*(2*(Tau+OldTau)+b*psi))))/(((EXP(alpha*a*psi)-EXP(alpha*(2*OldTau+b*psi)))^2)*(alpha^2)*(psi^2)) -> 0.0052246546 | K5: =-Beta/alpha -> 180 | L5: =(-EXP(alpha*zeta)*Beta*(-1+EXP(alpha*Size*psi)-Size*alpha*psi))/((alpha^3)*(psi^2)) -> 25.038896 | M5: =Beta*Theta -> 87.373123 | N5: =Beta*Theta -> 87.373123 | O5: =kappa -> 90 | P5: =Gamma*Size -> 0 | Q5: =Size*Beta*Phi -> 3.24 | R5: =-(EXP(alpha*a*psi)+EXP(alpha*b*psi)*(-1+Size*psi*alpha))*(Beta*Phi)/((alpha*psi)*(EXP(alpha*a*psi)-EXP(alpha*b*psi))) -> 1.5795152 | S5: =(EXP(alpha*(zeta-a*psi))*Beta*Phi*(-EXP(alpha*a*psi)*(-2+(-1)*Size*alpha*psi)+EXP(alpha*b*psi)*(-2+Size*alpha*psi)))/((alpha^3)*(psi^3)) -> 0.14651555 | T5: =Tau*Beta -> 178.96443 | U5: =Tau*Beta -> 178.96443 | V5: =Tau -> 0.99424681 | W5: =Profit+Utility -> -50.085113 | X5: =(2*ij*BRIJ)+2*jj*BRJJ -> 15.870488 | Y5: =2*(ij*BCCIJ)+(2*jj*BCCJJ)+BCS+jj*BCPTJJ+2*(ij*BCPTIJ)+BCPTII+BCk -> 98.03522 | Z5: =ij*BUTIJ+BUTII -> 32.079619 | AA5: =Revenue-Cost -> -82.164732 | AB5: =Size -> 1 | AC5: =Welfare/(Size) -> -50.085113 | AD5: =Profit/(Size) -> -82.164732 | AE5: =Utility/(Size) -> 32.079619 | AF5: 308.66096
A6: =C5 -> -0.090352791 | B6: =(I6+J6)*Beta*2 -> 99.82543 | C6: =(W6+B6*Theta-'W-Tax(All-Toll)-NONC'!$T$2)/B6 -> 0.48080255 | D6: 0.41854444 | E6: 0.41854444 | F6: 1 | G6: 0 | H6: =Size-a -> 1 | I6: =(EXP(alpha*(Tau+OldTau+zeta-2*a*psi))*((EXP(alpha*a*psi)-EXP(alpha*b*psi))^2))/((EXP(alpha*a*psi)-EXP(alpha*(2*OldTau+b*psi)))*(alpha^2)*(psi^2)) -> 0.17395691 | J6: =(EXP(alpha*(zeta+(2*b-a)*psi))*(-1+EXP(alpha*(-1)*Size*psi))*(EXP(alpha*(2*(Tau+OldTau)+a*psi))-EXP(alpha*(2*(Tau+OldTau)+b*psi))))/(((EXP(alpha*a*psi)-EXP(alpha*(2*OldTau+b*psi)))^2)*(alpha^2)*(psi^2)) -> 0.10333595 | K6: =-Beta/alpha -> 180 | L6: =(-EXP(alpha*zeta)*Beta*(-1+EXP(alpha*Size*psi)-Size*alpha*psi))/((alpha^3)*(psi^2)) -> 25.038896 | M6: =Beta*Theta -> -16.263502 | N6: =Beta*Theta -> -16.263502 | O6: =kappa -> 90 | P6: =Gamma*Size -> 0 | Q6: =Size*Beta*Phi -> 3.24 | R6: =-(EXP(alpha*a*psi)+EXP(alpha*b*psi)*(-1+Size*psi*alpha))*(Beta*Phi)/((alpha*psi)*(EXP(alpha*a*psi)-EXP(alpha*b*psi))) -> 1.5795152 | S6: =(EXP(alpha*(zeta-a*psi))*Beta*Phi*(-EXP(alpha*a*psi)*(-2+(-1)*Size*alpha*psi)+EXP(alpha*b*psi)*(-2+Size*alpha*psi)))/((alpha^3)*(psi^3)) -> 0.14651555 | T6: =Tau*Beta -> 75.337999 | U6: =Tau*Beta -> 75.337999 | V6: =Tau -> 0.41854444 | W6: =Profit+Utility -> 16.121166 | X6: =(2*ij*BRIJ)+2*jj*BRJJ -> 41.781378 | Y6: =2*(ij*BCCIJ)+(2*jj*BCCJJ)+BCS+jj*BCPTJJ+2*(ij*BCPTIJ)+BCPTII+BCk -> 82.011353 | Z6: =ij*BUTIJ+BUTII -> 56.35114 | AA6: =Revenue-Cost -> -40.229975 | AB6: =Size -> 1 | AC6: =Welfare/(Size) -> 16.121166 | AD6: =Profit/(Size) -> -40.229975 | AE6: =Utility/(Size) -> 56.35114 | AF6: 308.66096
A7: =C6 -> 0.48080255 | B7: =(I7+J7)*Beta*2 -> 35.08332 | C7: =(W7+B7*Theta-'W-Tax(All-Toll)-NONC'!$T$2)/B7 -> 0.40572361 | D7: =AVERAGE(D3:D6) -> 0.70894544 | E7: =AVERAGE(E3:E6) -> 0.70893107 | F7: 1 | G7: 0 | H7: =Size-a -> 1 | I7: =(EXP(alpha*(Tau+OldTau+zeta-2*a*psi))*((EXP(alpha*a*psi)-EXP(alpha*b*psi))^2))/((EXP(alpha*a*psi)-EXP(alpha*(2*OldTau+b*psi)))*(alpha^2)*(psi^2)) -> 0.07713574 | J7: =(EXP(alpha*(zeta+(2*b-a)*psi))*(-1+EXP(alpha*(-1)*Size*psi))*(EXP(alpha*(2*(Tau+OldTau)+a*psi))-EXP(alpha*(2*(Tau+OldTau)+b*psi))))/(((EXP(alpha*a*psi)-EXP(alpha*(2*OldTau+b*psi)))^2)*(alpha^2)*(psi^2)) -> 0.020317926 | K7: =-Beta/alpha -> 180 | L7: =(-EXP(alpha*zeta)*Beta*(-1+EXP(alpha*Size*psi)-Size*alpha*psi))/((alpha^3)*(psi^2)) -> 25.038896 | M7: =Beta*Theta -> 86.544459 | N7: =Beta*Theta -> 86.544459 | O7: =kappa -> 90 | P7: =Gamma*Size -> 0 | Q7: =Size*Beta*Phi -> 3.24 | R7: =-(EXP(alpha*a*psi)+EXP(alpha*b*psi)*(-1+Size*psi*alpha))*(Beta*Phi)/((alpha*psi)*(EXP(alpha*a*psi)-EXP(alpha*b*psi))) -> 1.5795152 | S7: =(EXP(alpha*(zeta-a*psi))*Beta*Phi*(-EXP(alpha*a*psi)*(-2+(-1)*Size*alpha*psi)+EXP(alpha*b*psi)*(-2+Size*alpha*psi)))/((alpha^3)*(psi^3)) -> 0.14651555 | T7: =Tau*Beta -> 127.61018 | U7: =Tau*Beta -> 127.61018 | V7: =Tau -> 0.70894544 | W7: =Profit+Utility -> -43.528681 | X7: =(2*ij*BRIJ)+2*jj*BRJJ -> 24.872159 | Y7: =2*(ij*BCCIJ)+(2*jj*BCCJJ)+BCS+jj*BCPTJJ+2*(ij*BCPTIJ)+BCPTII+BCk -> 107.32417 | Z7: =ij*BUTIJ+BUTII -> 38.92333 | AA7: =Revenue-Cost -> -82.45201 | AB7: =Size -> 1 | AC7: =Welfare/(Size) -> -43.528681 | AD7: =Profit/(Size) -> -82.45201 | AE7: =Utility/(Size) -> 38.92333 | AF7: 308.66096
A8: =C7 -> 0.40572361 | B8: =(I8+J8)*Beta*2 -> 19.614536 | C8: =(W8+B8*Theta-'W-Tax(All-Toll)-NONC'!$T$2)/B8 -> 0.10223213 | D8: 0.91457154 | E8: 0.91457154 | F8: 1 | G8: 0 | H8: =Size-a -> 1 | I8: =(EXP(alpha*(Tau+OldTau+zeta-2*a*psi))*((EXP(alpha*a*psi)-EXP(alpha*b*psi))^2))/((EXP(alpha*a*psi)-EXP(alpha*(2*OldTau+b*psi)))*(alpha^2)*(psi^2)) -> 0.046955696 | J8: =(EXP(alpha*(zeta+(2*b-a)*psi))*(-1+EXP(alpha*(-1)*Size*psi))*(EXP(alpha*(2*(Tau+OldTau)+a*psi))-EXP(alpha*(2*(Tau+OldTau)+b*psi))))/(((EXP(alpha*a*psi)-EXP(alpha*(2*OldTau+b*psi)))^2)*(alpha^2)*(psi^2)) -> 0.0075291272 | K8: =-Beta/alpha -> 180 | L8: =(-EXP(alpha*zeta)*Beta*(-1+EXP(alpha*Size*psi)-Size*alpha*psi))/((alpha^3)*(psi^2)) -> 25.038896 | M8: =Beta*Theta -> 73.03025 | N8: =Beta*Theta -> 73.03025 | O8: =kappa -> 90 | P8: =Gamma*Size -> 0 | Q8: =Size*Beta*Phi -> 3.24 | R8: =-(EXP(alpha*a*psi)+EXP(alpha*b*psi)*(-1+Size*psi*alpha))*(Beta*Phi)/((alpha*psi)*(EXP(alpha*a*psi)-EXP(alpha*b*psi))) -> 1.5795152 | S8: =(EXP(alpha*(zeta-a*psi))*Beta*Phi*(-EXP(alpha*a*psi)*(-2+(-1)*Size*alpha*psi)+EXP(alpha*b*psi)*(-2+Size*alpha*psi)))/((alpha^3)*(psi^3)) -> 0.14651555 | T8: =Tau*Beta -> 164.62288 | U8: =Tau*Beta -> 164.62288 | V8: =Tau -> 0.91457154 | W8: =Profit+Utility -> -46.847507 | X8: =(2*ij*BRIJ)+2*jj*BRJJ -> 17.938897 | Y8: =2*(ij*BCCIJ)+(2*jj*BCCJJ)+BCS+jj*BCPTJJ+2*(ij*BCPTIJ)+BCPTII+BCk -> 98.277325 | Z8: =ij*BUTIJ+BUTII -> 33.490922 | AA8: =Revenue-Cost -> -80.338428 | AB8: =Size -> 1 | AC8: =Welfare/(Size) -> -46.847507 | AD8: =Profit/(Size) -> -80.338428 | AE8: =Utility/(Size) -> 33.490922 | AF8: 308.66096
A9: =C8 -> 0.10223213 | B9: =(I9+J9)*Beta*2 -> 47.97648 | C9: =(W9+B9*Theta-'W-Tax(All-Toll)-NONC'!$T$2)/B9 -> 0.4707788 | D9: 0.61107533 | E9: 0.61107533 | F9: 1 | G9: 0 | H9: =Size-a -> 1 | I9: =(EXP(alpha*(Tau+OldTau+zeta-2*a*psi))*((EXP(alpha*a*psi)-EXP(alpha*b*psi))^2))/((EXP(alpha*a*psi)-EXP(alpha*(2*OldTau+b*psi)))*(alpha^2)*(psi^2)) -> 0.099476427 | J9: =(EXP(alpha*(zeta+(2*b-a)*psi))*(-1+EXP(alpha*(-1)*Size*psi))*(EXP(alpha*(2*(Tau+OldTau)+a*psi))-EXP(alpha*(2*(Tau+OldTau)+b*psi))))/(((EXP(alpha*a*psi)-EXP(alpha*(2*OldTau+b*psi)))^2)*(alpha^2)*(psi^2)) -> 0.033791574 | K9: =-Beta/alpha -> 180 | L9: =(-EXP(alpha*zeta)*Beta*(-1+EXP(alpha*Size*psi)-Size*alpha*psi))/((alpha^3)*(psi^2)) -> 25.038896 | M9: =Beta*Theta -> 18.401784 | N9: =Beta*Theta -> 18.401784 | O9: =kappa -> 90 | P9: =Gamma*Size -> 0 | Q9: =Size*Beta*Phi -> 3.24 | R9: =-(EXP(alpha*a*psi)+EXP(alpha*b*psi)*(-1+Size*psi*alpha))*(Beta*Phi)/((alpha*psi)*(EXP(alpha*a*psi)-EXP(alpha*b*psi))) -> 1.5795152 | S9: =(EXP(alpha*(zeta-a*psi))*Beta*Phi*(-EXP(alpha*a*psi)*(-2+(-1)*Size*alpha*psi)+EXP(alpha*b*psi)*(-2+Size*alpha*psi)))/((alpha^3)*(psi^3)) -> 0.14651555 | T9: =Tau*Beta -> 109.99356 | U9: =Tau*Beta -> 109.99356 | V9: =Tau -> 0.61107533 | W9: =Profit+Utility -> -23.21309 | X9: =(2*ij*BRIJ)+2*jj*BRJJ -> 29.317244 | Y9: =2*(ij*BCCIJ)+(2*jj*BCCJJ)+BCS+jj*BCPTJJ+2*(ij*BCPTIJ)+BCPTII+BCk -> 95.474987 | Z9: =ij*BUTIJ+BUTII -> 42.944653 | AA9: =Revenue-Cost -> -66.157744 | AB9: =Size -> 1 | AC9: =Welfare/(Size) -> -23.21309 | AD9: =Profit/(Size) -> -66.157744 | AE9: =Utility/(Size) -> 42.944653 | AF9: 308.66096
A10: =C9 -> 0.4707788 | B10: =(I10+J10)*Beta*2 -> 16.567053 | C10: =(W10+B10*Theta-'W-Tax(All-Toll)-NONC'!$T$2)/B10 -> -0.051353561 | D10: 0.97962579 | E10: 0.97962579 | F10: 1 | G10: 0 | H10: =Size-a -> 1 | I10: =(EXP(alpha*(Tau+OldTau+zeta-2*a*psi))*((EXP(alpha*a*psi)-EXP(alpha*b*psi))^2))/((EXP(alpha*a*psi)-EXP(alpha*(2*OldTau+b*psi)))*(alpha^2)*(psi^2)) -> 0.040436093 | J10: =(EXP(alpha*(zeta+(2*b-a)*psi))*(-1+EXP(alpha*(-1)*Size*psi))*(EXP(alpha*(2*(Tau+OldTau)+a*psi))-EXP(alpha*(2*(Tau+OldTau)+b*psi))))/(((EXP(alpha*a*psi)-EXP(alpha*(2*OldTau+b*psi)))^2)*(alpha^2)*(psi^2)) -> 0.005583499 | K10: =-Beta/alpha -> 180 | L10: =(-EXP(alpha*zeta)*Beta*(-1+EXP(alpha*Size*psi)-Size*alpha*psi))/((alpha^3)*(psi^2)) -> 25.038896 | M10: =Beta*Theta -> 84.740183 | N10: =Beta*Theta -> 84.740183 | O10: =kappa -> 90 | P10: =Gamma*Size -> 0 | Q10: =Size*Beta*Phi -> 3.24 | R10: =-(EXP(alpha*a*psi)+EXP(alpha*b*psi)*(-1+Size*psi*alpha))*(Beta*Phi)/((alpha*psi)*(EXP(alpha*a*psi)-EXP(alpha*b*psi))) -> 1.5795152 | S10: =(EXP(alpha*(zeta-a*psi))*Beta*Phi*(-EXP(alpha*a*psi)*(-2+(-1)*Size*alpha*psi)+EXP(alpha*b*psi)*(-2+Size*alpha*psi)))/((alpha^3)*(psi^3)) -> 0.14651555 | T10: =Tau*Beta -> 176.33264 | U10: =Tau*Beta -> 176.33264 | V10: =Tau -> 0.97962579 | W10: =Profit+Utility -> -49.544857 | X10: =(2*ij*BRIJ)+2*jj*BRJJ -> 16.229513 | Y10: =2*(ij*BCCIJ)+(2*jj*BCCJJ)+BCS+jj*BCPTJJ+2*(ij*BCPTIJ)+BCPTII+BCk -> 98.091762 | Z10: =ij*BUTIJ+BUTII -> 32.317393 | AA10: =Revenue-Cost -> -81.86225 | AB10: =Size -> 1 | AC10: =Welfare/(Size) -> -49.544857 | AD10: =Profit/(Size) -> -81.86225 | AE10: =Utility/(Size) -> 32.317393 | AF10: 308.66096
A11: =C10 -> -0.051353561 | B11: =(I11+J11)*Beta*2 -> 84.631118 | C11: =(W11+B11*Theta-'W-Tax(All-Toll)-NONC'!$T$2)/B11 -> 0.49021168 | D11: 0.45752094 | E11: 0.45752094 | F11: 1 | G11: 0 | H11: =Size-a -> 1 | I11: =(EXP(alpha*(Tau+OldTau+zeta-2*a*psi))*((EXP(alpha*a*psi)-EXP(alpha*b*psi))^2))/((EXP(alpha*a*psi)-EXP(alpha*(2*OldTau+b*psi)))*(alpha^2)*(psi^2)) -> 0.15404899 | J11: =(EXP(alpha*(zeta+(2*b-a)*psi))*(-1+EXP(alpha*(-1)*Size*psi))*(EXP(alpha*(2*(Tau+OldTau)+a*psi))-EXP(alpha*(2*(Tau+OldTau)+b*psi))))/(((EXP(alpha*a*psi)-EXP(alpha*(2*OldTau+b*psi)))^2)*(alpha^2)*(psi^2)) -> 0.08103745 | K11: =-Beta/alpha -> 180 | L11: =(-EXP(alpha*zeta)*Beta*(-1+EXP(alpha*Size*psi)-Size*alpha*psi))/((alpha^3)*(psi^2)) -> 25.038896 | M11: =Beta*Theta -> -9.2436409 | N11: =Beta*Theta -> -9.2436409 | O11: =kappa -> 90 | P11: =Gamma*Size -> 0 | Q11: =Size*Beta*Phi -> 3.24 | R11: =-(EXP(alpha*a*psi)+EXP(alpha*b*psi)*(-1+Size*psi*alpha))*(Beta*Phi)/((alpha*psi)*(EXP(alpha*a*psi)-EXP(alpha*b*psi))) -> 1.5795152 | S11: =(EXP(alpha*(zeta-a*psi))*Beta*Phi*(-EXP(alpha*a*psi)*(-2+(-1)*Size*alpha*psi)+EXP(alpha*b*psi)*(-2+Size*alpha*psi)))/((alpha^3)*(psi^3)) -> 0.14651555 | T11: =Tau*Beta -> 82.353769 | U11: =Tau*Beta -> 82.353769 | V11: =Tau -> 0.45752094 | W11: =Profit+Utility -> 4.9386097 | X11: =(2*ij*BRIJ)+2*jj*BRJJ -> 38.720509 | Y11: =2*(ij*BCCIJ)+(2*jj*BCCJJ)+BCS+jj*BCPTJJ+2*(ij*BCPTIJ)+BCPTII+BCk -> 86.549613 | Z11: =ij*BUTIJ+BUTII -> 52.767714 | AA11: =Revenue-Cost -> -47.829105 | AB11: =Size -> 1 | AC11: =Welfare/(Size) -> 4.9386097 | AD11: =Profit/(Size) -> -47.829105 | AE11: =Utility/(Size) -> 52.767714 | AF11: 308.66096
A13: 0.08 | B13: =(I13+J13)*Beta*2 -> 870.51131 | C13: =(W13+B13*Theta-'W-Tax(All-Toll)-NONC'!$T$5)/B13 -> 0.45545343 | D13: 0.65078513 | E13: 0.65078513 | F13: 10 | G13: 0 | H13: =Size-a -> 10 | I13: =(EXP(alpha*(Tau+OldTau+zeta-2*a*psi))*((EXP(alpha*a*psi)-EXP(alpha*b*psi))^2))/((EXP(alpha*a*psi)-EXP(alpha*(2*OldTau+b*psi)))*(alpha^2)*(psi^2)) -> 2.2712737 | J13: =(EXP(alpha*(zeta+(2*b-a)*psi))*(-1+EXP(alpha*(-1)*Size*psi))*(EXP(alpha*(2*(Tau+OldTau)+a*psi))-EXP(alpha*(2*(Tau+OldTau)+b*psi))))/(((EXP(alpha*a*psi)-EXP(alpha*(2*OldTau+b*psi)))^2)*(alpha^2)*(psi^2)) -> 0.1468133 | K13: =-Beta/alpha -> 180 | L13: =(-EXP(alpha*zeta)*Beta*(-1+EXP(alpha*Size*psi)-Size*alpha*psi))/((alpha^3)*(psi^2)) -> 1690.9246 | M13: =Beta*Theta -> 14.4 | N13: =Beta*Theta -> 14.4 | O13: =kappa -> 90 | P13: =Gamma*Size -> 0 | Q13: =Size*Beta*Phi -> 32.4 | R13: =-(EXP(alpha*a*psi)+EXP(alpha*b*psi)*(-1+Size*psi*alpha))*(Beta*Phi)/((alpha*psi)*(EXP(alpha*a*psi)-EXP(alpha*b*psi))) -> 12.294172 | S13: =(EXP(alpha*(zeta-a*psi))*Beta*Phi*(-EXP(alpha*a*psi)*(-2+(-1)*Size*alpha*psi)+EXP(alpha*b*psi)*(-2+Size*alpha*psi)))/((alpha^3)*(psi^3)) -> 78.836376 | T13: =Tau*Beta -> 117.14132 | U13: =Tau*Beta -> 117.14132 | V13: =Tau -> 0.65078513 | W13: =Profit+Utility -> 2367.1888 | X13: =(2*ij*BRIJ)+2*jj*BRJJ -> 566.51581 | Y13: =2*(ij*BCCIJ)+(2*jj*BCCJJ)+BCS+jj*BCPTJJ+2*(ij*BCPTIJ)+BCPTII+BCk -> 299.08089 | Z13: =ij*BUTIJ+BUTII -> 2099.7539 | AA13: =Revenue-Cost -> 267.43492 | AB13: =Size -> 10 | AC13: =Welfare/(Size) -> 236.71888 | AD13: =Profit/(Size) -> 26.743492 | AE13: =Utility/(Size) -> 209.97539 | AF13: 308.66096
A14: =C13 -> 0.45545343 | B14: =(I14+J14)*Beta*2 -> 385.10344 | C14: =(W14+B14*Theta-'W-Tax(All-Toll)-NONC'!$T$5)/B14 -> 0.095902777 | D14: 1.0249661 | E14: 1.0251767 | F14: 10 | G14: 0 | H14: =Size-a -> 10 | I14: =(EXP(alpha*(Tau+OldTau+zeta-2*a*psi))*((EXP(alpha*a*psi)-EXP(alpha*b*psi))^2))/((EXP(alpha*a*psi)-EXP(alpha*(2*OldTau+b*psi)))*(alpha^2)*(psi^2)) -> 1.0390087 | J14: =(EXP(alpha*(zeta+(2*b-a)*psi))*(-1+EXP(alpha*(-1)*Size*psi))*(EXP(alpha*(2*(Tau+OldTau)+a*psi))-EXP(alpha*(2*(Tau+OldTau)+b*psi))))/(((EXP(alpha*a*psi)-EXP(alpha*(2*OldTau+b*psi)))^2)*(alpha^2)*(psi^2)) -> 0.030723086 | K14: =-Beta/alpha -> 180 | L14: =(-EXP(alpha*zeta)*Beta*(-1+EXP(alpha*Size*psi)-Size*alpha*psi))/((alpha^3)*(psi^2)) -> 1690.9246 | M14: =Beta*Theta -> 81.981618 | N14: =Beta*Theta -> 81.981618 | O14: =kappa -> 90 | P14: =Gamma*Size -> 0 | Q14: =Size*Beta*Phi -> 32.4 | R14: =-(EXP(alpha*a*psi)+EXP(alpha*b*psi)*(-1+Size*psi*alpha))*(Beta*Phi)/((alpha*psi)*(EXP(alpha*a*psi)-EXP(alpha*b*psi))) -> 12.294172 | S14: =(EXP(alpha*(zeta-a*psi))*Beta*Phi*(-EXP(alpha*a*psi)*(-2+(-1)*Size*alpha*psi)+EXP(alpha*b*psi)*(-2+Size*alpha*psi)))/((alpha^3)*(psi^3)) -> 78.836376 | T14: =Tau*Beta -> 184.49389 | U14: =Tau*Beta -> 184.49389 | V14: =Tau -> 1.0249661 | W14: =Profit+Utility -> 1901.8882 | X14: =(2*ij*BRIJ)+2*jj*BRJJ -> 394.71795 | Y14: =2*(ij*BCCIJ)+(2*jj*BCCJJ)+BCS+jj*BCPTJJ+2*(ij*BCPTIJ)+BCPTII+BCk -> 370.77599 | Z14: =ij*BUTIJ+BUTII -> 1877.9462 | AA14: =Revenue-Cost -> 23.941965 | AB14: =Size -> 10 | AC14: =Welfare/(Size) -> 190.18882 | AD14: =Profit/(Size) -> 2.3941965 | AE14: =Utility/(Size) -> 187.79462 | AF14: 308.66096
A15: =C14 -> 0.095902777 | B15: =(I15+J15)*Beta*2 -> 839.99233 | C15: =(W15+B15*Theta-'W-Tax(All-Toll)-NONC'!$T$5)/B15 -> 0.45064132 | D15: 0.66661655 | E15: 0.66661655 | F15: 10 | G15: 0 | H15: =Size-a -> 10 | I15: =(EXP(alpha*(Tau+OldTau+zeta-2*a*psi))*((EXP(alpha*a*psi)-EXP(alpha*b*psi))^2))/((EXP(alpha*a*psi)-EXP(alpha*(2*OldTau+b*psi)))*(alpha^2)*(psi^2)) -> 2.1960611 | J15: =(EXP(alpha*(zeta+(2*b-a)*psi))*(-1+EXP(alpha*(-1)*Size*psi))*(EXP(alpha*(2*(Tau+OldTau)+a*psi))-EXP(alpha*(2*(Tau+OldTau)+b*psi))))/(((EXP(alpha*a*psi)-EXP(alpha*(2*OldTau+b*psi)))^2)*(alpha^2)*(psi^2)) -> 0.13725094 | K15: =-Beta/alpha -> 180 | L15: =(-EXP(alpha*zeta)*Beta*(-1+EXP(alpha*Size*psi)-Size*alpha*psi))/((alpha^3)*(psi^2)) -> 1690.9246 | M15: =Beta*Theta -> 17.2625 | N15: =Beta*Theta -> 17.2625 | O15: =kappa -> 90 | P15: =Gamma*Size -> 0 | Q15: =Size*Beta*Phi -> 32.4 | R15: =-(EXP(alpha*a*psi)+EXP(alpha*b*psi)*(-1+Size*psi*alpha))*(Beta*Phi)/((alpha*psi)*(EXP(alpha*a*psi)-EXP(alpha*b*psi))) -> 12.294172 | S15: =(EXP(alpha*(zeta-a*psi))*Beta*Phi*(-EXP(alpha*a*psi)*(-2+(-1)*Size*alpha*psi)+EXP(alpha*b*psi)*(-2+Size*alpha*psi)))/((alpha^3)*(psi^3)) -> 78.836376 | T15: =Tau*Beta -> 119.99098 | U15: =Tau*Beta -> 119.99098 | V15: =Tau -> 0.66661655 | W15: =Profit+Utility -> 2338.33 | X15: =(2*ij*BRIJ)+2*jj*BRJJ -> 559.95279 | Y15: =2*(ij*BCCIJ)+(2*jj*BCCJJ)+BCS+jj*BCPTJJ+2*(ij*BCPTIJ)+BCPTII+BCk -> 307.83841 | Z15: =ij*BUTIJ+BUTII -> 2086.2156 | AA15: =Revenue-Cost -> 252.11438 | AB15: =Size -> 10 | AC15: =Welfare/(Size) -> 233.833 | AD15: =Profit/(Size) -> 25.211438 | AE15: =Utility/(Size) -> 208.62156 | AF15: 308.66096
A16: =C15 -> 0.45064132 | B16: =(I16+J16)*Beta*2 -> 389.00147 | C16: =(W16+B16*Theta-'W-Tax(All-Toll)-NONC'!$T$5)/B16 -> 0.10460045 | D16: 1.0203213 | E16: 1.0203213 | F16: 10 | G16: 0 | H16: =Size-a -> 10 | I16: =(EXP(alpha*(Tau+OldTau+zeta-2*a*psi))*((EXP(alpha*a*psi)-EXP(alpha*b*psi))^2))/((EXP(alpha*a*psi)-EXP(alpha*(2*OldTau+b*psi)))*(alpha^2)*(psi^2)) -> 1.0492291 | J16: =(EXP(alpha*(zeta+(2*b-a)*psi))*(-1+EXP(alpha*(-1)*Size*psi))*(EXP(alpha*(2*(Tau+OldTau)+a*psi))-EXP(alpha*(2*(Tau+OldTau)+b*psi))))/(((EXP(alpha*a*psi)-EXP(alpha*(2*OldTau+b*psi)))^2)*(alpha^2)*(psi^2)) -> 0.03133049 | K16: =-Beta/alpha -> 180 | L16: =(-EXP(alpha*zeta)*Beta*(-1+EXP(alpha*Size*psi)-Size*alpha*psi))/((alpha^3)*(psi^2)) -> 1690.9246 | M16: =Beta*Theta -> 81.115437 | N16: =Beta*Theta -> 81.115437 | O16: =kappa -> 90 | P16: =Gamma*Size -> 0 | Q16: =Size*Beta*Phi -> 32.4 | R16: =-(EXP(alpha*a*psi)+EXP(alpha*b*psi)*(-1+Size*psi*alpha))*(Beta*Phi)/((alpha*psi)*(EXP(alpha*a*psi)-EXP(alpha*b*psi))) -> 12.294172 | S16: =(EXP(alpha*(zeta-a*psi))*Beta*Phi*(-EXP(alpha*a*psi)*(-2+(-1)*Size*alpha*psi)+EXP(alpha*b*psi)*(-2+Size*alpha*psi)))/((alpha^3)*(psi^3)) -> 78.836376 | T16: =Tau*Beta -> 183.65784 | U16: =Tau*Beta -> 183.65784 | V16: =Tau -> 1.0203213 | W16: =Profit+Utility -> 1905.7419 | X16: =(2*ij*BRIJ)+2*jj*BRJJ -> 396.90649 | Y16: =2*(ij*BCCIJ)+(2*jj*BCCJJ)+BCS+jj*BCPTJJ+2*(ij*BCPTIJ)+BCPTII+BCk -> 370.95043 | Z16: =ij*BUTIJ+BUTII -> 1879.7859 | AA16: =Revenue-Cost -> 25.956068 | AB16: =Size -> 10 | AC16: =Welfare/(Size) -> 190.57419 | AD16: =Profit/(Size) -> 2.5956068 | AE16: =Utility/(Size) -> 187.97859 | AF16: 308.66096
A17: =C16 -> 0.10460045 | B17: =(I17+J17)*Beta*2 -> 824.47241 | C17: =(W17+B17*Theta-'W-Tax(All-Toll)-NONC'!$T$5)/B17 -> 0.4481915 | D17: 0.67527592 | E17: 0.67459002 | F17: 10 | G17: 0 | H17: =Size-a -> 10 | I17: =(EXP(alpha*(Tau+OldTau+zeta-2*a*psi))*((EXP(alpha*a*psi)-EXP(alpha*b*psi))^2))/((EXP(alpha*a*psi)-EXP(alpha*(2*OldTau+b*psi)))*(alpha^2)*(psi^2)) -> 2.157703 | J17: =(EXP(alpha*(zeta+(2*b-a)*psi))*(-1+EXP(alpha*(-1)*Size*psi))*(EXP(alpha*(2*(Tau+OldTau)+a*psi))-EXP(alpha*(2*(Tau+OldTau)+b*psi))))/(((EXP(alpha*a*psi)-EXP(alpha*(2*OldTau+b*psi)))^2)*(alpha^2)*(psi^2)) -> 0.13249815 | K17: =-Beta/alpha -> 180 | L17: =(-EXP(alpha*zeta)*Beta*(-1+EXP(alpha*Size*psi)-Size*alpha*psi))/((alpha^3)*(psi^2)) -> 1690.9246 | M17: =Beta*Theta -> 18.828081 | N17: =Beta*Theta -> 18.828081 | O17: =kappa -> 90 | P17: =Gamma*Size -> 0 | Q17: =Size*Beta*Phi -> 32.4 | R17: =-(EXP(alpha*a*psi)+EXP(alpha*b*psi)*(-1+Size*psi*alpha))*(Beta*Phi)/((alpha*psi)*(EXP(alpha*a*psi)-EXP(alpha*b*psi))) -> 12.294172 | S17: =(EXP(alpha*(zeta-a*psi))*Beta*Phi*(-EXP(alpha*a*psi)*(-2+(-1)*Size*alpha*psi)+EXP(alpha*b*psi)*(-2+Size*alpha*psi)))/((alpha^3)*(psi^3)) -> 78.836376 | T17: =Tau*Beta -> 121.54967 | U17: =Tau*Beta -> 121.54967 | V17: =Tau -> 0.67527592 | W17: =Profit+Utility -> 2323.6337 | X17: =(2*ij*BRIJ)+2*jj*BRJJ -> 556.74636 | Y17: =2*(ij*BCCIJ)+(2*jj*BCCJJ)+BCS+jj*BCPTJJ+2*(ij*BCPTIJ)+BCPTII+BCk -> 312.42384 | Z17: =ij*BUTIJ+BUTII -> 2079.3112 | AA17: =Revenue-Cost -> 244.32252 | AB17: =Size -> 10 | AC17: =Welfare/(Size) -> 232.36337 | AD17: =Profit/(Size) -> 24.432252 | AE17: =Utility/(Size) -> 207.93112 | AF17: 308.66096
A18: =C17 -> 0.4481915 | B18: =(I18+J18)*Beta*2 -> 564.36577 | C18: =(W18+B18*Theta-'W-Tax(All-Toll)-NONC'!$T$5)/B18 -> 0.33877659 | D18: =AVERAGE(D14:D17) -> 0.84679496 | E18: =AVERAGE(E14:E17) -> 0.84667616 | F18: 10 | G18: 0 | H18: =Size-a -> 10 | I18: =(EXP(alpha*(Tau+OldTau+zeta-2*a*psi))*((EXP(alpha*a*psi)-EXP(alpha*b*psi))^2))/((EXP(alpha*a*psi)-EXP(alpha*(2*OldTau+b*psi)))*(alpha^2)*(psi^2)) -> 1.5033616 | J18: =(EXP(alpha*(zeta+(2*b-a)*psi))*(-1+EXP(alpha*(-1)*Size*psi))*(EXP(alpha*(2*(Tau+OldTau)+a*psi))-EXP(alpha*(2*(Tau+OldTau)+b*psi))))/(((EXP(alpha*a*psi)-EXP(alpha*(2*OldTau+b*psi)))^2)*(alpha^2)*(psi^2)) -> 0.06432109 | K18: =-Beta/alpha -> 180 | L18: =(-EXP(alpha*zeta)*Beta*(-1+EXP(alpha*Size*psi)-Size*alpha*psi))/((alpha^3)*(psi^2)) -> 1690.9246 | M18: =Beta*Theta -> 80.674469 | N18: =Beta*Theta -> 80.674469 | O18: =kappa -> 90 | P18: =Gamma*Size -> 0 | Q18: =Size*Beta*Phi -> 32.4 | R18: =-(EXP(alpha*a*psi)+EXP(alpha*b*psi)*(-1+Size*psi*alpha))*(Beta*Phi)/((alpha*psi)*(EXP(alpha*a*psi)-EXP(alpha*b*psi))) -> 12.294172 | S18: =(EXP(alpha*(zeta-a*psi))*Beta*Phi*(-EXP(alpha*a*psi)*(-2+(-1)*Size*alpha*psi)+EXP(alpha*b*psi)*(-2+Size*alpha*psi)))/((alpha^3)*(psi^3)) -> 78.836376 | T18: =Tau*Beta -> 152.42309 | U18: =Tau*Beta -> 152.42309 | V18: =Tau -> 0.84679496 | W18: =Profit+Utility -> 1978.6023 | X18: =(2*ij*BRIJ)+2*jj*BRJJ -> 477.90209 | Y18: =2*(ij*BCCIJ)+(2*jj*BCCJJ)+BCS+jj*BCPTJJ+2*(ij*BCPTIJ)+BCPTII+BCk -> 460.82949 | Z18: =ij*BUTIJ+BUTII -> 1961.5297 | AA18: =Revenue-Cost -> 17.072603 | AB18: =Size -> 10 | AC18: =Welfare/(Size) -> 197.86023 | AD18: =Profit/(Size) -> 1.7072603 | AE18: =Utility/(Size) -> 196.15297 | AF18: 308.66096
A19: =C18 -> 0.33877659 | B19: =(I19+J19)*Beta*2 -> 493.84318 | C19: =(W19+B19*Theta-'W-Tax(All-Toll)-NONC'!$T$5)/B19 -> 0.27192744 | D19: 0.90859616 | E19: 0.90843887 | F19: 10 | G19: 0 | H19: =Size-a -> 10 | I19: =(EXP(alpha*(Tau+OldTau+zeta-2*a*psi))*((EXP(alpha*a*psi)-EXP(alpha*b*psi))^2))/((EXP(alpha*a*psi)-EXP(alpha*(2*OldTau+b*psi)))*(alpha^2)*(psi^2)) -> 1.3220451 | J19: =(EXP(alpha*(zeta+(2*b-a)*psi))*(-1+EXP(alpha*(-1)*Size*psi))*(EXP(alpha*(2*(Tau+OldTau)+a*psi))-EXP(alpha*(2*(Tau+OldTau)+b*psi))))/(((EXP(alpha*a*psi)-EXP(alpha*(2*OldTau+b*psi)))^2)*(alpha^2)*(psi^2)) -> 0.049741517 | K19: =-Beta/alpha -> 180 | L19: =(-EXP(alpha*zeta)*Beta*(-1+EXP(alpha*Size*psi)-Size*alpha*psi))/((alpha^3)*(psi^2)) -> 1690.9246 | M19: =Beta*Theta -> 60.979786 | N19: =Beta*Theta -> 60.979786 | O19: =kappa -> 90 | P19: =Gamma*Size -> 0 | Q19: =Size*Beta*Phi -> 32.4 | R19: =-(EXP(alpha*a*psi)+EXP(alpha*b*psi)*(-1+Size*psi*alpha))*(Beta*Phi)/((alpha*psi)*(EXP(alpha*a*psi)-EXP(alpha*b*psi))) -> 12.294172 | S19: =(EXP(alpha*(zeta-a*psi))*Beta*Phi*(-EXP(alpha*a*psi)*(-2+(-1)*Size*alpha*psi)+EXP(alpha*b*psi)*(-2+Size*alpha*psi)))/((alpha^3)*(psi^3)) -> 78.836376 | T19: =Tau*Beta -> 163.54731 | U19: =Tau*Beta -> 163.54731 | V19: =Tau -> 0.90859616 | W19: =Profit+Utility -> 2007.3394 | X19: =(2*ij*BRIJ)+2*jj*BRJJ -> 448.70402 | Y19: =2*(ij*BCCIJ)+(2*jj*BCCJJ)+BCS+jj*BCPTJJ+2*(ij*BCPTIJ)+BCPTII+BCk -> 370.25741 | Z19: =ij*BUTIJ+BUTII -> 1928.8927 | AA19: =Revenue-Cost -> 78.44661 | AB19: =Size -> 10 | AC19: =Welfare/(Size) -> 200.73394 | AD19: =Profit/(Size) -> 7.844661 | AE19: =Utility/(Size) -> 192.88927 | AF19: 308.66096
A20: =C19 -> 0.27192744 | B20: =(I20+J20)*Beta*2 -> 570.42458 | C20: =(W20+B20*Theta-'W-Tax(All-Toll)-NONC'!$T$5)/B20 -> 0.34347913 | D20: 0.8419551 | E20: 0.84168948 | F20: 10 | G20: 0 | H20: =Size-a -> 10 | I20: =(EXP(alpha*(Tau+OldTau+zeta-2*a*psi))*((EXP(alpha*a*psi)-EXP(alpha*b*psi))^2))/((EXP(alpha*a*psi)-EXP(alpha*(2*OldTau+b*psi)))*(alpha^2)*(psi^2)) -> 1.5188587 | J20: =(EXP(alpha*(zeta+(2*b-a)*psi))*(-1+EXP(alpha*(-1)*Size*psi))*(EXP(alpha*(2*(Tau+OldTau)+a*psi))-EXP(alpha*(2*(Tau+OldTau)+b*psi))))/(((EXP(alpha*a*psi)-EXP(alpha*(2*OldTau+b*psi)))^2)*(alpha^2)*(psi^2)) -> 0.065654007 | K20: =-Beta/alpha -> 180 | L20: =(-EXP(alpha*zeta)*Beta*(-1+EXP(alpha*Size*psi)-Size*alpha*psi))/((alpha^3)*(psi^2)) -> 1690.9246 | M20: =Beta*Theta -> 48.94694 | N20: =Beta*Theta -> 48.94694 | O20: =kappa -> 90 | P20: =Gamma*Size -> 0 | Q20: =Size*Beta*Phi -> 32.4 | R20: =-(EXP(alpha*a*psi)+EXP(alpha*b*psi)*(-1+Size*psi*alpha))*(Beta*Phi)/((alpha*psi)*(EXP(alpha*a*psi)-EXP(alpha*b*psi))) -> 12.294172 | S20: =(EXP(alpha*(zeta-a*psi))*Beta*Phi*(-EXP(alpha*a*psi)*(-2+(-1)*Size*alpha*psi)+EXP(alpha*b*psi)*(-2+Size*alpha*psi)))/((alpha^3)*(psi^3)) -> 78.836376 | T20: =Tau*Beta -> 151.55192 | U20: =Tau*Beta -> 151.55192 | V20: =Tau -> 0.8419551 | W20: =Profit+Utility -> 2081.1672 | X20: =(2*ij*BRIJ)+2*jj*BRJJ -> 480.27188 | Y20: =2*(ij*BCCIJ)+(2*jj*BCCJJ)+BCS+jj*BCPTJJ+2*(ij*BCPTIJ)+BCPTII+BCk -> 363.42388 | Z20: =ij*BUTIJ+BUTII -> 1964.3192 | AA20: =Revenue-Cost -> 116.848 | AB20: =Size -> 10 | AC20: =Welfare/(Size) -> 208.11672 | AD20: =Profit/(Size) -> 11.6848 | AE20: =Utility/(Size) -> 196.43192 | AF20: 308.66096
A21: =C20 -> 0.34347913 | B21: =(I21+J21)*Beta*2 -> 488.88621 | C21: =(W21+B21*Theta-'W-Tax(All-Toll)-NONC'!$T$5)/B21 -> 0.26615229 | D21: 0.91328501 | E21: 0.91313515 | F21: 10 | G21: 0 | H21: =Size-a -> 10 | I21: =(EXP(alpha*(Tau+OldTau+zeta-2*a*psi))*((EXP(alpha*a*psi)-EXP(alpha*b*psi))^2))/((EXP(alpha*a*psi)-EXP(alpha*(2*OldTau+b*psi)))*(alpha^2)*(psi^2)) -> 1.309235 | J21: =(EXP(alpha*(zeta+(2*b-a)*psi))*(-1+EXP(alpha*(-1)*Size*psi))*(EXP(alpha*(2*(Tau+OldTau)+a*psi))-EXP(alpha*(2*(Tau+OldTau)+b*psi))))/(((EXP(alpha*a*psi)-EXP(alpha*(2*OldTau+b*psi)))^2)*(alpha^2)*(psi^2)) -> 0.048782236 | K21: =-Beta/alpha -> 180 | L21: =(-EXP(alpha*zeta)*Beta*(-1+EXP(alpha*Size*psi)-Size*alpha*psi))/((alpha^3)*(psi^2)) -> 1690.9246 | M21: =Beta*Theta -> 61.826244 | N21: =Beta*Theta -> 61.826244 | O21: =kappa -> 90 | P21: =Gamma*Size -> 0 | Q21: =Size*Beta*Phi -> 32.4 | R21: =-(EXP(alpha*a*psi)+EXP(alpha*b*psi)*(-1+Size*psi*alpha))*(Beta*Phi)/((alpha*psi)*(EXP(alpha*a*psi)-EXP(alpha*b*psi))) -> 12.294172 | S21: =(EXP(alpha*(zeta-a*psi))*Beta*Phi*(-EXP(alpha*a*psi)*(-2+(-1)*Size*alpha*psi)+EXP(alpha*b*psi)*(-2+Size*alpha*psi)))/((alpha^3)*(psi^3)) -> 78.836376 | T21: =Tau*Beta -> 164.3913 | U21: =Tau*Beta -> 164.3913 | V21: =Tau -> 0.91328501 | W21: =Profit+Utility -> 2002.5483 | X21: =(2*ij*BRIJ)+2*jj*BRJJ -> 446.49244 | Y21: =2*(ij*BCCIJ)+(2*jj*BCCJJ)+BCS+jj*BCPTJJ+2*(ij*BCPTIJ)+BCPTII+BCk -> 370.53105 | Z21: =ij*BUTIJ+BUTII -> 1926.5869 | AA21: =Revenue-Cost -> 75.961392 | AB21: =Size -> 10 | AC21: =Welfare/(Size) -> 200.25483 | AD21: =Profit/(Size) -> 7.5961392 | AE21: =Utility/(Size) -> 192.65869 | AF21: 308.66096
A22: =C21 -> 0.26615229 | B22: =(I22+J22)*Beta*2 -> 577.5953 | C22: =(W22+B22*Theta-'W-Tax(All-Toll)-NONC'!$T$5)/B22 -> 0.34862405 | D22: 0.83607032 | E22: 0.83607032 | F22: 10 | G22: 0 | H22: =Size-a -> 10 | I22: =(EXP(alpha*(Tau+OldTau+zeta-2*a*psi))*((EXP(alpha*a*psi)-EXP(alpha*b*psi))^2))/((EXP(alpha*a*psi)-EXP(alpha*(2*OldTau+b*psi)))*(alpha^2)*(psi^2)) -> 1.5371836 | J22: =(EXP(alpha*(zeta+(2*b-a)*psi))*(-1+EXP(alpha*(-1)*Size*psi))*(EXP(alpha*(2*(Tau+OldTau)+a*psi))-EXP(alpha*(2*(Tau+OldTau)+b*psi))))/(((EXP(alpha*a*psi)-EXP(alpha*(2*OldTau+b*psi)))^2)*(alpha^2)*(psi^2)) -> 0.067247783 | K22: =-Beta/alpha -> 180 | L22: =(-EXP(alpha*zeta)*Beta*(-1+EXP(alpha*Size*psi)-Size*alpha*psi))/((alpha^3)*(psi^2)) -> 1690.9246 | M22: =Beta*Theta -> 47.907412 | N22: =Beta*Theta -> 47.907412 | O22: =kappa -> 90 | P22: =Gamma*Size -> 0 | Q22: =Size*Beta*Phi -> 32.4 | R22: =-(EXP(alpha*a*psi)+EXP(alpha*b*psi)*(-1+Size*psi*alpha))*(Beta*Phi)/((alpha*psi)*(EXP(alpha*a*psi)-EXP(alpha*b*psi))) -> 12.294172 | S22: =(EXP(alpha*(zeta-a*psi))*Beta*Phi*(-EXP(alpha*a*psi)*(-2+(-1)*Size*alpha*psi)+EXP(alpha*b*psi)*(-2+Size*alpha*psi)))/((alpha^3)*(psi^3)) -> 78.836376 | T22: =Tau*Beta -> 150.49266 | U22: =Tau*Beta -> 150.49266 | V22: =Tau -> 0.83607032 | W22: =Profit+Utility -> 2087.9876 | X22: =(2*ij*BRIJ)+2*jj*BRJJ -> 482.91029 | Y22: =2*(ij*BCCIJ)+(2*jj*BCCJJ)+BCS+jj*BCPTJJ+2*(ij*BCPTIJ)+BCPTII+BCk -> 362.54031 | Z22: =ij*BUTIJ+BUTII -> 1967.6177 | AA22: =Revenue-Cost -> 120.36997 | AB22: =Size -> 10 | AC22: =Welfare/(Size) -> 208.79876 | AD22: =Profit/(Size) -> 12.036997 | AE22: =Utility/(Size) -> 196.76177 | AF22: 308.66096
A23: =C22 -> 0.34862405 | B23: =(I23+J23)*Beta*2 -> 530.95761 | C23: =(W23+B23*Theta-'W-Tax(All-Toll)-NONC'!$T$5)/B23 -> 0.3103501 | D23: =AVERAGE(D19:D22) -> 0.87497665 | E23: =AVERAGE(E19:E22) -> 0.87483346 | F23: 10 | G23: 0 | H23: =Size-a -> 10 | I23: =(EXP(alpha*(Tau+OldTau+zeta-2*a*psi))*((EXP(alpha*a*psi)-EXP(alpha*b*psi))^2))/((EXP(alpha*a*psi)-EXP(alpha*(2*OldTau+b*psi)))*(alpha^2)*(psi^2)) -> 1.4176837 | J23: =(EXP(alpha*(zeta+(2*b-a)*psi))*(-1+EXP(alpha*(-1)*Size*psi))*(EXP(alpha*(2*(Tau+OldTau)+a*psi))-EXP(alpha*(2*(Tau+OldTau)+b*psi))))/(((EXP(alpha*a*psi)-EXP(alpha*(2*OldTau+b*psi)))^2)*(alpha^2)*(psi^2)) -> 0.057198569 | K23: =-Beta/alpha -> 180 | L23: =(-EXP(alpha*zeta)*Beta*(-1+EXP(alpha*Size*psi)-Size*alpha*psi))/((alpha^3)*(psi^2)) -> 1690.9246 | M23: =Beta*Theta -> 62.752328 | N23: =Beta*Theta -> 62.752328 | O23: =kappa -> 90 | P23: =Gamma*Size -> 0 | Q23: =Size*Beta*Phi -> 32.4 | R23: =-(EXP(alpha*a*psi)+EXP(alpha*b*psi)*(-1+Size*psi*alpha))*(Beta*Phi)/((alpha*psi)*(EXP(alpha*a*psi)-EXP(alpha*b*psi))) -> 12.294172 | S23: =(EXP(alpha*(zeta-a*psi))*Beta*Phi*(-EXP(alpha*a*psi)*(-2+(-1)*Size*alpha*psi)+EXP(alpha*b*psi)*(-2+Size*alpha*psi)))/((alpha^3)*(psi^3)) -> 78.836376 | T23: =Tau*Beta -> 157.4958 | U23: =Tau*Beta -> 157.4958 | V23: =Tau -> 0.87497665 | W23: =Profit+Utility -> 2020.0305 | X23: =(2*ij*BRIJ)+2*jj*BRJJ -> 464.57551 | Y23: =2*(ij*BCCIJ)+(2*jj*BCCJJ)+BCS+jj*BCPTJJ+2*(ij*BCPTIJ)+BCPTII+BCk -> 390.65269 | Z23: =ij*BUTIJ+BUTII -> 1946.1077 | AA23: =Revenue-Cost -> 73.922815 | AB23: =Size -> 10 | AC23: =Welfare/(Size) -> 202.00305 | AD23: =Profit/(Size) -> 7.3922815 | AE23: =Utility/(Size) -> 194.61077 | AF23: 308.66096
A24: =C23 -> 0.3103501 | B24: =(I24+J24)*Beta*2 -> 524.88338 | C24: =(W24+B24*Theta-'W-Tax(All-Toll)-NONC'!$T$5)/B24 -> 0.3045467 | D24: 0.88025476 | E24: 0.88020311 | F24: 10 | G24: 0 | H24: =Size-a -> 10 | I24: =(EXP(alpha*(Tau+OldTau+zeta-2*a*psi))*((EXP(alpha*a*psi)-EXP(alpha*b*psi))^2))/((EXP(alpha*a*psi)-EXP(alpha*(2*OldTau+b*psi)))*(alpha^2)*(psi^2)) -> 1.4020643 | J24: =(EXP(alpha*(zeta+(2*b-a)*psi))*(-1+EXP(alpha*(-1)*Size*psi))*(EXP(alpha*(2*(Tau+OldTau)+a*psi))-EXP(alpha*(2*(Tau+OldTau)+b*psi))))/(((EXP(alpha*a*psi)-EXP(alpha*(2*OldTau+b*psi)))^2)*(alpha^2)*(psi^2)) -> 0.055945135 | K24: =-Beta/alpha -> 180 | L24: =(-EXP(alpha*zeta)*Beta*(-1+EXP(alpha*Size*psi)-Size*alpha*psi))/((alpha^3)*(psi^2)) -> 1690.9246 | M24: =Beta*Theta -> 55.863018 | N24: =Beta*Theta -> 55.863018 | O24: =kappa -> 90 | P24: =Gamma*Size -> 0 | Q24: =Size*Beta*Phi -> 32.4 | R24: =-(EXP(alpha*a*psi)+EXP(alpha*b*psi)*(-1+Size*psi*alpha))*(Beta*Phi)/((alpha*psi)*(EXP(alpha*a*psi)-EXP(alpha*b*psi))) -> 12.294172 | S24: =(EXP(alpha*(zeta-a*psi))*Beta*Phi*(-EXP(alpha*a*psi)*(-2+(-1)*Size*alpha*psi)+EXP(alpha*b*psi)*(-2+Size*alpha*psi)))/((alpha^3)*(psi^3)) -> 78.836376 | T24: =Tau*Beta -> 158.44586 | U24: =Tau*Beta -> 158.44586 | V24: =Tau -> 0.88025476 | W24: =Profit+Utility -> 2037.3062 | X24: =(2*ij*BRIJ)+2*jj*BRJJ -> 462.0311 | Y24: =2*(ij*BCCIJ)+(2*jj*BCCJJ)+BCS+jj*BCPTJJ+2*(ij*BCPTIJ)+BCPTII+BCk -> 368.02105 | Z24: =ij*BUTIJ+BUTII -> 1943.2962 | AA24: =Revenue-Cost -> 94.010049 | AB24: =Size -> 10 | AC24: =Welfare/(Size) -> 203.73062 | AD24: =Profit/(Size) -> 9.4010049 | AE24: =Utility/(Size) -> 194.32962 | AF24: 308.66096
A25: =C24 -> 0.3045467 | B25: =(I25+J25)*Beta*2 -> 531.42564 | C25: =(W25+B25*Theta-'W-Tax(All-Toll)-NONC'!$T$5)/B25 -> 0.31071124 | D25: 0.87449463 | E25: 0.87449463 | F25: 10 | G25: 0 | H25: =Size-a -> 10 | I25: =(EXP(alpha*(Tau+OldTau+zeta-2*a*psi))*((EXP(alpha*a*psi)-EXP(alpha*b*psi))^2))/((EXP(alpha*a*psi)-EXP(alpha*(2*OldTau+b*psi)))*(alpha^2)*(psi^2)) -> 1.4188867 | J25: =(EXP(alpha*(zeta+(2*b-a)*psi))*(-1+EXP(alpha*(-1)*Size*psi))*(EXP(alpha*(2*(Tau+OldTau)+a*psi))-EXP(alpha*(2*(Tau+OldTau)+b*psi))))/(((EXP(alpha*a*psi)-EXP(alpha*(2*OldTau+b*psi)))^2)*(alpha^2)*(psi^2)) -> 0.057295682 | K25: =-Beta/alpha -> 180 | L25: =(-EXP(alpha*zeta)*Beta*(-1+EXP(alpha*Size*psi)-Size*alpha*psi))/((alpha^3)*(psi^2)) -> 1690.9246 | M25: =Beta*Theta -> 54.818407 | N25: =Beta*Theta -> 54.818407 | O25: =kappa -> 90 | P25: =Gamma*Size -> 0 | Q25: =Size*Beta*Phi -> 32.4 | R25: =-(EXP(alpha*a*psi)+EXP(alpha*b*psi)*(-1+Size*psi*alpha))*(Beta*Phi)/((alpha*psi)*(EXP(alpha*a*psi)-EXP(alpha*b*psi))) -> 12.294172 | S25: =(EXP(alpha*(zeta-a*psi))*Beta*Phi*(-EXP(alpha*a*psi)*(-2+(-1)*Size*alpha*psi)+EXP(alpha*b*psi)*(-2+Size*alpha*psi)))/((alpha^3)*(psi^3)) -> 78.836376 | T25: =Tau*Beta -> 157.40903 | U25: =Tau*Beta -> 157.40903 | V25: =Tau -> 0.87449463 | W25: =Profit+Utility -> 2043.6283 | X25: =(2*ij*BRIJ)+2*jj*BRJJ -> 464.72887 | Y25: =2*(ij*BCCIJ)+(2*jj*BCCJJ)+BCS+jj*BCPTJJ+2*(ij*BCPTIJ)+BCPTII+BCk -> 367.42476 | Z25: =ij*BUTIJ+BUTII -> 1946.3242 | AA25: =Revenue-Cost -> 97.304115 | AB25: =Size -> 10 | AC25: =Welfare/(Size) -> 204.36283 | AD25: =Profit/(Size) -> 9.7304115 | AE25: =Utility/(Size) -> 194.63242 | AF25: 308.66096
A26: =C25 -> 0.31071124 | B26: =(I26+J26)*Beta*2 -> 524.44432 | C26: =(W26+B26*Theta-'W-Tax(All-Toll)-NONC'!$T$5)/B26 -> 0.30409627 | D26: 0.88061545 | E26: 0.88061545 | F26: 10 | G26: 0 | H26: =Size-a -> 10 | I26: =(EXP(alpha*(Tau+OldTau+zeta-2*a*psi))*((EXP(alpha*a*psi)-EXP(alpha*b*psi))^2))/((EXP(alpha*a*psi)-EXP(alpha*(2*OldTau+b*psi)))*(alpha^2)*(psi^2)) -> 1.4009347 | J26: =(EXP(alpha*(zeta+(2*b-a)*psi))*(-1+EXP(alpha*(-1)*Size*psi))*(EXP(alpha*(2*(Tau+OldTau)+a*psi))-EXP(alpha*(2*(Tau+OldTau)+b*psi))))/(((EXP(alpha*a*psi)-EXP(alpha*(2*OldTau+b*psi)))^2)*(alpha^2)*(psi^2)) -> 0.055855031 | K26: =-Beta/alpha -> 180 | L26: =(-EXP(alpha*zeta)*Beta*(-1+EXP(alpha*Size*psi)-Size*alpha*psi))/((alpha^3)*(psi^2)) -> 1690.9246 | M26: =Beta*Theta -> 55.928023 | N26: =Beta*Theta -> 55.928023 | O26: =kappa -> 90 | P26: =Gamma*Size -> 0 | Q26: =Size*Beta*Phi -> 32.4 | R26: =-(EXP(alpha*a*psi)+EXP(alpha*b*psi)*(-1+Size*psi*alpha))*(Beta*Phi)/((alpha*psi)*(EXP(alpha*a*psi)-EXP(alpha*b*psi))) -> 12.294172 | S26: =(EXP(alpha*(zeta-a*psi))*Beta*Phi*(-EXP(alpha*a*psi)*(-2+(-1)*Size*alpha*psi)+EXP(alpha*b*psi)*(-2+Size*alpha*psi)))/((alpha^3)*(psi^3)) -> 78.836376 | T26: =Tau*Beta -> 158.51078 | U26: =Tau*Beta -> 158.51078 | V26: =Tau -> 0.88061545 | W26: =Profit+Utility -> 2036.8832 | X26: =(2*ij*BRIJ)+2*jj*BRJJ -> 461.83377 | Y26: =2*(ij*BCCIJ)+(2*jj*BCCJJ)+BCS+jj*BCPTJJ+2*(ij*BCPTIJ)+BCPTII+BCk -> 368.04349 | Z26: =ij*BUTIJ+BUTII -> 1943.0929 | AA26: =Revenue-Cost -> 93.790283 | AB26: =Size -> 10 | AC26: =Welfare/(Size) -> 203.68832 | AD26: =Profit/(Size) -> 9.3790283 | AE26: =Utility/(Size) -> 194.30929 | AF26: 308.66096
A27: =C26 -> 0.30409627 | B27: =(I27+J27)*Beta*2 -> 528.27755 | C27: =(W27+B27*Theta-'W-Tax(All-Toll)-NONC'!$T$5)/B27 -> 0.304564 | D27: 0.87404793 | E27: 0.88020311 | F27: 10 | G27: 0 | H27: =Size-a -> 10 | I27: =(EXP(alpha*(Tau+OldTau+zeta-2*a*psi))*((EXP(alpha*a*psi)-EXP(alpha*b*psi))^2))/((EXP(alpha*a*psi)-EXP(alpha*(2*OldTau+b*psi)))*(alpha^2)*(psi^2)) -> 1.4107937 | J27: =(EXP(alpha*(zeta+(2*b-a)*psi))*(-1+EXP(alpha*(-1)*Size*psi))*(EXP(alpha*(2*(Tau+OldTau)+a*psi))-EXP(alpha*(2*(Tau+OldTau)+b*psi))))/(((EXP(alpha*a*psi)-EXP(alpha*(2*OldTau+b*psi)))^2)*(alpha^2)*(psi^2)) -> 0.056643947 | K27: =-Beta/alpha -> 180 | L27: =(-EXP(alpha*zeta)*Beta*(-1+EXP(alpha*Size*psi)-Size*alpha*psi))/((alpha^3)*(psi^2)) -> 1690.9246 | M27: =Beta*Theta -> 54.737328 | N27: =Beta*Theta -> 54.737328 | O27: =kappa -> 90 | P27: =Gamma*Size -> 0 | Q27: =Size*Beta*Phi -> 32.4 | R27: =-(EXP(alpha*a*psi)+EXP(alpha*b*psi)*(-1+Size*psi*alpha))*(Beta*Phi)/((alpha*psi)*(EXP(alpha*a*psi)-EXP(alpha*b*psi))) -> 12.294172 | S27: =(EXP(alpha*(zeta-a*psi))*Beta*Phi*(-EXP(alpha*a*psi)*(-2+(-1)*Size*alpha*psi)+EXP(alpha*b*psi)*(-2+Size*alpha*psi)))/((alpha^3)*(psi^3)) -> 78.836376 | T27: =Tau*Beta -> 157.32863 | U27: =Tau*Beta -> 157.32863 | V27: =Tau -> 0.87404793 | W27: =Profit+Utility -> 2040.5994 | X27: =(2*ij*BRIJ)+2*jj*BRJJ -> 461.7399 | Y27: =2*(ij*BCCIJ)+(2*jj*BCCJJ)+BCS+jj*BCPTJJ+2*(ij*BCPTIJ)+BCPTII+BCk -> 366.00795 | Z27: =ij*BUTIJ+BUTII -> 1944.8675 | AA27: =Revenue-Cost -> 95.731948 | AB27: =Size -> 10 | AC27: =Welfare/(Size) -> 204.05994 | AD27: =Profit/(Size) -> 9.5731948 | AE27: =Utility/(Size) -> 194.48675 | AF27: 308.66096
A28: =C27 -> 0.304564 | B28: =(I28+J28)*Beta*2 -> 527.2496 | C28: =(W28+B28*Theta-'W-Tax(All-Toll)-NONC'!$T$5)/B28 -> 0.30599285 | D28: =AVERAGE(D24:D27) -> 0.87735319 | E28: =AVERAGE(E24:E27) -> 0.87887907 | F28: 10 | G28: 0 | H28: =Size-a -> 10 | I28: =(EXP(alpha*(Tau+OldTau+zeta-2*a*psi))*((EXP(alpha*a*psi)-EXP(alpha*b*psi))^2))/((EXP(alpha*a*psi)-EXP(alpha*(2*OldTau+b*psi)))*(alpha^2)*(psi^2)) -> 1.4081504 | J28: =(EXP(alpha*(zeta+(2*b-a)*psi))*(-1+EXP(alpha*(-1)*Size*psi))*(EXP(alpha*(2*(Tau+OldTau)+a*psi))-EXP(alpha*(2*(Tau+OldTau)+b*psi))))/(((EXP(alpha*a*psi)-EXP(alpha*(2*OldTau+b*psi)))^2)*(alpha^2)*(psi^2)) -> 0.056431883 | K28: =-Beta/alpha -> 180 | L28: =(-EXP(alpha*zeta)*Beta*(-1+EXP(alpha*Size*psi)-Size*alpha*psi))/((alpha^3)*(psi^2)) -> 1690.9246 | M28: =Beta*Theta -> 54.82152 | N28: =Beta*Theta -> 54.82152 | O28: =kappa -> 90 | P28: =Gamma*Size -> 0 | Q28: =Size*Beta*Phi -> 32.4 | R28: =-(EXP(alpha*a*psi)+EXP(alpha*b*psi)*(-1+Size*psi*alpha))*(Beta*Phi)/((alpha*psi)*(EXP(alpha*a*psi)-EXP(alpha*b*psi))) -> 12.294172 | S28: =(EXP(alpha*(zeta-a*psi))*Beta*Phi*(-EXP(alpha*a*psi)*(-2+(-1)*Size*alpha*psi)+EXP(alpha*b*psi)*(-2+Size*alpha*psi)))/((alpha^3)*(psi^3)) -> 78.836376 | T28: =Tau*Beta -> 157.92357 | U28: =Tau*Beta -> 157.92357 | V28: =Tau -> 0.87735319 | W28: =Profit+Utility -> 2041.1057 | X28: =(2*ij*BRIJ)+2*jj*BRJJ -> 462.58412 | Y28: =2*(ij*BCCIJ)+(2*jj*BCCJJ)+BCS+jj*BCPTJJ+2*(ij*BCPTIJ)+BCPTII+BCk -> 365.8701 | Z28: =ij*BUTIJ+BUTII -> 1944.3917 | AA28: =Revenue-Cost -> 96.714021 | AB28: =Size -> 10 | AC28: =Welfare/(Size) -> 204.11057 | AD28: =Profit/(Size) -> 9.6714021 | AE28: =Utility/(Size) -> 194.43917 | AF28: 308.66096
A29: =C28 -> 0.30599285 | B29: =(I29+J29)*Beta*2 -> 529.78428 | C29: =(W29+B29*Theta-'W-Tax(All-Toll)-NONC'!$T$5)/B29 -> 0.30917895 | D29: 0.8759259 | E29: 0.8759259 | F29: 10 | G29: 0 | H29: =Size-a -> 10 | I29: =(EXP(alpha*(Tau+OldTau+zeta-2*a*psi))*((EXP(alpha*a*psi)-EXP(alpha*b*psi))^2))/((EXP(alpha*a*psi)-EXP(alpha*(2*OldTau+b*psi)))*(alpha^2)*(psi^2)) -> 1.4146676 | J29: =(EXP(alpha*(zeta+(2*b-a)*psi))*(-1+EXP(alpha*(-1)*Size*psi))*(EXP(alpha*(2*(Tau+OldTau)+a*psi))-EXP(alpha*(2*(Tau+OldTau)+b*psi))))/(((EXP(alpha*a*psi)-EXP(alpha*(2*OldTau+b*psi)))^2)*(alpha^2)*(psi^2)) -> 0.056955448 | K29: =-Beta/alpha -> 180 | L29: =(-EXP(alpha*zeta)*Beta*(-1+EXP(alpha*Size*psi)-Size*alpha*psi))/((alpha^3)*(psi^2)) -> 1690.9246 | M29: =Beta*Theta -> 55.078714 | N29: =Beta*Theta -> 55.078714 | O29: =kappa -> 90 | P29: =Gamma*Size -> 0 | Q29: =Size*Beta*Phi -> 32.4 | R29: =-(EXP(alpha*a*psi)+EXP(alpha*b*psi)*(-1+Size*psi*alpha))*(Beta*Phi)/((alpha*psi)*(EXP(alpha*a*psi)-EXP(alpha*b*psi))) -> 12.294172 | S29: =(EXP(alpha*(zeta-a*psi))*Beta*Phi*(-EXP(alpha*a*psi)*(-2+(-1)*Size*alpha*psi)+EXP(alpha*b*psi)*(-2+Size*alpha*psi)))/((alpha^3)*(psi^3)) -> 78.836376 | T29: =Tau*Beta -> 157.66666 | U29: =Tau*Beta -> 157.66666 | V29: =Tau -> 0.8759259 | W29: =Profit+Utility -> 2042.0403 | X29: =(2*ij*BRIJ)+2*jj*BRJJ -> 464.05178 | Y29: =2*(ij*BCCIJ)+(2*jj*BCCJJ)+BCS+jj*BCPTJJ+2*(ij*BCPTIJ)+BCPTII+BCk -> 367.57627 | Z29: =ij*BUTIJ+BUTII -> 1945.5648 | AA29: =Revenue-Cost -> 96.475506 | AB29: =Size -> 10 | AC29: =Welfare/(Size) -> 204.20403 | AD29: =Profit/(Size) -> 9.6475506 | AE29: =Utility/(Size) -> 194.55648 | AF29: 308.66096
A30: =C29 -> 0.30917895 | B30: =(I30+J30)*Beta*2 -> 526.14186 | C30: =(W30+B30*Theta-'W-Tax(All-Toll)-NONC'!$T$5)/B30 -> 0.30572839 | D30: 0.87911915 | E30: 0.87911915 | F30: 10 | G30: 0 | H30: =Size-a -> 10 | I30: =(EXP(alpha*(Tau+OldTau+zeta-2*a*psi))*((EXP(alpha*a*psi)-EXP(alpha*b*psi))^2))/((EXP(alpha*a*psi)-EXP(alpha*(2*OldTau+b*psi)))*(alpha^2)*(psi^2)) -> 1.4053014 | J30: =(EXP(alpha*(zeta+(2*b-a)*psi))*(-1+EXP(alpha*(-1)*Size*psi))*(EXP(alpha*(2*(Tau+OldTau)+a*psi))-EXP(alpha*(2*(Tau+OldTau)+b*psi))))/(((EXP(alpha*a*psi)-EXP(alpha*(2*OldTau+b*psi)))^2)*(alpha^2)*(psi^2)) -> 0.05620377 | K30: =-Beta/alpha -> 180 | L30: =(-EXP(alpha*zeta)*Beta*(-1+EXP(alpha*Size*psi)-Size*alpha*psi))/((alpha^3)*(psi^2)) -> 1690.9246 | M30: =Beta*Theta -> 55.652212 | N30: =Beta*Theta -> 55.652212 | O30: =kappa -> 90 | P30: =Gamma*Size -> 0 | Q30: =Size*Beta*Phi -> 32.4 | R30: =-(EXP(alpha*a*psi)+EXP(alpha*b*psi)*(-1+Size*psi*alpha))*(Beta*Phi)/((alpha*psi)*(EXP(alpha*a*psi)-EXP(alpha*b*psi))) -> 12.294172 | S30: =(EXP(alpha*(zeta-a*psi))*Beta*Phi*(-EXP(alpha*a*psi)*(-2+(-1)*Size*alpha*psi)+EXP(alpha*b*psi)*(-2+Size*alpha*psi)))/((alpha^3)*(psi^3)) -> 78.836376 | T30: =Tau*Beta -> 158.24145 | U30: =Tau*Beta -> 158.24145 | V30: =Tau -> 0.87911915 | W30: =Profit+Utility -> 2038.5369 | X30: =(2*ij*BRIJ)+2*jj*BRJJ -> 462.54139 | Y30: =2*(ij*BCCIJ)+(2*jj*BCCJJ)+BCS+jj*BCPTJJ+2*(ij*BCPTIJ)+BCPTII+BCk -> 367.8834 | Z30: =ij*BUTIJ+BUTII -> 1943.8789 | AA30: =Revenue-Cost -> 94.657982 | AB30: =Size -> 10 | AC30: =Welfare/(Size) -> 203.85369 | AD30: =Profit/(Size) -> 9.4657982 | AE30: =Utility/(Size) -> 194.38789 | AF30: 308.66096
A31: =C30 -> 0.30572839 | B31: =(I31+J31)*Beta*2 -> 530.08053 | C31: =(W31+B31*Theta-'W-Tax(All-Toll)-NONC'!$T$5)/B31 -> 0.30945654 | D31: 0.87566723 | E31: 0.87566723 | F31: 10 | G31: 0 | H31: =Size-a -> 10 | I31: =(EXP(alpha*(Tau+OldTau+zeta-2*a*psi))*((EXP(alpha*a*psi)-EXP(alpha*b*psi))^2))/((EXP(alpha*a*psi)-EXP(alpha*(2*OldTau+b*psi)))*(alpha^2)*(psi^2)) -> 1.4154291 | J31: =(EXP(alpha*(zeta+(2*b-a)*psi))*(-1+EXP(alpha*(-1)*Size*psi))*(EXP(alpha*(2*(Tau+OldTau)+a*psi))-EXP(alpha*(2*(Tau+OldTau)+b*psi))))/(((EXP(alpha*a*psi)-EXP(alpha*(2*OldTau+b*psi)))^2)*(alpha^2)*(psi^2)) -> 0.057016787 | K31: =-Beta/alpha -> 180 | L31: =(-EXP(alpha*zeta)*Beta*(-1+EXP(alpha*Size*psi)-Size*alpha*psi))/((alpha^3)*(psi^2)) -> 1690.9246 | M31: =Beta*Theta -> 55.03111 | N31: =Beta*Theta -> 55.03111 | O31: =kappa -> 90 | P31: =Gamma*Size -> 0 | Q31: =Size*Beta*Phi -> 32.4 | R31: =-(EXP(alpha*a*psi)+EXP(alpha*b*psi)*(-1+Size*psi*alpha))*(Beta*Phi)/((alpha*psi)*(EXP(alpha*a*psi)-EXP(alpha*b*psi))) -> 12.294172 | S31: =(EXP(alpha*(zeta-a*psi))*Beta*Phi*(-EXP(alpha*a*psi)*(-2+(-1)*Size*alpha*psi)+EXP(alpha*b*psi)*(-2+Size*alpha*psi)))/((alpha^3)*(psi^3)) -> 78.836376 | T31: =Tau*Beta -> 157.6201 | U31: =Tau*Beta -> 157.6201 | V31: =Tau -> 0.87566723 | W31: =Profit+Utility -> 2042.3286 | X31: =(2*ij*BRIJ)+2*jj*BRJJ -> 464.17414 | Y31: =2*(ij*BCCIJ)+(2*jj*BCCJJ)+BCS+jj*BCPTJJ+2*(ij*BCPTIJ)+BCPTII+BCk -> 367.54744 | Z31: =ij*BUTIJ+BUTII -> 1945.7019 | AA31: =Revenue-Cost -> 96.626701 | AB31: =Size -> 10 | AC31: =Welfare/(Size) -> 204.23286 | AD31: =Profit/(Size) -> 9.6626701 | AE31: =Utility/(Size) -> 194.57019 | AF31: 308.66096
A32: =C31 -> 0.30945654 | B32: =(I32+J32)*Beta*2 -> 525.83017 | C32: =(W32+B32*Theta-'W-Tax(All-Toll)-NONC'!$T$5)/B32 -> 0.30542986 | D32: 0.8793935 | E32: 0.8793935 | F32: 10 | G32: 0 | H32: =Size-a -> 10 | I32: =(EXP(alpha*(Tau+OldTau+zeta-2*a*psi))*((EXP(alpha*a*psi)-EXP(alpha*b*psi))^2))/((EXP(alpha*a*psi)-EXP(alpha*(2*OldTau+b*psi)))*(alpha^2)*(psi^2)) -> 1.4044997 | J32: =(EXP(alpha*(zeta+(2*b-a)*psi))*(-1+EXP(alpha*(-1)*Size*psi))*(EXP(alpha*(2*(Tau+OldTau)+a*psi))-EXP(alpha*(2*(Tau+OldTau)+b*psi))))/(((EXP(alpha*a*psi)-EXP(alpha*(2*OldTau+b*psi)))^2)*(alpha^2)*(psi^2)) -> 0.056139662 | K32: =-Beta/alpha -> 180 | L32: =(-EXP(alpha*zeta)*Beta*(-1+EXP(alpha*Size*psi)-Size*alpha*psi))/((alpha^3)*(psi^2)) -> 1690.9246 | M32: =Beta*Theta -> 55.702177 | N32: =Beta*Theta -> 55.702177 | O32: =kappa -> 90 | P32: =Gamma*Size -> 0 | Q32: =Size*Beta*Phi -> 32.4 | R32: =-(EXP(alpha*a*psi)+EXP(alpha*b*psi)*(-1+Size*psi*alpha))*(Beta*Phi)/((alpha*psi)*(EXP(alpha*a*psi)-EXP(alpha*b*psi))) -> 12.294172 | S32: =(EXP(alpha*(zeta-a*psi))*Beta*Phi*(-EXP(alpha*a*psi)*(-2+(-1)*Size*alpha*psi)+EXP(alpha*b*psi)*(-2+Size*alpha*psi)))/((alpha^3)*(psi^3)) -> 78.836376 | T32: =Tau*Beta -> 158.29083 | U32: =Tau*Beta -> 158.29083 | V32: =Tau -> 0.8793935 | W32: =Profit+Utility -> 2038.235 | X32: =(2*ij*BRIJ)+2*jj*BRJJ -> 462.41164 | Y32: =2*(ij*BCCIJ)+(2*jj*BCCJJ)+BCS+jj*BCPTJJ+2*(ij*BCPTIJ)+BCPTII+BCk -> 367.91121 | Z32: =ij*BUTIJ+BUTII -> 1943.7346 | AA32: =Revenue-Cost -> 94.500426 | AB32: =Size -> 10 | AC32: =Welfare/(Size) -> 203.8235 | AD32: =Profit/(Size) -> 9.4500426 | AE32: =Utility/(Size) -> 194.37346 | AF32: 308.66096
A34: 0.08 | B34: =(I34+J34)*Beta*2 -> 1152.8979 | C34: =(W34+B34*Theta-'W-Tax(All-Toll)-NONC'!$T$8)/B34 -> 0.47584193 | D34: 0.70015477 | E34: 0.70015477 | F34: 100 | G34: 0 | H34: =Size-a -> 100 | I34: =(EXP(alpha*(Tau+OldTau+zeta-2*a*psi))*((EXP(alpha*a*psi)-EXP(alpha*b*psi))^2))/((EXP(alpha*a*psi)-EXP(alpha*(2*OldTau+b*psi)))*(alpha^2)*(psi^2)) -> 3.2024941 | J34: =(EXP(alpha*(zeta+(2*b-a)*psi))*(-1+EXP(alpha*(-1)*Size*psi))*(EXP(alpha*(2*(Tau+OldTau)+a*psi))-EXP(alpha*(2*(Tau+OldTau)+b*psi))))/(((EXP(alpha*a*psi)-EXP(alpha*(2*OldTau+b*psi)))^2)*(alpha^2)*(psi^2)) -> 2.4150406e-07 | K34: =-Beta/alpha -> 180 | L34: =(-EXP(alpha*zeta)*Beta*(-1+EXP(alpha*Size*psi)-Size*alpha*psi))/((alpha^3)*(psi^2)) -> 32736.769 | M34: =Beta*Theta -> 14.4 | N34: =Beta*Theta -> 14.4 | O34: =kappa -> 90 | P34: =Gamma*Size -> 0 | Q34: =Size*Beta*Phi -> 324 | R34: =-(EXP(alpha*a*psi)+EXP(alpha*b*psi)*(-1+Size*psi*alpha))*(Beta*Phi)/((alpha*psi)*(EXP(alpha*a*psi)-EXP(alpha*b*psi))) -> 21.599901 | S34: =(EXP(alpha*(zeta-a*psi))*Beta*Phi*(-EXP(alpha*a*psi)*(-2+(-1)*Size*alpha*psi)+EXP(alpha*b*psi)*(-2+Size*alpha*psi)))/((alpha^3)*(psi^3)) -> 3647.8128 | T34: =Tau*Beta -> 126.02786 | U34: =Tau*Beta -> 126.02786 | V34: =Tau -> 0.70015477 | W34: =Profit+Utility -> 30152.033 | X34: =(2*ij*BRIJ)+2*jj*BRJJ -> 807.20699 | Y34: =2*(ij*BCCIJ)+(2*jj*BCCJJ)+BCS+jj*BCPTJJ+2*(ij*BCPTIJ)+BCPTII+BCk -> 3968.3919 | Z34: =ij*BUTIJ+BUTII -> 33313.218 | AA34: =Revenue-Cost -> -3161.1849 | AB34: =Size -> 100 | AC34: =Welfare/(Size) -> 301.52033 | AD34: =Profit/(Size) -> -31.611849 | AE34: =Utility/(Size) -> 333.13218 | AF34: 308.66096
A35: =C34 -> 0.47584193 | B35: =(I35+J35)*Beta*2 -> 522.47691 | C35: =(W35+B35*Theta-'W-Tax(All-Toll)-NONC'!$T$8)/B35 -> 0.14240368 | D35: 1.0958813 | E35: 1.0958813 | F35: 100 | G35: 0 | H35: =Size-a -> 100 | I35: =(EXP(alpha*(Tau+OldTau+zeta-2*a*psi))*((EXP(alpha*a*psi)-EXP(alpha*b*psi))^2))/((EXP(alpha*a*psi)-EXP(alpha*(2*OldTau+b*psi)))*(alpha^2)*(psi^2)) -> 1.4513247 | J35: =(EXP(alpha*(zeta+(2*b-a)*psi))*(-1+EXP(alpha*(-1)*Size*psi))*(EXP(alpha*(2*(Tau+OldTau)+a*psi))-EXP(alpha*(2*(Tau+OldTau)+b*psi))))/(((EXP(alpha*a*psi)-EXP(alpha*(2*OldTau+b*psi)))^2)*(alpha^2)*(psi^2)) -> 4.959946e-08 | K35: =-Beta/alpha -> 180 | L35: =(-EXP(alpha*zeta)*Beta*(-1+EXP(alpha*Size*psi)-Size*alpha*psi))/((alpha^3)*(psi^2)) -> 32736.769 | M35: =Beta*Theta -> 85.651548 | N35: =Beta*Theta -> 85.651548 | O35: =kappa -> 90 | P35: =Gamma*Size -> 0 | Q35: =Size*Beta*Phi -> 324 | R35: =-(EXP(alpha*a*psi)+EXP(alpha*b*psi)*(-1+Size*psi*alpha))*(Beta*Phi)/((alpha*psi)*(EXP(alpha*a*psi)-EXP(alpha*b*psi))) -> 21.599901 | S35: =(EXP(alpha*(zeta-a*psi))*Beta*Phi*(-EXP(alpha*a*psi)*(-2+(-1)*Size*alpha*psi)+EXP(alpha*b*psi)*(-2+Size*alpha*psi)))/((alpha^3)*(psi^3)) -> 3647.8128 | T35: =Tau*Beta -> 197.25864 | U35: =Tau*Beta -> 197.25864 | V35: =Tau -> 1.0958813 | W35: =Profit+Utility -> 29521.454 | X35: =(2*ij*BRIJ)+2*jj*BRJJ -> 572.57269 | Y35: =2*(ij*BCCIJ)+(2*jj*BCCJJ)+BCS+jj*BCPTJJ+2*(ij*BCPTIJ)+BCPTII+BCk -> 4049.1262 | Z35: =ij*BUTIJ+BUTII -> 32998.008 | AA35: =Revenue-Cost -> -3476.5535 | AB35: =Size -> 100 | AC35: =Welfare/(Size) -> 295.21454 | AD35: =Profit/(Size) -> -34.765535 | AE35: =Utility/(Size) -> 329.98008 | AF35: 308.66096
A36: =C35 -> 0.14240368 | B36: =(I36+J36)*Beta*2 -> 1017.9338 | C36: =(W36+B36*Theta-'W-Tax(All-Toll)-NONC'!$T$8)/B36 -> 0.45797016 | D36: 0.76240667 | E36: 0.76240667 | F36: 100 | G36: 0 | H36: =Size-a -> 100 | I36: =(EXP(alpha*(Tau+OldTau+zeta-2*a*psi))*((EXP(alpha*a*psi)-EXP(alpha*b*psi))^2))/((EXP(alpha*a*psi)-EXP(alpha*(2*OldTau+b*psi)))*(alpha^2)*(psi^2)) -> 2.8275938 | J36: =(EXP(alpha*(zeta+(2*b-a)*psi))*(-1+EXP(alpha*(-1)*Size*psi))*(EXP(alpha*(2*(Tau+OldTau)+a*psi))-EXP(alpha*(2*(Tau+OldTau)+b*psi))))/(((EXP(alpha*a*psi)-EXP(alpha*(2*OldTau+b*psi)))^2)*(alpha^2)*(psi^2)) -> 1.8827029e-07 | K36: =-Beta/alpha -> 180 | L36: =(-EXP(alpha*zeta)*Beta*(-1+EXP(alpha*Size*psi)-Size*alpha*psi))/((alpha^3)*(psi^2)) -> 32736.769 | M36: =Beta*Theta -> 25.632663 | N36: =Beta*Theta -> 25.632663 | O36: =kappa -> 90 | P36: =Gamma*Size -> 0 | Q36: =Size*Beta*Phi -> 324 | R36: =-(EXP(alpha*a*psi)+EXP(alpha*b*psi)*(-1+Size*psi*alpha))*(Beta*Phi)/((alpha*psi)*(EXP(alpha*a*psi)-EXP(alpha*b*psi))) -> 21.599901 | S36: =(EXP(alpha*(zeta-a*psi))*Beta*Phi*(-EXP(alpha*a*psi)*(-2+(-1)*Size*alpha*psi)+EXP(alpha*b*psi)*(-2+Size*alpha*psi)))/((alpha^3)*(psi^3)) -> 3647.8128 | T36: =Tau*Beta -> 137.2332 | U36: =Tau*Beta -> 137.2332 | V36: =Tau -> 0.76240667 | W36: =Profit+Utility -> 30016.894 | X36: =(2*ij*BRIJ)+2*jj*BRJJ -> 776.07953 | Y36: =2*(ij*BCCIJ)+(2*jj*BCCJJ)+BCS+jj*BCPTJJ+2*(ij*BCPTIJ)+BCPTII+BCk -> 4004.9219 | Z36: =ij*BUTIJ+BUTII -> 33245.736 | AA36: =Revenue-Cost -> -3228.8424 | AB36: =Size -> 100 | AC36: =Welfare/(Size) -> 300.16894 | AD36: =Profit/(Size) -> -32.288424 | AE36: =Utility/(Size) -> 332.45736 | AF36: 308.66096
A37: =C36 -> 0.45797016 | B37: =(I37+J37)*Beta*2 -> 541.52224 | C37: =(W37+B37*Theta-'W-Tax(All-Toll)-NONC'!$T$8)/B37 -> 0.17140042 | D37: 1.0779797 | E37: 1.0779797 | F37: 100 | G37: 0 | H37: =Size-a -> 100 | I37: =(EXP(alpha*(Tau+OldTau+zeta-2*a*psi))*((EXP(alpha*a*psi)-EXP(alpha*b*psi))^2))/((EXP(alpha*a*psi)-EXP(alpha*(2*OldTau+b*psi)))*(alpha^2)*(psi^2)) -> 1.5042284 | J37: =(EXP(alpha*(zeta+(2*b-a)*psi))*(-1+EXP(alpha*(-1)*Size*psi))*(EXP(alpha*(2*(Tau+OldTau)+a*psi))-EXP(alpha*(2*(Tau+OldTau)+b*psi))))/(((EXP(alpha*a*psi)-EXP(alpha*(2*OldTau+b*psi)))^2)*(alpha^2)*(psi^2)) -> 5.3281364e-08 | K37: =-Beta/alpha -> 180 | L37: =(-EXP(alpha*zeta)*Beta*(-1+EXP(alpha*Size*psi)-Size*alpha*psi))/((alpha^3)*(psi^2)) -> 32736.769 | M37: =Beta*Theta -> 82.434628 | N37: =Beta*Theta -> 82.434628 | O37: =kappa -> 90 | P37: =Gamma*Size -> 0 | Q37: =Size*Beta*Phi -> 324 | R37: =-(EXP(alpha*a*psi)+EXP(alpha*b*psi)*(-1+Size*psi*alpha))*(Beta*Phi)/((alpha*psi)*(EXP(alpha*a*psi)-EXP(alpha*b*psi))) -> 21.599901 | S37: =(EXP(alpha*(zeta-a*psi))*Beta*Phi*(-EXP(alpha*a*psi)*(-2+(-1)*Size*alpha*psi)+EXP(alpha*b*psi)*(-2+Size*alpha*psi)))/((alpha^3)*(psi^3)) -> 3647.8128 | T37: =Tau*Beta -> 194.03634 | U37: =Tau*Beta -> 194.03634 | V37: =Tau -> 1.0779797 | W37: =Profit+Utility -> 29540.484 | X37: =(2*ij*BRIJ)+2*jj*BRJJ -> 583.74996 | Y37: =2*(ij*BCCIJ)+(2*jj*BCCJJ)+BCS+jj*BCPTJJ+2*(ij*BCPTIJ)+BCPTII+BCk -> 4050.7962 | Z37: =ij*BUTIJ+BUTII -> 33007.531 | AA37: =Revenue-Cost -> -3467.0463 | AB37: =Size -> 100 | AC37: =Welfare/(Size) -> 295.40484 | AD37: =Profit/(Size) -> -34.670463 | AE37: =Utility/(Size) -> 330.07531 | AF37: 308.66096
A38: =C37 -> 0.17140042 | B38: =(I38+J38)*Beta*2 -> 960.58125 | C38: =(W38+B38*Theta-'W-Tax(All-Toll)-NONC'!$T$8)/B38 -> 0.44610089 | D38: 0.79140247 | E38: 0.79140247 | F38: 100 | G38: 0 | H38: =Size-a -> 100 | I38: =(EXP(alpha*(Tau+OldTau+zeta-2*a*psi))*((EXP(alpha*a*psi)-EXP(alpha*b*psi))^2))/((EXP(alpha*a*psi)-EXP(alpha*(2*OldTau+b*psi)))*(alpha^2)*(psi^2)) -> 2.6682811 | J38: =(EXP(alpha*(zeta+(2*b-a)*psi))*(-1+EXP(alpha*(-1)*Size*psi))*(EXP(alpha*(2*(Tau+OldTau)+a*psi))-EXP(alpha*(2*(Tau+OldTau)+b*psi))))/(((EXP(alpha*a*psi)-EXP(alpha*(2*OldTau+b*psi)))^2)*(alpha^2)*(psi^2)) -> 1.6765284e-07 | K38: =-Beta/alpha -> 180 | L38: =(-EXP(alpha*zeta)*Beta*(-1+EXP(alpha*Size*psi)-Size*alpha*psi))/((alpha^3)*(psi^2)) -> 32736.769 | M38: =Beta*Theta -> 30.852076 | N38: =Beta*Theta -> 30.852076 | O38: =kappa -> 90 | P38: =Gamma*Size -> 0 | Q38: =Size*Beta*Phi -> 324 | R38: =-(EXP(alpha*a*psi)+EXP(alpha*b*psi)*(-1+Size*psi*alpha))*(Beta*Phi)/((alpha*psi)*(EXP(alpha*a*psi)-EXP(alpha*b*psi))) -> 21.599901 | S38: =(EXP(alpha*(zeta-a*psi))*Beta*Phi*(-EXP(alpha*a*psi)*(-2+(-1)*Size*alpha*psi)+EXP(alpha*b*psi)*(-2+Size*alpha*psi)))/((alpha^3)*(psi^3)) -> 3647.8128 | T38: =Tau*Beta -> 142.45245 | U38: =Tau*Beta -> 142.45245 | V38: =Tau -> 0.79140247 | W38: =Profit+Utility -> 29959.54 | X38: =(2*ij*BRIJ)+2*jj*BRJJ -> 760.20638 | Y38: =2*(ij*BCCIJ)+(2*jj*BCCJJ)+BCS+jj*BCPTJJ+2*(ij*BCPTIJ)+BCPTII+BCk -> 4017.7261 | Z38: =ij*BUTIJ+BUTII -> 33217.06 | AA38: =Revenue-Cost -> -3257.5198 | AB38: =Size -> 100 | AC38: =Welfare/(Size) -> 299.5954 | AD38: =Profit/(Size) -> -32.575198 | AE38: =Utility/(Size) -> 332.1706 | AF38: 308.66096
A39: =C38 -> 0.44610089 | B39: =(I39+J39)*Beta*2 -> 725.2442 | C39: =(W39+B39*Theta-'W-Tax(All-Toll)-NONC'!$T$8)/B39 -> 0.35126015 | D39: =AVERAGE(D35:D38) -> 0.93191753 | E39: =AVERAGE(E35:E38) -> 0.93191753 | F39: 100 | G39: 0 | H39: =Size-a -> 100 | I39: =(EXP(alpha*(Tau+OldTau+zeta-2*a*psi))*((EXP(alpha*a*psi)-EXP(alpha*b*psi))^2))/((EXP(alpha*a*psi)-EXP(alpha*(2*OldTau+b*psi)))*(alpha^2)*(psi^2)) -> 2.0145671 | J39: =(EXP(alpha*(zeta+(2*b-a)*psi))*(-1+EXP(alpha*(-1)*Size*psi))*(EXP(alpha*(2*(Tau+OldTau)+a*psi))-EXP(alpha*(2*(Tau+OldTau)+b*psi))))/(((EXP(alpha*a*psi)-EXP(alpha*(2*OldTau+b*psi)))^2)*(alpha^2)*(psi^2)) -> 9.5567725e-08 | K39: =-Beta/alpha -> 180 | L39: =(-EXP(alpha*zeta)*Beta*(-1+EXP(alpha*Size*psi)-Size*alpha*psi))/((alpha^3)*(psi^2)) -> 32736.769 | M39: =Beta*Theta -> 80.298161 | N39: =Beta*Theta -> 80.298161 | O39: =kappa -> 90 | P39: =Gamma*Size -> 0 | Q39: =Size*Beta*Phi -> 324 | R39: =-(EXP(alpha*a*psi)+EXP(alpha*b*psi)*(-1+Size*psi*alpha))*(Beta*Phi)/((alpha*psi)*(EXP(alpha*a*psi)-EXP(alpha*b*psi))) -> 21.599901 | S39: =(EXP(alpha*(zeta-a*psi))*Beta*Phi*(-EXP(alpha*a*psi)*(-2+(-1)*Size*alpha*psi)+EXP(alpha*b*psi)*(-2+Size*alpha*psi)))/((alpha^3)*(psi^3)) -> 3647.8128 | T39: =Tau*Beta -> 167.74516 | U39: =Tau*Beta -> 167.74516 | V39: =Tau -> 0.93191753 | W39: =Profit+Utility -> 29626.885 | X39: =(2*ij*BRIJ)+2*jj*BRJJ -> 675.86778 | Y39: =2*(ij*BCCIJ)+(2*jj*BCCJJ)+BCS+jj*BCPTJJ+2*(ij*BCPTIJ)+BCPTII+BCk -> 4148.3738 | Z39: =ij*BUTIJ+BUTII -> 33099.391 | AA39: =Revenue-Cost -> -3472.5061 | AB39: =Size -> 100 | AC39: =Welfare/(Size) -> 296.26885 | AD39: =Profit/(Size) -> -34.725061 | AE39: =Utility/(Size) -> 330.99391 | AF39: 308.66096
A40: =C39 -> 0.35126015 | B40: =(I40+J40)*Beta*2 -> 670.33263 | C40: =(W40+B40*Theta-'W-Tax(All-Toll)-NONC'!$T$8)/B40 -> 0.31193322 | D40: 0.97128471 | E40: 0.97128471 | F40: 100 | G40: 0 | H40: =Size-a -> 100 | I40: =(EXP(alpha*(Tau+OldTau+zeta-2*a*psi))*((EXP(alpha*a*psi)-EXP(alpha*b*psi))^2))/((EXP(alpha*a*psi)-EXP(alpha*(2*OldTau+b*psi)))*(alpha^2)*(psi^2)) -> 1.862035 | J40: =(EXP(alpha*(zeta+(2*b-a)*psi))*(-1+EXP(alpha*(-1)*Size*psi))*(EXP(alpha*(2*(Tau+OldTau)+a*psi))-EXP(alpha*(2*(Tau+OldTau)+b*psi))))/(((EXP(alpha*a*psi)-EXP(alpha*(2*OldTau+b*psi)))^2)*(alpha^2)*(psi^2)) -> 8.1643844e-08 | K40: =-Beta/alpha -> 180 | L40: =(-EXP(alpha*zeta)*Beta*(-1+EXP(alpha*Size*psi)-Size*alpha*psi))/((alpha^3)*(psi^2)) -> 32736.769 | M40: =Beta*Theta -> 63.226826 | N40: =Beta*Theta -> 63.226826 | O40: =kappa -> 90 | P40: =Gamma*Size -> 0 | Q40: =Size*Beta*Phi -> 324 | R40: =-(EXP(alpha*a*psi)+EXP(alpha*b*psi)*(-1+Size*psi*alpha))*(Beta*Phi)/((alpha*psi)*(EXP(alpha*a*psi)-EXP(alpha*b*psi))) -> 21.599901 | S40: =(EXP(alpha*(zeta-a*psi))*Beta*Phi*(-EXP(alpha*a*psi)*(-2+(-1)*Size*alpha*psi)+EXP(alpha*b*psi)*(-2+Size*alpha*psi)))/((alpha^3)*(psi^3)) -> 3647.8128 | T40: =Tau*Beta -> 174.83125 | U40: =Tau*Beta -> 174.83125 | V40: =Tau -> 0.97128471 | W40: =Profit+Utility -> 29669.306 | X40: =(2*ij*BRIJ)+2*jj*BRJJ -> 651.08383 | Y40: =2*(ij*BCCIJ)+(2*jj*BCCJJ)+BCS+jj*BCPTJJ+2*(ij*BCPTIJ)+BCPTII+BCk -> 4053.7135 | Z40: =ij*BUTIJ+BUTII -> 33071.936 | AA40: =Revenue-Cost -> -3402.6297 | AB40: =Size -> 100 | AC40: =Welfare/(Size) -> 296.69306 | AD40: =Profit/(Size) -> -34.026297 | AE40: =Utility/(Size) -> 330.71936 | AF40: 308.66096
A41: =C40 -> 0.31193322 | B41: =(I41+J41)*Beta*2 -> 725.21535 | C41: =(W41+B41*Theta-'W-Tax(All-Toll)-NONC'!$T$8)/B41 -> 0.35124182 | D41: 0.93193742 | E41: 0.93193742 | F41: 100 | G41: 0 | H41: =Size-a -> 100 | I41: =(EXP(alpha*(Tau+OldTau+zeta-2*a*psi))*((EXP(alpha*a*psi)-EXP(alpha*b*psi))^2))/((EXP(alpha*a*psi)-EXP(alpha*(2*OldTau+b*psi)))*(alpha^2)*(psi^2)) -> 2.014487 | J41: =(EXP(alpha*(zeta+(2*b-a)*psi))*(-1+EXP(alpha*(-1)*Size*psi))*(EXP(alpha*(2*(Tau+OldTau)+a*psi))-EXP(alpha*(2*(Tau+OldTau)+b*psi))))/(((EXP(alpha*a*psi)-EXP(alpha*(2*OldTau+b*psi)))^2)*(alpha^2)*(psi^2)) -> 9.5560123e-08 | K41: =-Beta/alpha -> 180 | L41: =(-EXP(alpha*zeta)*Beta*(-1+EXP(alpha*Size*psi)-Size*alpha*psi))/((alpha^3)*(psi^2)) -> 32736.769 | M41: =Beta*Theta -> 56.14798 | N41: =Beta*Theta -> 56.14798 | O41: =kappa -> 90 | P41: =Gamma*Size -> 0 | Q41: =Size*Beta*Phi -> 324 | R41: =-(EXP(alpha*a*psi)+EXP(alpha*b*psi)*(-1+Size*psi*alpha))*(Beta*Phi)/((alpha*psi)*(EXP(alpha*a*psi)-EXP(alpha*b*psi))) -> 21.599901 | S41: =(EXP(alpha*(zeta-a*psi))*Beta*Phi*(-EXP(alpha*a*psi)*(-2+(-1)*Size*alpha*psi)+EXP(alpha*b*psi)*(-2+Size*alpha*psi)))/((alpha^3)*(psi^3)) -> 3647.8128 | T41: =Tau*Beta -> 167.74874 | U41: =Tau*Beta -> 167.74874 | V41: =Tau -> 0.93193742 | W41: =Profit+Utility -> 29724.175 | X41: =(2*ij*BRIJ)+2*jj*BRJJ -> 675.85532 | Y41: =2*(ij*BCCIJ)+(2*jj*BCCJJ)+BCS+jj*BCPTJJ+2*(ij*BCPTIJ)+BCPTII+BCk -> 4051.0571 | Z41: =ij*BUTIJ+BUTII -> 33099.377 | AA41: =Revenue-Cost -> -3375.2017 | AB41: =Size -> 100 | AC41: =Welfare/(Size) -> 297.24175 | AD41: =Profit/(Size) -> -33.752017 | AE41: =Utility/(Size) -> 330.99377 | AF41: 308.66096
A42: =C41 -> 0.35124182 | B42: =(I42+J42)*Beta*2 -> 670.35719 | C42: =(W42+B42*Theta-'W-Tax(All-Toll)-NONC'!$T$8)/B42 -> 0.31195299 | D42: 0.97126639 | E42: 0.97126639 | F42: 100 | G42: 0 | H42: =Size-a -> 100 | I42: =(EXP(alpha*(Tau+OldTau+zeta-2*a*psi))*((EXP(alpha*a*psi)-EXP(alpha*b*psi))^2))/((EXP(alpha*a*psi)-EXP(alpha*(2*OldTau+b*psi)))*(alpha^2)*(psi^2)) -> 1.8621032 | J42: =(EXP(alpha*(zeta+(2*b-a)*psi))*(-1+EXP(alpha*(-1)*Size*psi))*(EXP(alpha*(2*(Tau+OldTau)+a*psi))-EXP(alpha*(2*(Tau+OldTau)+b*psi))))/(((EXP(alpha*a*psi)-EXP(alpha*(2*OldTau+b*psi)))^2)*(alpha^2)*(psi^2)) -> 8.1649828e-08 | K42: =-Beta/alpha -> 180 | L42: =(-EXP(alpha*zeta)*Beta*(-1+EXP(alpha*Size*psi)-Size*alpha*psi))/((alpha^3)*(psi^2)) -> 32736.769 | M42: =Beta*Theta -> 63.223528 | N42: =Beta*Theta -> 63.223528 | O42: =kappa -> 90 | P42: =Gamma*Size -> 0 | Q42: =Size*Beta*Phi -> 324 | R42: =-(EXP(alpha*a*psi)+EXP(alpha*b*psi)*(-1+Size*psi*alpha))*(Beta*Phi)/((alpha*psi)*(EXP(alpha*a*psi)-EXP(alpha*b*psi))) -> 21.599901 | S42: =(EXP(alpha*(zeta-a*psi))*Beta*Phi*(-EXP(alpha*a*psi)*(-2+(-1)*Size*alpha*psi)+EXP(alpha*b*psi)*(-2+Size*alpha*psi)))/((alpha^3)*(psi^3)) -> 3647.8128 | T42: =Tau*Beta -> 174.82795 | U42: =Tau*Beta -> 174.82795 | V42: =Tau -> 0.97126639 | W42: =Profit+Utility -> 29669.331 | X42: =(2*ij*BRIJ)+2*jj*BRJJ -> 651.09541 | Y42: =2*(ij*BCCIJ)+(2*jj*BCCJJ)+BCS+jj*BCPTJJ+2*(ij*BCPTIJ)+BCPTII+BCk -> 4053.7128 | Z42: =ij*BUTIJ+BUTII -> 33071.948 | AA42: =Revenue-Cost -> -3402.6174 | AB42: =Size -> 100 | AC42: =Welfare/(Size) -> 296.69331 | AD42: =Profit/(Size) -> -34.026174 | AE42: =Utility/(Size) -> 330.71948 | AF42: 308.66096
A43: =C42 -> 0.31195299 | B43: =(I43+J43)*Beta*2 -> 697.24751 | C43: =(W43+B43*Theta-'W-Tax(All-Toll)-NONC'!$T$8)/B43 -> 0.33237068 | D43: =AVERAGE(D39:D42) -> 0.95160151 | E43: =AVERAGE(E39:E42) -> 0.95160151 | F43: 100 | G43: 0 | H43: =Size-a -> 100 | I43: =(EXP(alpha*(Tau+OldTau+zeta-2*a*psi))*((EXP(alpha*a*psi)-EXP(alpha*b*psi))^2))/((EXP(alpha*a*psi)-EXP(alpha*(2*OldTau+b*psi)))*(alpha^2)*(psi^2)) -> 1.9367985 | J43: =(EXP(alpha*(zeta+(2*b-a)*psi))*(-1+EXP(alpha*(-1)*Size*psi))*(EXP(alpha*(2*(Tau+OldTau)+a*psi))-EXP(alpha*(2*(Tau+OldTau)+b*psi))))/(((EXP(alpha*a*psi)-EXP(alpha*(2*OldTau+b*psi)))^2)*(alpha^2)*(psi^2)) -> 8.8331716e-08 | K43: =-Beta/alpha -> 180 | L43: =(-EXP(alpha*zeta)*Beta*(-1+EXP(alpha*Size*psi)-Size*alpha*psi))/((alpha^3)*(psi^2)) -> 32736.769 | M43: =Beta*Theta -> 56.151537 | N43: =Beta*Theta -> 56.151537 | O43: =kappa -> 90 | P43: =Gamma*Size -> 0 | Q43: =Size*Beta*Phi -> 324 | R43: =-(EXP(alpha*a*psi)+EXP(alpha*b*psi)*(-1+Size*psi*alpha))*(Beta*Phi)/((alpha*psi)*(EXP(alpha*a*psi)-EXP(alpha*b*psi))) -> 21.599901 | S43: =(EXP(alpha*(zeta-a*psi))*Beta*Phi*(-EXP(alpha*a*psi)*(-2+(-1)*Size*alpha*psi)+EXP(alpha*b*psi)*(-2+Size*alpha*psi)))/((alpha^3)*(psi^3)) -> 3647.8128 | T43: =Tau*Beta -> 171.28827 | U43: =Tau*Beta -> 171.28827 | V43: =Tau -> 0.95160151 | W43: =Profit+Utility -> 29709.904 | X43: =(2*ij*BRIJ)+2*jj*BRJJ -> 663.50178 | Y43: =2*(ij*BCCIJ)+(2*jj*BCCJJ)+BCS+jj*BCPTJJ+2*(ij*BCPTIJ)+BCPTII+BCk -> 4038.9906 | Z43: =ij*BUTIJ+BUTII -> 33085.393 | AA43: =Revenue-Cost -> -3375.4888 | AB43: =Size -> 100 | AC43: =Welfare/(Size) -> 297.09904 | AD43: =Profit/(Size) -> -33.754888 | AE43: =Utility/(Size) -> 330.85393 | AF43: 308.66096
A44: =C43 -> 0.33237068 | B44: =(I44+J44)*Beta*2 -> 696.17183 | C44: =(W44+B44*Theta-'W-Tax(All-Toll)-NONC'!$T$8)/B44 -> 0.33159871 | D44: 0.95237349 | E44: 0.95237349 | F44: 100 | G44: 0 | H44: =Size-a -> 100 | I44: =(EXP(alpha*(Tau+OldTau+zeta-2*a*psi))*((EXP(alpha*a*psi)-EXP(alpha*b*psi))^2))/((EXP(alpha*a*psi)-EXP(alpha*(2*OldTau+b*psi)))*(alpha^2)*(psi^2)) -> 1.9338105 | J44: =(EXP(alpha*(zeta+(2*b-a)*psi))*(-1+EXP(alpha*(-1)*Size*psi))*(EXP(alpha*(2*(Tau+OldTau)+a*psi))-EXP(alpha*(2*(Tau+OldTau)+b*psi))))/(((EXP(alpha*a*psi)-EXP(alpha*(2*OldTau+b*psi)))^2)*(alpha^2)*(psi^2)) -> 8.8059378e-08 | K44: =-Beta/alpha -> 180 | L44: =(-EXP(alpha*zeta)*Beta*(-1+EXP(alpha*Size*psi)-Size*alpha*psi))/((alpha^3)*(psi^2)) -> 32736.769 | M44: =Beta*Theta -> 59.826723 | N44: =Beta*Theta -> 59.826723 | O44: =kappa -> 90 | P44: =Gamma*Size -> 0 | Q44: =Size*Beta*Phi -> 324 | R44: =-(EXP(alpha*a*psi)+EXP(alpha*b*psi)*(-1+Size*psi*alpha))*(Beta*Phi)/((alpha*psi)*(EXP(alpha*a*psi)-EXP(alpha*b*psi))) -> 21.599901 | S44: =(EXP(alpha*(zeta-a*psi))*Beta*Phi*(-EXP(alpha*a*psi)*(-2+(-1)*Size*alpha*psi)+EXP(alpha*b*psi)*(-2+Size*alpha*psi)))/((alpha^3)*(psi^3)) -> 3647.8128 | T44: =Tau*Beta -> 171.42723 | U44: =Tau*Beta -> 171.42723 | V44: =Tau -> 0.95237349 | W44: =Profit+Utility -> 29695.131 | X44: =(2*ij*BRIJ)+2*jj*BRJJ -> 663.01559 | Y44: =2*(ij*BCCIJ)+(2*jj*BCCJJ)+BCS+jj*BCPTJJ+2*(ij*BCPTIJ)+BCPTII+BCk -> 4052.7402 | Z44: =ij*BUTIJ+BUTII -> 33084.855 | AA44: =Revenue-Cost -> -3389.7246 | AB44: =Size -> 100 | AC44: =Welfare/(Size) -> 296.95131 | AD44: =Profit/(Size) -> -33.897246 | AE44: =Utility/(Size) -> 330.84855 | AF44: 308.66096
A46: 0.08 | B46: =(I46+J46)*Beta*2 -> 1153.2532 | C46: =(W46+B46*Theta-'W-Tax(All-Toll)-NONC'!$T$11)/B46 -> 0.47627203 | D46: 0.70000093 | E46: 0.70000093 | F46: 1000 | G46: 0 | H46: =Size-a -> 1000 | I46: =(EXP(alpha*(Tau+OldTau+zeta-2*a*psi))*((EXP(alpha*a*psi)-EXP(alpha*b*psi))^2))/((EXP(alpha*a*psi)-EXP(alpha*(2*OldTau+b*psi)))*(alpha^2)*(psi^2)) -> 3.2034812 | J46: =(EXP(alpha*(zeta+(2*b-a)*psi))*(-1+EXP(alpha*(-1)*Size*psi))*(EXP(alpha*(2*(Tau+OldTau)+a*psi))-EXP(alpha*(2*(Tau+OldTau)+b*psi))))/(((EXP(alpha*a*psi)-EXP(alpha*(2*OldTau+b*psi)))^2)*(alpha^2)*(psi^2)) -> 5.668091e-66 | K46: =-Beta/alpha -> 180 | L46: =(-EXP(alpha*zeta)*Beta*(-1+EXP(alpha*Size*psi)-Size*alpha*psi))/((alpha^3)*(psi^2)) -> 348412.75 | M46: =Beta*Theta -> 14.4 | N46: =Beta*Theta -> 14.4 | O46: =kappa -> 90 | P46: =Gamma*Size -> 0 | Q46: =Size*Beta*Phi -> 3240 | R46: =-(EXP(alpha*a*psi)+EXP(alpha*b*psi)*(-1+Size*psi*alpha))*(Beta*Phi)/((alpha*psi)*(EXP(alpha*a*psi)-EXP(alpha*b*psi))) -> 21.6 | S46: =(EXP(alpha*(zeta-a*psi))*Beta*Phi*(-EXP(alpha*a*psi)*(-2+(-1)*Size*alpha*psi)+EXP(alpha*b*psi)*(-2+Size*alpha*psi)))/((alpha^3)*(psi^3)) -> 41528.929 | T46: =Tau*Beta -> 126.00017 | U46: =Tau*Beta -> 126.00017 | V46: =Tau -> 0.70000093 | W46: =Profit+Utility -> 307947.08 | X46: =(2*ij*BRIJ)+2*jj*BRJJ -> 807.27835 | Y46: =2*(ij*BCCIJ)+(2*jj*BCCJJ)+BCS+jj*BCPTJJ+2*(ij*BCPTIJ)+BCPTII+BCk -> 41849.58 | Z46: =ij*BUTIJ+BUTII -> 348989.38 | AA46: =Revenue-Cost -> -41042.302 | AB46: =Size -> 1000 | AC46: =Welfare/(Size) -> 307.94708 | AD46: =Profit/(Size) -> -41.042302 | AE46: =Utility/(Size) -> 348.98938 | AF46: 308.66096
A47: =C46 -> 0.47627203 | B47: =(I47+J47)*Beta*2 -> 522.00284 | C47: =(W47+B47*Theta-'W-Tax(All-Toll)-NONC'!$T$11)/B47 -> 0.14252606 | D47: 1.0963355 | E47: 1.0963355 | F47: 1000 | G47: 0 | H47: =Size-a -> 1000 | I47: =(EXP(alpha*(Tau+OldTau+zeta-2*a*psi))*((EXP(alpha*a*psi)-EXP(alpha*b*psi))^2))/((EXP(alpha*a*psi)-EXP(alpha*(2*OldTau+b*psi)))*(alpha^2)*(psi^2)) -> 1.4500079 | J47: =(EXP(alpha*(zeta+(2*b-a)*psi))*(-1+EXP(alpha*(-1)*Size*psi))*(EXP(alpha*(2*(Tau+OldTau)+a*psi))-EXP(alpha*(2*(Tau+OldTau)+b*psi))))/(((EXP(alpha*a*psi)-EXP(alpha*(2*OldTau+b*psi)))^2)*(alpha^2)*(psi^2)) -> 1.1612699e-66 | K47: =-Beta/alpha -> 180 | L47: =(-EXP(alpha*zeta)*Beta*(-1+EXP(alpha*Size*psi)-Size*alpha*psi))/((alpha^3)*(psi^2)) -> 348412.75 | M47: =Beta*Theta -> 85.728966 | N47: =Beta*Theta -> 85.728966 | O47: =kappa -> 90 | P47: =Gamma*Size -> 0 | Q47: =Size*Beta*Phi -> 3240 | R47: =-(EXP(alpha*a*psi)+EXP(alpha*b*psi)*(-1+Size*psi*alpha))*(Beta*Phi)/((alpha*psi)*(EXP(alpha*a*psi)-EXP(alpha*b*psi))) -> 21.6 | S47: =(EXP(alpha*(zeta-a*psi))*Beta*Phi*(-EXP(alpha*a*psi)*(-2+(-1)*Size*alpha*psi)+EXP(alpha*b*psi)*(-2+Size*alpha*psi)))/((alpha^3)*(psi^3)) -> 41528.929 | T47: =Tau*Beta -> 197.34039 | U47: =Tau*Beta -> 197.34039 | V47: =Tau -> 1.0963355 | W47: =Profit+Utility -> 307315.86 | X47: =(2*ij*BRIJ)+2*jj*BRJJ -> 572.29024 | Y47: =2*(ij*BCCIJ)+(2*jj*BCCJJ)+BCS+jj*BCPTJJ+2*(ij*BCPTIJ)+BCPTII+BCk -> 41930.185 | Z47: =ij*BUTIJ+BUTII -> 348673.75 | AA47: =Revenue-Cost -> -41357.895 | AB47: =Size -> 1000 | AC47: =Welfare/(Size) -> 307.31586 | AD47: =Profit/(Size) -> -41.357895 | AE47: =Utility/(Size) -> 348.67375 | AF47: 308.66096
A48: =C47 -> 0.14252606 | B48: =(I48+J48)*Beta*2 -> 696.17219 | C48: =(W48+B48*Theta-'W-Tax(All-Toll)-NONC'!$T$11)/B48 -> 0.3322584 | D48: 0.95237349 | E48: 0.95237349 | F48: 1000 | G48: 0 | H48: =Size-a -> 1000 | I48: =(EXP(alpha*(Tau+OldTau+zeta-2*a*psi))*((EXP(alpha*a*psi)-EXP(alpha*b*psi))^2))/((EXP(alpha*a*psi)-EXP(alpha*(2*OldTau+b*psi)))*(alpha^2)*(psi^2)) -> 1.9338116 | J48: =(EXP(alpha*(zeta+(2*b-a)*psi))*(-1+EXP(alpha*(-1)*Size*psi))*(EXP(alpha*(2*(Tau+OldTau)+a*psi))-EXP(alpha*(2*(Tau+OldTau)+b*psi))))/(((EXP(alpha*a*psi)-EXP(alpha*(2*OldTau+b*psi)))^2)*(alpha^2)*(psi^2)) -> 2.065479e-66 | K48: =-Beta/alpha -> 180 | L48: =(-EXP(alpha*zeta)*Beta*(-1+EXP(alpha*Size*psi)-Size*alpha*psi))/((alpha^3)*(psi^2)) -> 348412.75 | M48: =Beta*Theta -> 25.65469 | N48: =Beta*Theta -> 25.65469 | O48: =kappa -> 90 | P48: =Gamma*Size -> 0 | Q48: =Size*Beta*Phi -> 3240 | R48: =-(EXP(alpha*a*psi)+EXP(alpha*b*psi)*(-1+Size*psi*alpha))*(Beta*Phi)/((alpha*psi)*(EXP(alpha*a*psi)-EXP(alpha*b*psi))) -> 21.6 | S48: =(EXP(alpha*(zeta-a*psi))*Beta*Phi*(-EXP(alpha*a*psi)*(-2+(-1)*Size*alpha*psi)+EXP(alpha*b*psi)*(-2+Size*alpha*psi)))/((alpha^3)*(psi^3)) -> 41528.929 | T48: =Tau*Beta -> 171.42723 | U48: =Tau*Beta -> 171.42723 | V48: =Tau -> 0.95237349 | W48: =Profit+Utility -> 307622.16 | X48: =(2*ij*BRIJ)+2*jj*BRJJ -> 663.01593 | Y48: =2*(ij*BCCIJ)+(2*jj*BCCJJ)+BCS+jj*BCPTJJ+2*(ij*BCPTIJ)+BCPTII+BCk -> 41801.693 | Z48: =ij*BUTIJ+BUTII -> 348760.84 | AA48: =Revenue-Cost -> -41138.677 | AB48: =Size -> 1000 | AC48: =Welfare/(Size) -> 307.62216 | AD48: =Profit/(Size) -> -41.138677 | AE48: =Utility/(Size) -> 348.76084 | AF48: 308.66096
A49: =C48 -> 0.3322584 | B49: =(I49+J49)*Beta*2 -> 696.25974 | C49: =(W49+B49*Theta-'W-Tax(All-Toll)-NONC'!$T$11)/B49 -> 0.33232128 | D49: 0.95231061 | E49: 0.95231061 | F49: 1000 | G49: 0 | H49: =Size-a -> 1000 | I49: =(EXP(alpha*(Tau+OldTau+zeta-2*a*psi))*((EXP(alpha*a*psi)-EXP(alpha*b*psi))^2))/((EXP(alpha*a*psi)-EXP(alpha*(2*OldTau+b*psi)))*(alpha^2)*(psi^2)) -> 1.9340548 | J49: =(EXP(alpha*(zeta+(2*b-a)*psi))*(-1+EXP(alpha*(-1)*Size*psi))*(EXP(alpha*(2*(Tau+OldTau)+a*psi))-EXP(alpha*(2*(Tau+OldTau)+b*psi))))/(((EXP(alpha*a*psi)-EXP(alpha*(2*OldTau+b*psi)))^2)*(alpha^2)*(psi^2)) -> 2.0659985e-66 | K49: =-Beta/alpha -> 180 | L49: =(-EXP(alpha*zeta)*Beta*(-1+EXP(alpha*Size*psi)-Size*alpha*psi))/((alpha^3)*(psi^2)) -> 348412.75 | M49: =Beta*Theta -> 59.806511 | N49: =Beta*Theta -> 59.806511 | O49: =kappa -> 90 | P49: =Gamma*Size -> 0 | Q49: =Size*Beta*Phi -> 3240 | R49: =-(EXP(alpha*a*psi)+EXP(alpha*b*psi)*(-1+Size*psi*alpha))*(Beta*Phi)/((alpha*psi)*(EXP(alpha*a*psi)-EXP(alpha*b*psi))) -> 21.6 | S49: =(EXP(alpha*(zeta-a*psi))*Beta*Phi*(-EXP(alpha*a*psi)*(-2+(-1)*Size*alpha*psi)+EXP(alpha*b*psi)*(-2+Size*alpha*psi)))/((alpha^3)*(psi^3)) -> 41528.929 | T49: =Tau*Beta -> 171.41591 | U49: =Tau*Beta -> 171.41591 | V49: =Tau -> 0.95231061 | W49: =Profit+Utility -> 307490.12 | X49: =(2*ij*BRIJ)+2*jj*BRJJ -> 663.05554 | Y49: =2*(ij*BCCIJ)+(2*jj*BCCJJ)+BCS+jj*BCPTJJ+2*(ij*BCPTIJ)+BCPTII+BCk -> 41933.819 | Z49: =ij*BUTIJ+BUTII -> 348760.88 | AA49: =Revenue-Cost -> -41270.763 | AB49: =Size -> 1000 | AC49: =Welfare/(Size) -> 307.49012 | AD49: =Profit/(Size) -> -41.270763 | AE49: =Utility/(Size) -> 348.76088 | AF49: 308.66096
A50: =C49 -> 0.33232128 | B50: =(I50+J50)*Beta*2 -> 1153.2532 | C50: =(W50+B50*Theta-'W-Tax(All-Toll)-NONC'!$T$11)/B50 -> 0.47627203 | D50: 0.70000093 | E50: 0.70000093 | F50: 1000 | G50: 0 | H50: =Size-a -> 1000 | I50: =(EXP(alpha*(Tau+OldTau+zeta-2*a*psi))*((EXP(alpha*a*psi)-EXP(alpha*b*psi))^2))/((EXP(alpha*a*psi)-EXP(alpha*(2*OldTau+b*psi)))*(alpha^2)*(psi^2)) -> 3.2034812 | J50: =(EXP(alpha*(zeta+(2*b-a)*psi))*(-1+EXP(alpha*(-1)*Size*psi))*(EXP(alpha*(2*(Tau+OldTau)+a*psi))-EXP(alpha*(2*(Tau+OldTau)+b*psi))))/(((EXP(alpha*a*psi)-EXP(alpha*(2*OldTau+b*psi)))^2)*(alpha^2)*(psi^2)) -> 5.668091e-66 | K50: =-Beta/alpha -> 180 | L50: =(-EXP(alpha*zeta)*Beta*(-1+EXP(alpha*Size*psi)-Size*alpha*psi))/((alpha^3)*(psi^2)) -> 348412.75 | M50: =Beta*Theta -> 59.81783 | N50: =Beta*Theta -> 59.81783 | O50: =kappa -> 90 | P50: =Gamma*Size -> 0 | Q50: =Size*Beta*Phi -> 3240 | R50: =-(EXP(alpha*a*psi)+EXP(alpha*b*psi)*(-1+Size*psi*alpha))*(Beta*Phi)/((alpha*psi)*(EXP(alpha*a*psi)-EXP(alpha*b*psi))) -> 21.6 | S50: =(EXP(alpha*(zeta-a*psi))*Beta*Phi*(-EXP(alpha*a*psi)*(-2+(-1)*Size*alpha*psi)+EXP(alpha*b*psi)*(-2+Size*alpha*psi)))/((alpha^3)*(psi^3)) -> 41528.929 | T50: =Tau*Beta -> 126.00017 | U50: =Tau*Beta -> 126.00017 | V50: =Tau -> 0.70000093 | W50: =Profit+Utility -> 307656.09 | X50: =(2*ij*BRIJ)+2*jj*BRJJ -> 807.27835 | Y50: =2*(ij*BCCIJ)+(2*jj*BCCJJ)+BCS+jj*BCPTJJ+2*(ij*BCPTIJ)+BCPTII+BCk -> 42140.57 | Z50: =ij*BUTIJ+BUTII -> 348989.38 | AA50: =Revenue-Cost -> -41333.292 | AB50: =Size -> 1000 | AC50: =Welfare/(Size) -> 307.65609 | AD50: =Profit/(Size) -> -41.333292 | AE50: =Utility/(Size) -> 348.98938 | AF50: 308.66096

Sheet W-Toll(All-Toll)-Coop
A1: Tau | B1: OldTau | C1: Size | D1: a | E1: b | F1: ij | G1: jj | H1: BUTIJ | I1: BUTII | J1: BCCIJ | K1: BCCJJ | L1: BCk | M1: BCS | N1: BCPTJJ | O1: BCPTIJ | P1: BCPTII | Q1: BRIJ | R1: BRJJ | S1: Toll | T1: Welfare | U1: Revenue | V1: Cost | W1: Utility | X1: Profit | Y1: Size2 | Z1: W/Size | AA1: ∏/Size | AB1: U/Size
A2: 0.088963449 | B2: =Tau -> 0.088963449 | C2: 1 | D2: 0 | E2: =Size-a -> 1 | F2: =(EXP(alpha*(Tau+OldTau+zeta-2*a*psi))*((EXP(alpha*a*psi)-EXP(alpha*b*psi))^2))/((EXP(alpha*a*psi)-EXP(alpha*(2*OldTau+b*psi)))*(alpha^2)*(psi^2)) -> 0.75457478 | G2: =(EXP(alpha*(zeta+(2*b-a)*psi))*(-1+EXP(alpha*(-1)*Size*psi))*(EXP(alpha*(2*(Tau+OldTau)+a*psi))-EXP(alpha*(2*(Tau+OldTau)+b*psi))))/(((EXP(alpha*a*psi)-EXP(alpha*(2*OldTau+b*psi)))^2)*(alpha^2)*(psi^2)) -> 1.9443419 | H2: =-Beta/alpha -> 180 | I2: =(-EXP(alpha*zeta)*Beta*(-1+EXP(alpha*Size*psi)-Size*alpha*psi))/((alpha^3)*(psi^2)) -> 25.038896 | J2: =Beta*Theta -> 14.4 | K2: =Beta*Theta -> 14.4 | L2: =kappa -> 90 | M2: =Gamma*Size -> 0 | N2: =Size*Beta*Phi -> 3.24 | O2: =-(EXP(alpha*a*psi)+EXP(alpha*b*psi)*(-1+Size*psi*alpha))*(Beta*Phi)/((alpha*psi)*(EXP(alpha*a*psi)-EXP(alpha*b*psi))) -> 1.5795152 | P2: =(EXP(alpha*(zeta-a*psi))*Beta*Phi*(-EXP(alpha*a*psi)*(-2+(-1)*Size*alpha*psi)+EXP(alpha*b*psi)*(-2+Size*alpha*psi)))/((alpha^3)*(psi^3)) -> 0.14651555 | Q2: =Tau*Beta -> 16.013421 | R2: =Tau*Beta -> 16.013421 | S2: =Tau -> 0.088963449 | T2: =Profit+Utility -> 70.741425 | U2: =(2*ij*BRIJ)+2*jj*BRJJ -> 86.437777 | V2: =2*(ij*BCCIJ)+(2*jj*BCCJJ)+BCS+jj*BCPTJJ+2*(ij*BCPTIJ)+BCPTII+BCk -> 176.55871 | W2: =ij*BUTIJ+BUTII -> 160.86236 | X2: =Revenue-Cost -> -90.120931 | Y2: =Size -> 1 | Z2: =Welfare/(Size) -> 70.741425 | AA2: =Profit/(Size) -> -90.120931 | AB2: =Utility/(Size) -> 160.86236
A3: 0.097781815 | B3: =Tau -> 0.097781815 | C3: 2 | D3: 0 | E3: =Size-a -> 2 | F3: =(EXP(alpha*(Tau+OldTau+zeta-2*a*psi))*((EXP(alpha*a*psi)-EXP(alpha*b*psi))^2))/((EXP(alpha*a*psi)-EXP(alpha*(2*OldTau+b*psi)))*(alpha^2)*(psi^2)) -> 1.8364873 | G3: =(EXP(alpha*(zeta+(2*b-a)*psi))*(-1+EXP(alpha*(-1)*Size*psi))*(EXP(alpha*(2*(Tau+OldTau)+a*psi))-EXP(alpha*(2*(Tau+OldTau)+b*psi))))/(((EXP(alpha*a*psi)-EXP(alpha*(2*OldTau+b*psi)))^2)*(alpha^2)*(psi^2)) -> 2.8631448 | H3: =-Beta/alpha -> 180 | I3: =(-EXP(alpha*zeta)*Beta*(-1+EXP(alpha*Size*psi)-Size*alpha*psi))/((alpha^3)*(psi^2)) -> 95.446904 | J3: =Beta*Theta -> 14.4 | K3: =Beta*Theta -> 14.4 | L3: =kappa -> 90 | M3: =Gamma*Size -> 0 | N3: =Size*Beta*Phi -> 6.48 | O3: =-(EXP(alpha*a*psi)+EXP(alpha*b*psi)*(-1+Size*psi*alpha))*(Beta*Phi)/((alpha*psi)*(EXP(alpha*a*psi)-EXP(alpha*b*psi))) -> 3.0782425 | P3: =(EXP(alpha*(zeta-a*psi))*Beta*Phi*(-EXP(alpha*a*psi)*(-2+(-1)*Size*alpha*psi)+EXP(alpha*b*psi)*(-2+Size*alpha*psi)))/((alpha^3)*(psi^3)) -> 1.0892667 | Q3: =Tau*Beta -> 17.600727 | R3: =Tau*Beta -> 17.600727 | S3: =Tau -> 0.097781815 | T3: =Profit+Utility -> 335.15034 | U3: =(2*ij*BRIJ)+2*jj*BRJJ -> 165.43388 | V3: =2*(ij*BCCIJ)+(2*jj*BCCJJ)+BCS+jj*BCPTJJ+2*(ij*BCPTIJ)+BCPTII+BCk -> 256.29815 | W3: =ij*BUTIJ+BUTII -> 426.01462 | X3: =Revenue-Cost -> -90.864275 | Y3: =Size -> 2 | Z3: =Welfare/(Size) -> 167.57517 | AA3: =Profit/(Size) -> -45.432138 | AB3: =Utility/(Size) -> 213.00731
A4: 0.12245057 | B4: =Tau -> 0.12245057 | C4: 5 | D4: 0 | E4: =Size-a -> 5 | F4: =(EXP(alpha*(Tau+OldTau+zeta-2*a*psi))*((EXP(alpha*a*psi)-EXP(alpha*b*psi))^2))/((EXP(alpha*a*psi)-EXP(alpha*(2*OldTau+b*psi)))*(alpha^2)*(psi^2)) -> 4.4919481 | G4: =(EXP(alpha*(zeta+(2*b-a)*psi))*(-1+EXP(alpha*(-1)*Size*psi))*(EXP(alpha*(2*(Tau+OldTau)+a*psi))-EXP(alpha*(2*(Tau+OldTau)+b*psi))))/(((EXP(alpha*a*psi)-EXP(alpha*(2*OldTau+b*psi)))^2)*(alpha^2)*(psi^2)) -> 2.6354131 | H4: =-Beta/alpha -> 180 | I4: =(-EXP(alpha*zeta)*Beta*(-1+EXP(alpha*Size*psi)-Size*alpha*psi))/((alpha^3)*(psi^2)) -> 519.96874 | J4: =Beta*Theta -> 14.4 | K4: =Beta*Theta -> 14.4 | L4: =kappa -> 90 | M4: =Gamma*Size -> 0 | N4: =Size*Beta*Phi -> 16.2 | O4: =-(EXP(alpha*a*psi)+EXP(alpha*b*psi)*(-1+Size*psi*alpha))*(Beta*Phi)/((alpha*psi)*(EXP(alpha*a*psi)-EXP(alpha*b*psi))) -> 7.0968668 | P4: =(EXP(alpha*(zeta-a*psi))*Beta*Phi*(-EXP(alpha*a*psi)*(-2+(-1)*Size*alpha*psi)+EXP(alpha*b*psi)*(-2+Size*alpha*psi)))/((alpha^3)*(psi^3)) -> 13.751693 | Q4: =Tau*Beta -> 22.041102 | R4: =Tau*Beta -> 22.041102 | S4: =Tau -> 0.12245057 | T4: =Profit+Utility -> 1227.2383 | U4: =(2*ij*BRIJ)+2*jj*BRJJ -> 314.18979 | V4: =2*(ij*BCCIJ)+(2*jj*BCCJJ)+BCS+jj*BCPTJJ+2*(ij*BCPTIJ)+BCPTII+BCk -> 415.4709 | W4: =ij*BUTIJ+BUTII -> 1328.5194 | X4: =Revenue-Cost -> -101.28111 | Y4: =Size -> 5 | Z4: =Welfare/(Size) -> 245.44766 | AA4: =Profit/(Size) -> -20.256222 | AB4: =Utility/(Size) -> 265.70388
A5: 0.15441518 | B5: =Tau -> 0.15441518 | C5: 10 | D5: 0 | E5: =Size-a -> 10 | F5: =(EXP(alpha*(Tau+OldTau+zeta-2*a*psi))*((EXP(alpha*a*psi)-EXP(alpha*b*psi))^2))/((EXP(alpha*a*psi)-EXP(alpha*(2*OldTau+b*psi)))*(alpha^2)*(psi^2)) -> 6.8852866 | G5: =(EXP(alpha*(zeta+(2*b-a)*psi))*(-1+EXP(alpha*(-1)*Size*psi))*(EXP(alpha*(2*(Tau+OldTau)+a*psi))-EXP(alpha*(2*(Tau+OldTau)+b*psi))))/(((EXP(alpha*a*psi)-EXP(alpha*(2*OldTau+b*psi)))^2)*(alpha^2)*(psi^2)) -> 1.349182 | H5: =-Beta/alpha -> 180 | I5: =(-EXP(alpha*zeta)*Beta*(-1+EXP(alpha*Size*psi)-Size*alpha*psi))/((alpha^3)*(psi^2)) -> 1690.9246 | J5: =Beta*Theta -> 14.4 | K5: =Beta*Theta -> 14.4 | L5: =kappa -> 90 | M5: =Gamma*Size -> 0 | N5: =Size*Beta*Phi -> 32.4 | O5: =-(EXP(alpha*a*psi)+EXP(alpha*b*psi)*(-1+Size*psi*alpha))*(Beta*Phi)/((alpha*psi)*(EXP(alpha*a*psi)-EXP(alpha*b*psi))) -> 12.294172 | P5: =(EXP(alpha*(zeta-a*psi))*Beta*Phi*(-EXP(alpha*a*psi)*(-2+(-1)*Size*alpha*psi)+EXP(alpha*b*psi)*(-2+Size*alpha*psi)))/((alpha^3)*(psi^3)) -> 78.836376 | Q5: =Tau*Beta -> 27.794733 | R5: =Tau*Beta -> 27.794733 | S5: =Tau -> 0.15441518 | T5: =Profit+Utility -> 2769.0256 | U5: =(2*ij*BRIJ)+2*jj*BRJJ -> 457.74971 | V5: =2*(ij*BCCIJ)+(2*jj*BCCJJ)+BCS+jj*BCPTJJ+2*(ij*BCPTIJ)+BCPTII+BCk -> 619.00036 | W5: =ij*BUTIJ+BUTII -> 2930.2762 | X5: =Revenue-Cost -> -161.25066 | Y5: =Size -> 10 | Z5: =Welfare/(Size) -> 276.90256 | AA5: =Profit/(Size) -> -16.125066 | AB5: =Utility/(Size) -> 293.02762
A6: 0.18637005 | B6: =Tau -> 0.18637005 | C6: 20 | D6: 0 | E6: =Size-a -> 20 | F6: =(EXP(alpha*(Tau+OldTau+zeta-2*a*psi))*((EXP(alpha*a*psi)-EXP(alpha*b*psi))^2))/((EXP(alpha*a*psi)-EXP(alpha*(2*OldTau+b*psi)))*(alpha^2)*(psi^2)) -> 8.3666949 | G6: =(EXP(alpha*(zeta+(2*b-a)*psi))*(-1+EXP(alpha*(-1)*Size*psi))*(EXP(alpha*(2*(Tau+OldTau)+a*psi))-EXP(alpha*(2*(Tau+OldTau)+b*psi))))/(((EXP(alpha*a*psi)-EXP(alpha*(2*OldTau+b*psi)))^2)*(alpha^2)*(psi^2)) -> 0.29713053 | H6: =-Beta/alpha -> 180 | I6: =(-EXP(alpha*zeta)*Beta*(-1+EXP(alpha*Size*psi)-Size*alpha*psi))/((alpha^3)*(psi^2)) -> 4793.1004 | J6: =Beta*Theta -> 14.4 | K6: =Beta*Theta -> 14.4 | L6: =kappa -> 90 | M6: =Gamma*Size -> 0 | N6: =Size*Beta*Phi -> 64.8 | O6: =-(EXP(alpha*a*psi)+EXP(alpha*b*psi)*(-1+Size*psi*alpha))*(Beta*Phi)/((alpha*psi)*(EXP(alpha*a*psi)-EXP(alpha*b*psi))) -> 18.204759 | P6: =(EXP(alpha*(zeta-a*psi))*Beta*Phi*(-EXP(alpha*a*psi)*(-2+(-1)*Size*alpha*psi)+EXP(alpha*b*psi)*(-2+Size*alpha*psi)))/((alpha^3)*(psi^3)) -> 350.45235 | Q6: =Tau*Beta -> 33.546609 | R6: =Tau*Beta -> 33.546609 | S6: =Tau -> 0.18637005 | T6: =Profit+Utility -> 5866.5375 | U6: =(2*ij*BRIJ)+2*jj*BRJJ -> 581.28393 | V6: =2*(ij*BCCIJ)+(2*jj*BCCJJ)+BCS+jj*BCPTJJ+2*(ij*BCPTIJ)+BCPTII+BCk -> 1013.8519 | W6: =ij*BUTIJ+BUTII -> 6299.1055 | X6: =Revenue-Cost -> -432.56797 | Y6: =Size -> 20 | Z6: =Welfare/(Size) -> 293.32687 | AA6: =Profit/(Size) -> -21.628399 | AB6: =Utility/(Size) -> 314.95527
A7: 0.19974985 | B7: =Tau -> 0.19974985 | C7: 50 | D7: 0 | E7: =Size-a -> 50 | F7: =(EXP(alpha*(Tau+OldTau+zeta-2*a*psi))*((EXP(alpha*a*psi)-EXP(alpha*b*psi))^2))/((EXP(alpha*a*psi)-EXP(alpha*(2*OldTau+b*psi)))*(alpha^2)*(psi^2)) -> 8.7059334 | G7: =(EXP(alpha*(zeta+(2*b-a)*psi))*(-1+EXP(alpha*(-1)*Size*psi))*(EXP(alpha*(2*(Tau+OldTau)+a*psi))-EXP(alpha*(2*(Tau+OldTau)+b*psi))))/(((EXP(alpha*a*psi)-EXP(alpha*(2*OldTau+b*psi)))^2)*(alpha^2)*(psi^2)) -> 0.0032304821 | H7: =-Beta/alpha -> 180 | I7: =(-EXP(alpha*zeta)*Beta*(-1+EXP(alpha*Size*psi)-Size*alpha*psi))/((alpha^3)*(psi^2)) -> 15200.507 | J7: =Beta*Theta -> 14.4 | K7: =Beta*Theta -> 14.4 | L7: =kappa -> 90 | M7: =Gamma*Size -> 0 | N7: =Size*Beta*Phi -> 162 | O7: =-(EXP(alpha*a*psi)+EXP(alpha*b*psi)*(-1+Size*psi*alpha))*(Beta*Phi)/((alpha*psi)*(EXP(alpha*a*psi)-EXP(alpha*b*psi))) -> 21.510351 | P7: =(EXP(alpha*(zeta-a*psi))*Beta*Phi*(-EXP(alpha*a*psi)*(-2+(-1)*Size*alpha*psi)+EXP(alpha*b*psi)*(-2+Size*alpha*psi)))/((alpha^3)*(psi^3)) -> 1544.7792 | Q7: =Tau*Beta -> 35.954973 | R7: =Tau*Beta -> 35.954973 | S7: =Tau -> 0.19974985 | T7: =Profit+Utility -> 15133.189 | U7: =(2*ij*BRIJ)+2*jj*BRJJ -> 626.2755 | V7: =2*(ij*BCCIJ)+(2*jj*BCCJJ)+BCS+jj*BCPTJJ+2*(ij*BCPTIJ)+BCPTII+BCk -> 2260.6618 | W7: =ij*BUTIJ+BUTII -> 16767.575 | X7: =Revenue-Cost -> -1634.3863 | Y7: =Size -> 50 | Z7: =Welfare/(Size) -> 302.66378 | AA7: =Profit/(Size) -> -32.687726 | AB7: =Utility/(Size) -> 335.35151
A8: 0.20000258 | B8: =Tau -> 0.20000258 | C8: 100 | D8: 0 | E8: =Size-a -> 100 | F8: =(EXP(alpha*(Tau+OldTau+zeta-2*a*psi))*((EXP(alpha*a*psi)-EXP(alpha*b*psi))^2))/((EXP(alpha*a*psi)-EXP(alpha*(2*OldTau+b*psi)))*(alpha^2)*(psi^2)) -> 8.7079326 | G8: =(EXP(alpha*(zeta+(2*b-a)*psi))*(-1+EXP(alpha*(-1)*Size*psi))*(EXP(alpha*(2*(Tau+OldTau)+a*psi))-EXP(alpha*(2*(Tau+OldTau)+b*psi))))/(((EXP(alpha*a*psi)-EXP(alpha*(2*OldTau+b*psi)))^2)*(alpha^2)*(psi^2)) -> 1.7855741e-06 | H8: =-Beta/alpha -> 180 | I8: =(-EXP(alpha*zeta)*Beta*(-1+EXP(alpha*Size*psi)-Size*alpha*psi))/((alpha^3)*(psi^2)) -> 32736.769 | J8: =Beta*Theta -> 14.4 | K8: =Beta*Theta -> 14.4 | L8: =kappa -> 90 | M8: =Gamma*Size -> 0 | N8: =Size*Beta*Phi -> 324 | O8: =-(EXP(alpha*a*psi)+EXP(alpha*b*psi)*(-1+Size*psi*alpha))*(Beta*Phi)/((alpha*psi)*(EXP(alpha*a*psi)-EXP(alpha*b*psi))) -> 21.599901 | P8: =(EXP(alpha*(zeta-a*psi))*Beta*Phi*(-EXP(alpha*a*psi)*(-2+(-1)*Size*alpha*psi)+EXP(alpha*b*psi)*(-2+Size*alpha*psi)))/((alpha^3)*(psi^3)) -> 3647.8128 | Q8: =Tau*Beta -> 36.000465 | R8: =Tau*Beta -> 36.000465 | S8: =Tau -> 0.20000258 | T8: =Profit+Utility -> 30566.394 | U8: =(2*ij*BRIJ)+2*jj*BRJJ -> 626.97936 | V8: =2*(ij*BCCIJ)+(2*jj*BCCJJ)+BCS+jj*BCPTJJ+2*(ij*BCPTIJ)+BCPTII+BCk -> 4364.7829 | W8: =ij*BUTIJ+BUTII -> 34304.197 | X8: =Revenue-Cost -> -3737.8035 | Y8: =Size -> 100 | Z8: =Welfare/(Size) -> 305.66394 | AA8: =Profit/(Size) -> -37.378035 | AB8: =Utility/(Size) -> 343.04197
A9: 0.20000281 | B9: =Tau -> 0.20000281 | C9: 200 | D9: 0 | E9: =Size-a -> 200 | F9: =(EXP(alpha*(Tau+OldTau+zeta-2*a*psi))*((EXP(alpha*a*psi)-EXP(alpha*b*psi))^2))/((EXP(alpha*a*psi)-EXP(alpha*(2*OldTau+b*psi)))*(alpha^2)*(psi^2)) -> 8.7079321 | G9: =(EXP(alpha*(zeta+(2*b-a)*psi))*(-1+EXP(alpha*(-1)*Size*psi))*(EXP(alpha*(2*(Tau+OldTau)+a*psi))-EXP(alpha*(2*(Tau+OldTau)+b*psi))))/(((EXP(alpha*a*psi)-EXP(alpha*(2*OldTau+b*psi)))^2)*(alpha^2)*(psi^2)) -> 5.4621087e-13 | H9: =-Beta/alpha -> 180 | I9: =(-EXP(alpha*zeta)*Beta*(-1+EXP(alpha*Size*psi)-Size*alpha*psi))/((alpha^3)*(psi^2)) -> 67811.878 | J9: =Beta*Theta -> 14.4 | K9: =Beta*Theta -> 14.4 | L9: =kappa -> 90 | M9: =Gamma*Size -> 0 | N9: =Size*Beta*Phi -> 648 | O9: =-(EXP(alpha*a*psi)+EXP(alpha*b*psi)*(-1+Size*psi*alpha))*(Beta*Phi)/((alpha*psi)*(EXP(alpha*a*psi)-EXP(alpha*b*psi))) -> 21.6 | P9: =(EXP(alpha*(zeta-a*psi))*Beta*Phi*(-EXP(alpha*a*psi)*(-2+(-1)*Size*alpha*psi)+EXP(alpha*b*psi)*(-2+Size*alpha*psi)))/((alpha^3)*(psi^3)) -> 7856.8245 | Q9: =Tau*Beta -> 36.000506 | R9: =Tau*Beta -> 36.000506 | S9: =Tau -> 0.20000281 | T9: =Profit+Utility -> 61432.49 | U9: =(2*ij*BRIJ)+2*jj*BRJJ -> 626.97993 | V9: =2*(ij*BCCIJ)+(2*jj*BCCJJ)+BCS+jj*BCPTJJ+2*(ij*BCPTIJ)+BCPTII+BCk -> 8573.7956 | W9: =ij*BUTIJ+BUTII -> 69379.306 | X9: =Revenue-Cost -> -7946.8157 | Y9: =Size -> 200 | Z9: =Welfare/(Size) -> 307.16245 | AA9: =Profit/(Size) -> -39.734078 | AB9: =Utility/(Size) -> 346.89653
A10: 0.20115999 | B10: =Tau -> 0.20115999 | C10: 500 | D10: 0 | E10: =Size-a -> 500 | F10: =(EXP(alpha*(Tau+OldTau+zeta-2*a*psi))*((EXP(alpha*a*psi)-EXP(alpha*b*psi))^2))/((EXP(alpha*a*psi)-EXP(alpha*(2*OldTau+b*psi)))*(alpha^2)*(psi^2)) -> 8.6878021 | G10: =(EXP(alpha*(zeta+(2*b-a)*psi))*(-1+EXP(alpha*(-1)*Size*psi))*(EXP(alpha*(2*(Tau+OldTau)+a*psi))-EXP(alpha*(2*(Tau+OldTau)+b*psi))))/(((EXP(alpha*a*psi)-EXP(alpha*(2*OldTau+b*psi)))^2)*(alpha^2)*(psi^2)) -> 1.5563183e-32 | H10: =-Beta/alpha -> 180 | I10: =(-EXP(alpha*zeta)*Beta*(-1+EXP(alpha*Size*psi)-Size*alpha*psi))/((alpha^3)*(psi^2)) -> 173037.21 | J10: =Beta*Theta -> 14.4 | K10: =Beta*Theta -> 14.4 | L10: =kappa -> 90 | M10: =Gamma*Size -> 0 | N10: =Size*Beta*Phi -> 1620 | O10: =-(EXP(alpha*a*psi)+EXP(alpha*b*psi)*(-1+Size*psi*alpha))*(Beta*Phi)/((alpha*psi)*(EXP(alpha*a*psi)-EXP(alpha*b*psi))) -> 21.6 | P10: =(EXP(alpha*(zeta-a*psi))*Beta*Phi*(-EXP(alpha*a*psi)*(-2+(-1)*Size*alpha*psi)+EXP(alpha*b*psi)*(-2+Size*alpha*psi)))/((alpha^3)*(psi^3)) -> 20483.864 | Q10: =Tau*Beta -> 36.208799 | R10: =Tau*Beta -> 36.208799 | S10: =Tau -> 0.20115999 | T10: =Profit+Utility -> 154030.77 | U10: =(2*ij*BRIJ)+2*jj*BRJJ -> 629.14976 | V10: =2*(ij*BCCIJ)+(2*jj*BCCJJ)+BCS+jj*BCPTJJ+2*(ij*BCPTIJ)+BCPTII+BCk -> 21199.386 | W10: =ij*BUTIJ+BUTII -> 174601.01 | X10: =Revenue-Cost -> -20570.236 | Y10: =Size -> 500 | Z10: =Welfare/(Size) -> 308.06155 | AA10: =Profit/(Size) -> -41.140472 | AB10: =Utility/(Size) -> 349.20202
A11: 0.20115999 | B11: =Tau -> 0.20115999 | C11: 1000 | D11: 0 | E11: =Size-a -> 1000 | F11: =(EXP(alpha*(Tau+OldTau+zeta-2*a*psi))*((EXP(alpha*a*psi)-EXP(alpha*b*psi))^2))/((EXP(alpha*a*psi)-EXP(alpha*(2*OldTau+b*psi)))*(alpha^2)*(psi^2)) -> 8.6878021 | G11: =(EXP(alpha*(zeta+(2*b-a)*psi))*(-1+EXP(alpha*(-1)*Size*psi))*(EXP(alpha*(2*(Tau+OldTau)+a*psi))-EXP(alpha*(2*(Tau+OldTau)+b*psi))))/(((EXP(alpha*a*psi)-EXP(alpha*(2*OldTau+b*psi)))^2)*(alpha^2)*(psi^2)) -> 4.1688117e-65 | H11: =-Beta/alpha -> 180 | I11: =(-EXP(alpha*zeta)*Beta*(-1+EXP(alpha*Size*psi)-Size*alpha*psi))/((alpha^3)*(psi^2)) -> 348412.75 | J11: =Beta*Theta -> 14.4 | K11: =Beta*Theta -> 14.4 | L11: =kappa -> 90 | M11: =Gamma*Size -> 0 | N11: =Size*Beta*Phi -> 3240 | O11: =-(EXP(alpha*a*psi)+EXP(alpha*b*psi)*(-1+Size*psi*alpha))*(Beta*Phi)/((alpha*psi)*(EXP(alpha*a*psi)-EXP(alpha*b*psi))) -> 21.6 | P11: =(EXP(alpha*(zeta-a*psi))*Beta*Phi*(-EXP(alpha*a*psi)*(-2+(-1)*Size*alpha*psi)+EXP(alpha*b*psi)*(-2+Size*alpha*psi)))/((alpha^3)*(psi^3)) -> 41528.929 | Q11: =Tau*Beta -> 36.208799 | R11: =Tau*Beta -> 36.208799 | S11: =Tau -> 0.20115999 | T11: =Profit+Utility -> 308361.26 | U11: =(2*ij*BRIJ)+2*jj*BRJJ -> 629.14976 | V11: =2*(ij*BCCIJ)+(2*jj*BCCJJ)+BCS+jj*BCPTJJ+2*(ij*BCPTIJ)+BCPTII+BCk -> 42244.451 | W11: =ij*BUTIJ+BUTII -> 349976.56 | X11: =Revenue-Cost -> -41615.301 | Y11: =Size -> 1000 | Z11: =Welfare/(Size) -> 308.36126 | AA11: =Profit/(Size) -> -41.615301 | AB11: =Utility/(Size) -> 349.97656

Sheet W-Compare-NONC
A1: Size | B1: Welfare (TX) | C1: Welfare (XX) | D1: k-necessary | E1: Ratio | G1: Welfare (TT) | H1: Welfare (XT) | I1: k-necessary | J1: Ratio | L1: Size | M1: k-necessary (all-tax) | N1: k-necessary (all-toll) | O1: k-empirical | P1: Size | Q1: K/W (all-tax) | R1: K/W (all-toll) | U1: =A1 -> Size | V1: =B1 -> Welfare (TX) | W1: =C1 -> Welfare (XX) | X1: =G1 -> Welfare (TT) | Y1: =H1 -> Welfare (XT) | AC1: =A1 -> Size | AD1: =B1 -> Welfare (TX) | AE1: =+C1 -> Welfare (XX) | AF1: =G1 -> Welfare (TT) | AG1: =H1 -> Welfare (XT) | AH1: Size | AI1: Welfare (TX)/size | AJ1: Welfare (XX)/Size | AK1: Welfare (TT)/Size | AL1: Welfare(XT)/Size | AO1: GAME | AR1: J1 pay | AS1: J2 pay | AT1: J1 pay | AU1: J2 pay | AW1: J1 pay | AX1: J2 pay | AY1: J1 pay | AZ1: J2 pay | BA1: Tax Tax | BB1: Tax Toll | BC1: Toll Tax | BD1: Toll Toll
